Workbook

Sheet 1总概算
A1: 附表1
A2: 总概算执行情况一览表
A3: 建设单位：中国船舶集团有限公司第七一八研究所 | O3: 单位：万元 | Q3: 总1表
A4: 序号 | B4: 工程项目 | C4: 总概算 | H4: 实际完成 | M4: 尚需投资 | O4: 差额 | Q4: 备注
C5: 合计 | D5: 建筑 | E5: 设备 | F5: 安装 | G5: 其他 | H5: 合计 | I5: 建筑 | J5: 设备 | K5: 安装 | L5: 其他 | M5: 合计 | N5: 其中已列年度计划 | O5: 超支 | P5: 节约
A6: 1 | B6: 2 | C6: 3 | D6: 4 | E6: 5 | F6: 6 | G6: 7 | H6: 8 | I6: 9 | J6: 10 | K6: 11 | L6: 12 | M6: 13 | N6: 14 | O6: 15 | P6: 16 | Q6: 17
B7: 总计 | C7: =SUM(C8,C14,C18,C27:C28) -> 913 | D7: =SUM(D8,D14,D18,D27:D28) -> 549 | E7: =SUM(E8,E14,E18,E27:E28) -> 193 | F7: =SUM(F8,F14,F18,F27:F28) -> 42 | G7: =SUM(G8,G14,G18,G27:G28) -> 129 | H7: =SUM(H8,H14,H18,H27:H28) -> 602.65813 | I7: =SUM(I8,I14,I18,I27:I28) -> 368.61707 | J7: =SUM(J8,J14,J18,J27:J28) -> 180.23632 | ... L7: =SUM(L8,L14,L18,L27:L28) -> 49.405057 | O7: =IF(H7>C7,H7-C7,"") | P7: =IF(H7>C7,"",C7-H7) -> 310.34187
A8: 一 | B8: 工程费用 | C8: =C9+C11+C13 -> 742 | D8: =D9+D11+D13 -> 549 | E8: =E9+E11+E13 -> 193 | F8: =F9+F11+F13 -> 0 | G8: =G9+G11+G13 -> 0 | H8: =H9+H11+H13 -> 548.85339 | I8: =I9+I11+I13 -> 368.61707 | J8: =J9+J11+J13 -> 180.23632 | ... L8: =L9+L11+L13 -> 0 | O8: =IF(H8>C8,H8-C8,"") | P8: =IF(H8>C8,"",C8-H8) -> 193.14661
A9: （一） | B9: 室内工程 | C9: =C10 -> 727.6 | D9: =D10 -> 534.6 | E9: =E10 -> 193 | F9: =F10 -> 0 | G9: =G10 -> 0 | H9: =H10 -> 548.85339 | I9: =I10 -> 368.61707 | J9: =J10 -> 180.23632 | ... L9: =L10 -> 0 | O9: =IF(H9>C9,H9-C9,"") | P9: =IF(H9>C9,"",C9-H9) -> 178.74661
A10: 1 | B10: 制氢设备组装车间 | C10: =SUM(D10:G10) -> 727.6 | D10: ='2建筑工程'!J10 -> 534.6 | E10: ='3设备'!E8+'3设备'!E9 -> 193 | H10: =SUM(I10:L10) -> 548.85339 | I10: ='2建筑工程'!K10 -> 368.61707 | J10: ='3设备'!G8+'3设备'!G9 -> 180.23632 | O10: =IF(H10>C10,H10-C10,"") | P10: =IF(H10>C10,"",C10-H10) -> 178.74661
A11: （二） | B11: 室外工程 | C11: =SUM(D11:G11) -> 14.8 | D11: ='2建筑工程'!J11 -> 14.8 | H11: =SUM(I11:L11) -> 0 | I11: ='2建筑工程'!K11 -> 0 | O11: =IF(H11>C11,H11-C11,"") | P11: =IF(H11>C11,"",C11-H11) -> 14.8
A12: 1 | B12: 室外电气工程 | C12: =SUM(D12:G12) -> 14.8 | D12: ='2建筑工程'!J12 -> 14.8 | H12: =SUM(I12:L12) -> 0 | I12: ='2建筑工程'!K12 -> 0 | O12: =IF(H12>C12,H12-C12,"") | P12: =IF(H12>C12,"",C12-H12) -> 14.8
A13: （三） | B13: 概算调差 | C13: =SUM(D13:G13) -> -0.4 | D13: ='2建筑工程'!J13 -> -0.4 | H13: =SUM(I13:L13) -> 0 | I13: ='2建筑工程'!K13 -> 0 | O13: =IF(H13>C13,H13-C13,"") -> 0.4 | P13: =IF(H13>C13,"",C13-H13)
A14: 二 | B14: 设备安装费 | C14: =SUM(E14:G14) -> 42 | F14: ='2建筑工程'!J14 -> 42 | H14: =SUM(J14:L14) -> 4.399681 | K14: ='2建筑工程'!K14 -> 4.399681 | O14: =IF(H14>C14,H14-C14,"") | P14: =IF(H14>C14,"",C14-H14) -> 37.600319
A15: （一） | B15: 室内工程 | C15: =SUM(E15:G15) -> 42.2 | F15: ='2建筑工程'!J15 -> 42.2 | H15: =SUM(J15:L15) -> 4.399681 | K15: ='2建筑工程'!K15 -> 4.399681 | O15: =IF(H15>C15,H15-C15,"") | P15: =IF(H15>C15,"",C15-H15) -> 37.800319
A16: 1 | B16: 制氢设备组装车间 | C16: =SUM(E16:G16) -> 42.2 | F16: ='2建筑工程'!J16 -> 42.2 | H16: =SUM(J16:L16) -> 4.399681 | K16: ='2建筑工程'!K16 -> 4.399681 | O16: =IF(H16>C16,H16-C16,"") | P16: =IF(H16>C16,"",C16-H16) -> 37.800319
A17: （二） | B17: 概算调差 | C17: =SUM(E17:G17) -> -0.2 | F17: ='2建筑工程'!J17 -> -0.2 | H17: =SUM(I17:L17) -> 0 | I17: ='2建筑工程'!K17 -> 0 | O17: =IF(H17>C17,H17-C17,"") -> 0.2 | P17: =IF(H17>C17,"",C17-H17)
A18: 三 | B18: 工程建设其他费用 | C18: =SUM(D18:G18) -> 92.9 | D18: =SUM(D19:D26) -> 0 | E18: =SUM(E19:E26) -> 0 | F18: =SUM(F19:F26) -> 0 | G18: 92.9 | H18: =SUM(I18:L18) -> 49.405057 | I18: =SUM(I19:I26) -> 0 | J18: =SUM(J19:J26) -> 0 | K18: =SUM(K19:K26) -> 0 | L18: 49.405057 | O18: =IF(H18>C18,H18-C18,"") | P18: =IF(H18>C18,"",C18-H18) -> 43.494943
A19: 1 | B19: 建设单位管理费 | C19: =SUM(D19:G19) -> 17.9 | G19: 17.9 | H19: =SUM(I19:L19) -> 0 | L19: 0 | O19: =IF(H19>C19,H19-C19,"") | P19: =IF(H19>C19,"",C19-H19) -> 17.9
A20: 2 | B20: 前期工作咨询费 | C20: =SUM(D20:G20) -> 13.3 | G20: 13.3 | H20: =SUM(I20:L20) -> 0 | L20: 0 | O20: =IF(H20>C20,H20-C20,"") | P20: =IF(H20>C20,"",C20-H20) -> 13.3
A21: 3 | B21: 工程设计费 | C21: =SUM(D21:G21) -> 38.9 | G21: 38.9 | H21: =SUM(I21:L21) -> 17.11132 | L21: 17.11132 | O21: =IF(H21>C21,H21-C21,"") | P21: =IF(H21>C21,"",C21-H21) -> 21.78868
A22: 4 | B22: 工程建设监理费 | C22: =SUM(D22:G22) -> 17.8 | G22: 17.8 | H22: =SUM(I22:L22) -> 7.656513 | L22: 7.656513 | O22: =IF(H22>C22,H22-C22,"") | P22: =IF(H22>C22,"",C22-H22) -> 10.143487
A23: 5 | B23: 招标代理服务费 | C23: =SUM(D23:G23) -> 1 | G23: 1 | H23: =SUM(I23:L23) -> 0 | L23: 0 | O23: =IF(H23>C23,H23-C23,"") | P23: =IF(H23>C23,"",C23-H23) -> 1
A24: 6 | B24: 环境影响咨询费 | C24: =SUM(D24:G24) -> 2 | G24: 2 | H24: =SUM(I24:L24) -> 7.075472 | L24: 7.075472 | O24: =IF(H24>C24,H24-C24,"") -> 5.075472 | P24: =IF(H24>C24,"",C24-H24)
A25: 7 | B25: 安全设施及职业卫生评价费 | C25: =SUM(D25:G25) -> 2 | G25: 2 | H25: =SUM(I25:L25) -> 14.337755 | L25: 14.337755 | O25: =IF(H25>C25,H25-C25,"") -> 12.337755 | P25: =IF(H25>C25,"",C25-H25)
A26: 8 | B26: 工程造价咨询费 | C26: =SUM(D26:G26) -> 0 | G26: 0 | H26: =SUM(I26:L26) -> 3.223997 | L26: 3.223997 | O26: =IF(H26>C26,H26-C26,"") -> 3.223997 | P26: =IF(H26>C26,"",C26-H26)
A27: 四 | B27: 基本预备费 | C27: =SUM(D27:G27) -> 35.5 | G27: 35.5 | H27: =SUM(I27:L27) -> 0 | L27: 0 | O27: =IF(H27>C27,H27-C27,"") | P27: =IF(H27>C27,"",C27-H27) -> 35.5
A28: 五 | B28: 调整批复差异 | C28: =SUM(D28:G28) -> 0.6 | G28: 0.6 | L28: 0

Sheet 2建筑工程
A1: 附表2
A2: 建筑工程完成情况一览表
A3: ='1总概算'!A3 -> 建设单位：中国船舶集团有限公司第七一八研究所 | K3: 单位：万元 | M3: 总2表
A4: 序号 | B4: 工程项目编号及名称 | C4: 建设性质 | D4: 工程量 | G4: 结构及层数 | H4: 开竣工日期 | J4: 设计概算 | K4: 实际完成 | L4: 质量评定等级 | M4: 备注 | O4: 招标情况
D5: 单位 | E5: 设计 | F5: 实际 | H5: 开工 | I5: 竣工 | O5: 批复 | P5: 实际
A6: 1 | B6: 2 | C6: 3 | D6: 4 | E6: 5 | F6: 6 | G6: 7 | H6: 8 | I6: 9 | J6: 10 | K6: 11 | L6: 12 | M6: 13
B7: 建安工程 总计 | C7: 改造 | D7: 平方米 | E7: =SUM(E8,E17) -> 3095.3 | F7: =SUM(F8,F17) -> 3095.3 | J7: =SUM(J8,J17) -> 549.2 | K7: =SUM(K8,K17) -> 368.61707
A8: 一 | B8: 建筑工程 | C8: 改造 | D8: 平方米 | E8: =E9+E11 -> 3095.3 | F8: =F9+F11 -> 3095.3 | J8: =J9+J11 -> 549.4 | K8: =K9+K11 -> 368.61707 | O8: 部分委托公开
A9: （一） | B9: 室内工程 | C9: 改造 | D9: 平方米 | E9: =SUM(E10:E17) -> 3095.3 | F9: =SUM(F10:F17) -> 3095.3 | J9: 534.6 | K9: =K10 -> 368.61707
A10: 1 | B10: 制氢设备组装车间 | C10: 改造 | D10: 平方米 | E10: 3095.3 | F10: 3095.3 | G10: 门式刚架结构/单层，局部三层 | H10: 44742 | I10: 44902 | J10: 534.6 | K10: =401.242768-'3设备'!G9 -> 368.61707 | L10: 合格 | M10: 17# | P10: 委托公开
A11: （二） | B11: 室外工程 | J11: 14.8
A12: 1 | B12: 室外电气工程 | J12: 14.8
A13: （三） | B13: 概算调差 | J13: -0.4
A14: 二 | B14: 设备安装费 | J14: 42 | K14: 4.399681
A15: （一） | B15: 室内工程 | J15: 42.2 | K15: 4.399681
A16: 1 | B16: 制氢设备组装车间 | J16: 42.2 | K16: 4.399681
A17: （二） | B17: 概算调差 | J17: -0.2

Sheet 3设备
A1: 附表3
A2: 设备配备情况表
A3: ='1总概算'!A3 -> 建设单位：中国船舶集团有限公司第七一八研究所 | J3: 单位：万元 | L3: 总3表
A4: 序号 | B4: 设备类别 | C4: 单位 | D4: 设计 | F4: 实际 | H4: 多余 | J4: 尚缺 | L4: 备 注
D5: 数量 | E5: 金额 | F5: 数量 | G5: 金额 | H5: 数量 | I5: 金额 | J5: 数量 | K5: 金额
A6: 1 | B6: 2 | C6: 3 | D6: 4 | E6: 5 | F6: 6 | G6: 7 | H6: 8 | I6: 9 | J6: 10 | K6: 11 | L6: 12
B7: 总计 | C7: 套/万元 | D7: =D8+D9 -> 26 | E7: =E8+E9 -> 193 | F7: =F8+F9 -> 46 | G7: =G8+G9 -> 180.23632
A8: A | B8: 工艺设备 | C8: 套/万元 | D8: ='11工艺'!G6 -> 26 | E8: ='11工艺'!H6 -> 193 | F8: ='11工艺'!Q6 -> 26 | G8: ='11工艺'!R6 -> 147.61062
A9: B | B9: 公用设备 | C9: 套/万元 | D9: ='13公用'!G6 -> 0 | E9: ='13公用'!H6 -> 0 | F9: ='13公用'!Q6 -> 20 | G9: ='13公用'!R6 -> 32.625694
A10: D | B10: ='11工艺'!L9 -> 待抵扣进项税 | C10: 套/万元 | D10: ='11工艺'!G9 -> 0 | E10: ='11工艺'!H9 -> 0 | F10: ='11工艺'!Q9 -> 0 | G10: ='11工艺'!R9 -> 0

Sheet 4变更
A1: 附表4
A2: 重大设计变更一览表
A3: ='1总概算'!A3 -> 建设单位：中国船舶集团有限公司第七一八研究所 | H3: 总4表
A4: 序号 | B4: 工程项目 | C4: 变动内容 | D4: 变动原因 | E4: 变动后投资增减（+-） | F4: 原设计批准单位日期文号 | G4: 设计变更批准单位日期文号 | H4: 备注
A5: 1 | B5: 2 | C5: 3 | D5: 4 | E5: 5 | F5: 6 | G5: 7 | H5: 8
B6: 本项目不涉及

Sheet 5设备调整
A1: 附表5
A2: 设备调整明细表
A3: ='1总概算'!A3 -> 建设单位：中国船舶集团有限公司第七一八研究所 | I3: 单位：万元 | K3: 总5表
A4: 序号 | B4: 名称 | C4: 型号 | D4: 规格 | E4: 产地 | F4: 单位 | G4: 原设计 | I4: 调整设计 | K4: 调整说明
G5: 数量 | H5: 金额 | I5: 数量 | J5: 金额
A6: 1 | B6: 2 | C6: 3 | D6: 4 | E6: 5 | F6: 6 | G6: 7 | H6: 8 | I6: 9 | J6: 10 | K6: 11
B7: 本项目不涉及
A8: 一 | B8: 调增设备
A9: 1
A10: 2
A11: 3
A12: 二 | B12: 调减设备
A13: 1
A14: 2
A15: 三 | B15: 国别调整
A16: 1
A17: 2
A18: 四 | B18: 组成调整
A19: 1
A20: 2
A21: 五 | B21: 指标调整
A22: 1
A23: 2

Sheet 6未完工程
A1: 附表6
A2: 未完工程项目一览表
A3: ='1总概算'!A3 -> 建设单位：中国船舶集团有限公司第七一八研究所 | F3: 单位：万元 | H3: 总6表
A4: 序号 | B4: 工程项目编号及名称 | C4: 工程内容 | D4: 单位 | E4: 未完工程量 | F4: 尚需投资 | G4: 未完原因及说明 | H4: 备注
A5: 1 | B5: 2 | C5: 3 | D5: 4 | E5: 5 | F5: 6 | G5: 7 | H5: 8
B6: 本项目不涉及

Sheet 7未完设备
A1: 附表7
A2: 未完设备一览表
A3: ='1总概算'!A3 -> 建设单位：中国船舶集团有限公司第七一八研究所 | E3: 单位：万元 | G3: 总7表
A4: 序号 | B4: 设备名称 | C4: 型号及规格 | D4: 单位 | E4: 数量 | F4: 金额 | G4: 备注
A5: 1 | B5: 2 | C5: 3 | D5: 4 | E5: 5 | F5: 6 | G5: 7
B6: 本项目不涉及

Sheet 8人员
A1: 附表8
A2: 人员配备一览表
A3: ='1总概算'!A3 -> 建设单位：中国船舶集团有限公司第七一八研究所 | O3: 总8表
A4: 序号 | B4: 车间或科室名称 | C4: 设计人数 | G4: 现有人数 | K4: 缺余人数 | O4: 备注
C5: 合计 | D5: 生产工人 | E5: 辅助工人 | F5: 非生产 人员 | G5: 合计 | H5: 生产工人 | I5: 辅助 工人 | J5: 非生产 人员 | K5: 合计 | L5: 生产工人 | M5: 辅助 工人 | N5: 非生产人员
A6: 1 | B6: 2 | C6: 3 | D6: 4 | E6: 5 | F6: 6 | G6: 7 | H6: 8 | I6: 9 | J6: 10 | K6: 11 | L6: 12 | M6: 13 | N6: 14 | O6: 15
A7: 1 | B7: XXX厂房

Sheet 9贷款
A1: 附表9
A2: 项目贷款还贷情况表（财务）
A3: ='1总概算'!A3 -> 建设单位：中国船舶集团有限公司第七一八研究所 | E3: 总9表
A4: 年份 摘要 | B4: 20XX年 | C4: 20XX年 | D4: 20XX年 | E4: 20XX年
A6: 一、贷款总额
A7: 其中：贷款本金
A8: 贷款利息
A9: 二、已还贷款
A10: 其中：贷款本金
A11: 贷款利息
A12: 三、贷款余额
A13: 其中：贷款本金
A14: 贷款利息

Sheet 10决算
A1: 附表10
A2: 建设项目竣工决算表
A3: ='1总概算'!A3 -> 建设单位：中国船舶集团有限公司第七一八研究所 | E3: 项目名称：高纯电子气体产业化建设项目
E4: 20XX年至20XX年 | G4: 单位：万元 | H4: 总10表
A5: 金额 年份 项目 | B5: 合计 | C5: 20XX年 | D5: 20XX年 | E5: 20XX年 | F5: 20XX年 | G5: 20XX年 | H5: 20XX年
A6: 一、建设拨、借款
A7: 1、国家拨款
A8: 2、开发银行贷款
A9: 3、商业银行贷款
A10: 4、其他投资借款
A11: 5、集团公司自筹
A12: 6、企业自筹
A13: 7、项目资本
A14: 8、项目资本公积
A15: 二、建设支出
A16: 1、完成投资额
A17: 其中：建安投资
... A30: 四、年末建设节余资金

Sheet 11工艺
A1: 附表11
A2: 工艺设备批复与实施对比表
A3: ='1总概算'!A3 -> 建设单位：中国船舶集团有限公司第七一八研究所 | U3: 总11表
A4: 序号 | B4: 批复情况 | L4: 实施情况
B5: 名称 | C5: 功能及组成 | D5: 主要性能指标 | E5: 单位 | F5: 国别 | G5: 数量 | H5: 投资 (万元) | I5: 招标情况 | J5: 布置位置 | K5: 备注 | L5: 名称 | M5: 功能及组成 | N5: 主要性能指标 | O5: 单位 | P5: 国别 | Q5: 数量 | R5: 投资 (万元) | S5: 招标情况 | T5: 布置位置 | U5: 备注
A6: I | B6: 工艺设备 | G6: =G7+G8 -> 26 | H6: =H7+H8 -> 193 | L6: 工艺设备 | Q6: =Q7+Q8 -> 26 | R6: =R7+R8 -> 147.61062
A7: 1 | B7: 通风柜 | D7: 尺寸1800mm*850mm*2350mm;风速0.4-0.5m/s；风量2400m³/h | E7: 套 | F7: 国产 | G7: 22 | H7: 33 | L7: 通风柜 | N7: 非标 | O7: 套 | P7: 国产 | Q7: 22 | R7: 23.893806
A8: 2 | B8: 振动测试台 | D8: 尺寸（长×宽）：4m×4m，其高度≥400mm；测试台如有拼接，其整体平整度≤0.1mm，水平度≤0.2mm/m；测试台（铸钢件+钢筋混凝土）固有频率≥70Hz | E8: 套 | F8: 国产 | G8: 4 | H8: 160 | L8: 振动测试台 | N8: 非标 | O8: 套 | P8: 国产 | Q8: 4 | R8: 123.71682
A9: Ⅳ | B9: 待抵扣进项税 | L9: 待抵扣进项税 | W9: 402.73079

Sheet 12建筑物
A1: 附表12
A2: 建（构）筑物批复与实施对比表
A3: ='1总概算'!A3 -> 建设单位：中国船舶集团有限公司第七一八研究所 | P3: 总12表
A4: 序号 | B4: 名称 | C4: 批复情况 | H4: 实施情况
C5: 面积 | D5: 结构型式 | E5: 布局位置 | F5: 招标情况 | G5: 备注 | H5: 面积 | I5: 结构型式 | J5: 布局位置 | K5: 招标情况 | L5: 中标单位 | M5: 验收备案 | N5: 不动产权证书 | O5: 报建及验收情况 | P5: 备注
A6: 1 | B6: ='2建筑工程'!B10 -> 制氢设备组装车间 | C6: ='2建筑工程'!F9 -> 3095.3 | D6: ='2建筑工程'!G10 -> 门式刚架结构/单层，局部三层 | E6: 派瑞科技产业园西区 | F6: 委托公开 | H6: ='2建筑工程'!F10 -> 3095.3 | I6: =D6 -> 门式刚架结构/单层，局部三层 | J6: =E6 -> 派瑞科技产业园西区 | K6: =F6 -> 委托公开 | L6: 河北省磁县第一建筑安装公司 | O6: 工程质量评定 建设单位、施工单位、监理单位共同验收合格

Sheet 13公用
A1: 附表13
A2: 公用设备批复与实施对比表
A3: ='1总概算'!A3 -> 建设单位：中国船舶集团有限公司第七一八研究所 | U3: 总13表
A4: 序号 | B4: 批复情况 | L4: 实施情况
B5: 名称 | C5: 功能及组成 | D5: 主要性能指标 | E5: 单位 | F5: 国别 | G5: 数量 | H5: 投资 (万元) | I5: 招标情况 | J5: 布置位置 | K5: 备注 | L5: 名称 | M5: 功能及组成 | N5: 主要性能指标 | O5: 单位 | P5: 国别 | Q5: 数量 | R5: 投资 (万元) | S5: 招标情况 | T5: 布置位置 | U5: 备注
A6: II | B6: 公用设备 | G6: =SUM(G7:G25) -> 0 | H6: =SUM(H7:H25) -> 0 | L6: 公用设备 | Q6: =SUM(Q7:Q25) -> 20 | R6: =SUM(R7:R25) -> 32.625694
L7: 冷水机 | N7: DX-90WS | O7: 台 | Q7: 1 | R7: 14.699115
L8: 冷水机 | N8: DX-50WS | O8: 台 | Q8: 1 | R8: 9.99115
L9: 净水器 | N9: 3T | O9: 台 | Q9: 2 | R9: 1.504425
L10: 配电箱 | N10: AP1 | O10: 台 | Q10: 1 | R10: 0.216292
L11: 配电箱 | N11: AP2 | O11: 台 | Q11: 1 | R11: 0.216292
L12: 配电箱 | N12: AP3 | O12: 台 | Q12: 1 | R12: 0.216292
L13: 配电箱 | N13: AP4 | O13: 台 | Q13: 1 | R13: 0.216292
L14: 配电箱 | N14: AP10 | O14: 台 | Q14: 1 | R14: 0.216292
L15: 配电箱 | N15: AP5 | O15: 台 | Q15: 1 | R15: 0.307211
L16: 配电箱 | N16: AP6 | O16: 台 | Q16: 1 | R16: 0.307211
L17: 配电箱 | N17: AP6 | O17: 台 | Q17: 1 | R17: 0.307211
L18: 高压成套配电柜 | N18: AH1 | O18: 台 | Q18: 1 | R18: 0.457274
... L25: 低压开关柜 | N25: AA6 | O25: 台 | Q25: 1 | R25: 0.510331
A26: III | B26: 公用设备安装费 | L26: 公用设备安装费 | R26: 4.399681

Sheet 14特种设备
A1: 附表14
A2: 特种设备批复与实施对比表
A3: ='1总概算'!A3 -> 建设单位：中国船舶集团有限公司第七一八研究所 | V3: 总14表
A4: 序号 | B4: 批复情况 | L4: 实施情况
B5: 名称 | C5: 功能及组成 | D5: 主要性能指标 | E5: 单位 | F5: 国别 | G5: 数量 | H5: 投资 (万元) | I5: 招标情况 | J5: 布置位置 | K5: 备注 | L5: 名称 | M5: 功能及组成 | N5: 主要性能指标 | O5: 单位 | P5: 国别 | Q5: 数量 | R5: 投资 (万元) | S5: 招标情况 | T5: 布置位置 | U5: 特种设备取证情况 | V5: 备注
A6: ='11工艺'!#REF! -> #REF! | B6: ='11工艺'!#REF! -> #REF! | C6: ='11工艺'!#REF! -> #REF! | D6: ='11工艺'!#REF! -> #REF! | E6: ='11工艺'!#REF! -> #REF! | F6: ='11工艺'!#REF! -> #REF! | G6: ='11工艺'!#REF! -> #REF! | H6: ='11工艺'!#REF! -> #REF! | ... T6: ='11工艺'!#REF! -> #REF! | V6: ='11工艺'!#REF! -> #REF!
A7: ='11工艺'!A6 -> I | B7: ='11工艺'!B6 -> 工艺设备 | C7: ='11工艺'!C6 -> 0 | D7: ='11工艺'!D6 -> 0 | E7: ='11工艺'!E6 -> 0 | F7: ='11工艺'!F6 -> 0 | G7: ='11工艺'!G6 -> 26 | H7: ='11工艺'!H6 -> 193 | ... T7: ='11工艺'!T6 -> 0 | V7: ='11工艺'!U6 -> 0
A8: ='11工艺'!#REF! -> #REF! | B8: ='11工艺'!#REF! -> #REF! | C8: ='11工艺'!#REF! -> #REF! | D8: ='11工艺'!#REF! -> #REF! | E8: ='11工艺'!#REF! -> #REF! | F8: ='11工艺'!#REF! -> #REF! | G8: ='11工艺'!#REF! -> #REF! | H8: ='11工艺'!#REF! -> #REF! | ... T8: ='11工艺'!#REF! -> #REF! | V8: ='11工艺'!#REF! -> #REF!
A9: ='11工艺'!#REF! -> #REF! | B9: ='11工艺'!#REF! -> #REF! | C9: ='11工艺'!#REF! -> #REF! | D9: ='11工艺'!#REF! -> #REF! | E9: ='11工艺'!#REF! -> #REF! | F9: ='11工艺'!#REF! -> #REF! | G9: ='11工艺'!#REF! -> #REF! | H9: ='11工艺'!#REF! -> #REF! | ... T9: ='11工艺'!#REF! -> #REF! | V9: ='11工艺'!#REF! -> #REF!
A10: ='11工艺'!#REF! -> #REF! | B10: ='11工艺'!#REF! -> #REF! | C10: ='11工艺'!#REF! -> #REF! | D10: ='11工艺'!#REF! -> #REF! | E10: ='11工艺'!#REF! -> #REF! | F10: ='11工艺'!#REF! -> #REF! | G10: ='11工艺'!#REF! -> #REF! | H10: ='11工艺'!#REF! -> #REF! | ... T10: ='11工艺'!#REF! -> #REF! | V10: ='11工艺'!#REF! -> #REF!
A11: ='11工艺'!A7 -> 1 | B11: ='11工艺'!B7 -> 通风柜 | C11: ='11工艺'!C7 -> 0 | D11: ='11工艺'!D7 -> 尺寸1800mm*850mm*2350mm;风速0.4-0.5m/s；风量2400m³/h | E11: ='11工艺'!E7 -> 套 | F11: ='11工艺'!F7 -> 国产 | G11: ='11工艺'!G7 -> 22 | H11: ='11工艺'!H7 -> 33 | ... T11: ='11工艺'!T7 -> 0 | V11: ='11工艺'!U7 -> 0
A12: ='11工艺'!A8 -> 2 | B12: ='11工艺'!B8 -> 振动测试台 | C12: ='11工艺'!C8 -> 0 | D12: ='11工艺'!D8 -> 尺寸（长×宽）：4m×4m，其高度≥400mm；测试台如有拼接，其整体平整度≤0.1mm，水平度≤0.2mm/m；测试台（铸钢件+钢筋混凝土）固有频率≥70Hz | E12: ='11工艺'!E8 -> 套 | F12: ='11工艺'!F8 -> 国产 | G12: ='11工艺'!G8 -> 4 | H12: ='11工艺'!H8 -> 160 | ... T12: ='11工艺'!T8 -> 0 | V12: ='11工艺'!U8 -> 0
A13: ='11工艺'!#REF! -> #REF! | B13: ='11工艺'!#REF! -> #REF! | C13: ='11工艺'!#REF! -> #REF! | D13: ='11工艺'!#REF! -> #REF! | E13: ='11工艺'!#REF! -> #REF! | F13: ='11工艺'!#REF! -> #REF! | G13: ='11工艺'!#REF! -> #REF! | H13: ='11工艺'!#REF! -> #REF! | ... T13: ='11工艺'!#REF! -> #REF! | V13: ='11工艺'!#REF! -> #REF!
A14: ='11工艺'!#REF! -> #REF! | B14: ='11工艺'!#REF! -> #REF! | C14: ='11工艺'!#REF! -> #REF! | D14: ='11工艺'!#REF! -> #REF! | E14: ='11工艺'!#REF! -> #REF! | F14: ='11工艺'!#REF! -> #REF! | G14: ='11工艺'!#REF! -> #REF! | H14: ='11工艺'!#REF! -> #REF! | ... T14: ='11工艺'!#REF! -> #REF! | V14: ='11工艺'!#REF! -> #REF!
A15: ='11工艺'!#REF! -> #REF! | B15: ='11工艺'!#REF! -> #REF! | C15: ='11工艺'!#REF! -> #REF! | D15: ='11工艺'!#REF! -> #REF! | E15: ='11工艺'!#REF! -> #REF! | F15: ='11工艺'!#REF! -> #REF! | G15: ='11工艺'!#REF! -> #REF! | H15: ='11工艺'!#REF! -> #REF! | ... T15: ='11工艺'!#REF! -> #REF! | V15: ='11工艺'!#REF! -> #REF!
A16: ='11工艺'!#REF! -> #REF! | B16: ='11工艺'!#REF! -> #REF! | C16: ='11工艺'!#REF! -> #REF! | D16: ='11工艺'!#REF! -> #REF! | E16: ='11工艺'!#REF! -> #REF! | F16: ='11工艺'!#REF! -> #REF! | G16: ='11工艺'!#REF! -> #REF! | H16: ='11工艺'!#REF! -> #REF! | ... T16: ='11工艺'!#REF! -> #REF! | V16: ='11工艺'!#REF! -> #REF!
A17: ='11工艺'!#REF! -> #REF! | B17: ='11工艺'!#REF! -> #REF! | C17: ='11工艺'!#REF! -> #REF! | D17: ='11工艺'!#REF! -> #REF! | E17: ='11工艺'!#REF! -> #REF! | F17: ='11工艺'!#REF! -> #REF! | G17: ='11工艺'!#REF! -> #REF! | H17: ='11工艺'!#REF! -> #REF! | ... T17: ='11工艺'!#REF! -> #REF! | V17: ='11工艺'!#REF! -> #REF!
A18: ='11工艺'!#REF! -> #REF! | B18: ='11工艺'!#REF! -> #REF! | C18: ='11工艺'!#REF! -> #REF! | D18: ='11工艺'!#REF! -> #REF! | E18: ='11工艺'!#REF! -> #REF! | F18: ='11工艺'!#REF! -> #REF! | G18: ='11工艺'!#REF! -> #REF! | H18: ='11工艺'!#REF! -> #REF! | ... T18: ='11工艺'!#REF! -> #REF! | V18: ='11工艺'!#REF! -> #REF!
A19: ='11工艺'!#REF! -> #REF! | B19: ='11工艺'!#REF! -> #REF! | C19: ='11工艺'!#REF! -> #REF! | D19: ='11工艺'!#REF! -> #REF! | E19: ='11工艺'!#REF! -> #REF! | F19: ='11工艺'!#REF! -> #REF! | G19: ='11工艺'!#REF! -> #REF! | H19: ='11工艺'!#REF! -> #REF! | ... T19: ='11工艺'!#REF! -> #REF! | V19: ='11工艺'!#REF! -> #REF!
A20: ='11工艺'!#REF! -> #REF! | B20: ='11工艺'!#REF! -> #REF! | C20: ='11工艺'!#REF! -> #REF! | D20: ='11工艺'!#REF! -> #REF! | E20: ='11工艺'!#REF! -> #REF! | F20: ='11工艺'!#REF! -> #REF! | G20: ='11工艺'!#REF! -> #REF! | H20: ='11工艺'!#REF! -> #REF! | ... T20: ='11工艺'!#REF! -> #REF! | V20: ='11工艺'!#REF! -> #REF!
A21: ='11工艺'!#REF! -> #REF! | B21: ='11工艺'!#REF! -> #REF! | C21: ='11工艺'!#REF! -> #REF! | D21: ='11工艺'!#REF! -> #REF! | E21: ='11工艺'!#REF! -> #REF! | F21: ='11工艺'!#REF! -> #REF! | G21: ='11工艺'!#REF! -> #REF! | H21: ='11工艺'!#REF! -> #REF! | ... T21: ='11工艺'!#REF! -> #REF! | V21: ='11工艺'!#REF! -> #REF!
A22: ='11工艺'!#REF! -> #REF! | B22: ='11工艺'!#REF! -> #REF! | C22: ='11工艺'!#REF! -> #REF! | D22: ='11工艺'!#REF! -> #REF! | E22: ='11工艺'!#REF! -> #REF! | F22: ='11工艺'!#REF! -> #REF! | G22: ='11工艺'!#REF! -> #REF! | H22: ='11工艺'!#REF! -> #REF! | ... T22: ='11工艺'!#REF! -> #REF! | V22: ='11工艺'!#REF! -> #REF!
A23: ='11工艺'!#REF! -> #REF! | B23: ='11工艺'!#REF! -> #REF! | C23: ='11工艺'!#REF! -> #REF! | D23: ='11工艺'!#REF! -> #REF! | E23: ='11工艺'!#REF! -> #REF! | F23: ='11工艺'!#REF! -> #REF! | G23: ='11工艺'!#REF! -> #REF! | H23: ='11工艺'!#REF! -> #REF! | ... T23: ='11工艺'!#REF! -> #REF! | V23: ='11工艺'!#REF! -> #REF!
A24: ='11工艺'!#REF! -> #REF! | B24: ='11工艺'!#REF! -> #REF! | C24: ='11工艺'!#REF! -> #REF! | D24: ='11工艺'!#REF! -> #REF! | E24: ='11工艺'!#REF! -> #REF! | F24: ='11工艺'!#REF! -> #REF! | G24: ='11工艺'!#REF! -> #REF! | H24: ='11工艺'!#REF! -> #REF! | ... T24: ='11工艺'!#REF! -> #REF! | V24: ='11工艺'!#REF! -> #REF!
... A165: ='11工艺'!#REF! -> #REF! | B165: ='11工艺'!#REF! -> #REF! | C165: ='11工艺'!#REF! -> #REF! | D165: ='11工艺'!#REF! -> #REF! | E165: ='11工艺'!#REF! -> #REF! | F165: ='11工艺'!#REF! -> #REF! | G165: ='11工艺'!#REF! -> #REF! | H165: ='11工艺'!#REF! -> #REF! | ... T165: ='11工艺'!#REF! -> #REF! | V165: ='11工艺'!#REF! -> #REF!

Sheet 15成效
A1: 附表15
A2: 项目建设成效分析表
A3: ='1总概算'!A3 -> 建设单位：中国船舶集团有限公司第七一八研究所 | G3: 总15表
A4: 序号 | B4: 项目名称 | C4: 子项内容 | D4: 完成情况 | E4: 形成能力 | F4: 建设以来发挥的成效 | G4: 备注
A5: 1 | B5: 核电站安全系统项目 | C5: 核电安全设备总装车间 | D5: 已实施 | E5: 本项目建成后，形成年产核电站氨浓度监测仪、消氢系统和安全壳过滤排放系统设备 970台（套）的能力。 | F5: 通过本项目建设，满足了未来一段时期内七一八所核电站氨浓度监测仪、消氢系统和安全壳过滤排放系统设备的生产供货需要。在一定程度上缓解了生产规模不足的压力，实现了批复的建设目标。
C6: 综合楼（夜视仪组装车间） | D6: 已实施
C7: 催化剂及气体检测车间 | D7: 已实施
C8: 消防泵房及水池 | D8: 已实施
C9: 产品性能检测设备 | D9: 已实施
