Workbook
Name _: '[1]#REF!'!$B$186
Name _: '[2]#REF!'!$B$186
Name __PA7: '[3]SW-TEO'!#REF!
Name __PA8: '[3]SW-TEO'!#REF!
Name __PD1: '[3]SW-TEO'!#REF!
Name __PE12: '[3]SW-TEO'!#REF!
Name __PE13: '[3]SW-TEO'!#REF!
Name __PE6: '[3]SW-TEO'!#REF!
Name __PE7: '[3]SW-TEO'!#REF!
Name __PE8: '[3]SW-TEO'!#REF!
Name __PE9: '[3]SW-TEO'!#REF!
Name __PH1: '[3]SW-TEO'!#REF!
Name __PI1: '[3]SW-TEO'!#REF!
Name __PK1: '[3]SW-TEO'!#REF!
Name __PK3: '[3]SW-TEO'!#REF!
Name _PA7: '[3]SW-TEO'!#REF!
Name _PA8: '[3]SW-TEO'!#REF!
Name _PD1: '[3]SW-TEO'!#REF!
Name _PE12: '[3]SW-TEO'!#REF!
Name _PE13: '[3]SW-TEO'!#REF!
Name _PE6: '[3]SW-TEO'!#REF!
Name _PE7: '[3]SW-TEO'!#REF!
Name _PE8: '[3]SW-TEO'!#REF!
Name _PE9: '[3]SW-TEO'!#REF!
Name _PH1: '[3]SW-TEO'!#REF!
Name _PI1: '[3]SW-TEO'!#REF!
Name _PK1: '[3]SW-TEO'!#REF!
Name _PK3: '[3]SW-TEO'!#REF!
Name _Toc146509935: '[5]#REF!'!$A$19
Name _Toc146509935: '[6]#REF!'!$A$19
Name aaaaa: '[7]#REF!'!$A$1
Name aaaaa: '[8]#REF!'!$A$1
Name aiu_bottom: '[9]Financ. Overview'!#REF!
Name bd: '[1]#REF!'!$C$50
Name bd: '[2]#REF!'!$C$50
Name bdb: '[1]#REF!'!$C$51
Name bdb: '[2]#REF!'!$C$51
Name CAILIAO: '[1]#REF!'!$A$28
Name CAILIAO: '[2]#REF!'!$A$28
Name cb: '[1]#REF!'!$A$26
Name cb: '[2]#REF!'!$A$26
Name dl: '[1]#REF!'!$C$25
Name dl: '[2]#REF!'!$C$25
Name dlb: '[1]#REF!'!$C$31
Name dlb: '[2]#REF!'!$C$31
Name edline: #REF!
Name ff: '[10]#REF!'!$A$8:$A$28
Name ff: '[11]#REF!'!$A$8:$A$28
Name FRC: [12]Main!$C$9
Name fz: #REF!
Name gy: '[1]#REF!'!$C$7
Name gy: '[2]#REF!'!$C$7
Name gyb: '[1]#REF!'!$C$9
Name gyb: '[2]#REF!'!$C$9
Name gyg: '[1]#REF!'!#REF!
Name gyg: '[2]#REF!'!#REF!
Name hostfee: '[9]Financ. Overview'!$H$12
Name hraiu_bottom: '[9]Financ. Overview'!#REF!
Name hvac: '[9]Financ. Overview'!#REF!
Name HWSheet: 1

Sheet 投资估算表
A1: 附表1
A2: 投 资 估 算 表
A4: =设备!A3 -> 项目名称：XXXXXX建设项目 | G4: 单位：万元、万美元
A5: 序号 | B5: 总图编号 | C5: 费用名称 | D5: 建筑面积m2 | F5: 建筑工程费 | G5: 设备工程 | I5: 安装 工程 | J5: 其他 费用 | K5: 总计 | L5: 其中 外汇
D6: 新建 | E6: 改造 | G6: 公用设备 | H6: 工艺设备
C7: 第一部分：工程费用项目
A8: 一 | C8: 水工设施
A9: 1 | C9: 横向下水滑道(110m×195.2) | D9: 0 | F9: 23865 | K9: =SUM(F9:J9) -> 23865
A10: 2 | C10: 横移区 | D10: （40000） | F10: =-D10*0.11 -> 4400 | K10: =SUM(F10:J10) -> 4400
A11: 3 | C11: 水面产品室内船台（双柳基地） | D11: 13824 | F11: 8985.6 | G11: 898.56 | H11: =设备!H15 -> 2540 | I11: 130 | K11: =SUM(F11:J11) -> 12554.16
A12: 4 | C12: 水面产品室内船台及港口设施（海西湾基地） | D12: =240*48*2 -> 23040 | F12: =D12*0.8 -> 18432 | G12: =F12*0.1 -> 1843.2 | H12: =设备!H24 -> 23840 | I12: =H12*0.08 -> 1907.2 | K12: =SUM(F12:J12) -> 46022.4
A13: 5 | C13: 舾装码头（2个） | F13: =1050*2 -> 2100 | G13: 200 | H13: =设备!H31 -> 9032 | I13: 47 | K13: =SUM(F13:J13) -> 11379
C14: 小 计 | D14: =SUM(D9:D13) -> 36864 | E14: =SUM(E9:E11) -> 0 | F14: =SUM(F9:F13) -> 57782.6 | G14: =SUM(G9:G13) -> 2941.76 | H14: =SUM(H9:H13) -> 35412 | I14: =SUM(I9:I13) -> 2084.2 | J14: =SUM(J9:J13) -> 0 | K14: =SUM(K9:K13) -> 98220.56
A16: 二 | C16: 生产性建设项目
A17: 1 | C17: 武昌总部技改项目 | D17: 0 | H17: =设备!H54 -> 4440 | I17: =H17*0.06 -> 266.4 | K17: =SUM(F17:J17) -> 4706.4
A18: 2 | C18: 水下产品联合生产厂房 | D18: =SUM(D19:D28) -> 133920 | E18: =SUM(E19:E28) -> 0 | F18: =SUM(F19:F28) -> 44323.2 | G18: =SUM(G19:G28) -> 4432.32 | H18: =SUM(H19:H28) -> 50993.2 | I18: =SUM(I19:I28) -> 3059.592 | J18: =SUM(J19:J28) -> 0 | K18: =SUM(K19:K28) -> 102808.31
A19: 2.1 | C19: 预处理车间 | D19: =180*36 -> 6480 | F19: =D19*0.2 -> 1296 | G19: =F19*0.1 -> 129.6 | H19: =设备!H62 -> 743 | I19: =H19*0.06 -> 44.58 | K19: =SUM(F19:J19) -> 2213.18
A20: 2.2 | C20: 理料间 | D20: =180*36 -> 6480 | F20: =D20*0.2 -> 1296 | G20: =F20*0.1 -> 129.6 | H20: =设备!H70 -> 970 | I20: =H20*0.06 -> 58.2 | K20: =SUM(F20:J20) -> 2453.8
A21: 2.3 | C21: 肋骨制造车间 | D21: =144*36 -> 5184 | F21: =D21*0.2 -> 1036.8 | G21: =F21*0.1 -> 103.68 | H21: =设备!H84 -> 3015 | I21: =H21*0.06 -> 180.9 | K21: =SUM(F21:J21) -> 4336.38
A22: 2.4 | C22: 壳圈制造车间 | D22: =216*36*2 -> 15552 | F22: =D22*0.25 -> 3888 | G22: =F22*0.1 -> 388.8 | H22: =设备!H105 -> 10735 | I22: =H22*0.06 -> 644.1 | K22: =SUM(F22:J22) -> 15655.9
A23: 2.5 | C23: 耐压下料车间 | D23: =144*36 -> 5184 | F23: =D23*0.25 -> 1296 | G23: =F23*0.1 -> 129.6 | H23: =设备!H121 -> 4310 | I23: =H23*0.06 -> 258.6 | K23: =SUM(F23:J23) -> 5994.2
A24: 2.6 | C24: 非耐压下料车间 | D24: =144*36 -> 5184 | F24: =D24*0.2 -> 1036.8 | G24: =F24*0.1 -> 103.68 | H24: =设备!H136 -> 2338 | I24: =H24*0.06 -> 140.28 | K24: =SUM(F24:J24) -> 3618.76
A25: 2.7 | C25: 立装车间 | D25: =192*36*2 -> 13824 | F25: =D25*0.45 -> 6220.8 | G25: =F25*0.1 -> 622.08 | H25: =设备!H163 -> 11735.2 | I25: =H25*0.06 -> 704.112 | K25: =SUM(F25:J25) -> 19282.192
A26: 2.8 | C26: 非耐压结构件制造车间 | D26: =600*36*2 -> 43200 | F26: =D26*0.25 -> 10800 | G26: =F26*0.1 -> 1080 | H26: =设备!H180 -> 4715 | I26: =H26*0.06 -> 282.9 | K26: =SUM(F26:J26) -> 16877.9
A27: 2.9 | C27: 总段泵水车间 | D27: =168*36*2 -> 12096 | F27: =D27*0.5 -> 6048 | G27: =F27*0.1 -> 604.8 | H27: =设备!H191 -> 4866 | I27: =H27*0.06 -> 291.96 | K27: =SUM(F27:J27) -> 11810.76
A28: 2.1 | C28: 船台总装车间 | D28: =288*36*2 -> 20736 | F28: =D28*0.55 -> 11404.8 | G28: =F28*0.1 -> 1140.48 | H28: =设备!H202 -> 7566 | I28: =H28*0.06 -> 453.96 | K28: =SUM(F28:J28) -> 20565.24
A29: 3 | C29: 消声瓦联合生产厂房 | D29: =SUM(D30:D32) -> 17550 | E29: =SUM(E30:E32) -> 0 | F29: =SUM(F30:F32) -> 2826 | G29: =SUM(G30:G32) -> 282.6 | H29: =SUM(H30:H32) -> 2678.6 | I29: =SUM(I30:I32) -> 160.716 | J29: =SUM(J30:J32) -> 0 | K29: =SUM(K30:K32) -> 5947.916
A30: 3.1 | C30: 装料车间 | D30: =120*21 -> 2520 | F30: =D30*0.2 -> 504 | G30: =F30*0.1 -> 50.4 | H30: =设备!H209 -> 240 | I30: =H30*0.06 -> 14.4 | K30: =SUM(F30:J30) -> 808.8
A31: 3.2 | C31: 消声瓦敷设间 | D31: =120*(21+12+21) -> 6480 | F31: =D31*0.2 -> 1296 | G31: =F31*0.1 -> 129.6 | H31: =设备!H227 -> 1959 | I31: =H31*0.06 -> 117.54 | K31: =SUM(F31:J31) -> 3502.14
A32: 3.3 | C32: 消声瓦制造车间 | D32: =114*75 -> 8550 | F32: =D32*0.12 -> 1026 | G32: =F32*0.1 -> 102.6 | H32: =设备!H249 -> 479.6 | I32: =H32*0.06 -> 28.776 | K32: =SUM(F32:J32) -> 1636.976
A33: 4 | C33: 舾装中心 | D33: =SUM(D34:D40) -> 41904 | E33: =SUM(E34:E40) -> 0 | F33: =SUM(F34:F42) -> 17704.8 | G33: =SUM(G34:G42) -> 1770.48 | H33: =SUM(H34:H42) -> 6851 | I33: =SUM(I34:I42) -> 411.06 | K33: =SUM(K34:K42) -> 26737.34
A34: 4.1 | C34: 管装车间 | D34: =204*30 -> 6120 | F34: =D34*0.25 -> 1530 | G34: =F34*0.1 -> 153 | H34: =设备!H269 -> 941 | I34: =H34*0.06 -> 56.46 | K34: =SUM(F34:J34) -> 2680.46
A35: 4.2 | C35: 机装车间 | D35: =204*36 -> 7344 | F35: =D35*0.35 -> 2570.4 | G35: =F35*0.1 -> 257.04 | H35: =设备!H278 -> 1505 | I35: =H35*0.06 -> 90.3 | K35: =SUM(F35:J35) -> 4422.74
A36: 4.3 | C36: 单元模块制造车间 | D36: =312*36 -> 11232 | F36: =D36*0.35 -> 3931.2 | G36: =F36*0.1 -> 393.12 | H36: =设备!H282 -> 440 | I36: =H36*0.06 -> 26.4 | K36: =SUM(F36:J36) -> 4790.72
A37: 4.4 | C37: 电装调试制造间 | D37: =108*36 -> 3888 | F37: =D37*0.25 -> 972 | G37: =F37*0.1 -> 97.2 | H37: =设备!H286 -> 170 | I37: =H37*0.06 -> 10.2 | K37: =SUM(F37:J37) -> 1249.4
A38: 4.5 | C38: 蓄电池车间 | D38: =108*24 -> 2592 | F38: =D38*0.25 -> 648 | G38: =F38*0.1 -> 64.8 | H38: =设备!H295 -> 1270 | I38: =H38*0.06 -> 76.2 | K38: =SUM(F38:J38) -> 2059
A39: 4.6 | C39: 核级管路制造车间 | D39: =108*30 -> 3240 | F39: =D39*0.25 -> 810 | G39: =F39*0.1 -> 81 | H39: =设备!H310 -> 1755 | I39: =H39*0.06 -> 105.3 | K39: =SUM(F39:J39) -> 2751.3
A40: 4.7 | C40: 陆上联调中心 | D40: =312*24 -> 7488 | F40: =D40*0.25 -> 1872 | G40: =F40*0.1 -> 187.2 | H40: =设备!H315 -> 770 | I40: =H40*0.06 -> 46.2 | K40: =SUM(F40:J40) -> 2875.4
A41: 4.8 | C41: **车间 | D41: =204*24 -> 4896 | F41: =D41*0.25 -> 1224 | G41: =F41*0.1 -> 122.4 | K41: =SUM(F41:J41) -> 1346.4
A42: 4.9 | C42: 生产辅楼 | D42: =96*12*3*4 -> 13824 | F42: =D42*0.3 -> 4147.2 | G42: =F42*0.1 -> 414.72 | K42: =SUM(F42:J42) -> 4561.92
A43: 5 | C43: 水面产品分段制造厂房 | D43: =SUM(D44:D47) -> 75168 | E43: =SUM(E44:E47) -> 0 | F43: =SUM(F44:F47) -> 20217.6 | G43: =SUM(G44:G47) -> 2021.76 | H43: =SUM(H44:H47) -> 11998 | I43: =SUM(I44:I47) -> 719.88 | J43: =SUM(J44:J47) -> 0 | K43: =SUM(K44:K47) -> 34957.24
A44: 5.1 | C44: 板材下料加工车间 | D44: =144*36*2 -> 10368 | F44: =D44*0.2 -> 2073.6 | G44: =F44*0.1 -> 207.36 | H44: =设备!H330 -> 2788 | I44: =H44*0.06 -> 167.28 | K44: =SUM(F44:J44) -> 5236.24
A45: 5.2 | C45: 部件装焊车间 | D45: =180*36*2 -> 12960 | F45: =D45*0.25 -> 3240 | G45: =F45*0.1 -> 324 | H45: =设备!H336 -> 880 | I45: =H45*0.06 -> 52.8 | K45: =SUM(F45:J45) -> 4496.8
A46: 5.3 | C46: 自动生产线车间 | D46: =600*36 -> 21600 | F46: =D46*0.2 -> 4320 | G46: =F46*0.1 -> 432 | H46: =设备!H344 -> 6980 | I46: =H46*0.06 -> 418.8 | K46: =SUM(F46:J46) -> 12150.8
A47: 5.4 | C47: 分段装焊车间 | D47: =420*36*2 -> 30240 | F47: =D47*0.35 -> 10584 | G47: =F47*0.1 -> 1058.4 | H47: =设备!H350 -> 1350 | I47: =H47*0.06 -> 81 | K47: =SUM(F47:J47) -> 13073.4
A48: 6 | C48: 涂装工场（2喷4涂） | D48: 11130 | F48: 3300 | G48: 300 | H48: =设备!H391 -> 2954.7 | I48: 25 | K48: =SUM(F48:J48) -> 6579.7
A49: 7 | C49: 分段堆场及预舾装场地 | D49: （46605） | F49: =46605*0.0404 -> 1882.842 | G49: =300/74*22 -> 89.189189 | H49: =设备!H400 -> 1292 | I49: =H49*0.06 -> 77.52 | K49: =SUM(F49:J49) -> 3341.5512
A50: 8 | C50: 管子加工车间(24m×3跨) | D50: 19868.6 | F50: 4967.15 | G50: 367.7 | H50: =设备!H469 -> 2221.0039 | I50: =H50*0.06 -> 133.26023 | K50: =SUM(F50:J50) -> 7689.1141
A51: 9 | C51: 集配库及生产辅楼 | D51: 39400 | F51: =D51*0.21 -> 8274 | G51: 546 | H51: =设备!H480 -> 526 | I51: =H51*0.06 -> 31.56 | K51: =SUM(F51:J51) -> 9377.56
A52: 10 | C52: 内舾装及复合材料加工区 | D52: =240*30*2 -> 14400 | F52: =D52/10000*2000 -> 2880 | G52: =F52*0.1 -> 288 | H52: =设备!H521 -> 301 | I52: =H52*0.1 -> 30.1 | K52: =SUM(F52:J52) -> 3499.1
A53: 11 | C53: 机加中心 | D53: =SUM(D54:D58) -> 61560 | E53: =SUM(E54:E58) -> 0 | F53: =SUM(F54:F58) -> 16380 | G53: =SUM(G54:G58) -> 1638 | H53: =SUM(H54:H58) -> 25908 | I53: =SUM(I54:I58) -> 1554.48 | J53: =SUM(J54:J58) -> 0 | K53: =SUM(K54:K58) -> 45480.48
A54: 11.1 | C54: 钛合金加工中心 | D54: 10920 | F54: =D54/10000*2000 -> 2184 | G54: =F54*0.1 -> 218.4 | H54: =设备!H530 -> 17500 | I54: =H54*0.06 -> 1050 | K54: =SUM(F54:J54) -> 20952.4
A55: 11.2 | C55: 中小件加工区（A区） | D55: 9960 | F55: 2490 | G55: =F55*0.1 -> 249 | H55: =设备!H546 -> 1262 | I55: =H55*0.06 -> 75.72 | K55: =SUM(F55:J55) -> 4076.72
A56: 11.3 | C56: 中小件加工区（B区） | D56: 9960 | F56: 2490 | G56: =F56*0.1 -> 249 | H56: =设备!H575 -> 3528 | I56: =H56*0.06 -> 211.68 | K56: =SUM(F56:J56) -> 6478.68
A57: 11.4 | C57: 重型结构加工区（A区） | D57: 15360 | F57: 4608 | G57: =F57*0.1 -> 460.8 | H57: =设备!H598 -> 2251 | I57: =H57*0.06 -> 135.06 | K57: =SUM(F57:J57) -> 7454.86
A58: 11.5 | C58: 重型结构加工区（B区） | D58: 15360 | F58: 4608 | G58: =F58*0.1 -> 460.8 | H58: =设备!H616 -> 1367 | I58: =H58*0.06 -> 82.02 | K58: =SUM(F58:J58) -> 6517.82
C59: 小 计 | D59: =D17+D18+D29+D33+D43+D48+D49+D50+D51+D52+D53 -> 368295.6 | E59: =E17+E18+E29+E33+E43+E48+E49+E50+E51+E52+E53 -> 0 | F59: =F17+F18+F29+F33+F43+F48+F49+F50+F51+F52+F53 -> 122755.59 | G59: =G17+G18+G29+G33+G43+G48+G49+G50+G51+G52+G53 -> 11736.049 | H59: =H17+H18+H29+H33+H43+H48+H49+H50+H51+H52+H53 -> 110163.5 | I59: =I17+I18+I29+I33+I43+I48+I49+I50+I51+I52+I53 -> 6469.5682 | J59: =J17+J18+J29+J33+J43+J48+J49+J50+J51+J52+J53 -> 0 | K59: =K17+K18+K29+K33+K43+K48+K49+K50+K51+K52+K53 -> 251124.71
A61: 三 | C61: 辅助性建设项目
A62: 1 | C62: 备班楼 | D62: =16509 -> 16509 | F62: =D62/10000*2000 -> 3301.8 | G62: =F62*0.15 -> 495.27 | H62: =设备!H627 -> 24 | I62: =H62*0.1 -> 2.4 | K62: =SUM(F62:J62) -> 3823.47
A63: 2 | C63: 核应急中心 | D63: =18*45 -> 810 | F63: =D63/10000*2200 -> 178.2 | G63: =F63*0.1 -> 17.82 | H63: =设备!H636 -> 6330 | I63: =H63*0.1 -> 633 | K63: =SUM(F63:J63) -> 7159.02
A64: 3 | C64: 反应堆预装车间 | D64: =21*90+63*9*2 -> 3024 | F64: =D64/10000*3000 -> 907.2 | G64: =F64*0.1 -> 90.72 | H64: =设备!H645 -> 800 | I64: =H64*0.1 -> 80 | K64: =SUM(F64:J64) -> 1877.92
A65: 4 | C65: 核燃料库 | D65: =27*9 -> 243 | F65: =D65/10000*2000 -> 48.6 | G65: =F65*0.1 -> 4.86 | H65: =设备!H653 -> 180 | I65: =H65*0.1 -> 18 | K65: =SUM(F65:J65) -> 251.46
A66: 5 | C66: 核废弃物处置库 | D66: =18*45 -> 810 | F66: =D66/10000*2000 -> 162 | G66: =F66*0.1 -> 16.2 | H66: =设备!H658 -> 50 | K66: =SUM(F66:J66) -> 228.2
A67: 6 | C67: 现场办公楼 | D67: 12960 | F67: 3628.8 | G67: 362.88 | H67: 0 | K67: =SUM(F67:J67) -> 3991.68
A68: 7 | C68: 信息化工程 | F68: 0 | H68: =设备!H731 -> 4509.6 | I68: =H68*0.1 -> 450.96 | K68: =SUM(F68:J68) -> 4960.56
C69: 小 计 | D69: =SUM(D62:D68) -> 34356 | E69: =SUM(E62:E68) -> 0 | F69: =SUM(F62:F68) -> 8226.6 | G69: =SUM(G62:G68) -> 987.75 | H69: =SUM(H62:H68) -> 11893.6 | I69: =SUM(I62:I68) -> 1184.36 | J69: =SUM(J62:J68) -> 0 | K69: =SUM(K62:K68) -> 22292.31
A71: 四 | C71: 公用动力设施
A72: 1 | C72: 空压站 | D72: 1586 | F72: 475.8 | G72: 47.58 | H72: =设备!H741 -> 360 | I72: 18.85 | K72: =SUM(F72:J72) -> 902.23
A73: 2 | C73: 蒸汽锅炉房 | D73: 80 | F73: 26 | G73: 4 | H73: =设备!H746 -> 280 | I73: 6 | K73: =SUM(F73:J73) -> 316
C74: 小 计 | D74: =SUM(D72:D73) -> 1666 | E74: =SUM(E72:E73) -> 0 | F74: =SUM(F72:F73) -> 501.8 | G74: =SUM(G72:G73) -> 51.58 | H74: =SUM(H72:H73) -> 640 | I74: =SUM(I72:I73) -> 24.85 | J74: =SUM(J72:J73) -> 0 | K74: =SUM(K72:K73) -> 1218.23
A76: 五 | C76: 总图及室外工程
A77: 1 | C77: 道路 | D77: （80000） | F77: =-D77*0.027 -> 2160 | K77: =SUM(F77:J77) -> 2160
A78: 2 | C78: 绿化 | D78: （30000） | F78: =-D78*0.006 -> 180 | K78: =SUM(F78:J78) -> 180
A79: 3 | C79: 围墙 | F79: 300 | K79: =SUM(F79:J79) -> 300
A80: 4 | C80: 室外电气管网 | F80: 500 | K80: =SUM(F80:J80) -> 500
A81: 5 | C81: 室外排水管网 | F81: 200 | K81: =SUM(F81:J81) -> 200
A82: 6 | C82: 室外暖通动力管网 | F82: 1300 | K82: =SUM(F82:J82) -> 1300
C83: 小 计 | D83: =SUM(D77:D82) -> 0 | E83: =SUM(E77:E82) -> 0 | F83: =SUM(F77:F82) -> 4640 | G83: =SUM(G77:G82) -> 0 | H83: =SUM(H77:H82) -> 0 | I83: =SUM(I77:I82) -> 0 | J83: =SUM(J77:J82) -> 0 | K83: =SUM(K77:K82) -> 4640
C85: 第一部分合计 | D85: =D83+D74+D69+D59+D14 -> 441181.6 | E85: =E83+E74+E69+E59+E14 -> 0 | F85: =F83+F74+F69+F59+F14 -> 193906.59 | G85: =G83+G74+G69+G59+G14 -> 15717.139 | H85: =H83+H74+H69+H59+H14 -> 158109.1 | I85: =I83+I74+I69+I59+I14 -> 9762.9782 | J85: =J83+J74+J69+J59+J14 -> 0 | K85: =K83+K74+K69+K59+K14 -> 377495.81
C87: 第二部分：其他费用
A88: 1 | C88: 建设单位管理费 | J88: =(433+(69110-50000)*0.5%) -> 528.55 | K88: =J88 -> 528.55
A89: 2 | C89: 前期工作费 | J89: =139+(69110-50000)*(200-139)/(100000-50000) -> 162.3142 | K89: =J89 -> 162.3142
A90: 3 | C90: 工程设计费 | J90: =(1054+(K85-40000)*(1515.2-1054)/(60000-40000))*35%*1.15*1.25 -> 4445.9413 | K90: =J90 -> 4445.9413
A91: 4 | C91: 招标代理服务费 | J91: 45 | K91: =J91 -> 45
A92: 5 | C92: 环境评价收费 | J92: 40 | K92: =J92 -> 40
A93: 6 | C93: 劳动安全评价费 | J93: 18 | K93: =J93 -> 18
A94: 7 | C94: 职业卫生评价费 | J94: 18 | K94: =J94 -> 18
C96: 第二部分合计 | J96: =SUM(J88:J95) -> 5257.8055 | K96: =SUM(K88:K95) -> 5257.8055
C98: 第一、二部分合计 | D98: =D96+D85 -> 441181.6 | E98: =E96+E85 -> 0 | F98: =F96+F85 -> 193906.59 | G98: =G96+G85 -> 15717.139 | H98: =H96+H85 -> 158109.1 | I98: =I96+I85 -> 9762.9782 | J98: =J96+J85 -> 5257.8055 | K98: =K96+K85 -> 382753.62
C100: 第三部分：基本预备费(6%) | J100: =K98*6% -> 22965.217 | K100: =J100 -> 22965.217
C102: 第一、二、三部分合计 | D102: =D100+D98 -> 441181.6 | E102: =E100+E98 -> 0 | F102: =F100+F98 -> 193906.59 | G102: =G100+G98 -> 15717.139 | H102: =H100+H98 -> 158109.1 | I102: =I100+I98 -> 9762.9782 | J102: =J100+J98 -> 28223.023 | K102: =K100+K98 -> 405718.84
C104: 项目建设总投资 | D104: =D102 -> 441181.6 | E104: =E102 -> 0 | F104: =F102 -> 193906.59 | G104: =G102 -> 15717.139 | H104: =H102 -> 158109.1 | I104: =I102 -> 9762.9782 | J104: =J102 -> 28223.023 | K104: =K102 -> 405718.84
J109: =K104-K12 -> 359696.44

Sheet 设备
A2: 新 增 工 艺 设 备 表
A3: 项目名称：XXXXXX建设项目 | G3: 单位：万元、万美元
A4: 序号 | B4: 设 备 名 称 | C4: 主要技术（性能）指标 | D4: 国别 | E4: 单位 | F4: 数量 | G4: 设 备 价 格 | J4: 招标情况 | K4: 备注
G5: 单价 | H5: 合计 | I5: 其中外汇
A6: =投资估算表!A8 -> 一 | B6: =投资估算表!C8 -> 水工设施
A7: （一） | B7: 横向下水滑道
A9: （二） | B9: 横移区
A11: （三） | B11: =投资估算表!C11 -> 水面产品室内船台（双柳基地）
A12: 1 | B12: 各类焊机 | C12: 500~1000A | D12: 国产 | E12: 台 | F12: 200 | G12: 1.2 | H12: =F12*G12 -> 240
A13: 2 | B13: 桥式起重机 | C13: Gn＝150t/75t，S=46.5m，H=32m | D13: 国产 | E13: 台 | F13: 2 | G13: 650 | H13: =F13*G13 -> 1300
A14: 3 | B14: 桥式起重机 | C14: Gn＝100t/20t，S=46.5m，H=32m | D14: 国产 | E14: 台 | F14: 2 | G14: 500 | H14: =F14*G14 -> 1000
B15: 合 计 | F15: =SUM(F12:F14) -> 204 | H15: =SUM(H12:H14) -> 2540
A17: （四） | B17: =投资估算表!C12 -> 水面产品室内船台及港口设施（海西湾基地）
A18: 1 | B18: 各类焊机 | C18: 500~1000A | D18: 国产 | E18: 台 | F18: 200 | G18: 1.2 | H18: =F18*G18 -> 240
A19: 2 | B19: 桥式起重机 | C19: Gn＝200t/100t，S=46.5m，H=49m | D19: 国产 | E19: 台 | F19: 2 | G19: 800 | H19: =F19*G19 -> 1600
A20: 3 | B20: 桥式起重机 | C20: Gn＝200t/50t，S=46.5m，H=49m | D20: 国产 | E20: 台 | F20: 2 | G20: 750 | H20: =F20*G20 -> 1500
A21: 4 | B21: 门座吊 | C21: Gn＝100t | D21: 国产 | E21: 台 | F21: 1 | G21: 900 | H21: =F21*G21 -> 900
A22: 5 | B22: 港作拖轮 | C22: 5000HP | D22: 国产 | E22: 台 | F22: 2 | G22: 4900 | H22: =F22*G22 -> 9800
A23: 6 | B23: 液压模块运输车 | D23: 国产 | E23: 轴线 | F23: 280 | G23: 35 | H23: =F23*G23 -> 9800
B24: 合 计 | F24: =SUM(F18:F23) -> 487 | H24: =SUM(H18:H23) -> 23840
A26: （五） | B26: =投资估算表!C13 -> 舾装码头（2个）
A27: 1 | B27: 趸船 | C27: 120m | D27: 国产 | E27: 艘 | F27: 2 | G27: 2100 | H27: =F27*G27 -> 4200
A28: 2 | B28: 趸船 | C28: 90m | D28: 国产 | E28: 艘 | F28: 2 | G28: 1900 | H28: =F28*G28 -> 3800
A29: 3 | B29: 塔式起重机 | C29: D8039 | D29: 国产 | E29: 台 | F29: 4 | G29: 238 | H29: =F29*G29 -> 952
A30: 4 | B30: 卷扬提升系统 | D30: 国产 | E30: 套 | F30: 2 | G30: 40 | H30: =F30*G30 -> 80
B31: 合 计 | F31: =SUM(F27:F30) -> 10 | H31: =SUM(H27:H30) -> 9032
B33: 总 计 | F33: =F15+F24+F31 -> 701 | H33: =H15+H24+H31 -> 35412
A35: =投资估算表!A16 -> 二 | B35: =投资估算表!C16 -> 生产性建设项目
A36: （一） | B36: =投资估算表!C17 -> 武昌总部技改项目
A37: 1 | B37: 液压升降装置 | D37: 国产 | E37: 台 | F37: 1 | G37: 300 | H37: =F37*G37 -> 300
A38: 2 | B38: 工装液氧储罐 | C38: 20m3 | D38: 国产 | E38: 台 | F38: 1 | G38: 150 | H38: =F38*G38 -> 150
A39: 3 | B39: 工装液氧储罐 | C39: 30m3 | D39: 国产 | E39: 台 | F39: 1 | G39: 200 | H39: =F39*G39 -> 200
A40: 4 | B40: 隔振元件机械阻抗检测设备 | D40: 国产 | E40: 台 | F40: 1 | G40: 600 | H40: =F40*G40 -> 600
A41: 5 | B41: 橡胶减振器蠕变测量设备 | D41: 国产 | E41: 台 | F41: 1 | G41: 480 | H41: =F41*G41 -> 480
A42: 6 | B42: 轴系低噪声安装工艺试验台架 | C42: 补充建设 | D42: 国产 | E42: 台 | F42: 1 | G42: 700 | H42: =F42*G42 -> 700
A43: 7 | B43: 预处理设备 | D43: 国产 | E43: 台 | F43: 1 | G43: 300 | H43: =F43*G43 -> 300
A44: 8 | B44: 七星棍床 | C44: 宽4m，辊5mm～16mm | D44: 国产 | E44: 台 | F44: 1 | G44: 100 | H44: =F44*G44 -> 100
A45: 9 | B45: 十一辊校平机 | C45: 宽4m，辊5mm～16mm | D45: 国产 | E45: 台 | F45: 1 | G45: 190 | H45: =F45*G45 -> 190
A46: 10 | B46: 数控肋骨冷弯机床 | D46: 国产 | E46: 台 | F46: 1 | G46: 90 | H46: =F46*G46 -> 90
A47: 11 | B47: 数控火焰等离子切割机 | C47: 有效宽度5m，有效长度30m，最大切割厚度50mm | D47: 国产 | E47: 台 | F47: 2 | G47: 150 | H47: =F47*G47 -> 300
A48: 12 | B48: 活动式液压清洗站 | D48: 国产 | E48: 台 | F48: 1 | G48: 70 | H48: =F48*G48 -> 70
A49: 13 | B49: 活动式滑油清洗站 | C49: 20m3 | D49: 国产 | E49: 台 | F49: 1 | G49: 90 | H49: =F49*G49 -> 90
A50: 14 | B50: 活动式蒸馏水站 | C50: 30m3 | D50: 国产 | E50: 台 | F50: 1 | G50: 50 | H50: =F50*G50 -> 50
A51: 15 | B51: 活动式高压空压站 | D51: 国产 | E51: 台 | F51: 1 | G51: 90 | H51: =F51*G51 -> 90
A52: 16 | B52: 活动式充放电站 | D52: 国产 | E52: 台 | F52: 1 | G52: 160 | H52: =F52*G52 -> 160
A53: 17 | B53: 管子自动焊接专机 | C53: 补充建设 | D53: 国产 | E53: 台 | F53: 6 | G53: 95 | H53: =F53*G53 -> 570
B54: 合 计 | F54: =SUM(F37:F53) -> 23 | H54: =SUM(H37:H53) -> 4440
A56: （二） | B56: =投资估算表!C18 -> 水下产品联合生产厂房
A57: 1 | B57: =投资估算表!C19 -> 预处理车间
A58: 1.1 | B58: 七辊校平机 | C58: 宽4m，辊5mm～16mm | D58: 国产 | E58: 台 | F58: 1 | G58: 210 | H58: =F58*G58 -> 210
A59: 1.2 | B59: 预处理线 | C59: B=4m，V=5/3m/min | D59: 国产 | E59: 台 | F59: 1 | G59: 288 | H59: =F59*G59 -> 288
A60: 1.3 | B60: 桥式起重机 | C60: Gn=5t，S=19.5m,H=9m | D60: 国产 | E60: 台 | F60: 1 | G60: 25 | H60: =F60*G60 -> 25
A61: 1.4 | B61: 桥式起重机 | C61: Gn=20/5t，S=34.5m,H=9m | D61: 国产 | E61: 台 | F61: 2 | G61: 110 | H61: =F61*G61 -> 220
B62: 小 计 | F62: =SUM(F58:F61) -> 5 | H62: =SUM(H58:H61) -> 743
A64: 2 | B64: =投资估算表!C20 -> 理料间
A65: 2.1 | B65: 十一辊校平机 | C65: 宽4m，辊5mm～16mm | D65: 国产 | E65: 台 | F65: 1 | G65: 240 | H65: 240
A66: 2.2 | B66: 十三辊校平机 | C66: 宽4m，辊3mm～8mm | D66: 国产 | E66: 台 | F66: 1 | G66: 320 | H66: 320
A67: 2.3 | B67: 低压电动平板车 | C67: 10t | D67: 国产 | E67: 台 | F67: 5 | G67: 10 | H67: =F67*G67 -> 50
A68: 2.4 | B68: 低压电动平板车 | C68: 20t | D68: 国产 | E68: 台 | F68: 1 | G68: 15 | H68: =F68*G68 -> 15
A69: 2.5 | B69: 桥式起重机 | C69: Gn=20/5t，S=34.5m,H=9m | D69: 国产 | E69: 台 | F69: 3 | G69: 115 | H69: =F69*G69 -> 345
B70: 小 计 | F70: =SUM(F65:F69) -> 11 | H70: =SUM(H65:H69) -> 970
A72: 3 | B72: =投资估算表!C21 -> 肋骨制造车间
A73: 3.1 | B73: 热处理设备（预热炉及后热炉） | C73: 温控0~300℃ | D73: 国产 | E73: 套 | F73: 1 | G73: 400 | H73: =F73*G73 -> 400
A74: 3.2 | B74: 喉式油压机 | C74: 500t | D74: 国产 | E74: 台 | F74: 1 | G74: 150 | H74: =F74*G74 -> 150
A75: 3.3 | B75: 冷弯机 | C75: 800t | D75: 国产 | E75: 台 | F75: 1 | G75: 600 | H75: =F75*G75 -> 600
A76: 3.4 | B76: 数控立车 | C76: 加工直径10米 | D76: 国产 | E76: 台 | F76: 1 | G76: 1200 | H76: =F76*G76 -> 1200
A77: 3.5 | B77: 肋骨自动焊接系统 | C77: 直径6~8m，高2.5m以内筒体内、外肋骨焊接 | D77: 国产 | E77: 套 | F77: 2 | G77: 120 | H77: =F77*G77 -> 240
A78: 3.6 | B78: 肋骨自动装配胎架 | C78: φ10m | D78: 国产 | E78: 台 | F78: 1 | G78: 50 | H78: =F78*G78 -> 50
A79: 3.7 | B79: 肋骨焊接装夹平台 | C79: φ10m | D79: 国产 | E79: 台 | F79: 4 | G79: 20 | H79: =F79*G79 -> 80
A80: 3.8 | B80: 肋骨对接装配平台 | C80: φ10m | D80: 国产 | E80: 台 | F80: 2 | G80: 20 | H80: =F80*G80 -> 40
A81: 3.9 | B81: 肋骨气刨吸尘平台（带除尘设施） | D81: 国产 | E81: 套 | F81: 1 | G81: 60 | H81: =F81*G81 -> 60
A82: 3.10 | B82: 桥式起重机 | C82: Gn＝16t/3.2t，S=34.5m，H=12m | D82: 国产 | E82: 台 | F82: 2 | G82: 90 | H82: =F82*G82 -> 180
A83: 3.11 | B83: 低压电动平板车 | C83: 20t | D83: 国产 | E83: 台 | F83: 1 | G83: 15 | H83: =F83*G83 -> 15
B84: 小 计 | F84: =SUM(F73:F83) -> 17 | H84: =SUM(H73:H83) -> 3015
A86: 4 | B86: =投资估算表!C22 -> 壳圈制造车间
A87: 4.1 | B87: 壳圈装配平台 | C87: φ10m | D87: 国产 | E87: 套 | F87: 4 | G87: 30 | H87: =F87*G87 -> 120
A88: 4.2 | B88: 壳圈立式装配机 | D88: 国产 | E88: 台 | F88: 2 | G88: 55 | H88: =F88*G88 -> 110
A89: 4.3 | B89: 焊缝坡口加工机 | D89: 国产 | E89: 台 | F89: 2 | G89: 100 | H89: =F89*G89 -> 200
A90: 4.4 | B90: 肋骨壳圈自动装焊系统 | C90: φ10m | D90: 国产 | E90: 套 | F90: 4 | G90: 180 | H90: =F90*G90 -> 720
A91: 4.5 | B91: 加热控制箱 | C91: 0~1000℃，0~220V无极可调，控温精度≤1% | D91: 国产 | E91: 台 | F91: 5 | G91: 6 | H91: =F91*G91 -> 30
A92: 4.6 | B92: 摇摆胎架 | C92: 30t，直径0~9m | D92: 国产 | E92: 台 | F92: 2 | G92: 50 | H92: =F92*G92 -> 100
A93: 4.7 | B93: 悬臂焊机 | C93: 整机速度0.06~2.5m/min | D93: 国产 | E93: 台 | F93: 2 | G93: 80 | H93: =F93*G93 -> 160
A94: 4.8 | B94: 壳圈顶圆机 | C94: 400－500t | D94: 国产 | E94: 台 | F94: 1 | G94: 800 | H94: =F94*G94 -> 800
A95: 4.9 | B95: 壳圈检验平台 | C95: 4m*10m | D95: 国产 | E95: 套 | F95: 1 | G95: 50 | H95: =F95*G95 -> 50
A96: 4.10 | B96: 桥式起重机 | C96: Gn＝75t/20t，S=34.5m，H=20m | D96: 国产 | E96: 台 | F96: 2 | G96: 350 | H96: =F96*G96 -> 700
A97: 4.11 | B97: 低压电动平板车 | C97: 63t | D97: 国产 | E97: 台 | F97: 1 | G97: 45 | H97: =F97*G97 -> 45
A98: 4.12 | B98: 各类焊机 | D98: 国产 | E98: 台 | F98: 20 | G98: 3 | H98: =F98*G98 -> 60
A99: 4.13 | B99: 油压机 | C99: 10000t | D99: 国产 | E99: 台 | F99: 1 | G99: 6000 | H99: =F99*G99 -> 6000
A100: 4.14 | B100: 各类胎架 | D100: 国产 | E100: 套 | F100: 1 | G100: 70 | H100: =F100*G100 -> 70
A101: 4.15 | B101: 耐压零部件生产线 | D101: 国产 | E101: 套 | F101: 1 | G101: 350 | H101: =F101*G101 -> 350
A102: 4.16 | B102: 桥式起重机 | C102: Gn＝50t/10t，S=34.5m，H=20m | D102: 国产 | E102: 台 | F102: 2 | G102: 300 | H102: =F102*G102 -> 600
A103: 4.17 | B103: 桥式起重机 | C103: Gn＝50t/10t，S=28.5m，H=20m | D103: 国产 | E103: 台 | F103: 2 | G103: 280 | H103: =F103*G103 -> 560
A104: 4.18 | B104: 各类焊机 | D104: 国产 | E104: 台 | F104: 60 | G104: 1 | H104: =F104*G104 -> 60
B105: 小 计 | F105: =SUM(F87:F104) -> 113 | H105: =SUM(H87:H104) -> 10735
A107: 5 | B107: =投资估算表!C23 -> 耐压下料车间
A108: 5.1 | B108: 数控等离子水下切割机 | C108: 有效宽度5000mm，有效长度30000mm，最大切割厚度50mm，无级调速0～10000mm/min | D108: 国产 | E108: 台 | F108: 2 | G108: 130 | H108: =F108*G108 -> 260
A109: 5.2 | B109: 半自动火焰切割机 | D109: 国产 | E109: 台 | F109: 4 | G109: 4.5 | H109: =F109*G109 -> 18
A110: 5.3 | B110: 小蜜蜂数控切割机 | C110: 2.5m*1.2m | D110: 国产 | E110: 台 | F110: 1 | G110: 12 | H110: =F110*G110 -> 12
A111: 5.4 | B111: 数控铣边机 | C111: 铣边长度16m，宽度0.4~3m，厚度6~160mm，精度0.2mm。 | D111: 国产 | E111: 台 | F111: 1 | G111: 1000 | H111: =F111*G111 -> 1000
A112: 5.5 | B112: 坡口机 | D112: 国产 | E112: 台 | F112: 1 | G112: 200 | H112: =F112*G112 -> 200
...

Sheet 招标表
A1: 附表3
A2: 招标基本情况表
A3: =设备!A3 -> 项目名称：XXXXXX建设项目
B4: 招标范围 | D4: 招标组织形式 | F4: 招标方式 | H4: 不采用 招标方式 | I4: 说明
B5: 全部招标 | C5: 部分招标 | D5: 自行招标 | E5: 委托招标 | F5: 公开招标 | G5: 邀请招标
A6: 一、勘察 | H6: √ | I6: 单项合同低于50万元
A7: 二、设计 | H7: √ | I7: 涉及保密
A8: 三、建筑工程 | H8: √ | I8: 单项合同低于200万元
A9: 四、安装工程 | H9: √ | I9: 单项合同低于200万元
A10: 五、监理 | H10: √ | I10: 单项合同低于50万元
A11: 六、其他材料

Sheet Sheet2
B1: =1311.8*2+12740.6+24449.9+42777.9+42707.9 -> 125299.9
B2: =B1-124985.4 -> 314.5
G4: =42707.9-B2 -> 42393.4
G14: 1250.9 | H14: =G14*3 -> 3752.7
G15: 1934 | H15: =G15 -> 1934
I16: =22257.1-4407-5687 -> 12163.1
J20: =74606-28000 -> 46606
J21: =14900.6-10296 -> 4604.6
K22: =40373-10766.2-7441 -> 22165.8
