Workbook
Name aaaaa: #REF!
Name edline: #REF!
Name Print_Area1: #REF!
Name 图1: #REF!
Name 图2: [2]工程量屋面屋架柱!$A$1
Name 卧式旋铆机: #REF!
Name 装饰工程预算表: [3]装饰工程预算表!#REF!

Sheet Sheet1
A1: 附表1
A2: 投 资 估 算 表
A3: 项目名称：中国船舶重工集团公司重庆齿轮箱有限责任公司船舶与风力发电齿轮传动装置技术改造项目 单位：万元、万美元 | C3: 项目名称：中国船舶重工集团公司重庆齿轮箱有限责任公司船舶与风力发电齿轮传动装置技术改造项目 单位：万元、万美元
A4: 序号 | B4: 总图 编号 | D4: 费用名称 | E4: 建筑 面积 | F4: 建筑 工程 | G4: 设备工程费 | I4: 设备 安装费 | J4: 其它 费用 | K4: 总 计 | L4: 其中: 外汇 | M4: 投资 构成 | N4: 备 注
G5: 公用设备 | H5: 工艺设备
D6: 第一部分：工程费用名称
C7: 一 | D7: 生产性项目
C8: 1 | D8: 新增工艺设备
A9: 1 | C9: 1.1 | D9: 齿轮加工单元 | F9: 383.31 | H9: 13671.39 | I9: 383.31 | K9: 14438.01 | P9: 1305
A10: 2 | C10: 1.2 | D10: 箱体加工单元 | F10: 113.13 | H10: 4034.97 | I10: 113.13 | K10: 4261.23 | P10: 1385
A11: 3 | C11: 1.3 | D11: 装配单元 | F11: 21.5 | H11: 460.1 | I11: 10.75 | K11: 492.35 | P11: 1278
A12: 4 | C12: 1.4 | D12: 试验单元 | F12: 28.7 | H12: 1535.45 | I12: 28.7 | K12: 1592.85 | P12: 982
A13: 5 | C13: 1.5 | D13: 涂装及成品库房单元 | F13: 0.8 | H13: 85.6 | I13: 4 | K13: 90.4 | P13: 1072
C14: 1.6 | D14: 进口设备从属费 | F14: 0 | H14: 112.703 | I14: 0 | K14: 112.703 | P14: 130
D15: 小计 | F15: 547.44 | H15: 19900.213 | I15: 539.89 | K15: 20987.543 | L15: 685.22876 | O15: 20987.543
C17: 2 | D17: 土建工程
C18: 2.1 | D18: 装配、试验联合厂房 | E18: 16669.8 | F18: 3967.4124 | K18: 3967.4124
C19: 2.2 | D19: 齿轮、箱体加工联合厂房 | E19: 9903.6 | F19: 2347.1532 | K19: 2347.1532
C20: 2.3 | D20: 门卫 | E20: 100.8 | F20: 10.08 | K20: 10.08
C21: 2.4 | D21: 消防水池及泵房 | E21: -300 | F21: 24 | K21: 24
C22: 2.5 | D22: 降压站 | E22: -500 | F22: 25 | K22: 25
D23: 小 计 | E23: 26674.2 | F23: 6373.6456 | K23: 6373.6456 | O23: 6373.6456
C25: 二 | D25: 动力公用性项目
A26: 1 | C26: 1 | D26: 变配电系统 | G26: 775.75 | K26: 775.75
A27: 2 | C27: 2 | D27: 压缩空气系统 | G27: 85.6 | K27: 85.6
A28: 3 | C28: 3 | D28: 冷却水塔 | G28: 32.1 | K28: 32.1
A29: 4 | C29: 4 | D29: 中央空调系统及通风设备 | G29: 813.2 | K29: 813.2
C30: 5 | D30: 水泵房 | G30: 16.05 | K30: 16.05
D31: 小 计 | G31: =SUM(G26:G30) -> 1722.7 | K31: 1722.7
C33: 三 | D33: 总图设施性项目
C34: 1 | D34: 室外电缆 | F34: 100 | K34: 100
C35: 2 | D35: 室外给排水 | F35: 80 | K35: 80
C36: 3 | D36: 道路 | F36: 157.5 | K36: 157.5
C37: 4 | D37: 绿化 | F37: 60 | K37: 60
C38: 5 | D38: 围墙 | F38: 25 | K38: 25
C39: 6 | D39: 环保、劳动安全卫生及消防 | J39: 50 | K39: 50
D40: 小 计 | F40: 422.5 | J40: 50 | K40: 472.5
D41: 第 一 部 分 合 计 | E41: 26674.2 | F41: 7343.5856 | G41: 1722.7 | H41: 19900.213 | I41: 539.89 | J41: 50 | K41: 29556.389 | L41: 685.22876 | M41: 66.314529
D43: 第二部分 工程建设其他费用
A44: 1 | C44: 1 | D44: 建设单位管理费 | J44: 389.56 | K44: 389.56
A45: 2 | C45: 2 | D45: 前期工作费 | J45: 128.27575 | K45: 128.27575
A46: 4 | C46: 3 | D46: 设计费 | J46: 593.35033 | K46: 593.35033
A47: 5 | C47: 4 | D47: 勘察费 | J47: 32.00904 | K47: 32.00904
A48: 6 | C48: 5 | D48: 工程建设监理费 | J48: 178.66174 | K48: 178.66174
A49: 7 | C49: 6 | D49: 招标代理服务费 | J49: 39.273293 | K49: 39.273293
A50: 8 | C50: 7 | D50: 环境影响咨询费 | J50: 25.371 | K50: 25.371
C51: 8 | D51: 征地费 | J51: 1999.91 | K51: 1999.91
C52: 9 | D52: 培训费 | J52: 30 | K52: 30
C53: 10 | D53: 联合试运转费 | J53: 98.501065 | K53: 98.501065
D54: 第 二 部 分 合 计 | J54: 3514.9122 | K54: 3514.9122 | M54: 7.8862729
D56: 第一、二 部 分 合 计 | E56: 26674.2 | F56: 7343.5856 | G56: 1722.7 | H56: 19900.213 | I56: 539.89 | J56: 3564.9122 | K56: 33071.301 | L56: 0 | O56: 33071.301
D58: 第三部分、基本预备费（8%） | J58: 2648.7041 | K58: 2648.7041 | M58: 5.9427951
D60: 静态建设投资合计 第一、二、三 部 分 合 计 | E60: 26674.2 | F60: 7343.5856 | G60: 1722.7 | H60: 19900.213 | I60: 539.89 | J60: 6213.6163 | K60: 35720.005 | L60: 0 | O60: 35720.005
D62: 第四部分：动态投资
A64: 1 | D64: 综合预备费 | K64: 0
A65: 2 | D65: 固定资产投资方向调节税 | K65: 0
A66: 3 | C66: 1 | D66: 建设期贷款利息 | J66: 1200 | K66: 1200
C67: 2 | D67: 企业铺底流动资金 | J67: 7650 | K67: 7650
D68: 动态建设投资合计 | J68: 8850 | K68: 8850 | M68: 19.856403
D70: 工程项目总投资 | E70: 26674.2 | F70: 7343.5856 | G70: 1722.7 | H70: 19900.213 | I70: 539.89 | J70: 15063.616 | K70: 44570.005 | L70: 685.22876 | M70: 100 | O70: 44570.005
K72: -4570.0049
M73: 36920.005
J75: 原投资 | K75: 41960 | L75: 投资增加 | M75: 2610.0049
F76: 超投资 | G76: 1.1142501 | J76: 流金减少 | K76: -350

Sheet 工艺设备2 (2)
A1: 附表2
A2: 新增工艺设备表
A3: 项目名称：中船重工重庆齿轮箱有限责任公司船舶与风力发电齿轮传动装置生产线技术改造项目 单位：万元、万美元
A4: 序号 | B4: 设备名称 | C4: 主要性能指标 | D4: 规格型号 | E4: 国别与厂家 （供参考） | F4: 单位 | G4: 数量 | H4: 设备价格 | K4: 备注
H5: 单价 | I5: 总价 | J5: 其中外汇
A6: 一 | B6: 齿轮加工厂房
A7: （一） | B7: 磨齿机
A8: 1 | B8: 数控成形内齿磨齿机 | C8: DIN4级 | D8: ZPI25∮2500 | E8: 德国NILES公司 | F8: 台 | G8: 1 | H8: 1262 | I8: =H8*G8 -> 1262 | J8: =I8/7.65 -> 164.96732
A9: =A8+1 -> 2 | B9: 数控成形磨齿机 | C9: DIN4级 | D9: ZP20∮2000 | E9: 德国NILES公司 | F9: 台 | G9: 1 | H9: 1200 | I9: =H9*G9 -> 1200 | J9: =I9/7.65 -> 156.86275
A10: =A9+1 -> 3 | B10: 数控成形磨齿机 | C10: DIN4级 | D10: ZE1000∮1000 | E10: 德国NILES公司 | F10: 台 | G10: 1 | H10: 680 | I10: =H10*G10 -> 680 | J10: =I10/7.65 -> 88.888889
A11: =A10+1 -> 4 | B11: 数控成形磨齿机 | C11: DIN5级 | D11: ZE15∮1500 | E11: 德国NILES公司 | F11: 台 | G11: 1 | H11: 900 | I11: =H11*G11 -> 900 | J11: =I11/7.65 -> 117.64706
A12: =A11+1 -> 5 | B12: 数控成形磨齿机 | C12: DIN6级 | D12: YK7363∮630 | E12: 秦川机床厂 | F12: 台 | G12: 4 | H12: 180 | I12: =H12*G12 -> 720 | M12: 7.65
A13: =A12+1 -> 6 | B13: 数控成形磨齿机 | C13: DIN6级 | D13: YK73125∮1250 | E13: 秦川机床厂 | F13: 台 | G13: 3 | H13: 550 | I13: =H13*G13 -> 1650
B14: 小 计 | F14: 台 | G14: =SUM(G8:G13) -> 11 | I14: =SUM(I8:I13) -> 6412 | J14: =SUM(J8:J13) -> 528.36601
A16: （二） | B16: 滚齿机及专用铣齿机
A17: 1 | B17: 硬齿面滚齿机 | C17: 工作台4000mm | D17: YC31400Φ4000 | E17: 武汉机床厂 | F17: 台 | G17: 2 | H17: 400 | I17: =H17*G17 -> 800
A18: =A17+1 -> 2 | B18: 专用高速铣齿机 | D18: YK84250Φ2500 | E18: 宜昌长机科技股份公司 | F18: 台 | G18: 2 | H18: 340 | I18: =H18*G18 -> 680
A19: 3 | B19: 专用高速铣齿机 | D19: YKL51350Φ3500 | E19: 宜昌长机科技股份公司 | F19: 台 | G19: 2 | H19: 500 | I19: =H19*G19 -> 1000
A20: 4 | B20: 数控插齿机 | C20: GB10095-88，6级 | D20: YK51250Φ2500×M20 | E20: 宜昌长机科技股份公司 | F20: 台 | G20: 4 | H20: 270 | I20: =H20*G20 -> 1080
A21: 5 | B21: 数控插齿机 | D21: YK51160Φ1600×M20 | E21: 宜昌长机科技股份公司 | F21: 台 | G21: 4 | H21: 160 | I21: =H21*G21 -> 640
B22: 小 计 | F22: 台 | G22: =SUM(G17:G19) -> 6 | I22: =SUM(I17:I21) -> 4200
A24: （三） | B24: 螺旋伞齿轮加工设备
A25: 1 | B25: 螺旋锥齿轮铣齿机 | C25: DIN7级 | D25: YH6016ф1600×M20 | E25: 天津 | F25: 台 | G25: 2 | H25: 400 | I25: =H25*G25 -> 800
A26: =A25+1 -> 2 | B26: 车铣复合加工中心 | D26: VTM180 Φ1800 | E26: 秦川机床厂 | F26: 台 | G26: 1 | H26: 400 | I26: =H26*G26 -> 400
A27: =A26+1 -> 3 | B27: 三坐标测量机 | C27: CMM106060 1000×660×660mm | E27: 美国布朗--夏普公司 | F27: 台 | G27: 1 | H27: 100 | I27: =H27*G27 -> 100
A28: =A27+1 -> 4 | B28: 铣刀刃磨机 | D28: YH908 | E28: 天津 | F28: 台 | G28: 1 | H28: 60 | I28: =H28*G28 -> 60
B29: 小 计 | F29: 台 | G29: =SUM(G25:G28) -> 5 | I29: =SUM(I25:I28) -> 1360
A31: （四） | B31: 立式车床
A32: 1 | B32: 数控立式车床 | C32: 加工高度2000mm | D32: DVT250Φ2500 | E32: 齐重数控股份公司 | F32: 台 | G32: 1 | H32: 300 | I32: =H32*G32 -> 300
A33: =A32+1 -> 2 | B33: 数控立式车床 | C33: 加工高度2500mm | D33: DVT315Φ3150 | E33: 齐重数控股份公司 | F33: 台 | G33: 1 | H33: 340 | I33: =H33*G33 -> 340
B34: 小 计 | F34: 台 | G34: =SUM(G32:G33) -> 2 | I34: =SUM(I32:I33) -> 640
A36: (五) | B36: 起重运输设备
A37: 1 | B37: 桥式起重机 | D37: QD32t/10t×22.5m | E37: 重庆金象起重设备公司 | F37: 台 | G37: 1 | H37: 50 | I37: =H37*G37 -> 50
A38: 2 | B38: 桥式起重机 | D38: QD20t/10t×22.5m | E38: 重庆金象起重设备公司 | F38: 台 | G38: 1 | H38: 35 | I38: =H38*G38 -> 35
A39: 3 | B39: 电动平板车 | D39: KPD-40,40t | E39: 常熟市电动平板车厂 | F39: 台 | G39: 2 | H39: 40 | I39: =H39*G39 -> 80
B40: 小 计 | F40: 台 | G40: =SUM(G37:G39) -> 4 | I40: =SUM(I37:I39) -> 165
B41: 合 计 | F41: 台 | G41: =G14+G22+G29+G34+G40 -> 28 | I41: =I14+I22+I29+I34+I40 -> 12777 | J41: =J14+J22+J29+J34+J40 -> 528.36601
A43: 二 | B43: 箱体加工厂房
A44: （一） | B44: 落地镗铣床
A45: 1 | B45: 数控落地铣镗床 | D45: TK6925ф225 | E45: 齐齐哈尔第二机床厂 | F45: 台 | G45: 1 | H45: 1100 | I45: =H45*G45 -> 1100
A46: =A45+1 -> 2 | B46: 数控落地铣镗床 | D46: TK6920ф200 | E46: 齐齐哈尔第二机床厂 | F46: 台 | G46: 1 | H46: 900 | I46: =H46*G46 -> 900
A47: =A46+1 -> 3 | B47: 数控龙门镗铣床 | D47: XK3060 3000×6000 | E47: 中捷数控股份公司 | F47: 台 | G47: 1 | H47: 400 | I47: =H47*G47 -> 400
B48: 小 计 | F48: 台 | G48: =SUM(G45:G47) -> 3 | I48: =SUM(I45:I47) -> 2400
A50: （二） | B50: 卧式加工设备
A51: 1 | B51: 数控卧式镗床 | C51: 最大镗孔直径ф350 | D51: TK6113ф130 | E51: 交大昆机股份公司 | F51: 台 | G51: 2 | H51: 260 | I51: =H51*G51 -> 520
A52: 2 | B52: 卧式加工中心 | C52: 工作台1250×80 | D52: TH65125×80（1250×800） | E52: 中捷数控股份公司 | F52: 台 | G52: 1 | H52: 500 | I52: =H52*G52 -> 500
B53: 小 计 | F53: 台 | G53: =SUM(G51:G52) -> 3 | I53: =SUM(I51:I52) -> 1020
A55: （三） | B55: 摇臂钻床
A56: 1 | B56: 滑座式摇臂钻床 | D56: Z33100ф100 | E56: 中捷数控股份公司 | F56: 台 | G56: 2 | H56: 55 | I56: =H56*G56 -> 110
A57: 2 | B57: 摇臂钻床 | D57: Z3080ф80 | E57: 中捷数控股份公司 | F57: 台 | G57: 2 | H57: 18 | I57: =H57*G57 -> 36
B58: 小 计 | F58: 台 | G58: =SUM(G56:G57) -> 4 | I58: =SUM(I56:I57) -> 146
A60: （四） | B60: 起重运输设备
A61: 1 | B61: 桥式起重机 | D61: QD50t/10t×22.5m | E61: 重庆金象起重设备公司 | F61: 台 | G61: 1 | H61: 80 | I61: =H61*G61 -> 80
A62: 2 | B62: 桥式起重机 | D62: QD32t/10t×22.5m | E62: 重庆金象起重设备公司 | F62: 台 | G62: 1 | H62: 50 | I62: =H62*G62 -> 50
A63: 3 | B63: 桥式起重机 | D63: QD20t/10t×22.5m | E63: 重庆金象起重设备公司 | F63: 台 | G63: 1 | H63: 35 | I63: =H63*G63 -> 35
A64: 4 | B64: 电动平板车 | D64: KPD-40,40t | E64: 常熟市电动平板车厂 | F64: 台 | G64: 1 | H64: 40 | I64: =H64*G64 -> 40
B65: 小 计 | F65: 台 | G65: =SUM(G61:G64) -> 4 | I65: =SUM(I61:I64) -> 205
B66: 合 计 | F66: 台 | G66: =G48+G53+G58+G65 -> 14 | I66: =I48+I53+I58+I65 -> 3771
A68: 三 | B68: 装配厂房
A69: 1 | B69: 桥式起重机 | D69: QD50t/10t×28.5m | E69: 重庆金象起重设备公司 | F69: 台 | G69: 1 | H69: 90 | I69: =H69*G69 -> 90
A70: 2 | B70: 桥式起重机 | D70: QD100t/20t×28.5m | E70: 重庆金象起重设备公司 | F70: 台 | G70: 1 | H70: 120 | I70: =H70*G70 -> 120
A71: 3 | B71: 电动平板车 | D71: KPD-40,40t | E71: 常熟市电动平板车厂 | F71: 台 | G71: 1 | H71: 40 | I71: =H71*G71 -> 40
A72: 4 | B72: 悬臂吊车 | D72: QD5t | E72: 重庆金象起重设备公司 | F72: 台 | G72: 10 | H72: 18 | I72: =H72*G72 -> 180
B73: 合 计 | F73: 台 | G73: =SUM(G69:G72) -> 13 | I73: =SUM(I69:I72) -> 430
A75: 四 | B75: 试验厂房
A76: 1 | B76: 齿轮箱性能试验台 | D76: 1500KW×4，660V | E76: 西门子公司 | F76: 套 | G76: 2 | H76: 600 | I76: =H76*G76 -> 1200 | J76: =I76/7.65 -> 156.86275
A77: 2 | B77: 桥式起重机 | D77: QD100t/20t×28.5m | E77: 重庆金象起重设备公司 | F77: 台 | G77: 1 | H77: 120 | I77: =H77*G77 -> 120
A78: 3 | B78: 桥式起重机 | D78: QD32t/10t×28.5m | E78: 重庆金象起重设备公司 | F78: 台 | G78: 1 | H78: 65 | I78: =H78*G78 -> 65
A79: 4 | B79: 漆雾净化装置 | E79: 重庆 | F79: 套 | G79: 1 | H79: 50 | I79: 50
B80: 合 计 | F80: 套 | G80: =SUM(G76:G79) -> 5 | I80: =SUM(I76:I79) -> 1435 | J80: =SUM(J68:J76) -> 156.86275
A82: 五 | B82: 成品库房
A83: 1 | B83: 桥式起重机 | D83: QD50t/10t×22.5m | E83: 重庆金象起重设备公司 | F83: 台 | G83: 1 | H83: 80 | I83: =H83*G83 -> 80
B84: 合 计 | F84: 台 | G84: =G83 -> 1 | I84: =I83 -> 80
B86: 设备原价总计 | F86: 台 | G86: =G41+G66+G73+G80+G84 -> 61 | I86: =I41+I66+I73+I80+I84 -> 18493 | J86: =J41+J66+J73+J80+J84 -> 685.22876
B87: 设备运杂费 | I87: =I86*0.07 -> 1294.51
B88: 设备购置费总计 | I88: =SUM(I86:I87) -> 19787.51

Sheet 总概
A1: 附表1
A2: 总 概 算 表
A3: 项目名称：大连船舶重工集团装备制造有限公司装备制造基地建设项目（二期） | U3: 单位：万元
A4: 序号 | B4: 总图 编号 | C4: 工程和费用名称 | D4: 建筑面积(m2) | E4: 建 筑 工 程 | M4: 设 备 工 程 | P4: 安装 工程 | Q4: 其他费用 | R4: 工具器具及生产家具 | S4: 合计 | T4: 外汇额度 | U4: 备注
E5: 建筑物 | F5: 构筑物 | G5: 设备基础 | H5: 给排水 | I5: 采暖通风 | J5: 动力工程 | K5: 电气工程 | L5: 小计 | M5: 公用设备 | N5: 工艺设备 | O5: 小计
C6: 第一部分：工程费用
C7: 一、建筑工程
C8: 一、水工设施 | L8: =SUM(E8:K8) -> 0 | O8: =SUM(M8:N8) -> 0 | S8: =SUM(L8,O8,P8) -> 0
A9: 1 | B9: 401 | C9: 码头 | F9: =[4]码头概算厂提!I45/10000 -> 4708.8175 | G9: 156 | H9: =[4]汇总表1!C6/10000 -> 10.520542 | I9: =[4]汇总表!I8/10000 -> 0 | J9: =[4]汇总表1!C8/10000 -> 14.081857 | K9: =[4]汇总表1!C9/10000 -> 582.98653 | L9: =SUM(E9:K9) -> 5472.4065 | M9: =[4]汇总表1!D10/10000 -> 78.4 | O9: =SUM(M9:N9) -> 78.4 | S9: =SUM(L9,O9,P9) -> 5550.8065
A10: 2 | C10: 护岸 | F10: =[4]护岸概算厂提!I29/10000 -> 744.2765 | H10: =[4]汇总表!H9/10000 -> 0 | I10: =[4]汇总表!I9/10000 -> 0 | J10: =[4]汇总表!J9/10000 -> 0 | K10: =[4]汇总表!K9/10000 -> 0 | L10: =SUM(E10:K10) -> 744.2765 | M10: =[4]汇总表!Q9/10000 -> 0 | O10: =SUM(M10:N10) -> 0 | S10: =SUM(L10,O10,P10) -> 744.2765
A11: 3 | B11: 110 | C11: =[4]汇总表!C21 -> 周转场地 | D11: （38500） | F11: =38500*0.03 -> 1155 | H11: =[4]汇总表!H21/10000 -> 0 | I11: =[4]汇总表!I21/10000 -> 0 | J11: =[4]汇总表!J21/10000 -> 0 | K11: =[4]汇总表!K21/10000 -> 0 | L11: =SUM(E11:K11) -> 1155 | M11: =[4]汇总表!Q21/10000 -> 0 | O11: =SUM(M11:N11) -> 0 | S11: =SUM(L11,O11,P11) -> 1155
C12: 二、生产部门 | L12: =SUM(E12:K12) -> 0 | S12: =SUM(L12,O12,P12) -> 0
A13: 1 | B13: 101 | C13: 装备制造厂房 | E13: =[4]汇总表!E33/10000 -> 0 | F13: =[4]汇总表!F33/10000 -> 0 | G13: =[4]汇总表!G33/10000 -> 0 | H13: =[4]汇总表!H33/10000 -> 0 | I13: =[4]汇总表!I33/10000 -> 0 | J13: =[4]汇总表!J33/10000 -> 0 | K13: =[4]汇总表!K33/10000 -> 0 | L13: =SUM(E13:K13) -> 0 | M13: =[4]汇总表!Q33/10000 -> 0 | N13: =[4]工艺概算!I112-N21-N22 -> 5175.885 | O13: =SUM(M13:N13) -> 5175.885 | P13: =[4]工艺概算!O112-P21-P22 -> 303.2967 | S13: =SUM(L13,O13,P13) -> 5479.1817
A14: 1.1 | C14: 装备制造厂房地基及基础处理 | E14: =[4]汇总表4!C5/10000 -> 4500 | L14: =SUM(E14:K14) -> 4500 | S14: =SUM(L14,O14,P14) -> 4500
A15: 2 | B15: =[4]汇总表!B16 -> 102 | C15: =[4]汇总表!C16 -> 锅压厂房 | D15: 11785 | E15: =[4]汇总表5g!C5/10000+[4]汇总表5g!C6/10000 -> 4107.0817 | H15: =[4]汇总表5g!C7/10000 -> 71.726798 | I15: =[4]汇总表5g!C8/10000 -> 32.746396 | J15: =[4]汇总表5g!C9/10000 -> 56.035959 | K15: =[4]汇总表5g!C10/10000 -> 86.942809 | L15: =SUM(E15:K15) -> 4354.5337 | M15: =[4]汇总表5g!D11/10000 -> 446.36 | N15: =[4]工艺概算!I181 -> 4938.9937 | O15: =SUM(M15:N15) -> 5385.3537 | P15: =[4]工艺概算!O181 -> 61.331326 | S15: =SUM(L15,O15,P15) -> 9801.2187
A16: 3 | B16: 104 | C16: 联合厂房 | D16: 37201 | E16: =([4]汇总表6j!C5+[4]汇总表6j!C6)/10000 -> 9452.0695 | G16: 255.8 | H16: =[4]汇总表6j!C7/10000 -> 331.04326 | I16: =[4]汇总表6j!C8/10000 -> 1131.3385 | J16: =[4]汇总表6j!C9/10000 -> 103.71377 | K16: =[4]汇总表6j!C10/10000 -> 1233.5657 | L16: =SUM(E16:K16) -> 12507.531 | M16: =[4]汇总表6j!D11/10000 -> 4042 | N16: =[4]工艺概算!M186 -> 24 | O16: =SUM(M16:N16) -> 4066 | P16: =[4]工艺概算!O186 -> 2.4 | S16: =SUM(L16,O16,P16) -> 16575.931
A17: 4 | B17: 105 | C17: 钢加车间 | D17: 6644 | E17: =1485.502069+0.04*D17 -> 1751.2621 | G17: 124.902 | H17: 65.518095 | I17: 197.87982 | J17: =[4]汇总表7!C9/10000 -> 15.901847 | K17: 101.92092 | L17: =SUM(E17:K17) -> 2257.3848 | M17: =[4]汇总表7!D11/10000 -> 559.8 | O17: =SUM(M17:N17) -> 559.8 | S17: =SUM(L17,O17,P17) -> 2817.1848
A18: 5 | B18: 108 | C18: =[4]汇总表!C20 -> 2#总装场地 | D18: （10000） | E18: ='[4]汇总表8-2'!C5/10000 -> 406.32925 | F18: =[4]汇总表!F20/10000 -> 0 | G18: =[4]汇总表!G20/10000 -> 0 | H18: ='[4]汇总表8-2'!C6/10000 -> 15.499282 | I18: =[4]汇总表!I20/10000 -> 0 | J18: ='[4]汇总表8-2'!C8/10000 -> 15.788785 | K18: ='[4]汇总表8-2'!C9/10000 -> 378.21539 | L18: =SUM(E18:K18) -> 815.83272 | M18: ='[4]汇总表8-2'!D10/10000 -> 344 | O18: =SUM(M18:N18) -> 344 | S18: =SUM(L18,O18,P18) -> 1159.8327
A19: 6 | B19: =[4]汇总表!B34 -> 0 | C19: =[4]汇总表!C34 -> 工厂信息化工程 | E19: =[4]汇总表!E34/10000 -> 0 | F19: =[4]汇总表!F34/10000 -> 0 | G19: =[4]汇总表!G34/10000 -> 0 | H19: =[4]汇总表!H34/10000 -> 0 | I19: =[4]汇总表!I34/10000 -> 0 | J19: =[4]汇总表!J34/10000 -> 0 | K19: =[4]汇总表!K34/10000 -> 0 | L19: =SUM(E19:K19) -> 0 | M19: =[4]汇总表!Q34/10000 -> 0 | N19: =[4]工艺概算!I227 -> 607.02 | O19: =SUM(M19:N19) -> 607.02 | S19: =SUM(L19,O19,P19) -> 607.02
C20: 三、辅助部门 | L20: =SUM(E20:K20) -> 0 | S20: =SUM(L20,O20,P20) -> 0
A21: 1 | B21: 101-3 | C21: 装备制造厂房3#辅房 | D21: =3091-D22 -> 1372 | E21: ='[4]汇总表9-3'!C5/10000 -> 246.36954 | F21: =[4]汇总表!F14/10000 -> 0 | G21: =[4]汇总表!G14/10000 -> 0 | H21: ='[4]汇总表9-3'!C6/10000 -> 19.625683 | I21: ='[4]汇总表9-3'!C7/10000 -> 61.818734 | J21: =[4]汇总表!J14/10000 -> 0 | K21: ='[4]汇总表9-3'!C9/10000 -> 15.367596 | L21: =SUM(E21:K21) -> 343.18155 | M21: ='[4]汇总表9-3'!D10/10000 -> 148.1 | N21: =[4]工艺概算!M92 -> 68.96 | O21: =SUM(M21:N21) -> 217.06 | P21: =[4]工艺概算!O92 -> 1.45 | S21: =SUM(L21,O21,P21) -> 561.69155
A22: 2 | B22: 101-4 | C22: 装备制造厂房4#辅房 | D22: =573*3 -> 1719 | E22: ='[4]汇总表9-4'!C5/10000 -> 290.4531 | F22: =[4]汇总表!F15/10000 -> 0 | G22: =[4]汇总表!G15/10000 -> 0 | H22: =H21 -> 19.625683 | I22: =I21 -> 61.818734 | J22: =[4]汇总表!J15/10000 -> 0 | K22: =K21 -> 15.367596 | L22: =SUM(E22:K22) -> 387.26511 | M22: =M21 -> 148.1 | N22: =[4]工艺概算!M110 -> 164.71 | O22: =SUM(M22:N22) -> 312.81 | P22: =[4]工艺概算!O110 -> 2.2584 | S22: =SUM(L22,O22,P22) -> 702.33351
A23: 3 | B23: =[4]汇总表!B22 -> 301 | C23: =[4]汇总表!C22 -> 66KV总降压站 | D23: 2800 | E23: =[4]汇总表!E22/10000 -> 0 | F23: =[4]汇总表!F22/10000 -> 0 | G23: =[4]汇总表!G22/10000 -> 0 | H23: =[4]汇总表!H22/10000 -> 0 | I23: =[4]汇总表!I22/10000 -> 0 | J23: =[4]汇总表!J22/10000 -> 0 | K23: =[4]汇总表!K22/10000 -> 0 | L23: =SUM(E23:K23) -> 0 | M23: 2500 | O23: =SUM(M23:N23) -> 2500 | S23: =SUM(L23,O23,P23) -> 2500
A24: 4 | B24: =[4]汇总表!B24 -> 303 | C24: =[4]汇总表!C24 -> 1#空压站 | E24: =[4]汇总表!E24/10000 -> 0 | F24: =[4]汇总表!F24/10000 -> 0 | G24: =[4]汇总表!G24/10000 -> 0 | H24: ='[4]汇总表10-k1'!C6/10000 -> 28.428925 | I24: ='[4]汇总表10-k1'!C7/10000 -> 3.999288 | J24: ='[4]汇总表10-k1'!C8/10000 -> 27.291057 | K24: ='[4]汇总表10-k1'!C9/10000 -> 15.367596 | L24: =SUM(E24:K24) -> 75.086866 | M24: ='[4]汇总表10-k1'!D10/10000 -> 451.95 | O24: =SUM(M24:N24) -> 451.95 | S24: =SUM(L24,O24,P24) -> 527.03687
A25: 5 | B25: =[4]汇总表!B25 -> 304 | C25: =[4]汇总表!C25 -> 2#空压站 | D25: 640 | E25: 119.5 | H25: =H24 -> 28.428925 | I25: =I24 -> 3.999288 | J25: =J24 -> 27.291057 | K25: =K24 -> 15.367596 | L25: =SUM(E25:K25) -> 194.58687 | M25: =M24 -> 451.95 | O25: =SUM(M25:N25) -> 451.95 | S25: =SUM(L25,O25,P25) -> 646.53687
C26: 四、办公设施 | S26: =SUM(L26,O26,P26) -> 0
A27: 1 | B27: =[4]汇总表!B30 -> 301 | C27: =[4]汇总表!C30 -> 办公楼 | D27: 13990.9 | E27: ='[4]汇总表13-b'!C5/10000 -> 2801.9434 | G27: =[4]汇总表!G30/10000 -> 0 | H27: ='[4]汇总表13-b'!C6/10000 -> 171.44643 | I27: ='[4]汇总表13-b'!C7/10000 -> 68.666509 | J27: =[4]汇总表!J30/10000 -> 0 | K27: ='[4]汇总表13-b'!C9/10000 -> 99.965003 | L27: =SUM(E27:K27) -> 3142.0214 | M27: ='[4]汇总表13-b'!D10/10000 -> 716.0375 | O27: =SUM(M27:N27) -> 716.0375 | S27: =SUM(L27,O27,P27) -> 3858.0589
A28: 2 | B28: 202 | C28: =[4]汇总表!C31 -> 门卫房二 | D28: 63.6 | E28: =D28*0.15 -> 9.54 | F28: =[4]汇总表!F31/10000 -> 0 | G28: =[4]汇总表!G31/10000 -> 0 | I28: ='[4]汇总表12-m'!C7/10000 -> 3.819263 | J28: =[4]汇总表!J31/10000 -> 0 | K28: ='[4]汇总表12-m'!C9/10000 -> 1.055836 | L28: =SUM(E28:K28) -> 14.415099 | M28: ='[4]汇总表12-m'!D10/10000 -> 2.2 | O28: =SUM(M28:N28) -> 2.2 | S28: =SUM(L28,O28,P28) -> 16.615099
A29: 3 | B29: 203 | C29: =[4]汇总表!C32 -> 门卫房三 | D29: 63.6 | E29: =E28 -> 9.54 | F29: =F28 -> 0 | G29: =G28 -> 0 | H29: =H28 -> 0 | I29: =I28 -> 3.819263 | J29: =J28 -> 0 | K29: =K28 -> 1.055836 | L29: =L28 -> 14.415099 | ... R29: =R28 -> 0 | S29: =SUM(L29,O29,P29) -> 16.615099
C30: 五、总图公用工程 | L30: =SUM(E30:K30) -> 0 | S30: =SUM(L30,O30,P30) -> 0
A31: 1 | C31: 室外给排水工程 | H31: =[4]汇总表!H38/10000 -> 1288.2248 | I31: =[4]汇总表!I38/10000 -> 0 | J31: =[4]汇总表!J38/10000 -> 0 | K31: =[4]汇总表!K38/10000 -> 0 | L31: =SUM(E31:K31) -> 1288.2248 | S31: =SUM(L31,O31,P31) -> 1288.2248
A32: 2 | C32: 室外动力工程 | H32: =[4]汇总表!H39/10000 -> 0 | I32: =[4]汇总表!I39/10000 -> 0 | J32: =[4]汇总表14!C7/10000 -> 293.43566 | K32: =[4]汇总表!K39/10000 -> 0 | L32: =SUM(E32:K32) -> 293.43566 | S32: =SUM(L32,O32,P32) -> 293.43566
A33: 3 | C33: 室外采暖工程 | H33: =[4]汇总表!H40/10000 -> 0 | I33: =[4]汇总表14!C6/10000 -> 156.4724 | J33: =[4]汇总表!J40/10000 -> 0 | K33: =[4]汇总表!K40/10000 -> 0 | L33: =SUM(E33:K33) -> 156.4724 | S33: =SUM(L33,O33,P33) -> 156.4724
A34: 4 | C34: 室外电气工程 | H34: =[4]汇总表!H41/10000 -> 0 | I34: =[4]汇总表!I41/10000 -> 0 | J34: =[4]汇总表!J41/10000 -> 0 | K34: =[4]汇总表14!C8/10000 -> 467.29472 | L34: =SUM(E34:K34) -> 467.29472 | S34: =SUM(L34,O34,P34) -> 467.29472
A35: 5 | C35: 绿地(45253m2) | E35: =[4]汇总表14!C9/10000 -> 242.5 | L35: =SUM(E35:K35) -> 242.5 | S35: =SUM(L35,O35,P35) -> 242.5
A36: 6 | C36: 道路(37500m2) | E36: =[4]汇总表14!C10/10000 -> 975 | L36: =SUM(E36:K36) -> 975 | S36: =SUM(L36,O36,P36) -> 975
A37: 7 | C37: 围墙(1400m) | E37: =[4]汇总表14!C11/10000 -> 98 | L37: =SUM(E37:K37) -> 98 | S37: =SUM(L37,O37,P37) -> 98
C38: 小 计 | D38: =SUM(D9:D37) -> 76279.1 | E38: =SUM(E9:E37) -> 25009.589 | F38: =SUM(F9:F37) -> 6608.094 | G38: =SUM(G9:G37) -> 536.702 | H38: =SUM(H9:H37) -> 2050.0884 | I38: =SUM(I9:I37) -> 1726.3782 | J38: =SUM(J9:J37) -> 553.53999 | K38: =SUM(K9:K37) -> 3014.4731 | ... S38: =SUM(S9:S37) -> 60740.267
S39: =L39+O39+P39+Q39+R39 -> 0
C40: 工程费用合计 | D40: =D38 -> 76279.1 | E40: =E38 -> 25009.589 | F40: =F38 -> 6608.094 | G40: =G38 -> 536.702 | H40: =H38 -> 2050.0884 | I40: =I38 -> 1726.3782 | J40: =J38 -> 553.53999 | K40: =K38 -> 3014.4731 | ... S40: =S38 -> 60740.267
C42: 第二部分：其他费用
A43: 1 | C43: =[4]其他!B7 -> 建设单位管理费 | Q43: =[4]其他!F7 -> 563 | S43: =Q43 -> 563
A44: 2 | C44: =[4]其他!B8 -> 前期工作费 | Q44: =[4]其他!F8 -> 170.72 | S44: =Q44 -> 170.72
A45: 3 | C45: =[4]其他!B9 -> 勘察费 | Q45: =[4]其他!F9 -> 91.53492 | S45: =Q45 -> 91.53492
A46: 4 | C46: =[4]其他!B10 -> 工程设计费 | Q46: =[4]其他!H7 -> 1501.4216 | S46: =Q46 -> 1501.4216
A47: 5 | C47: =[4]其他!B11 -> 工程建设监理费 | Q47: =[4]其他!F11 -> 677.12919 | S47: =Q47 -> 677.12919
A48: 6 | C48: =[4]其他!B12 -> 招标代理服务费 | Q48: =[4]其他!F12 -> 87.427176 | S48: =Q48 -> 87.427176
A49: 7 | C49: =[4]其他!B13 -> 施工图审查费 | Q49: =[4]其他!F13 -> 75.071082 | S49: =Q49 -> 75.071082
A50: 8 | C50: =[4]其他!B14 -> 劳动卫生安全评价费 | Q50: =[4]其他!F14 -> 60 | S50: =Q50 -> 60
A51: 9 | C51: =[4]其他!B15 -> 环境影响咨询费 | Q51: =[4]其他!F15 -> 104.8 | S51: =Q51 -> 104.8
A52: 10 | C52: =[4]其他!B16 -> 设备搬迁费 | Q52: =[4]其他!F16 -> 600 | S52: =Q52 -> 600
A53: 11 | C53: =[4]其他!B17 -> 二期土地购置费 | Q53: =[4]其他!F17 -> 11931.772 | S53: =Q53 -> 11931.772
A54: 12 | C54: =[4]其他!B18 -> 一期土地购置费 | Q54: =[4]其他!F18 -> 7620.368 | S54: =Q54 -> 7620.368
A55: 13 | C55: =[4]其他!B19 -> 二期土地购置税金 | Q55: =[4]其他!F19 -> 536.92974 | S55: =Q55 -> 536.92974
A56: 14 | C56: =[4]其他!B20 -> 一期土地购置税金 | Q56: =[4]其他!F20 -> 342.91656 | S56: =Q56 -> 342.91656
A57: 15 | C57: =[4]其他!B21 -> 其他 | Q57: =-514530*(380-69)/10000 -> -16001.883 | S57: =Q57 -> -16001.883
A58: 16 | C58: =[4]其他!B22 -> 项目管理费 | Q58: =[4]其他!F22 -> 300 | S58: =Q58 -> 300
C59: 小 计 | Q59: =SUM(Q43:Q58) -> 8661.2073 | R59: =SUM(R43:R51) -> 0 | S59: =SUM(S43:S58) -> 8661.2073
C61: 第三部分：工具器具及办公生产家具费 | R61: 800 | S61: =R61 -> 800
C63: 第四部分:基本预备费（7%） | Q63: 5000 | S63: =L63+O63+P63+Q63+R63 -> 5000
C65: 静态投资合计 | D65: =SUM(D40,D59,D61,D63) -> 76279.1 | E65: =SUM(E40,E59,E61,E63) -> 25009.589 | F65: =SUM(F40,F59,F61,F63) -> 6608.094 | G65: =SUM(G40,G59,G61,G63) -> 536.702 | H65: =SUM(H40,H59,H61,H63) -> 2050.0884 | I65: =SUM(I40,I59,I61,I63) -> 1726.3782 | J65: =SUM(J40,J59,J61,J63) -> 553.53999 | K65: =SUM(K40,K59,K61,K63) -> 3014.4731 | ... S65: =SUM(S40,S59,S61,S63) -> 75201.474
C67: 第四部分:动态投资
C68: 建设期贷款利息 | J68: =I68 -> 0 | Q68: 798.8 | S68: =Q68 -> 798.8
C69: 小计 | Q69: =Q68 -> 798.8 | S69: =S68 -> 798.8
C71: 固定资产投资合计 | D71: =D69+D65 -> 76279.1 | E71: =E69+E65 -> 25009.589 | F71: =F69+F65 -> 6608.094 | G71: =G69+G65 -> 536.702 | H71: =H69+H65 -> 2050.0884 | I71: =I69+I65 -> 1726.3782 | J71: =J69+J65 -> 553.53999 | K71: =K69+K65 -> 3014.4731 | ... S71: =S69+S65 -> 76000.274
L73: =K74 -> 0 | M73: =L73+L74 -> 0

Sheet 工艺设备
A1: 附表2
A2: 工 艺 设 备 明 细 表
A3: =总概!A3:E3 -> 项目名称：大连船舶重工集团装备制造有限公司装备制造基地建设项目（二期）
A4: 序 号 | B4: 设备名称 | C4: 主要技术(性能)指标 | D4: 生产厂 | E4: 单位 | F4: 数量 | I4: 价格(万元) | K4: 招标情况 | L4: 备注
F5: 现有 | G5: 新增 | H5: 共计 | I5: 单价 | J5: 总价
B6: 装备制造厂房
B7: 一、下料成型设备
A8: 1 | B8: 等离子切割机 | C8: 有效切割范围：5m*20m、最大切割厚度：60mm，设备自带除烟尘装置 | D8: 国产 | E8: 套 | G8: 1 | H8: =G8 -> 1 | I8: 159 | J8: =I8*H8 -> 159 | K8: 委托公开
A9: 2 | B9: 高压水切割装置 | C9: 切割厚度100mm | D9: 国产 | E9: 台 | G9: 1 | H9: =G9 -> 1 | I9: 250 | J9: =I9*H9 -> 250 | K9: 委托公开
A10: 3 | B10: 数控相贯线切割机 | C10: Ø600mm×30 | D10: 国产 | E10: 台 | G10: 1 | H10: =G10 -> 1 | I10: 140 | J10: =I10*H10 -> 140 | K10: 委托公开
A11: 4 | B11: 数控深孔钻 | C11: 最大工件直径φ2500mm;钻孔直径:φ10～φ32mm;最大钻孔深度:800mm;工作台最大承重:100T | D11: 国产 | E11: 台 | G11: 1 | H11: =G11 -> 1 | I11: 485.54 | J11: =I11*H11 -> 485.54 | K11: 委托公开
A12: 5 | B12: 马鞍形数控切割机 | C12: 切割圆孔直径：Φ100~1200mm | D12: 国产 | E12: 台 | G12: 1 | H12: =G12 -> 1 | I12: 36.5 | J12: =I12*H12 -> 36.5
A13: 6 | B13: 针轮加工机 | D13: 国产 | E13: 台 | G13: 1 | H13: 1 | I13: 150 | J13: =I13*H13 -> 150 | K13: 不招标 | L13: 自制设备
A14: 7 | B14: 液压胀管机 | C14: 胀接管子内径不小于φ10；管壁厚不大于5mm;胀接长度：10mm~600mm | D14: 国产 | E14: 台 | G14: 2 | H14: =G14 -> 2 | I14: 24.8 | J14: =I14*H14 -> 49.6
B15: 小计 | G15: =SUM(G8:G14) -> 8 | H15: =SUM(H8:H14) -> 8 | J15: =SUM(J8:J14) -> 1270.64
B16: 二、焊接生产设备
A17: 1 | B17: 窄间隙焊成套设备 | D17: 国产 | E17: 套 | G17: 1 | H17: 1 | I17: 199.8 | J17: =H17*I17 -> 199.8 | K17: 委托公开
A18: （1） | B18: 双丝窄间隙焊机 | C18: 含焊剂回收及干燥系统 | D18: 国产 | E18: 套 | G18: （1） | H18: （1） | I18: (122.6） | J18: (122.6）
A19: （2） | B19: 操作机 | C19: 承重800kg | D19: 国产 | E19: 台 | G19: （1） | H19: （1） | I19: (32.3) | J19: (32.3)
A20: （3） | B20: 防窜滚轮架 | C20: 200t | D20: 国产 | E20: 套 | G20: （1） | H20: （1） | I20: （44.9） | J20: （44.9）
A21: 2 | B21: 带极堆焊成套设备 | D21: 国产 | E21: 套 | G21: 1 | H21: =SUM(F21:G21) -> 1 | I21: 115 | J21: =H21*I21 -> 115 | K21: 委托公开
A22: (1) | B22: 带极堆焊机 | C22: 焊带宽度:30mm-60mm | D22: 国产 | E22: 套 | G22: （1） | H22: （1） | I22: （13.3） | J22: （13.3）
A23: (2) | B23: 操作机 | C23: 5m×5m 承重200KG | D23: 国产 | E23: 台 | G23: （1） | H23: （1） | I23: （8.3） | J23: （8.3）
A24: (3) | B24: 带极堆焊电源 | C24: 1000A | D24: 国产 | E24: 套 | G24: （2） | H24: （2） | I24: （7.1） | J24: （14.2）
A25: (4) | B25: 变位机 | C25: φ3000mm(可扩展至6000mm);承重30t | D25: 国产 | E25: 台 | G25: （1） | H25: （1） | I25: （79.2） | J25: （79.2）
A26: 3 | B26: 埋弧焊成套设备 | D26: 国产 | E26: 套 | G26: 1 | H26: =SUM(F26:G26) -> 1 | I26: 47.625 | J26: =I26*H26 -> 47.625
A27: （1） | B27: 埋弧焊设备 | C27: 焊接额定电流：1250A | D27: 国产 | E27: 台 | G27: （1） | H27: （1） | I27: (4.775) | J27: (4.775)
A28: （2） | B28: 操作架 | C28: 6m×6m | D28: 国产 | E28: 套 | G28: （1） | H28: （1） | I28: (16.35) | J28: (16.35)
A29: （3） | B29: 防窜滚轮架 | C29: 400T | D29: 国产 | E29: 套 | G29: （1） | H29: （1） | I29: (26.5) | J29: (26.5)
A30: 4 | B30: 埋弧焊成套设备 | D30: 国产 | E30: 套 | G30: 1 | H30: =SUM(F30:G30) -> 1 | I30: 67.275 | J30: =I30*H30 -> 67.275 | K30: 不招标 | L30: 其中滚轮架自制，其它分项金额不超过50万，不招标
A31: （1） | B31: 埋弧焊设备 | C31: 焊接额定电流：1250A | D31: 国产 | E31: 台 | G31: （1） | H31: （1） | I31: (4.775) | J31: (4.775)
A32: （2） | B32: 门式焊接操作架 | C32: 10t | D32: 国产 | E32: 套 | G32: （1） | H32: （1） | I32: （36） | J32: （36）
A33: （3） | B33: 防窜滚轮架 | C33: 400T | D33: 国产 | E33: 套 | G33: （1） | H33: （1） | I33: (26.5) | J33: (26.5)
A34: 5 | B34: 埋弧焊成套设备 | D34: 国产 | E34: 套 | G34: 2 | H34: =SUM(F34:G34) -> 2 | I34: 62.875 | J34: =I34*H34 -> 125.75 | K34: 委托公开
A35: （1） | B35: 埋弧焊设备 | C35: 焊接额定电流：1250A | D35: 国产 | E35: 台 | G35: （2） | H35: （2） | I35: (4.775) | J35: (9.55)
A36: （2） | B36: 十字臂式焊接操作架 | C36: 6m×6m | D36: 国产 | E36: 套 | G36: （2） | H36: （2） | I36: (31.6) | J36: (63.2)
A37: （3） | B37: 防窜滚轮架 | C37: 400T | D37: 国产 | E37: 套 | G37: （2） | H37: （2） | I37: (26.5) | J37: (53)
A38: 6 | B38: 滚轮机 | C38: 60吨 | D38: 国产 | E38: 套 | G38: 1 | H38: =G38 -> 1 | I38: 11.6 | J38: =I38*H38 -> 11.6
A39: 7 | B39: 滚轮架 | C39: 200T | D39: 国产 | E39: 套 | G39: 2 | H39: =G39 -> 2 | I39: 42 | J39: =I39*H39 -> 84
A40: 8 | B40: 滚轮架 | C40: 400T | D40: 国产 | E40: 套 | G40: 6 | H40: =G40 -> 6 | I40: 9.3333333 | J40: =I40*H40 -> 56
A41: 9 | B41: 滚轮架 | C41: 100T | D41: 国产 | E41: 套 | G41: 2 | H41: =G41 -> 2 | I41: 43.8 | J41: =I41*H41 -> 87.6
A42: 10 | B42: 防窜滚轮架 | C42: 200T | D42: 国产 | E42: 套 | G42: 4 | H42: =G42 -> 4 | I42: 35 | J42: =I42*H42 -> 140
A43: 11 | B43: 焊接滚轮架 | C43: 20t | D43: 国产 | E43: 套 | G43: 1 | H43: =G43 -> 1 | I43: 5 | J43: =I43*H43 -> 5
A44: 12 | B44: 固溶炉 | C44: 炉膛尺寸：7m*4m*3m | D44: 国产 | E44: 台 | G44: 1 | H44: =G44 -> 1 | I44: 240.8 | J44: =I44*H44 -> 240.8 | K44: 不招标 | L44: 自制
A45: 13 | B45: 小管堆焊设备 | C45: 1堆焊管 长度≤2400mm；内径φ50mm-φ500mm（堆焊后管内径) | D45: 国产 | E45: 套 | G45: 1 | H45: =G45 -> 1 | I45: 75 | J45: =I45*H45 -> 75 | K45: 委托公开
A46: 14 | B46: 履带式加热装置 | C46: LCD型 | D46: 国产 | E46: 套 | G46: 2 | H46: =F46+G46 -> 2 | I46: 20 | J46: =G46*I46 -> 40 | K46: =IF(J46>=50,"委托公开"," ")
A47: 15 | B47: 管-管板焊接机 | C47: Ø8~Ø273 | D47: 国产 | E47: 台 | G47: 2 | H47: =G47 -> 2 | I47: 20 | J47: =I47*H47 -> 40
A48: 16 | B48: 丝极埋弧焊机头、电源 | C48: 6m×6m,厚度≤80mm | D48: 国产 | E48: 套 | G48: 1 | H48: =G48 -> 1 | I48: 28.615 | J48: =I48*H48 -> 28.615
A49: 17 | B49: 马鞍形数控焊接机 | C49: 焊接圆孔直径：Φ100~1200mm | D49: 国产 | E49: 台 | G49: 1 | H49: =G49 -> 1 | I49: 44 | J49: =I49*H49 -> 44
A50: 18 | B50: 直流氩弧焊机 | C50: 焊接额定电流：350A | D50: 国产 | E50: 台 | G50: 6 | H50: =G50 -> 6 | I50: 0.53 | J50: =I50*H50 -> 3.18
A51: 19 | B51: 逆变式直流弧焊机 | C51: 焊接额定电流：350A | D51: 国产 | E51: 台 | G51: 5 | H51: =G51 -> 5 | I51: 1 | J51: =I51*H51 -> 5
A52: 20 | B52: 碳弧气刨设备 | C52: 焊接额定电流：1250A | D52: 国产 | E52: 套 | G52: 4 | H52: =G52 -> 4 | I52: 2.875 | J52: =I52*H52 -> 11.5
B53: 小计 | H53: =SUM(H26,H30,H34,H38:H52,H17:H17,H21) -> 45 | J53: =SUM(J26,J30,J34,J38:J52,J17:J17,J21) -> 1427.745
B54: 三、生产辅助设备
A55: 1 | B55: 焊条烘干箱（带保温） | C55: 500kg | D55: 国产 | E55: 台 | G55: 4 | H55: =G55 -> 4 | I55: 2.56 | J55: =I55*H55 -> 10.24
A56: 2 | B56: 焊剂烘干机 | C56: 550kg | D56: 国产 | E56: 台 | G56: 5 | H56: =G56 -> 5 | I56: 1.92 | J56: =I56*H56 -> 9.6
A57: 3 | B57: 自动化全站仪 | C57: 放大赔率：30×，精度（ISO17123-3:2001):0.5″,0.15mgon | D57: 国产 | E57: 台 | G57: 1 | H57: =G57 -> 1 | I57: 38 | J57: =I57*H57 -> 38
A58: 4 | B58: 空气过滤器 | C58: 过滤精度： 粒径≤0.01um，残油≤0.01ppm 设计压力露点： ＜-50℃. 出口气体温度： 60～80℃ | D58: 国产 | E58: 台 | G58: 1 | H58: =G58 -> 1 | I58: 5.86 | J58: =I58*H58 -> 5.86
A59: 5 | B59: 离子造水机 | C59: 4t/h，水质达到A级水要求 | D59: 国产 | E59: 台 | G59: 1 | H59: =G59 -> 1 | I59: 8 | J59: =I59*H59 -> 8
A60: 6 | B60: 不锈压力水泵 | C60: 0~40MPa | D60: 国产 | E60: 台 | G60: 1 | H60: =G60 -> 1 | I60: 4.2 | J60: =I60*H60 -> 4.2
A61: 7 | B61: 真空泵机 | C61: 抽真空速度：10m3的产品在90分钟内，真空度可达到1 Pa,产品漏率：2×10-4 -2×10-12Pa.m3/S | D61: 国产 | E61: 台 | G61: 1 | H61: =G61 -> 1 | I61: 43.7 | J61: =I61*H61 -> 43.7
A62: 8 | B62: 试压水泵 | C62: 最高压力：36MPa | D62: 国产 | E62: 套 | G62: 6 | H62: =F62+G62 -> 6 | I62: 1 | J62: =G62*I62 -> 6 | K62: =IF(J62>=50,"委托公开"," ")
A63: 9 | B63: 焊条保温箱 | C63: 1.5m*2m*2m | D63: 国产 | E63: 台 | G63: 1 | H63: =G63 -> 1 | I63: 4.8 | J63: =I63*H63 -> 4.8
A64: 10 | B64: 除湿机 | D64: 国产 | E64: 台 | G64: 1 | H64: =G64 -> 1 | I64: 0.3 | J64: =I64*H64 -> 0.3
A65: 11 | B65: 曲线式加温箱 | C65: 1.3m*1.3m*1m | D65: 国产 | E65: 台 | G65: 1 | H65: =G65 -> 1 | I65: 9 | J65: =I65*H65 -> 9
B66: 小计 | H66: =SUM(H55:H65) -> 23 | J66: =SUM(J55:J65) -> 139.7
B67: 四、起重运输设备
A68: 1 | B68: 桥式起重机 | C68: Gn=50/10t， S=32m ，H=12m | D68: 国产 | E68: 台 | G68: 1 | H68: =G68 -> 1 | I68: 130 | J68: =I68*H68 -> 130 | K68: 不招标 | L68: 自制
A69: 2 | B69: 桥式起重机 | C69: Gn=32/5t， S=32m ，H=12m | D69: 国产 | E69: 台 | G69: 2 | H69: =G69 -> 2 | I69: 90 | J69: =I69*H69 -> 180 | K69: 不招标 | L69: 自制
A70: 3 | B70: 桥式起重机 | C70: Gn=200/50t,S=34m,H=19m | D70: 国产 | E70: 台 | G70: 2 | H70: =G70 -> 2 | I70: 720 | J70: =I70*H70 -> 1440 | K70: 不招标 | L70: 自制
A71: 4 | B71: 桥式起重机 | C71: Gn=50/10t,S=32.5m,H=12m | D71: 国产 | E71: 台 | G71: 3 | H71: =G71 -> 3 | I71: 130 | J71: =I71*H71 -> 390 | K71: 不招标 | L71: 自制
A72: 5 | B72: 桥式起重机 | C72: Gn=32/5t,S=32.5m,H=12m | D72: 国产 | E72: 台 | G72: 2 | H72: =G72 -> 2 | I72: 90 | J72: =I72*H72 -> 180 | K72: 不招标 | L72: 自制
A73: 6 | B73: 三相低压电动平车 | C73: 100T | D73: 国产 | E73: 台 | G73: 3 | H73: =G73 -> 3 | I73: 5.9333333 | J73: =I73*H73 -> 17.8
B74: 小计 | H74: =SUM(H68:H73) -> 13 | J74: =SUM(J68:J73) -> 2337.8
B75: 合计 | H75: =H15+H53+H66+H74 -> 89 | I75: =I15+I53+I66+I74 -> 0 | J75: =J15+J53+J66+J74 -> 5175.885
B76: 装备制造厂房3#辅房
B77: 五、焊接试验室设备
A78: 1 | B78: 数字化MIG/MAG 焊机 | C78: 焊接额定电流：350A | D78: 国产 | E78: 台 | G78: 2 | H78: =G78 -> 2 | I78: 14.1 | J78: =I78*H78 -> 28.2
A79: 2 | B79: 便携式自动火焰切割机 | D79: 国产 | E79: 台 | G79: 1 | H79: =G79 -> 1 | I79: 0.7 | J79: =I79*H79 -> 0.7
A80: 3 | B80: 直流埋弧焊机 | C80: 焊接额定电流：1250A | D80: 国产 | E80: 台 | G80: 1 | H80: =G80 -> 1 | I80: 3.8 | J80: =I80*H80 -> 3.8
A81: 4 | B81: 逆变直流弧焊机 | C81: 焊接额定电流：350A | D81: 国产 | E81: 台 | G81: 2 | H81: =G81 -> 2 | I81: 1.5 | J81: =I81*H81 -> 3
A82: 5 | B82: 直流氩弧焊机 | C82: 焊接额定电流：300A | D82: 国产 | E82: 台 | G82: 2 | H82: =G82 -> 2 | I82: 2.5 | J82: =I82*H82 -> 5
A83: 6 | B83: CO2气体保护焊机 | C83: 焊接额定电流：400A | D83: 国产 | E83: 台 | G83: 2 | H83: =G83 -> 2 | I83: 1.9 | J83: =I83*H83 -> 3.8
A84: 7 | B84: 碳弧气刨机 | C84: 焊接额定电流：1500A | D84: 国产 | E84: 台 | G84: 1 | H84: =G84 -> 1 | I84: 2 | J84: =I84*H84 -> 2
A85: 8 | B85: 焊剂烘干机 | C85: 400kg，温度均匀性：±10℃，最高温度500℃ | D85: 国产 | E85: 台 | G85: 1 | H85: =G85 -> 1 | I85: 2.7 | J85: =I85*H85 -> 2.7
A86: 9 | B86: 焊条烘干箱 | C86: 500kg，温度均匀性：±10℃，最高温度500℃ | D86: 国产 | E86: 台 | G86: 1 | H86: =G86 -> 1 | I86: 1.66 | J86: =I86*H86 -> 1.66
A87: 10 | B87: 温度控制箱 | C87: 额定输出功率240kW，控温点：6路12点 | D87: 国产 | E87: 台 | G87: 1 | H87: =G87 -> 1 | I87: 3.6 | J87: =I87*H87 -> 3.6
A88: 11 | B88: 电动单梁悬挂起重机 | C88: Gn=5t,Lk=7.5m | D88: 国产 | E88: 台 | G88: 1 | H88: =G88 -> 1 | I88: 14.5 | J88: =I88*H88 -> 14.5
B89: 小计 | H89: =SUM(H78:H88) -> 15 | J89: =SUM(J78:J88) -> 68.96
B90: 装备制造厂房4#辅房
B91: 六、理化计量设备
A92: 1 | B92: 液压万能试验机 | C92: 1000kN | D92: 国产 | E92: 台 | G92: 1 | H92: =G92 -> 1 | I92: 26 | J92: =I92*H92 -> 26
A93: 2 | B93: 冲击试验机 | C93: 300J | D93: 国产 | E93: 台 | G93: 1 | H93: =G93 -> 1 | I93: 7.2 | J93: =I93*H93 -> 7.2
A94: 3 | B94: 磨床 | C94: M7130G/F | D94: 国产 | E94: 台 | G94: 1 | H94: =G94 -> 1 | I94: 8.3 | J94: =I94*H94 -> 8.3
A95: 4 | B95: 低温槽 | C95: DWC-60. | D95: 国产 | E95: 套 | G95: 1 | H95: =G95 -> 1 | I95: 1.7 | J95: =I95*H95 -> 1.7
A96: 5 | B96: 投影仪 | C96: CST-50 | D96: 国产 | E96: 台 | G96: 1 | H96: =G96 -> 1 | I96: 0.73 | J96: =I96*H96 -> 0.73
A97: 6 | B97: 冲击缺口制样机（拉床） | C97: VU-2D | D97: 国产 | E97: 台 | G97: 1 | H97: =G97 -> 1 | I97: 1.8 | J97: =I97*H97 -> 1.8
A98: 7 | B98: 标点机 | C98: DX-300 | D98: 国产 | E98: 台 | G98: 1 | H98: =G98 -> 1 | I98: 0.28 | J98: =I98*H98 -> 0.28
A99: 8 | B99: 高温拉伸试验机 | C99: 100kN | D99: 国产 | E99: 台 | G99: 1 | H99: =G99 -> 1 | I99: 18 | J99: =I99*H99 -> 18
A100: 9 | B100: 布式硬度计 | C100: 650HB | D100: 国产 | E100: 台 | G100: 1 | H100: =G100 -> 1 | I100: 1.5 | J100: =I100*H100 -> 1.5
...

Sheet 招标基本情况表
A1: 附表4
B2: 招 标 基 本 情 况 表
A4: =总概!A3:E3 -> 项目名称：大连船舶重工集团装备制造有限公司装备制造基地建设项目（二期）
A5: 序号 | B5: 项目名称 | C5: 招标范围 | E5: 招标组织形式 | G5: 招标方式 | I5: 不采用 招标方式 | J5: 说明
C6: 全部招标 | D6: 部分招标 | E6: 自行招标 | F6: 委托招标 | G6: 公开招标 | H6: 邀请招标
A7: 一 | B7: 勘察 | I7: √ | J7: 单项合同低于50万元
A8: 二 | B8: 设计 | I8: √ | J8: 项目专业性强
A9: 三 | B9: 建筑工程 | D9: √ | F9: √ | G9: √
A10: 四 | B10: 安装工程 | I10: √ | J10: 单项合同金额低于200万元
A11: 五 | B11: 监理 | I11: √ | J11: 单项合同低于50万元
A12: 六 | B12: 重要材料 | J12: 无此项内容
A13: 七 | B13: 其它 | J13: 无此项内容
