Workbook
Name _: #REF!
Name _: #REF!
Name __bli3: #REF!
Name __bli5: #REF!
Name __bzz240: #REF!
Name __clt176: #REF!
Name __clt221: #REF!
Name __clt29: #REF!
Name __clt88: #REF!
Name __cyc272: #REF!
Name __cyy10: #REF!
Name __dhj25: #REF!
Name __dlg1: #REF!
Name __dwb100: #REF!
Name __dwb25: #REF!
Name __dwb50: #REF!
Name __dwc80: #REF!
Name __dzc40: #REF!
Name __dzc50: #REF!
Name __dzc60: #REF!
Name __dzc70: #REF!
Name __dzc80: #REF!
Name __dzj4: #REF!
Name __fmt1000: #REF!
Name __fmt350: #REF!
Name __fmt400: #REF!
Name __gbz16: #REF!
Name __gfl100: #REF!
Name __gfl15: #REF!
Name __gfl150: #REF!
Name __gfl20: #REF!
Name __gfl200: #REF!
Name __gfl25: #REF!
Name __gfl250: #REF!
Name __gfl300: #REF!
Name __gfl32: #REF!
Name __gfl350: #REF!
Name __gfl40: #REF!
Name __gfl400: #REF!
Name __gfl450: #REF!
Name __gfl50: #REF!
Name __gfl80: #REF!
Name __ggd43: #REF!
Name __gkz100: #REF!
Name __gkz20: #REF!
Name __gkz32: #REF!
Name __gkz50: #REF!
Name __gpc176: #REF!
Name __gpc221: #REF!
Name __gpc279: #REF!
Name __gyb100: #REF!
Name __gyb200: #REF!
Name __gyb30: #REF!
Name __gyb60: #REF!
Name __hlt1: #REF!
Name __hlt10: #REF!
Name __hlt11: #REF!
Name __hlt12: #REF!
Name __hlt13: #REF!
Name __hlt14: #REF!

Sheet 总概
A1: 附表1-1 | AB1: 440.832 | AD1: 440.832 | AE1: 123.5496
A2: 总 概 算 表
A3: 项目名称:武船重型工程股份有限公司双柳基地桥梁区办公楼及珠港澳大桥生产设备建设项目 | S3: 单位：万元、万美元
A4: 序 号 | B4: 总图 编号 | C4: 工程项目和费用名称 | D4: 建筑面积(m2) | F4: 建 筑 工 程 | N4: 设备工程 | Q4: 安装 工程 | R4: 其他 费用 | S4: 工具器 具及生 产家具 | T4: 合计 | U4: 外汇 额度
D5: 新建 | E5: 改造 | F5: 建筑物 | G5: 构筑物 | H5: 设备 基础 | I5: 给排水 | J5: 采暖 通风 | K5: 动力 工程 | L5: 电气 工程 | M5: 小计 | N5: 公用 设备 | O5: 工艺 设备 | P5: 小计 | T5: 合计
C6: 第一部分：工程费用项目
C7: 一、生产性项目
B8: 2601# | C8: 综合办公楼 | D8: 12222.11 | F8: =汇总表!G11 -> 4265.5875 | I8: =汇总表!E14 -> 137.63698 | J8: =汇总表!E15 -> 269.69616 | L8: =汇总表!E16 -> 274.95907 | M8: =SUM(F8:L8) -> 4947.8797 | N8: =公用设备表!G56 -> 650.23 | P8: =SUM(N8:O8) -> 650.23 | T8: =SUM(M8,P8,Q8,R8) -> 5598.1097 | V8: =SUM(#REF!,#REF!,#REF!) -> #REF! | W8: =SUM(#REF!,#REF!,#REF!) -> #REF! | X8: =SUM(#REF!,#REF!,#REF!) -> #REF! | Y8: =SUM(#REF!,#REF!,#REF!) -> #REF! | Z8: =SUM(#REF!,#REF!,#REF!) -> #REF! | AA8: =SUM(#REF!,#REF!,#REF!) -> #REF! | AB8: =(M8-G8)/D8 -> 0.40483024 | AC8: =T8/D8 -> 0.45803136
C9: 珠港澳大桥生产设备 | H9: =工艺设备!K95 -> 158.778 | M9: =SUM(F9:L9) -> 158.778 | O9: =工艺设备!H95 -> 10027.155 | P9: =SUM(N9:O9) -> 10027.155 | Q9: =工艺设备!J95 -> 77.7795 | T9: =SUM(M9,P9,Q9,R9) -> 10263.713
M10: =SUM(F10:L10) -> 0 | P10: =SUM(N10:O10) -> 0 | T10: =SUM(M10,P10,Q10,R10) -> 0
C11: 小 计 | D11: =SUM(D8:D10) -> 12222.11 | E11: =SUM(E8:E10) -> 0 | F11: =SUM(F8:F10) -> 4265.5875 | G11: =SUM(G8:G10) -> 0 | H11: =SUM(H8:H10) -> 158.778 | I11: =SUM(I8:I10) -> 137.63698 | J11: =SUM(J8:J10) -> 269.69616 | K11: =SUM(K8:K10) -> 0 | ... T11: =SUM(T8:T10) -> 15861.822 | U11: =U8 -> 0 | V11: =SUM(V8:V8) -> #REF! | W11: =SUM(W8:W8) -> #REF! | X11: =SUM(X8:X8) -> #REF! | Y11: =SUM(Y8:Y8) -> #REF! | Z11: =SUM(Z8:Z8) -> #REF! | AA11: =SUM(AA8:AA8) -> #REF!
C13: 二、总图设施项目 | T13: =SUM(M13,P13,Q13) -> 0
A14: 1 | C14: 道路、广场 | F14: =3944*260/10000 -> 102.544 | M14: =SUM(F14:L14) -> 102.544 | T14: =SUM(M14,P14,Q14) -> 102.544
A15: 2 | C15: 绿化 | F15: =3046*100/10000 -> 30.46 | M15: =SUM(F15:L15) -> 30.46 | T15: =SUM(M15,P15,Q15) -> 30.46
A16: 3 | C16: 室外给排水工程 | I16: =外水费!G31/10000 -> 35.454305 | M16: =SUM(F16:L16) -> 35.454305 | T16: =SUM(M16,P16,Q16) -> 35.454305
A17: 4 | C17: 室外电气工程 | L17: =外电费!G31/10000 -> 29.011947 | M17: =SUM(F17:L17) -> 29.011947 | T17: =SUM(M17,P17,Q17) -> 29.011947
C19: 小 计 | D19: =SUM(D14:D18) -> 0 | E19: =SUM(E14:E18) -> 0 | F19: =SUM(F14:F18) -> 133.004 | G19: =SUM(G14:G18) -> 0 | H19: =SUM(H14:H18) -> 0 | I19: =SUM(I14:I18) -> 35.454305 | J19: =SUM(J14:J18) -> 0 | K19: =SUM(K14:K18) -> 0 | ... N19: =SUM(N14:N18) -> 0 | P19: =SUM(P14:P18) -> 0 | T19: =SUM(T14:T18) -> 197.47025
C21: 第一部分合计 | D21: =D19+D11 -> 12222.11 | E21: =E19+E11 -> 0 | F21: =F19+F11 -> 4398.5915 | G21: =G19+G11 -> 0 | H21: =H19+H11 -> 158.778 | I21: =I19+I11 -> 173.09128 | J21: =J19+J11 -> 269.69616 | K21: =K19+K11 -> 0 | ... U21: =U19+U11 -> 0 | V21: =SUM(V11,V19,#REF!) -> #REF! | W21: =SUM(W11,W19,#REF!) -> #REF! | X21: =SUM(X11,X19,#REF!) -> #REF! | Y21: =SUM(Y11,Y19,#REF!) -> #REF! | Z21: =SUM(Z11,Z19,#REF!) -> #REF! | AA21: =SUM(AA11,AA19,#REF!) -> #REF! | AC21: =SUM(F21,H21,I21,J21,K21,L21,N21,O21,Q21,R21,S21) -> 16059.292
C23: 第二部分：其他费用
A24: 1 | C24: =其他!B7 -> 建设单位管理费 | R24: =其他!G7 -> 175.4 | T24: =R24 -> 175.4
A25: 2 | C25: =其他!B8 -> 前期工作费 | R25: =其他!G8 -> 75.405 | T25: =R25 -> 75.405
A26: 3 | C26: =其他!B9 -> 工程建设监理费 | R26: =其他!G9 -> 128.46361 | T26: =R26 -> 128.46361
A27: 4 | C27: =其他!B10 -> 工程设计费 | R27: =其他!G10 -> 358.92541 | T27: =R27 -> 358.92541 | AB27: =M21+Q21 -> 5381.9074 | AC27: =M45+N45+Q45 -> 6032.1374
A28: 5 | C28: =其他!B11 -> 施工图审查费 | R28: =其他!G11 -> 17.94627 | T28: =R28 -> 17.94627 | AB28: =M45+Q45+N45 -> 6032.1374
A29: 6 | C29: =其他!B12 -> 工程勘察费 | R29: =其他!G12 -> 18.333165 | T29: =R29 -> 18.333165
A30: 7 | C30: =其他!B13 -> 招标代理服务费 | R30: =其他!G13 -> 79 | T30: =R30 -> 79
A31: 8 | C31: =其他!B14 -> 环境评价收费 | R31: =其他!G14 -> 16.641176 | T31: =R31 -> 16.641176
A32: 9 | C32: =其他!B15 -> 劳动安全卫生评价费 | R32: =其他!G15 -> 22.4 | T32: =R32 -> 22.4
C33: 第二部分小计 | R33: =SUM(R24:R32) -> 892.51463 | T33: =R33 -> 892.51463
C35: 第一、二部分合计 | D35: =D33+D21 -> 12222.11 | E35: =E33+E21 -> 0 | F35: =F33+F21 -> 4398.5915 | G35: =G33+G21 -> 0 | H35: =H33+H21 -> 158.778 | I35: =I33+I21 -> 173.09128 | J35: =J33+J21 -> 269.69616 | K35: =K33+K21 -> 0 | ... T35: =T33+T21 -> 16951.807 | U35: =SUM(U21,U33) -> 0 | V35: =SUM(V21,V33) -> #REF! | W35: =SUM(W21,W33) -> #REF! | X35: =SUM(X21,X33) -> #REF! | Y35: =SUM(Y21,Y33) -> #REF! | Z35: =SUM(Z21,Z33) -> #REF! | AA35: =SUM(AA21,AA33) -> #REF!
C37: 第三部分：基本预备费 | R37: =(T35)*5%+0.612155334416457 -> 848.20251 | T37: =R37 -> 848.20251
C39: 第四部分：动态投资
A40: 1 | C40: 综合预备费(动态预备费)
A41: 2 | C41: 建设期贷款利息 | R41: 0 | T41: =R41 -> 0
A42: 3 | C42: 固定资产投资方向调节税
C43: 动态投资合计 | R43: =SUM(R40:R42) -> 0 | T43: =SUM(T40:T42) -> 0
C45: 建设项目总投资 | D45: =D37+D35 -> 12222.11 | E45: =E37+E35 -> 0 | F45: =F37+F35 -> 4398.5915 | G45: =G37+G35 -> 0 | H45: =H37+H35 -> 158.778 | I45: =I37+I35 -> 173.09128 | J45: =J37+J35 -> 269.69616 | K45: =K37+K35 -> 0 | ... T45: =T37+T35 -> 17800.01 | U45: =U37+U35+U21 -> 0
T47: 17800 | U47: 0.14790845
B48: 序号 | C48: 工程费名称 | D48: 投资额 (万元) | E48: 占投资数（%） | F48: 其中外汇（万美元） | S48: 0.61215533 | T48: =T47-T45 -> -0.0095807972 | AB48: =T33/T21 -> 0.055576211
B49: 1 | C49: 建筑工程费 | D49: =M45 -> 5304.1279 | E49: =D49/$D$54 -> 0.29798456
B50: 2 | C50: 设备工程费 | D50: =P45 -> 10677.385 | E50: =D50/$D$54 -> 0.59985277 | AC50: =M45+Q45+O45*0.4 -> 9392.7694
B51: 3 | C51: 安装工程费 | D51: =Q45 -> 77.7795 | E51: =D51/$D$54 -> 0.0043696325
B52: 4 | C52: 工程建设其他费用 | D52: =T33 -> 892.51463 | E52: =D52/$D$54 -> 0.050141244
B53: 5 | C53: 基本预备费 | D53: =R37 -> 848.20251 | E53: =D53/$D$54 -> 0.047651801
C54: 合 计 | D54: =SUM(D49:D53) -> 17800.01 | E54: =SUM(E49:E53) -> 1 | F54: =SUM(F49:F53) -> 0

Sheet 其他
A1: 附表1-2
A2: 其它费用估算表
A4: 序号 | B4: 工程或费用名称 | C4: 收费依据 | D4: 单位 | E4: 单位指标 | F4: 计算基数 | G4: 投资 （万元）
A6: 一 | B6: 其他费用 | G6: =SUM(G7:G10,G11:G16) -> 892.51463
A7: 1 | B7: 建设单位管理费 | C7: 财建[2002]394号文 | D7: 万元 | F7: =总概!T47 -> 17800 | G7: =113+(F7-10000)*0.8% -> 175.4
A8: 2 | B8: 前期工作费 | C8: 计价格[1999]1283号文 | D8: 万元 | E8: 插入法 | F8: =F7 -> 17800 | G8: =(60+(F8-10000)*(139-60)/40000) -> 75.405
A9: 3 | B9: 工程建设监理费 | C9: 发改价格[2007]670号文 | D9: 万元 | E9: 插入法 | F9: =总概!M45+总概!Q45 -> 5381.9074 | G9: =(120.8+(F9-5000)*(181-120.8)/3000) -> 128.46361
A10: 4 | B10: 工程设计费 | C10: 计价格[2002]10号文 | D10: 万元 | E10: 插入法 | F10: =总概!T21 -> 16059.292 | G10: =(304.8+(F10-10000)*(566.8-304.8)/10000)*35%*1.15*1.25+(163.9+(H10-5000)*(249.6-163.9)/3000)*65% -> 358.92541 | H10: =总概!M45+总概!Q45+总概!N45 -> 6032.1374
A11: 5 | B11: 施工图审查费 | C11: 发改价格[2011]534号文 | D11: 万元 | E11: 0.05 | F11: =G10 -> 358.92541 | G11: =F11*E11 -> 17.94627
A12: 6 | B12: 工程勘察费 | C12: 计价格[2002]10号文 | D12: 万元 | E12: 15元/m2 | F12: =总概!D45 -> 12222.11 | G12: =F12*15/10000 -> 18.333165 | H12: 工程 | I12: 公用设备 | J12: 工艺设备
A13: 7 | B13: 招标代理服务费 | C13: 计价格[2002]1980号文 | D13: 万元 | G13: 79 | H13: =[18]估算表!F27 -> 24171.334 | I13: =[18]估算表!G27 -> 3057.035
A14: 8 | B14: 环境评价收费 | C14: 计价格[2002]125号文 | D14: 万元 | F14: =F7 -> 17800 | G14: =7.5+(F14-3000)*(18-7.5)/(20000-3000) -> 16.641176
A15: 9 | B15: 劳动安全卫生评价费 | C15: 地方有关规定 | D15: 万元 | G15: 22.4
A18: 二 | B18: 基本预备费 | C18: 科工法［2005］496号 | E18: =G18/F18 -> 0.050036112 | F18: =总概!T35 -> 16951.807 | G18: =总概!T37 -> 848.20251
B20: 合计 | G20: =SUM(G6,G18:G18) -> 1740.7171

Sheet 工艺设备
A1: 附表1-3
A2: 工艺设备明细及概算表
A4: 序号 | B4: 设备名称 | C4: 设 备 购 置 费 | J4: 安装 调试费 | K4: 设备 基础费 | L4: 备注
C5: 设备价格(万元、万美元) | E5: 关税 增值税 | F5: 进口 费用 | G5: 国内 运杂费 | H5: 合价 | I5: 其中： 外币
C6: 共计 | D6: 其中外汇
A7: =新增工艺设备!A6 -> 一 | B7: =新增工艺设备!B6 -> 板单元生产线 | C7: =新增工艺设备!H6 -> 0 | D7: =新增工艺设备!I6 -> 0
A8: =新增工艺设备!A7 -> （一） | B8: =新增工艺设备!B7 -> 钢材预处理生产线 | C8: =新增工艺设备!H7 -> 0 | D8: =新增工艺设备!I7 -> 0 | H8: =C8+E8+F8+G8 -> 0
A9: =新增工艺设备!A8 -> 1.1 | B9: =新增工艺设备!B8 -> 钢板矫平机 | C9: =新增工艺设备!H8 -> 993.6 | D9: =新增工艺设备!I8 -> 0 | G9: =C9*6% -> 59.616 | H9: =C9+E9+F9+G9 -> 1053.216 | K9: =C9*3% -> 29.808
A10: =新增工艺设备!A9 -> （二） | B10: =新增工艺设备!B9 -> 下料切割生产线 | C10: =新增工艺设备!H9 -> 0 | D10: =新增工艺设备!I9 -> 0 | H10: =C10+E10+F10+G10 -> 0
A11: =新增工艺设备!A10 -> 1 | B11: =新增工艺设备!B10 -> 数控等离子切割机 | C11: =新增工艺设备!H10 -> 92.2 | D11: =新增工艺设备!I10 -> 0 | G11: =C11*6% -> 5.532 | H11: =C11+E11+F11+G11 -> 97.732 | K11: =C11*3% -> 2.766
A12: =新增工艺设备!A11 -> 2 | B12: =新增工艺设备!B11 -> 数控火焰切割机 | C12: =新增工艺设备!H11 -> 95.6 | D12: =新增工艺设备!I11 -> 0 | G12: =C12*6% -> 5.736 | H12: =C12+E12+F12+G12 -> 101.336 | K12: =C12*3% -> 2.868
A13: =新增工艺设备!A12 -> 3 | B13: =新增工艺设备!B12 -> 门式多头火焰切割机 | C13: =新增工艺设备!H12 -> 103.5 | D13: =新增工艺设备!I12 -> 0 | G13: =C13*6% -> 6.21 | H13: =C13+E13+F13+G13 -> 109.71 | K13: =C13*3% -> 3.105
A14: =新增工艺设备!A13 -> 4 | B14: =新增工艺设备!B13 -> 数控划线号料机 | C14: =新增工艺设备!H13 -> 98.6 | D14: =新增工艺设备!I13 -> 0 | G14: =C14*6% -> 5.916 | H14: =C14+E14+F14+G14 -> 104.516 | K14: =C14*3% -> 2.958
A15: =新增工艺设备!A14 -> （三） | B15: =新增工艺设备!B14 -> U肋生产线 | C15: =新增工艺设备!H14 -> 0 | D15: =新增工艺设备!I14 -> 0 | H15: =C15+E15+F15+G15 -> 0
A16: =新增工艺设备!A15 -> 1 | B16: =新增工艺设备!B15 -> 坡口铣边机 | C16: =新增工艺设备!H15 -> 240 | D16: =新增工艺设备!I15 -> 0 | G16: =C16*6% -> 14.4 | H16: =C16+E16+F16+G16 -> 254.4 | K16: =C16*3% -> 7.2
A17: =新增工艺设备!A16 -> 2 | B17: =新增工艺设备!B16 -> 双头坡口铣边机 | C17: =新增工艺设备!H16 -> 70 | D17: =新增工艺设备!I16 -> 0 | G17: =C17*6% -> 4.2 | H17: =C17+E17+F17+G17 -> 74.2 | K17: =C17*3% -> 2.1
A18: =新增工艺设备!A17 -> 3 | B18: =新增工艺设备!B17 -> R2倒角机 | C18: =新增工艺设备!H17 -> 40 | D18: =新增工艺设备!I17 -> 0 | G18: =C18*6% -> 2.4 | H18: =C18+E18+F18+G18 -> 42.4 | K18: =C18*3% -> 1.2
A19: =新增工艺设备!A18 -> 4 | B19: =新增工艺设备!B18 -> U肋板矫平机 | C19: =新增工艺设备!H18 -> 90 | D19: =新增工艺设备!I18 -> 0 | G19: =C19*6% -> 5.4 | H19: =C19+E19+F19+G19 -> 95.4 | K19: =C19*3% -> 2.7
A20: =新增工艺设备!A19 -> 5 | B20: =新增工艺设备!B19 -> 数控多边坡口成型机 | C20: =新增工艺设备!H19 -> 372 | D20: =新增工艺设备!I19 -> 0 | G20: =C20*6% -> 22.32 | H20: =C20+E20+F20+G20 -> 394.32 | J20: =C20*8% -> 29.76
A21: =新增工艺设备!A20 -> 6 | B21: =新增工艺设备!B20 -> 双台联动电液伺服数控折弯机 | C21: =新增工艺设备!H20 -> 404.5 | D21: =新增工艺设备!I20 -> 0 | G21: =C21*6% -> 24.27 | H21: =C21+E21+F21+G21 -> 428.77
A22: =新增工艺设备!A21 -> （四） | B22: =新增工艺设备!B21 -> U肋板单元生产线 | C22: =新增工艺设备!H21 -> 0 | D22: =新增工艺设备!I21 -> 0 | H22: =C22+E22+F22+G22 -> 0
A23: =新增工艺设备!A22 -> 1 | B23: =新增工艺设备!B22 -> U肋端口栓孔定位装置 | C23: =新增工艺设备!H22 -> 55.9 | D23: =新增工艺设备!I22 -> 0 | G23: =C23*6% -> 3.354 | H23: =C23+E23+F23+G23 -> 59.254
A24: =新增工艺设备!A23 -> 2 | B24: =新增工艺设备!B23 -> 移动式U肋装配机 | C24: =新增工艺设备!H23 -> 222.4 | D24: =新增工艺设备!I23 -> 0 | G24: =C24*6% -> 13.344 | H24: =C24+E24+F24+G24 -> 235.744
A25: =新增工艺设备!A24 -> 3 | B25: =新增工艺设备!B24 -> U肋龙门焊接系统 | C25: =SUM(C26:C27) -> 838.7 | D25: =SUM(D26:D27) -> 0 | E25: =SUM(E26:E27) -> 0 | F25: =SUM(F26:F27) -> 0 | G25: =SUM(G26:G27) -> 50.322 | H25: =SUM(H26:H27) -> 889.022 | I25: =SUM(I26:I27) -> 0 | J25: =SUM(J26:J27) -> 0 | ... L25: =SUM(L26:L27) -> 0
A26: =新增工艺设备!A25 -> 1 | B26: =新增工艺设备!B25 -> U肋龙门焊接机 | C26: =新增工艺设备!H25 -> 718.7 | D26: =新增工艺设备!I25 -> 0 | G26: =C26*6% -> 43.122 | H26: =C26+E26+F26+G26 -> 761.822 | K26: =C26*3% -> 21.561
A27: =新增工艺设备!A26 -> 2 | B27: =新增工艺设备!B26 -> 逆变埋弧自动焊机 | C27: =新增工艺设备!H26 -> 120 | D27: =新增工艺设备!I26 -> 0 | G27: =C27*6% -> 7.2 | H27: =C27+E27+F27+G27 -> 127.2 | K27: =C27*3% -> 3.6
A28: =新增工艺设备!A27 -> 4 | B28: =新增工艺设备!B27 -> U肋板单元机械滚压矫正机 | C28: =新增工艺设备!H27 -> 417.9 | D28: =新增工艺设备!I27 -> 0 | G28: =C28*6% -> 25.074 | H28: =C28+E28+F28+G28 -> 442.974 | K28: =C28*3% -> 12.537
A29: =新增工艺设备!A28 -> 5 | B29: =新增工艺设备!B28 -> 底板对齐装配胎架 | C29: =新增工艺设备!H28 -> 78.8 | D29: =新增工艺设备!I28 -> 0 | G29: =C29*6% -> 4.728 | H29: =C29+E29+F29+G29 -> 83.528
A30: =新增工艺设备!A29 -> 6 | B30: =新增工艺设备!B29 -> U肋反变形焊接系统 | C30: =SUM(C31:C32) -> 686.4 | D30: =SUM(D31:D32) -> 0 | E30: =SUM(E31:E32) -> 0 | F30: =SUM(F31:F32) -> 0 | G30: =SUM(G31:G32) -> 41.184 | H30: =SUM(H31:H32) -> 727.584 | I30: =SUM(I31:I32) -> 0 | J30: =SUM(J31:J32) -> 0 | K30: =SUM(K31:K32) -> 0
A31: =新增工艺设备!A30 -> 1 | B31: =新增工艺设备!B30 -> 可调式液压反变形胎架 | C31: =新增工艺设备!H30 -> 446.4 | D31: =新增工艺设备!I30 -> 0 | G31: =C31*6% -> 26.784 | H31: =C31+E31+F31+G31 -> 473.184
A32: =新增工艺设备!A31 -> 2 | B32: =新增工艺设备!B31 -> CO2气体保护焊机 | C32: =新增工艺设备!H31 -> 240 | D32: =新增工艺设备!I31 -> 0 | G32: =C32*6% -> 14.4 | H32: =C32+E32+F32+G32 -> 254.4
A33: =新增工艺设备!A32 -> （五） | B33: =新增工艺设备!B32 -> 板肋板单元生产线 | C33: =新增工艺设备!H32 -> 0 | D33: =新增工艺设备!I32 -> 0 | H33: =C33+E33+F33+G33 -> 0
A34: =新增工艺设备!A33 -> 1 | B34: =新增工艺设备!B33 -> 钢板对齐装配胎架 | C34: =新增工艺设备!H33 -> 40.4 | D34: =新增工艺设备!I33 -> 0 | G34: =C34*6% -> 2.424 | H34: =C34+E34+F34+G34 -> 42.824
A35: =新增工艺设备!A34 -> 2 | B35: =新增工艺设备!B34 -> 板肋定位装置 | C35: =新增工艺设备!H34 -> 24.2 | D35: =新增工艺设备!I34 -> 0 | G35: =C35*6% -> 1.452 | H35: =C35+E35+F35+G35 -> 25.652
A36: =新增工艺设备!A35 -> 3 | B36: =新增工艺设备!B35 -> 移动式板肋装配机 | C36: =新增工艺设备!H35 -> 289.9 | D36: =新增工艺设备!I35 -> 0 | G36: =C36*6% -> 17.394 | H36: =C36+E36+F36+G36 -> 307.294
A37: =新增工艺设备!A36 -> 4 | B37: =新增工艺设备!B36 -> 板肋板单元对齐压紧焊接胎架 | C37: =新增工艺设备!H36 -> 80.8 | D37: =新增工艺设备!I36 -> 0 | G37: =C37*6% -> 4.848 | H37: =C37+E37+F37+G37 -> 85.648
A38: =新增工艺设备!A37 -> 5 | B38: =新增工艺设备!B37 -> 十头双丝双边板肋龙门焊接机 | C38: =新增工艺设备!H37 -> 485.3 | D38: =新增工艺设备!I37 -> 0 | G38: =C38*6% -> 29.118 | H38: =C38+E38+F38+G38 -> 514.418 | K38: =C38*3% -> 14.559
A39: =新增工艺设备!A38 -> 6 | B39: =新增工艺设备!B38 -> 板肋板单元机械滚压矫正机 | C39: =新增工艺设备!H38 -> 445.1 | D39: =新增工艺设备!I38 -> 0 | G39: =C39*6% -> 26.706 | H39: =C39+E39+F39+G39 -> 471.806 | K39: =C39*3% -> 13.353
A40: =新增工艺设备!A39 -> （六） | B40: =新增工艺设备!B39 -> 横隔板单元件生产线 | C40: =新增工艺设备!H39 -> 0 | D40: =新增工艺设备!I39 -> 0 | H40: =C40+E40+F40+G40 -> 0
A41: =新增工艺设备!A40 -> 1 | B41: =新增工艺设备!B40 -> 钢板对齐装配胎架 | C41: =新增工艺设备!H40 -> 56.7 | D41: =新增工艺设备!I40 -> 0 | G41: =C41*6% -> 3.402 | H41: =C41+E41+F41+G41 -> 60.102
A42: =新增工艺设备!A41 -> 2 | B42: =新增工艺设备!B41 -> 焊机存放移动龙门架 | C42: =新增工艺设备!H41 -> 232.8 | D42: =新增工艺设备!I41 -> 0 | G42: =C42*6% -> 13.968 | H42: =C42+E42+F42+G42 -> 246.768 | K42: =C42*3% -> 6.984
A43: =新增工艺设备!A42 -> 3 | B43: =新增工艺设备!B42 -> 压点可移动油压矫正机 | C43: =新增工艺设备!H42 -> 310.5 | D43: =新增工艺设备!I42 -> 0 | G43: =C43*6% -> 18.63 | H43: =C43+E43+F43+G43 -> 329.13 | K43: =C43*3% -> 9.315
A44: =新增工艺设备!A43 -> 4 | B44: =新增工艺设备!B43 -> 横隔板焊接机器人系统 | C44: =新增工艺设备!H43 -> 475 | D44: =新增工艺设备!I43 -> 0 | G44: =C44*6% -> 28.5 | H44: =C44+E44+F44+G44 -> 503.5 | K44: =C44*3% -> 14.25
A45: =新增工艺设备!A44 -> （七） | B45: =新增工艺设备!B44 -> T型梁单元件生产线 | C45: =新增工艺设备!H44 -> 0 | D45: =新增工艺设备!I44 -> 0 | H45: =C45+E45+F45+G45 -> 0
A46: =新增工艺设备!A45 -> 1 | B46: =新增工艺设备!B45 -> T型梁装焊矫正机 | C46: =新增工艺设备!H45 -> 51.8 | D46: =新增工艺设备!I45 -> 0 | G46: =C46*6% -> 3.108 | H46: =C46+E46+F46+G46 -> 54.908 | K46: =C46*3% -> 1.554
A47: =新增工艺设备!A46 -> （八） | B47: =新增工艺设备!B46 -> 钢塔生产线 | C47: =新增工艺设备!H46 -> 0 | D47: =新增工艺设备!I46 -> 0 | H47: =C47+E47+F47+G47 -> 0
A48: =新增工艺设备!A47 -> 1 | B48: =新增工艺设备!B47 -> 数控落地铣镗床 | C48: =新增工艺设备!H47 -> 698.5 | D48: =新增工艺设备!I47 -> 0 | G48: =C48*6% -> 41.91 | H48: =C48+E48+F48+G48 -> 740.41
A49: =新增工艺设备!A48 -> 2 | B49: =新增工艺设备!B48 -> 龙门数控钻床 | C49: =新增工艺设备!H48 -> 212 | D49: =新增工艺设备!I48 -> 0 | G49: =C49*6% -> 12.72 | H49: =C49+E49+F49+G49 -> 224.72 | K49: =C49*3% -> 6.36
A50: =新增工艺设备!A49 -> 3 | B50: =新增工艺设备!B49 -> 铣镗床加工调整平台 | C50: =新增工艺设备!H49 -> 204 | D50: =新增工艺设备!I49 -> 0 | H50: =C50+E50+F50+G50 -> 204
A51: =新增工艺设备!A50 -> 4 | B51: =新增工艺设备!B50 -> 摇臂转床 | C51: =新增工艺设备!H50 -> 20 | D51: =新增工艺设备!I50 -> 0 | G51: =C51*6% -> 1.2 | H51: =C51+E51+F51+G51 -> 21.2
A52: =新增工艺设备!A51 -> 5 | B52: =新增工艺设备!B51 -> 桥式起重机220t | C52: =新增工艺设备!H51 -> 330 | D52: =新增工艺设备!I51 -> 0 | H52: =C52+E52+F52+G52 -> 330 | J52: =C52*10% -> 33
A53: =新增工艺设备!A52 -> （九） | B53: =新增工艺设备!B52 -> 焊接切割小型设备 | C53: =新增工艺设备!H52 -> 0 | D53: =新增工艺设备!I52 -> 0 | H53: =C53+E53+F53+G53 -> 0
A54: =新增工艺设备!A53 -> 1 | B54: =新增工艺设备!B53 -> 全位置焊接小车 | C54: =新增工艺设备!H53 -> 20 | D54: =新增工艺设备!I53 -> 0 | H54: =C54+E54+F54+G54 -> 20
A55: =新增工艺设备!A54 -> 2 | B55: =新增工艺设备!B54 -> 半自动切割机 | C55: =新增工艺设备!H54 -> 40.02 | D55: =新增工艺设备!I54 -> 0 | H55: =C55+E55+F55+G55 -> 40.02
A56: =新增工艺设备!A55 -> 3 | B56: =新增工艺设备!B55 -> 全位置切割机 | C56: =新增工艺设备!H55 -> 20 | D56: =新增工艺设备!I55 -> 0 | H56: =C56+E56+F56+G56 -> 20
A57: =新增工艺设备!A56 -> 0 | B57: =新增工艺设备!B56 -> 0 | C57: =新增工艺设备!H56 -> 0 | D57: =新增工艺设备!I56 -> 0 | H57: =C57+E57+F57+G57 -> 0
A58: =新增工艺设备!A57 -> 0 | B58: =新增工艺设备!B57 -> 小 计 | C58: =SUM(C9:C25)+C28+C29+C30+SUM(C34:C56) -> 8937.12 | D58: =SUM(D9:D25)+D28+D29+D30+SUM(D34:D56) -> 0 | E58: =SUM(E9:E25)+E28+E29+E30+SUM(E34:E56) -> 0 | F58: =SUM(F9:F25)+F28+F29+F30+SUM(F34:F56) -> 0 | G58: =SUM(G9:G25)+G28+G29+G30+SUM(G34:G56) -> 499.386 | H58: =SUM(H9:H25)+H28+H29+H30+SUM(H34:H56) -> 9436.506 | I58: =SUM(I9:I25)+I28+I29+I30+SUM(I34:I56) -> 0 | J58: =SUM(J9:J25)+J28+J29+J30+SUM(J34:J56) -> 62.76 | K58: =SUM(K9:K25)+K28+K29+K30+SUM(K34:K56) -> 158.778
A59: =新增工艺设备!A58 -> 0 | B59: =新增工艺设备!B58 -> 0 | C59: =新增工艺设备!H58 -> 0 | D59: =新增工艺设备!I58 -> 0 | H59: =C59+E59+F59+G59 -> 0
A60: =新增工艺设备!A59 -> 二 | B60: =新增工艺设备!B59 -> 测量设备 | C60: =新增工艺设备!H59 -> 0 | D60: =新增工艺设备!I59 -> 0 | H60: =C60+E60+F60+G60 -> 0
A61: =新增工艺设备!A60 -> 1 | B61: =新增工艺设备!B60 -> 油漆干膜测厚仪 | C61: =新增工艺设备!H60 -> 5 | D61: =新增工艺设备!I60 -> 0 | H61: =C61+E61+F61+G61 -> 5
A62: =新增工艺设备!A61 -> 2 | B62: =新增工艺设备!B61 -> 激光经纬仪 | C62: =新增工艺设备!H61 -> 10 | D62: =新增工艺设备!I61 -> 0 | H62: =C62+E62+F62+G62 -> 10
A63: =新增工艺设备!A62 -> 3 | B63: =新增工艺设备!B62 -> 电子全站仪 | C63: =新增工艺设备!H62 -> 69.999 | D63: =新增工艺设备!I62 -> 0 | H63: =C63+E63+F63+G63 -> 69.999
A64: =新增工艺设备!A63 -> 4 | B64: =新增工艺设备!B63 -> 拉拔（附着力测试）仪 | C64: =新增工艺设备!H63 -> 2 | D64: =新增工艺设备!I63 -> 0 | H64: =C64+E64+F64+G64 -> 2
A65: =新增工艺设备!A64 -> 5 | B65: =新增工艺设备!B64 -> 露点测试仪 | C65: =新增工艺设备!H64 -> 3 | D65: =新增工艺设备!I64 -> 0 | H65: =C65+E65+F65+G65 -> 3
A66: =新增工艺设备!A65 -> 0 | B66: =新增工艺设备!B65 -> 0 | C66: =新增工艺设备!H65 -> 0 | D66: =新增工艺设备!I65 -> 0 | H66: =C66+E66+F66+G66 -> 0
A67: =新增工艺设备!A66 -> 0 | B67: =新增工艺设备!B66 -> 小 计 | C67: =SUM(C61:C66) -> 89.999 | D67: =SUM(D61:D66) -> 0 | E67: =SUM(E61:E66) -> 0 | F67: =SUM(F61:F66) -> 0 | G67: =SUM(G61:G66) -> 0 | H67: =SUM(H61:H66) -> 89.999 | I67: =SUM(I61:I66) -> 0 | J67: =SUM(J61:J66) -> 0 | K67: =SUM(K61:K66) -> 0
A68: =新增工艺设备!A67 -> 0 | B68: =新增工艺设备!B67 -> 0 | C68: =新增工艺设备!H67 -> 0 | D68: =新增工艺设备!I67 -> 0 | H68: =C68+E68+F68+G68 -> 0
A69: =新增工艺设备!A68 -> 三 | B69: =新增工艺设备!B68 -> 监控设备 | C69: =新增工艺设备!H68 -> 0 | D69: =新增工艺设备!I68 -> 0 | H69: =C69+E69+F69+G69 -> 0
A70: =新增工艺设备!A69 -> 1 | B70: =新增工艺设备!B69 -> 监控系统
A71: =新增工艺设备!A70 -> 1 | B71: =新增工艺设备!B70 -> 红外摄像头 | C71: =新增工艺设备!H70 -> 24.4 | D71: =新增工艺设备!I70 -> 0 | H71: =C71+E71+F71+G71 -> 24.4
A72: =新增工艺设备!A71 -> 2 | B72: =新增工艺设备!B71 -> 摄像头电源 | C72: =新增工艺设备!H71 -> 14.64 | D72: =新增工艺设备!I71 -> 0 | H72: =C72+E72+F72+G72 -> 14.64
A73: =新增工艺设备!A72 -> 3 | B73: =新增工艺设备!B72 -> 红外摄像头支架 | C73: =新增工艺设备!H72 -> 0.61 | D73: =新增工艺设备!I72 -> 0 | H73: =C73+E73+F73+G73 -> 0.61
A74: =新增工艺设备!A73 -> 4 | B74: =新增工艺设备!B73 -> 一体化摄像机 | C74: =新增工艺设备!H73 -> 48.8 | D74: =新增工艺设备!I73 -> 0 | H74: =C74+E74+F74+G74 -> 48.8
A75: =新增工艺设备!A74 -> 5 | B75: =新增工艺设备!B74 -> 红外灯板 | C75: =新增工艺设备!H74 -> 12.2 | D75: =新增工艺设备!I74 -> 0 | H75: =C75+E75+F75+G75 -> 12.2
A76: =新增工艺设备!A75 -> 6 | B76: =新增工艺设备!B75 -> 重型云台 | C76: =新增工艺设备!H75 -> 12.2 | D76: =新增工艺设备!I75 -> 0 | H76: =C76+E76+F76+G76 -> 12.2
A77: =新增工艺设备!A76 -> 7 | B77: =新增工艺设备!B76 -> 摄像机外壳 | C77: =新增工艺设备!H76 -> 6.1 | D77: =新增工艺设备!I76 -> 0 | H77: =C77+E77+F77+G77 -> 6.1
A78: =新增工艺设备!A77 -> 8 | B78: =新增工艺设备!B77 -> 解码器 | C78: =新增工艺设备!H77 -> 12.2 | D78: =新增工艺设备!I77 -> 0 | H78: =C78+E78+F78+G78 -> 12.2
A79: =新增工艺设备!A78 -> 9 | B79: =新增工艺设备!B78 -> 光端机 | C79: =新增工艺设备!H78 -> 161.04 | D79: =新增工艺设备!I78 -> 0 | H79: =C79+E79+F79+G79 -> 161.04
A80: =新增工艺设备!A79 -> 10 | B80: =新增工艺设备!B79 -> 防水终端箱 | C80: =新增工艺设备!H79 -> 20 | D80: =新增工艺设备!I79 -> 0 | H80: =C80+E80+F80+G80 -> 20
A81: =新增工艺设备!A80 -> 11 | B81: =新增工艺设备!B80 -> 云台支架 | C81: =新增工艺设备!H80 -> 3.66 | D81: =新增工艺设备!I80 -> 0 | H81: =C81+E81+F81+G81 -> 3.66
A82: =新增工艺设备!A81 -> 12 | B82: =新增工艺设备!B81 -> 熔纤盒 | C82: =新增工艺设备!H81 -> 2 | D82: =新增工艺设备!I81 -> 0 | H82: =C82+E82+F82+G82 -> 2
... A92: =新增工艺设备!A91 -> 0 | B92: =新增工艺设备!B91 -> 0 | C92: =新增工艺设备!H91 -> 0 | D92: =新增工艺设备!I91 -> 0 | H92: =C92+E92+F92+G92 -> 0
A93: =新增工艺设备!A92 -> 0 | B93: =新增工艺设备!B92 -> 小 计 | C93: =SUM(C70:C92) -> 500.65 | D93: =SUM(D70:D92) -> 0 | E93: =SUM(E70:E92) -> 0 | F93: =SUM(F70:F92) -> 0 | G93: =SUM(G70:G92) -> 0 | H93: =SUM(H70:H92) -> 500.65 | I93: =SUM(I70:I92) -> 0 | J93: =C93*3% -> 15.0195 | K93: =SUM(K70:K92) -> 0
A94: =新增工艺设备!A93 -> 0 | B94: =新增工艺设备!B93 -> 0 | C94: =新增工艺设备!H93 -> 0 | D94: =新增工艺设备!I93 -> 0 | H94: =C94+E94+F94+G94 -> 0
A95: ='[19]设备表（董提资）'!A650 -> 0 | B95: ='[19]设备表（董提资）'!B650 -> 总 计 | C95: =C93+C67+C58 -> 9527.769 | D95: =D93+D67+D58 -> 0 | E95: =E93+E67+E58 -> 0 | F95: =F93+F67+F58 -> 0 | G95: =G93+G67+G58 -> 499.386 | H95: =H93+H67+H58 -> 10027.155 | I95: =I93+I67+I58 -> 0 | J95: =J93+J67+J58 -> 77.7795 | ... L95: =L93+L67+L58 -> 0

Sheet 公用设备表
A1: 附表1-4
A2: 公 用 设 备 表
G3: 单位：万元
A4: 序号 | B4: 名称 | C4: 规格型号 | D4: 单位 | E4: 数量 | F4: 单价 | G4: 合价 | H4: 备注
A5: 一 | B5: 电气工程
B6: 强电工程
A7: 1 | B7: 变压器 | C7: SCB11-630/10/0.4KV | D7: 台 | E7: 2 | F7: 18 | G7: =F7*E7 -> 36
A8: 2 | B8: 高压开关柜 | C8: HXGN15-12 | D8: 台 | E8: 4 | F8: 10 | G8: =F8*E8 -> 40
A9: 3 | B9: 抽屉式低压配电柜 | C9: GCS-12 | D9: 台 | E9: 9 | F9: 4 | G9: =F9*E9 -> 36
B10: 弱电工程
A11: 1 | B11: 综合布线系统 | C11: 209点 | D11: 套 | E11: 1 | F11: =209*3000/10000 -> 62.7 | G11: =F11*E11 -> 62.7
A12: 2 | B12: 火灾自动报警系统 | C12: 326点 | D12: 套 | E12: 1 | F12: =326*2000/10000 -> 65.2 | G12: =F12*E12 -> 65.2
B13: 小计 | G13: =SUM(G7:G12) -> 239.9
A15: 二 | B15: 暖通、空调工程
A16: 1 | B16: 离心风机箱 | C16: 型号：HYPA15-15A-II 风量：7700m3/h；全压：320Pa 功率：1.5KW 噪声：60dB(A ) | D16: 台 | E16: 1 | F16: 0.8 | G16: =F16*E16 -> 0.8
A17: 2 | B17: 斜流风机 | C17: 型号：GXF-7-A 风量：13952m3/h 风压：457Pa 功率：3kW | D17: 台 | E17: 2 | F17: 1 | G17: =F17*E17 -> 2
A18: 3 | B18: 混流风机 | C18: 型号：HL3-2A-2.5A 风量：1341m3/h；转速：1450r/min 全压：79Pa 功率：0.55KW | D18: 台 | E18: 1 | F18: 0.15 | G18: =F18*E18 -> 0.15
A19: 4 | B19: 混流风机 | C19: 型号：PYHL3-2AI-3.5A 风量：3680m3/h；转速：1450r/min 全压：154Pa 功率：0.55KW | D19: 台 | E19: 1 | F19: 0.3 | G19: =F19*E19 -> 0.3
A20: 5 | B20: 混流风机 | C20: 型号：HL3-2AI-3A 风量：1411m3/h；转速：960r/min 全压：56Pa 功率：0.75KW | D20: 台 | E20: 1 | F20: 0.15 | G20: =F20*E20 -> 0.15
A21: 6 | B21: 斜流风机 | C21: 型号：GXF-4-A 风量：4014m3/h；转速：1450r/min 全压：218Pa 功率：0.37KW | D21: 台 | E21: 2 | F21: 0.5 | G21: =F21*E21 -> 1
A22: 7 | B22: 风机盘管 | C22: 型号:FP-34;中档风量:270m3/h ; 中档冷量：1700W;中档热量：2720W 电量：41W 噪声：39dB(A) | D22: 台 | E22: 30 | F22: 0.12 | G22: =F22*E22 -> 3.6
A23: 8 | B23: 风机盘管 | C23: 型号:FP-51;中档风量:400m3/h 中档冷量：2295W;中档热量：3570W 电量：51W 噪声：41dB(A) | D23: 台 | E23: 29 | F23: 0.15 | G23: =F23*E23 -> 4.35
A24: 9 | B24: 风机盘管 | C24: 型号:FP-68;中档风量:540m3/h;中档冷量：3096W;中档热量：4644W 电量：71W 噪声：43dB(A) | D24: 台 | E24: 171 | F24: 0.16 | G24: =F24*E24 -> 27.36
A25: 10 | B25: 风机盘管 | C25: 型号:FP-85 ;中档风量:680m3/h ; 中档冷量：3870W;中档热量：5848W 电量：87W 噪声：45dB(A) | D25: 台 | E25: 8 | F25: 0.17 | G25: =F25*E25 -> 1.36
A26: 11 | B26: 风机盘管 | C26: 型号:FP-102 ;中档风量:810m3/h; 中档冷量：4816W;中档热量：7052W 电量：101W 噪声：46dB(A) | D26: 台 | E26: 12 | F26: 0.18 | G26: =F26*E26 -> 2.16
A27: 12 | B27: 风机盘管 | C27: 型号:FP-136 ;中档风量:1080m3/h; 中档冷量：6192W;中档热量：9288W 电量：138W 噪声：47dB(A) | D27: 台 | E27: 41 | F27: 0.2 | G27: =F27*E27 -> 8.2
A28: 13 | B28: 分体空调 | C28: 制热量：3.0Kw 制冷量：2.5Kw;功率：2.0Kw(220V/50Hz) | D28: 台 | E28: 3 | F28: 0.5 | G28: =F28*E28 -> 1.5
A29: 14 | B29: 恒温恒湿空调 | C29: 型号：HF12N;制冷量：12.6Kw 风量：3000m\/h ；功率：5.4Kw；空调室外机（室内外机高差35.80m） | D29: 台 | E29: 1 | F29: 2.5 | G29: =F29*E29 -> 2.5 | J29: =12.6/2.4*0.4 -> 2.1
A30: 15 | B30: 热泵机组 | C30: 型号：LSRF280 ；制冷量：279kW 制热量：297kW ；夏季供回水温度：7/12℃ ；冬季供回水温度：45/40℃ | D30: 台 | E30: 4 | F30: 35 | G30: =F30*E30 -> 140
A31: 16 | B31: 循环水泵 | C31: 型号：CDL110-20 ；流量：110m3/h；扬程：28m 电量：15Kw | D31: 台 | E31: 3 | F31: 1.5 | G31: =F31*E31 -> 4.5
A32: 17 | B32: 补水泵 | C32: 型号：CDL2-14 流量：2m3/h ；扬程：55m 电量：2.0Kw | D32: 台 | E32: 2 | F32: 0.6 | G32: =F32*E32 -> 1.2
A33: 18 | B33: 软化水处理器 | C33: 型号：TRB-250 处理量：1-2m3/h | D33: 台 | E33: 1 | F33: 1.5 | G33: =F33*E33 -> 1.5
A34: 19 | B34: 软化水箱 | C34: 外形尺寸：1400X1400X1200 | D34: 台 | E34: 1 | F34: 1 | G34: =F34*E34 -> 1
A35: 20 | B35: 定压罐 | C35: 型号：SN800-1.0；调节容积：0.26m3 总容积：0.86m3 | D35: 台 | E35: 1 | F35: 1 | G35: =F35*E35 -> 1
A36: 21 | B36: 新风机组 | C36: 型号：QGK-D-10-H ；送风风量：1000m3/h 6排表冷器冷量：9.6Kw ；水量：1.66m\/h 送风功率：0.2Kw | D36: 台 | E36: 1 | F36: 0.6 | G36: =F36*E36 -> 0.6
A37: 22 | B37: 新风机组 | C37: 型号：QGK-D-20-H；送风风量：2000m3/h 6排表冷器冷量：19.3Kw ；水量：3.31m\/h 送风功率：0.7Kw | D37: 台 | E37: 1 | F37: 0.8 | G37: =F37*E37 -> 0.8
A38: 23 | B38: 全热交换器新风机组 | C38: 型号：QGK-D-25-H;送风风量：2500m3/h 回风风量：2000m\/h ;水量：3.31m3/h 送风功率：0.7Kw | D38: 台 | E38: 1 | F38: 1 | G38: =F38*E38 -> 1
A39: 24 | B39: 全热交换器新风机组 | C39: 型号：QGK-D-30-H;送风风量：3000m3/h 回风风量：2400m3/h ；6排表冷器冷量：30.7Kw 水量：5.29m3/h ;送风功率：2.2Kw 排风功率：0.5Kw | D39: 台 | E39: 8 | F39: 1.2 | G39: =F39*E39 -> 9.6
A40: 25 | B40: 全热交换器新风机组 | C40: 型号：QGK-D-35-H;送风风量：3500m3/h 回风风量：2800m\/h ;6排表冷器冷量：34.6Kw 水量：5.94m\/h | D40: 台 | E40: 2 | F40: 1.5 | G40: =F40*E40 -> 3
A41: 26 | B41: 壁式轴流风机 | C41: 型号：SPF2.5-Z 风量：1000m3/h ;全压：52Pa 功率：0.06KW 噪声：60dB(A) | D41: 台 | E41: 1 | F41: 0.2 | G41: =F41*E41 -> 0.2
... A46: 31 | B46: 斜流风机 | C46: 型号：GXF-5.5-A 转速：1450r/min;风量：8035m\/h 全压：313Pa ;功率：1.5KW 噪声：85dB(A) | D46: 台 | E46: 1 | F46: 0.8 | G46: =F46*E46 -> 0.8
B47: 小计 | G47: =SUM(G16:G46) -> 227.33 | J47: =G47/总概!D8*10000 -> 185.99898
A49: 三 | B49: 给排水工程
A50: 1 | B50: 变频给水设备 | C50: 80ZWG2/APV12-50； APV12-50；Q=3.4L/s H=50m N=3.0KW | D50: 套 | E50: 1 | F50: 1.2 | G50: =F50*E50 -> 1.2
A51: 1 | B51: 潜污泵 | C51: 80YW70-14 Q=20L/s H=14 m N=5.5kW | D51: 台 | E51: 2 | F51: 0.9 | G51: =F51*E51 -> 1.8
B52: 小计 | G52: =SUM(G50:G51) -> 3
A54: 四 | B54: 电梯 | C54: 13/13 | D54: 部 | E54: 3 | F54: 60 | G54: =F54*E54 -> 180
B56: 合计 | G56: =SUM(G52,G47,G13,G54) -> 650.23 | J56: =G13+G47+G52+G54 -> 650.23

Sheet 新增工艺设备
A1: 附表2
A2: 新 增 工 艺 设 备 表
A3: ='[20]估算表1－1'!A3 -> 项目名称：武船重型工程股份有限公司双柳桥区办公楼及珠港澳大桥生产设备建设项目 | G3: 单位：万元、万美元
A4: 序号 | B4: 设 备 名 称 | C4: 规格型号或参考型号 及其主要技术（性能）指标 | D4: 国别 | E4: 单位 | F4: 数量 | G4: 设 备 价 格 | J4: 招标情况 | K4: 备注
G5: 单价 | H5: 合计 | I5: 其中外汇
A6: 一 | B6: 板单元生产线
A7: （一） | B7: 钢材预处理生产线
A8: 1.1 | B8: 钢板矫平机 | C8: 加工板厚10-40mm 最大板宽4500mm，数控七辊 | D8: 国产 | E8: 台 | F8: 1 | G8: 993.6 | H8: =G8*F8 -> 993.6 | J8: 不招标 | K8: 非标集成
A9: （二） | B9: 下料切割生产线
A10: 1 | B10: 数控等离子切割机 | C10: 30x6000x40000,自动编程、自动划线、坡口开制、喷码打标 | D10: 国产 | E10: 台 | F10: 1 | G10: 92.2 | H10: =G10*F10 -> 92.2
A11: 2 | B11: 数控火焰切割机 | C11: 100x6000x40000,自动编程、自动划线、坡口开制、喷码打标 | D11: 国产 | E11: 台 | F11: 2 | G11: 47.8 | H11: =G11*F11 -> 95.6
A12: 3 | B12: 门式多头火焰切割机 | C12: 100x6000x40000,横向割炬2付、纵向割炬15付 | D12: 国产 | E12: 台 | F12: 3 | G12: 34.5 | H12: =G12*F12 -> 103.5 | J12: 不招标 | K12: 非标集成
A13: 4 | B13: 数控划线号料机 | C13: 6000x40000,自动编程、自动划线、喷码打标 | D13: 国产 | E13: 台 | F13: 2 | G13: 49.3 | H13: =G13*F13 -> 98.6
A14: （三） | B14: U肋生产线
A15: 1 | B15: 坡口铣边机 | C15: 双45°坡口 宽度100-500mm | D15: 国产 | E15: 台 | F15: 1 | G15: 240 | H15: =G15*F15 -> 240 | J15: 不招标 | K15: 非标集成
A16: 2 | B16: 双头坡口铣边机 | C16: 最大长度15m 最大宽度5000m | D16: 国产 | E16: 台 | F16: 1 | G16: 70 | H16: =G16*F16 -> 70 | J16: 不招标 | K16: 非标集成
A17: 3 | B17: R2倒角机 | C17: 宽度100-500mm 速度10m/min | D17: 国产 | E17: 台 | F17: 1 | G17: 40 | H17: =G17*F17 -> 40 | J17: 不招标 | K17: 非标集成
A18: 4 | B18: U肋板矫平机 | C18: 矫平厚度4-16mm 最大宽度1100mm | D18: 国产 | E18: 台 | F18: 1 | G18: 90 | H18: =G18*F18 -> 90 | J18: 不招标 | K18: 非标集成
A19: 5 | B19: 数控多边坡口成型机 | C19: 最大加工长度：17000mm，最大加工板料宽度： 1100mm，最大加工板料厚度：10mm | D19: 国产 | E19: 台 | F19: 1 | G19: 372 | H19: =G19*F19 -> 372 | J19: 不招标 | K19: 非标集成
A20: 6 | B20: 双台联动电液伺服数控折弯机 | C20: 最大加工长度：18000m，最大加工板料厚度：12mm | D20: 国产 | E20: 台 | F20: 1 | G20: 404.5 | H20: =G20*F20 -> 404.5 | J20: 不招标 | K20: 非标集成
A21: （四） | B21: U肋板单元生产线
A22: 1 | B22: U肋端口栓孔定位装置 | C22: 轨距4500×2000，前后移动范围500 | D22: 国产 | E22: 套 | F22: 2 | G22: =6.9/2+24.5 -> 27.95 | H22: =G22*F22 -> 55.9
A23: 2 | B23: 移动式U肋装配机 | C23: 轨距6000×40000,总压力15t,行走速度10m/min | D23: 国产 | E23: 台 | F23: 2 | G23: =7.7+103.5 -> 111.2 | H23: =G23*F23 -> 222.4 | J23: 不招标 | K23: 非标集成
A24: 3 | B24: U肋龙门焊接系统 | E24: 套 | F24: 1 | H24: =SUM(H25:H26) -> 838.7 | J24: 不招标 | K24: 非标集成
A25: 1 | B25: U肋龙门焊接机 | C25: 轨距6000×40000,行走速度V=10m/min 焊接速度V=250-1000mm/min | D25: 国产 | E25: （台） | F25: 4 | G25: =35.5/4+170.8 -> 179.675 | H25: =G25*F25 -> 718.7
A26: 2 | B26: 逆变埋弧自动焊机 | C26: 1250A | D26: 国产 | E26: （台） | F26: 30 | G26: 4 | H26: =G26*F26 -> 120 | J26: 不招标 | K26: 非标集成
A27: 4 | B27: U肋板单元机械滚压矫正机 | C27: 工作速度6m/min,上辊矫正力100吨/个，前后各15米输送辊道 | D27: 国产 | E27: 台 | F27: 1 | G27: =60.1+357.8 -> 417.9 | H27: =G27*F27 -> 417.9 | J27: 不招标 | K27: 非标集成
A28: 5 | B28: 底板对齐装配胎架 | C28: 轨距5000×40000,每隔4米放置一个侧边对齐装置 | D28: 国产 | E28: 套 | F28: 2 | G28: 39.4 | H28: =G28*F28 -> 78.8
A29: 6 | B29: U肋反变形焊接系统 | F29: 1 | H29: =SUM(H30:H31) -> 686.4
A30: 1 | B30: 可调式液压反变形胎架 | C30: 正后方向倾斜0～±30° | D30: 国产 | E30: （套） | F30: 8 | G30: 55.8 | H30: =G30*F30 -> 446.4 | J30: 不招标 | K30: 非标集成
A31: 2 | B31: CO2气体保护焊机 | C31: 500A | D31: 国产 | E31: （台） | F31: 200 | G31: 1.2 | H31: =G31*F31 -> 240 | J31: 不招标 | K31: 非标集成
A32: （五） | B32: 板肋板单元生产线
A33: 1 | B33: 钢板对齐装配胎架 | C33: 轨距5000×40000，每隔4m放置一个侧边对齐压紧装置 | D33: 国产 | E33: 套 | F33: 1 | G33: 40.4 | H33: =G33*F33 -> 40.4
A34: 2 | B34: 板肋定位装置 | C34: 轨距4500，前后行程500mm | D34: 国产 | E34: 套 | F34: 2 | G34: =0.5+11.6 -> 12.1 | H34: =G34*F34 -> 24.2
A35: 3 | B35: 移动式板肋装配机 | C35: 轨距6000×20000，行走速度V=2-10m/min，多根板肋双面自动点焊 | D35: 国产 | E35: 台 | F35: 2 | G35: =36.5/2+126.7 -> 144.95 | H35: =G35*F35 -> 289.9 | J35: 不招标 | K35: 非标集成
A36: 4 | B36: 板肋板单元对齐压紧焊接胎架 | C36: 每隔3m放置一个侧边对齐压紧装置，行程2000mm | D36: 国产 | E36: 套 | F36: 1 | G36: 80.8 | H36: =G36*F36 -> 80.8
A37: 5 | B37: 十头双丝双边板肋龙门焊接机 | C37: 行走速度V=10m/min，双丝焊，焊接速度V=250-1000mm/min | D37: 国产 | E37: 台 | F37: 2 | G37: =50.5/2+217.4 -> 242.65 | H37: =G37*F37 -> 485.3 | J37: 不招标 | K37: 非标集成
A38: 6 | B38: 板肋板单元机械滚压矫正机 | C38: V=6m/min,矫正力100吨/个，前后辊道各15米 | D38: 国产 | E38: 台 | F38: 1 | G38: =60.1+385 -> 445.1 | H38: =G38*F38 -> 445.1 | J38: 不招标 | K38: 非标集成
A39: （六） | B39: 横隔板单元件生产线
A40: 1 | B40: 钢板对齐装配胎架 | C40: 主要由450×450梅花排放的活动套管组成，一侧面设有板边定位死挡和钢板压紧装置 | D40: 国产 | E40: 套 | F40: 1 | G40: 56.7 | H40: =G40*F40 -> 56.7
A41: 2 | B41: 焊机存放移动龙门架 | C41: 行走速度V=10m/min | D41: 国产 | E41: 套 | F41: 4 | G41: 58.2 | H41: =G41*F41 -> 232.8 | J41: 不招标 | K41: 非标集成
A42: 3 | B42: 压点可移动油压矫正机 | C42: V=6m/min,矫正力100吨/个，前后辊道各15米 | D42: 国产 | E42: 台 | F42: 1 | G42: 310.5 | H42: =G42*F42 -> 310.5 | J42: 不招标 | K42: 非标集成
A43: 4 | B43: 横隔板焊接机器人系统 | C43: 行走速度V=10m/min，焊接速度V=250-600mm/min，龙门架结构，配置适宜用于中厚板弧焊的六轴焊接机器人，精确稳定的控制系统，重复定位精度±0.1mm | D43: 国产 | E43: 套 | F43: 1 | G43: 475 | H43: =G43*F43 -> 475 | J43: 不招标 | K43: 非标集成
A44: （七） | B44: T型梁单元件生产线
A45: 1 | B45: T型梁装焊矫正机 | C45: 腹板高度200-1500mm 厚度8-20mm 翼缘板宽度200-800mm 厚度8-30mm 焊接速度V=400-1000mm/min | D45: 国产 | E45: 台 | F45: 1 | G45: 51.8 | H45: =G45*F45 -> 51.8
A46: （八） | B46: 钢塔生产线
A47: 1 | B47: 数控落地铣镗床 | C47: 立柱行程14m 给进范围0-6000mm 主动力头功率71KW | D47: 国产 | E47: 台 | F47: 1 | G47: 698.5 | H47: =G47*F47 -> 698.5 | J47: 不招标 | K47: 非标集成
A48: 2 | B48: 龙门数控钻床 | C48: Φ60×5000×10000 | D48: 国产 | E48: 台 | F48: 1 | G48: 212 | H48: =G48*F48 -> 212 | J48: 不招标 | K48: 非标集成
A49: 3 | B49: 铣镗床加工调整平台 | C49: 垂直顶升力200吨*6个 行程200mm 水平调整力100吨 行程150mm | D49: 国产 | E49: 台 | F49: 1 | G49: 204 | H49: =G49*F49 -> 204 | J49: 不招标 | K49: 非标集成
A50: 4 | B50: 摇臂转床 | C50: 最大钻孔直径：50mm | D50: 国产 | E50: 台 | F50: 2 | G50: 10 | H50: =G50*F50 -> 20
A51: 5 | B51: 桥式起重机220t | C51: Gn=220t，S=25.5m，H=22m | D51: 国产 | E51: 台 | F51: 1 | G51: 330 | H51: =G51*F51 -> 330 | J51: 不招标 | K51: 非标自制
A52: （九） | B52: 焊接切割小型设备
A53: 1 | B53: 全位置焊接小车 | D53: 国产 | E53: 台 | F53: 10 | G53: 2 | H53: =G53*F53 -> 20
A54: 2 | B54: 半自动切割机 | C54: 切割速度150-700mm/min 切割厚度5-30mm 角度0-45° | D54: 国产 | E54: 台 | F54: 30 | G54: 1.334 | H54: =G54*F54 -> 40.02
A55: 3 | B55: 全位置切割机 | C55: 切割速度150-800mm/min 切割厚度5-30mm | D55: 国产 | E55: 台 | F55: 10 | G55: 2 | H55: =G55*F55 -> 20
B57: 小 计 | F57: =SUM(F8,F10:F13,F15:F20,F22:F24,F27:F29,F33:F38,F40:F43,F45,F47:F51,F53:F55) -> 97 | H57: =SUM(H8,H10:H13,H15:H20,H22:H24,H27:H29,H33:H38,H40:H43,H45,H47:H51,H53:H55) -> 8937.12
A59: 二 | B59: 测量设备
A60: 1 | B60: 油漆干膜测厚仪 | C60: 456FBS，4Hz | D60: 国产 | E60: 台 | F60: 5 | G60: 1 | H60: =G60*F60 -> 5
A61: 2 | B61: 激光经纬仪 | C61: J1 | D61: 国产 | E61: 台 | F61: 5 | G61: 2 | H61: =G61*F61 -> 10
A62: 3 | B62: 电子全站仪 | C62: ±0.5/1mm+1ppm | D62: 国产 | E62: 台 | F62: 3 | G62: 23.333 | H62: =G62*F62 -> 69.999
A63: 4 | B63: 拉拔（附着力测试）仪 | C63: X1003 | D63: 国产 | E63: 台 | F63: 1 | G63: 2 | H63: =G63*F63 -> 2
A64: 5 | B64: 露点测试仪 | D64: 国产 | E64: 台 | F64: 3 | G64: 1 | H64: =G64*F64 -> 3
B66: 小 计 | F66: =SUM(F60:F65) -> 17 | H66: =SUM(H60:H65) -> 89.999
A68: 三 | B68: 监控设备
A69: 1 | B69: 监控系统 | F69: 1 | H69: =SUM(H70:H90) -> 500.65 | J69: 不招标 | K69: 非标集成
A70: 1 | B70: 红外摄像头 | C70: 540线 | D70: 国产 | E70: 台 | F70: 122 | G70: 0.2 | H70: =G70*F70 -> 24.4
A71: 2 | B71: 摄像头电源 | C71: 12V，2A | D71: 国产 | E71: 台 | F71: 122 | G71: 0.12 | H71: =G71*F71 -> 14.64
A72: 3 | B72: 红外摄像头支架 | C72: BS201 | D72: 国产 | E72: 台 | F72: 122 | G72: 0.005 | H72: =G72*F72 -> 0.61
A73: 4 | B73: 一体化摄像机 | C73: 水平清晰度480，镜头3.6mm，有效像素44万 | D73: 国产 | E73: 台 | F73: 122 | G73: 0.4 | H73: =G73*F73 -> 48.8
A74: 5 | B74: 红外灯板 | C74: IWILL DB200 | D74: 国产 | E74: 台 | F74: 122 | G74: 0.1 | H74: =G74*F74 -> 12.2
A75: 6 | B75: 重型云台 | C75: IWILL YT361 | D75: 国产 | E75: 台 | F75: 122 | G75: 0.1 | H75: =G75*F75 -> 12.2
A76: 7 | B76: 摄像机外壳 | C76: BS101 | D76: 国产 | E76: 台 | F76: 122 | G76: 0.05 | H76: =G76*F76 -> 6.1
A77: 8 | B77: 解码器 | C77: 可扩充255个地址，对云台实现64至128个预置精确定位 | D77: 国产 | E77: 台 | F77: 122 | G77: 0.1 | H77: =G77*F77 -> 12.2
A78: 9 | B78: 光端机 | C78: 8位数字编码及无压缩式视频传输，自适应PAL、NTSC、SECAM视频制式 | D78: 国产 | E78: 台 | F78: 488 | G78: 0.33 | H78: =G78*F78 -> 161.04
A79: 10 | B79: 防水终端箱 | C79: BS408 | D79: 国产 | E79: 台 | F79: 400 | G79: 0.05 | H79: =G79*F79 -> 20
A80: 11 | B80: 云台支架 | C80: BS308 | D80: 国产 | E80: 台 | F80: 122 | G80: 0.03 | H80: =G80*F80 -> 3.66
A81: 12 | B81: 熔纤盒 | C81: BS301 | D81: 国产 | E81: 台 | F81: 200 | G81: 0.01 | H81: =G81*F81 -> 2
... A90: 21 | B90: 辅材及安装件 | C90: 线缆等辅材 | D90: 国产 | E90: 套 | F90: 1 | G90: 95 | H90: =G90*F90 -> 95
B92: 小 计 | F92: =SUM(F69) -> 1 | H92: =SUM(H69) -> 500.65
B94: 设备原值合计 | F94: =SUM(F92,F66,F57) -> 115 | H94: =SUM(H92,H66,H57) -> 9527.769
B95: 设备进口费合计
B96: 设备运杂费合计 | H96: =工艺设备!G95 -> 499.386
B97: 设备购置费合计 | H97: =SUM(H94:H96) -> 10027.155
G100: 招 | H100: =SUM(H69,H26:H52,H42:H43,H23:H27,H50,H20,H15:H18,H47:H49,H37:H38,H35,) -> 12749.65
F101: 356 | H101: 9481.26
H103: 503.0766
H104: 9984.3366

Sheet 汇总表
B2: 单项工程投资构成表 | M2: 地上 | N2: 地下
B3: 序号 | C3: 工程费用名称 | D3: 估算价值（万元） | H3: 技术经济指标 | K3: 现 | L3: 31579.6 | M3: 23152.8 | N3: 8873
D4: 建筑工程 | E4: 安装工程 | F4: 公用设备 | G4: 合计 | H4: 数量 M2 | I4: 单位价值 元/M2
B5: 一 | C5: 工程费用
B6: 1 | C6: 建筑装饰工程
B7: 1.1 | C7: 建筑工程 | D7: =土费!G28/10000 -> 2114.5793 | G7: =SUM(D7:F7) -> 2114.5793 | H7: =总概!D8 -> 12222.11 | I7: =D7/H7*10000 -> 1730.1263
B8: 1.2 | C8: 装饰工程 | D8: =土费!G58/10000 -> 1295.4604 | G8: =SUM(D8:F8) -> 1295.4604 | H8: =H7 -> 12222.11 | I8: =D8/H8*10000 -> 1059.9319
B9: 1.3 | C9: 精装工程 | D9: =H9*I9/10000 -> 855.5477 | G9: =SUM(D9:F9) -> 855.5477 | H9: =H8*0.35 -> 4277.7385 | I9: 2000
C11: 小计 | D11: =SUM(D7:D10) -> 4265.5875 | E11: =SUM(E7:E10) -> 0 | F11: =SUM(F7:F10) -> 0 | G11: =SUM(G7:G10) -> 4265.5875 | I11: =G11/H7*10000 -> 3490.0582
B13: 2 | C13: 安装工程
B14: 2.1 | C14: 给排水及消防工程 | E14: =水费!G31/10000 -> 137.63698 | F14: =公用设备表!G52 -> 3 | G14: =SUM(D14:F14) -> 140.63698 | H14: =H8 -> 12222.11 | I14: =G14/H14*10000 -> 115.06768 | J14: =[18]公用设备材料表!H22 -> 398.965 | K14: =J14/H14*10000 -> 326.42891 | N14: 530
B15: 2.2 | C15: 暖通动力工程 | E15: =暖费!G31/10000 -> 269.69616 | F15: =公用设备表!G47 -> 227.33 | G15: =SUM(D15:F15) -> 497.02616 | H15: =H14 -> 12222.11 | I15: =G15/H15*10000 -> 406.6615 | J15: =[18]公用设备材料表!H68 -> 842.67 | K15: =J15/H15*10000 -> 689.4636 | L15: 750 | M15: =L15-K15 -> 60.536397 | N15: 750
B16: 2.3 | C16: 电气工程 | E16: =电费!G31/10000 -> 274.95907 | F16: =公用设备表!G13 -> 239.9 | G16: =SUM(D16:F16) -> 514.85907 | H16: =H15 -> 12222.11 | I16: =G16/H16*10000 -> 421.2522 | J16: =[18]公用设备材料表!H86 -> 862 | K16: =J16/H16*10000 -> 705.2792 | L16: 700 | M16: =L16-K16 -> -5.279203 | N16: 990
B17: 2.4 | C17: 电梯工程 | F17: =公用设备表!G54 -> 180 | G17: =SUM(D17:F17) -> 180
C19: 小计 | D19: =SUM(D14:D16) -> 0 | E19: =SUM(E14:E17) -> 682.29221 | F19: =SUM(F14:F17) -> 650.23 | G19: =SUM(G14:G17) -> 1332.5222 | H19: =SUM(H14:H17) -> 36666.33 | I19: =G19/H14*10000 -> 1090.2555
C21: 合计 | D21: =D19+D11 -> 4265.5875 | E21: =E19+E11 -> 682.29221 | F21: =F19+F11 -> 650.23 | G21: =G19+G11 -> 5598.1097 | I21: =I19+I11 -> 4580.3136 | K21: =G21/H7*10000 -> 4580.3136
C24: 建设期利息 | D24: 1 | E24: 2 | F24: 3
C25: 0.0655 | D25: 0.2 | E25: 0.4 | F25: 0.4
C26: =C27*C28 -> 18740 | D26: =D25*$C$26 -> 3748 | E26: =E25*$C$26 -> 7496 | F26: =F25*$C$26 -> 7496 | H26: =C26*2 -> 37480
B27: =D27+E27+F27 -> 1595.711 | C27: 0.5 | D27: =D26*C25/2 -> 122.747 | E27: =(D26+E26/2)*C25 -> 490.988 | F27: =(D26+E26+F26/2)*C25 -> 981.976
B28: =C26+C32 -> 37480 | C28: =[18]估算表!K63 -> 37480 | D28: =D26 -> 3748 | E28: =D26+E26 -> 11244 | F28: =D26+E26+F26 -> 18740
C30: 自筹
C31: =1-C27 -> 0.5 | D31: =D25*$C$28*$C$31 -> 3748 | E31: =E25*$C$28*$C$31 -> 7496 | F31: =F25*$C$28*$C$31 -> 7496
C32: =SUM(D31:F31) -> 18740
C34: 建设期利息 | D34: 1 | E34: 2 | F34: 3
C35: 0.0655 | D35: 0.2 | E35: 0.4 | F35: 0.4
C36: =C37*C38 -> 26236 | D36: =D35*$C$36 -> 5247.2 | E36: =E35*$C$36 -> 10494.4 | F36: =F35*$C$36 -> 10494.4
B37: =D37+E37+F37 -> 2233.9954 | C37: 0.7 | D37: =D36*C35/2 -> 171.8458 | E37: =(D36+E36/2)*C35 -> 687.3832 | F37: =(D36+E36+F36/2)*C35 -> 1374.7664
B38: =C36+C42 -> 37480 | C38: =C28 -> 37480 | D38: =D36 -> 5247.2 | E38: =D36+E36 -> 15741.6 | F38: =D36+E36+F36 -> 26236
C40: 自筹
C41: =1-C37 -> 0.3 | D41: =D35*$C$28*$C$41 -> 2248.8 | E41: =E35*$C$28*$C$41 -> 4497.6 | F41: =F35*$C$28*$C$41 -> 4497.6
C42: =SUM(D41:F41) -> 11244
C44: 建设期利息 | D44: 1 | E44: 2 | F44: 3
C45: 0.0655 | D45: 0.2 | E45: 0.4 | F45: 0.4
C46: =C47*C48 -> 37480 | D46: =D45*$C$46 -> 7496 | E46: =E45*$C$46 -> 14992 | F46: =F45*$C$46 -> 14992
B47: =D47+E47+F47 -> 3191.422 | C47: 1 | D47: =D46*C45/2 -> 245.494 | E47: =(D46+E46/2)*C45 -> 981.976 | F47: =(D46+E46+F46/2)*C45 -> 1963.952
B48: =C46+C52 -> 37480 | C48: =C38 -> 37480 | D48: =D46 -> 7496 | E48: =D46+E46 -> 22488 | F48: =D46+E46+F46 -> 37480
C50: 自筹
C51: =1-C47 -> 0 | D51: =D45*$C$28*$C$51 -> 0 | E51: =E45*$C$28*$C$51 -> 0 | F51: =F45*$C$28*$C$51 -> 0
C52: =SUM(D51:F51) -> 0

Sheet 土费
A2: 单位工程费用汇总表
A3: 工程名称：2601#土建工程 | E3: 第 1 页 共 2 页
A4: 序号 | B4: 费用名称 | D4: 取费基数 | F4: 费率 | G4: 费用金额
A5: 1 | B5: 建筑工程12层以上 | D5: 建筑工程12层以上 | G5: 21145793
A6: 一 | B6: 分部分项工程费（含5%零星工程） | D6: (人工费+材料费+未计价材料费+施工机具使用费)*1.05 | G6: 13393177
A7: 1 | B7: 人工费 | D7: 人工费 | G7: 2087434
A8: 2 | B8: 材料费 | D8: 材料费 | G8: 9617986.6
A9: 3 | B9: 未计价材料费 | D9: 主材费
A10: 4 | B10: 施工机具使用费 | D10: 机械费 | G10: 1049986.2
A11: 二 | B11: 措施项目费 | D11: 单价措施项目费+总价措施项目费 | G11: 3570092.9
A12: 2.1 | B12: 单价措施项目费 | D12: 人工费+材料费+施工机具使用费 | G12: 2887867.6
A13: 2.1.1 | B13: 人工费 | D13: 技术措施项目人工费 | G13: 1901708.8
A14: 2.1.2 | B14: 材料费 | D14: 技术措施项目材料费 | G14: 841205.19
A15: 2.1.3 | B15: 施工机具使用费 | D15: 技术措施项目机械费 | G15: 144953.65
A16: 2.2 | B16: 总价措施项目费 | D16: 安全文明施工费+其它总价措施项目费 | G16: 682225.29
A17: 2.2.1 | B17: 安全文明施工费 | D17: 人工费+施工机具使用费+人工费+施工机具使用费 | F17: 12.51 | G17: 648528.75
A18: 2.2.2 | B18: 其它总价措施项目费 | D18: 人工费+施工机具使用费+人工费+施工机具使用费 | F18: 0.65 | G18: 33696.54
A19: 三 | B19: 总包服务费
A20: 四 | B20: 企业管理费 | D20: 人工费+施工机具使用费+人工费+施工机具使用费 | F20: 23.84 | G20: 1235885.3
A21: 五 | B21: 利润 | D21: 人工费+施工机具使用费+人工费+施工机具使用费 | F21: 18.17 | G21: 941947.83
A22: 六 | B22: 规费 | D22: 人工费+施工机具使用费+人工费+施工机具使用费 | F22: 24.72 | G22: 1281505.2
A23: 七 | B23: 索赔与现场签证
A24: 八 | B24: 不含税工程造价 | D24: 分部分项工程费（含5%零星工程）+措施项目费+总包服务费+企业管理费+利润+规费+索赔与现场签证 | G24: 20422608
A25: 九 | B25: 税前包干项目 | D25: 税前包干价
A26: 十 | B26: 税金 | D26: 不含税工程造价+税前包干价 | F26: 3.5411 | G26: 723184.99
A27: 十一 | B27: 税后包干项目 | D27: 税后包干价
A28: 十二 | B28: 含税工程造价 | D28: 不含税工程造价+税金+税前包干项目+税后包干项目 | G28: 21145793
A30: 2 | B30: 装饰工程 | D30: 装饰工程 | G30: 12954604
A31: 一 | B31: 分部分项工程费（含5%零星工程） | D31: (人工费+材料费+未计价材料费+施工机具使用费)*1.05 | G31: 11125023
A32: 1 | B32: 人工费 | D32: 人工费 | G32: 1500489.7
A33: 2 | B33: 材料费 | D33: 材料费 | G33: 9060053.2
A34: 3 | B34: 未计价材料费 | D34: 主材费
A35: 4 | B35: 施工机具使用费 | D35: 机械费 | G35: 34717.17
A36: 编制人: | C36: 审核人: | E36: 编制日期:
A38: 单位工程费用汇总表
A39: 工程名称：2601#土建工程 | E39: 第 2 页 共 2 页
A40: 序号 | B40: 费用名称 | D40: 取费基数 | F40: 费率 | G40: 费用金额
A41: 二 | B41: 措施项目费 | D41: 单价措施项目费+总价措施项目费 | G41: 605804.19
A42: 2.1 | B42: 单价措施项目费 | D42: 人工费+材料费+施工机具使用费 | G42: 480405.93
A43: 2.1.1 | B43: 人工费 | D43: 技术措施项目人工费 | G43: 305102.98
A44: 2.1.2 | B44: 材料费 | D44: 技术措施项目材料费 | G44: 74463.21
A45: 2.1.3 | B45: 施工机具使用费 | D45: 技术措施项目机械费 | G45: 100839.74
A46: 2.2 | B46: 总价措施项目费 | D46: 安全文明施工费+其它总价措施项目费 | G46: 125398.26
A47: 2.2.1 | B47: 安全文明施工费 | D47: 人工费+施工机具使用费+人工费+施工机具使用费 | F47: 5.81 | G47: 112780.79
A48: 2.2.2 | B48: 其它总价措施项目费 | D48: 人工费+施工机具使用费+人工费+施工机具使用费 | F48: 0.65 | G48: 12617.47
A49: 三 | B49: 总包服务费
A50: 四 | B50: 企业管理费 | D50: 人工费+施工机具使用费+人工费+施工机具使用费 | F50: 13.47 | G50: 261472.85
A51: 五 | B51: 利润 | D51: 人工费+施工机具使用费+人工费+施工机具使用费 | F51: 15.8 | G51: 306701.63
A52: 六 | B52: 规费 | D52: 人工费+施工机具使用费+人工费+施工机具使用费 | F52: 10.95 | G52: 212555.88
A53: 七 | B53: 索赔与现场签证
A54: 八 | B54: 不含税工程造价 | D54: 分部分项工程费（含5%零星工程）+措施项目费+总包服务费+企业管理费+利润+规费+索赔与现场签证 | G54: 12511558
A55: 九 | B55: 税前包干项目 | D55: 税前包干价
A56: 十 | B56: 税金 | D56: 不含税工程造价+税前包干价 | F56: 3.5411 | G56: 443046.76
A57: 十一 | B57: 税后包干项目 | D57: 税后包干价
A58: 十二 | B58: 含税工程造价 | D58: 不含税工程造价+税金+税前包干项目+税后包干项目 | G58: 12954604
A60: 3 | B60: 工程造价 | D60: 专业造价总合计 | G60: 34100398
A74: 编制人: | C74: 审核人: | E74: 编制日期:

Sheet 土
A2: 单位工程预结算书
A3: 工程名称：2601#土建工程 | L3: 第 1 页 共 7 页
A4: 序号 | B4: 编号 | C4: 定额名称 | D4: 单位 | E4: 工程量 | G4: 单价（元） | H4: 其中（元） | K4: 合价 | M4: 其中（元）
H5: 人工费单价 | I5: 材料费单价 | J5: 机械费单价 | M5: 人工费合价 | N5: 材料费合价 | O5: 机械费合价
C6: 010105、砌块砌体 | K6: 936010.45 | M6: 254593.39 | N6: 677347.4 | O6: 4069.67
A7: 1 | B7: A1-46 | C7: 加气混凝土砌块墙 600*300*(125、200、250) 混合砂浆M5 外墙 | D7: 10m3 | E7: 121.9 | G7: 3300.46 | H7: 897.72 | I7: 2388.39 | J7: 14.35 | K7: 402326.07 | M7: 109432.07 | N7: 291144.74 | O7: 1749.27
A8: 2 | B8: A1-46 | C8: 加气混凝土砌块墙 600*300*(125、200、250) 混合砂浆M5 内墙 | D8: 10m3 | E8: 161.7 | G8: 3300.46 | H8: 897.72 | I8: 2388.39 | J8: 14.35 | K8: 533684.38 | M8: 145161.32 | N8: 386202.66 | O8: 2320.4
C9: 010201、现场搅拌混凝土 | K9: 2807838.3 | M9: 697889.45 | N9: 2048585.3 | O9: 61363.59
A10: 3 | B10: A2-17换 | C10: 矩形柱 C20现浇混凝土换为【C40碎石混凝土】 | D10: 10m3 | E10: 53.7 | G10: 4938.77 | H10: 1263.88 | I10: 3572.11 | J10: 102.78 | K10: 265211.95 | M10: 67870.36 | N10: 191822.31 | O10: 5519.29
A11: 4 | B11: A2-17 H1-55 1-79 | C11: 矩形柱 C20现浇混凝土换为【C30碎石混凝土】换为【C35碎石混凝土】 | D11: 10m3 | E11: 12.7 | G11: 4608.79 | H11: 1263.88 | I11: 3242.13 | J11: 102.78 | K11: 58531.63 | M11: 16051.28 | N11: 41175.05 | O11: 1305.31
A12: 5 | B12: A2-23换 | C12: 单梁、连续梁、悬臂梁 C20现浇混凝土换为【C35碎石混凝土】 | D12: 10m3 | E12: 82.8 | G12: 4636.22 | H12: 1043.72 | I12: 3489.72 | J12: 102.78 | K12: 383879.02 | M12: 86420.02 | N12: 288948.82 | O12: 8510.18
A13: 6 | B13: A2-23换 | C13: 单梁、连续梁、悬臂梁 C20现浇混凝土换为【C30碎石混凝土】 | D13: 10m3 | E13: 56.5 | G13: 4720.26 | H13: 1043.72 | I13: 3573.76 | J13: 102.78 | K13: 266694.69 | M13: 58970.18 | N13: 201917.44 | O13: 5807.07
A14: 7 | B14: A2-29换 | C14: 直形混凝土墙 C20现浇混凝土换为【C40 | D14: 10m3 | E14: 79.9 | G14: 4978.13 | H14: 1191.92 | I14: 3683.43 | J14: 102.78 | K14: 397752.59 | M14: 95234.41 | N14: 294306.06 | O14: 8212.12
A15: 编制人: | F15: 审核人: | L15: 编制日期:
A17: 单位工程预结算书
A18: 工程名称：2601#土建工程 | L18: 第 2 页 共 7 页
A19: 序号 | B19: 编号 | C19: 定额名称 | D19: 单位 | E19: 工程量 | G19: 单价（元） | H19: 其中（元） | K19: 合价 | M19: 其中（元）
H20: 人工费单价 | I20: 材料费单价 | J20: 机械费单价 | M20: 人工费合价 | N20: 材料费合价 | O20: 机械费合价
C21: 碎石混凝土】
A22: 8 | B22: A2-29换 | C22: 直形混凝土墙 C20现浇混凝土换为【C35碎石混凝土】 | D22: 10m3 | E22: 25 | G22: 4714.84 | H22: 1191.92 | I22: 3420.14 | J22: 102.78 | K22: 117871 | M22: 29798 | N22: 85503.5 | O22: 2569.5
A23: 9 | B23: A2-30 H1-55 1-80 | C23: 直形混凝土墙 C20现浇混凝土换为【C40碎石混凝土、抗渗】 | D23: 10m3 | E23: 37.3 | G23: 5239.93 | H23: 1703.6 | I23: 3433.55 | J23: 102.78 | K23: 195449.39 | M23: 63544.28 | N23: 128071.42 | O23: 3833.69
A24: 10 | B24: A2-38换 | C24: 有梁板 C20现浇混凝土换为【C30碎石混凝土】 | D24: 10m3 | E24: 22.4 | G24: 4504.86 | H24: 1130.28 | I24: 3271.8 | J24: 102.78 | K24: 100908.86 | M24: 25318.27 | N24: 73288.32 | O24: 2302.27
A25: 11 | B25: A2-38换 | C25: 有梁板 C20现浇混凝土换为【C35碎石混凝土】 | D25: 10m3 | E25: 182.9 | G25: 4786.82 | H25: 1130.28 | I25: 3553.76 | J25: 102.78 | K25: 875509.38 | M25: 206728.21 | N25: 649982.7 | O25: 18798.46
A26: 12 | B26: A2-50换 | C26: 整体楼梯 C20现浇混凝土换为【C30碎石混凝土】 | D26: 10m2 | E26: 65 | G26: 1341.45 | H26: 444.88 | I26: 857.42 | J26: 39.15 | K26: 87194.25 | M26: 28917.2 | N26: 55732.3 | O26: 2544.75
A27: 13 | B27: A2-55 | C27: 台阶 C20现浇混凝土 | D27: 10m2 | E27: 11 | G27: 645.46 | H27: 168.24 | I27: 449.49 | J27: 27.73 | K27: 7100.06 | M27: 1850.64 | N27: 4944.39 | O27: 305.03
A28: 14 | B28: A2-57 | C28: 雨棚 C20现浇混凝土 | D28: 10m3 | E28: 3.5 | G28: 4833.3 | H28: 1499.24 | I28: 3170.92 | J28: 163.14 | K28: 16916.55 | M28: 5247.34 | N28: 11098.22 | O28: 570.99
A29: 15 | B29: A2-57 | C29: 零星构件 C20现浇混凝土 | D29: 10m3 | E29: 3 | G29: 4833.3 | H29: 1499.24 | I29: 3170.92 | J29: 163.14 | K29: 14499.9 | M29: 4497.72 | N29: 9512.76 | O29: 489.42
A30: 16 | B30: A2-60 | C30: 砼散水面层一次抹光 C15现浇混凝土 | D30: 100m2 | E30: 1.64 | G30: 2969.05 | H30: 787.12 | I30: 2056.16 | J30: 125.77 | K30: 4869.24 | M30: 1290.88 | N30: 3372.1 | O30: 206.26
A31: 17 | B31: A2-61 | C31: 防滑坡道 1:2水泥砂浆 | D31: 100m2 | E31: 8.2 | G31: 1884.12 | H31: 750.08 | I31: 1086.57 | J31: 47.47 | K31: 15449.78 | M31: 6150.66 | N31: 8909.87 | O31: 389.25
C32: 010202、商品混凝土 | K32: 339739.29 | M32: 29914.97 | N32: 309824.32
A33: 编制人: | F33: 审核人: | L33: 编制日期:
A35: 单位工程预结算书
A36: 工程名称：2601#土建工程 | L36: 第 3 页 共 7 页
A37: 序号 | B37: 编号 | C37: 定额名称 | D37: 单位 | E37: 工程量 | G37: 单价（元） | H37: 其中（元） | K37: 合价 | M37: 其中（元）
H38: 人工费单价 | I38: 材料费单价 | J38: 机械费单价 | M38: 人工费合价 | N38: 材料费合价 | O38: 机械费合价
A39: 18 | B39: A2-74换 | C39: 独立式桩承台 C20商品混凝土换为【商品混凝土C30】 | D39: 10m3 | E39: 67.98 | G39: 4561.28 | H39: 404.8 | I39: 4156.48 | K39: 310075.81 | M39: 27518.3 | N39: 282557.51
A40: 19 | B40: A2-75换 | C40: 基础垫层 C10商品混凝土换为【商品混凝土C15 碎石20】 | D40: 10m3 | E40: 0.98 | G40: 3910.66 | H40: 428.48 | I40: 3482.18 | K40: 3832.45 | M40: 419.91 | N40: 3412.54
A41: 20 | B41: A2-85换 | C41: 基础梁 C20商品混凝土换为【商品混凝土C30 】 | D41: 10m3 | E41: 5.7 | G41: 4531.76 | H41: 346.8 | I41: 4184.96 | K41: 25831.03 | M41: 1976.76 | N41: 23854.27
C42: 010206、钢筋及铁件 | K42: 5917902 | M42: 804547.44 | N42: 4989209 | O42: 124145.56
A43: 21 | B43: A2-453 | C43: 现浇构件螺纹钢筋(mm以外) φ12 | D43: t | E43: 659 | G43: 5368.52 | H43: 756.92 | I43: 4548.64 | J43: 62.96 | K43: 3537854.7 | M43: 498810.28 | N43: 2997553.8 | O43: 41490.64
A44: 22 | B44: A2-454 | C44: 现浇构件螺纹钢筋(mm以内) φ12 | D44: t | E44: 439 | G44: 5421.52 | H44: 696.44 | I44: 4536.8 | J44: 188.28 | K44: 2380047.3 | M44: 305737.16 | N44: 1991655.2 | O44: 82654.92
C45: 010503、屋面防水、排水 | K45: 121342.86 | M45: 17766.95 | N45: 103575.91
A46: 23 | B46: A5-37 | C46: 高聚物改性沥青防水卷材屋面 满铺(加强型) 平面 | D46: 100m2 | E46: 10.74 | G46: 7479.61 | H46: 747.52 | I46: 6732.09 | K46: 80331.01 | M46: 8028.36 | N46: 72302.65
A47: 24 | B47: A5-63 | C47: 铸铁落水管 φ150mm | D47: 10m | E47: 38.7 | G47: 1042.38 | H47: 247.04 | I47: 795.34 | K47: 40340.11 | M47: 9560.45 | N47: 30779.66
A48: 25 | B48: A5-67 | C48: 铸铁水斗(接水口) φ150mm | D48: 10个 | E48: 0.8 | G48: 839.68 | H48: 222.68 | I48: 617 | K48: 671.74 | M48: 178.14 | N48: 493.6
C49: 010504、墙地面防水(防潮) | K49: 327606.92 | M49: 52582.36 | N49: 275024.55
A50: 26 | B50: A5-102换 | C50: 聚苯乙烯泡沫塑料板 | D50: 100m2 | E50: 19.986 | G50: 6375 | H50: 1076.2 | I50: 5298.8 | K50: 127410.75 | M50: 21508.93 | N50: 105901.82
A51: 编制人: | F51: 审核人: | L51: 编制日期:
A53: 单位工程预结算书
A54: 工程名称：2601#土建工程 | L54: 第 4 页 共 7 页
A55: 序号 | B55: 编号 | C55: 定额名称 | D55: 单位 | E55: 工程量 | G55: 单价（元） | H55: 其中（元） | K55: 合价 | M55: 其中（元）
H56: 人工费单价 | I56: 材料费单价 | J56: 机械费单价 | M56: 人工费合价 | N56: 材料费合价 | O56: 机械费合价
C57: 立面
A58: 27 | B58: A5-104 | C58: 复合双面自粘橡胶沥青防水卷材 立面 | D58: 100m2 | E58: 19.986 | G58: 7936.63 | H58: 1027.16 | I58: 6909.47 | K58: 158621.49 | M58: 20528.82 | N58: 138092.67
A59: 28 | B59: A5-135换 | C59: 聚氨酯防水涂膜 双组份 厚2mm | D59: 100m2 | E59: 19.986 | G59: 2080.19 | H59: 527.6 | I59: 1552.59 | K59: 41574.68 | M59: 10544.61 | N59: 31030.06
C60: 010601、保温隔热 | K60: 361595.27 | M60: 104113.01 | N60: 257482.26
A61: 29 | B61: A6-12换 | C61: 屋面防水保温 挤塑聚苯板 | D61: 100m2 | E61: 8.87 | G61: 4113.16 | H61: 578.16 | I61: 3535 | K61: 36483.73 | M61: 5128.28 | N61: 31355.45
A62: 30 | B62: A6-56换 | C62: 墙体保温 岩棉板 厚50mm | D62: 100m2 | E62: 50.79 | G62: 5079 | H62: 1269.75 | I62: 3809.25 | K62: 257962.41 | M62: 64490.6 | N62: 193471.81
A63: 31 | B63: A6-92换 | C63: 楼地面隔热 岩棉板 | D63: 100m2 | E63: 9.33 | G63: 7197.12 | H63: 3697.12 | I63: 3500 | K63: 67149.13 | M63: 34494.13 | N63: 32655
C64: 020101、楼地面工程 | K64: 1807235.3 | M64: 506118.62 | N64: 1290943.8 | O64: 10172.86
A65: 32 | B65: A13-17 | C65: 垫层 现浇混凝土 | D65: 10m3 | E65: 15.582 | G65: 3390.26 | H65: 696.32 | I65: 2529.17 | J65: 164.77 | K65: 52827.03 | M65: 10850.06 | N65: 39409.53 | O65: 2567.45
A66: 33 | B66: A13-20 | C66: 水泥砂浆找平层 混凝土或硬基层上 厚度20mm | D66: 100m2 | E66: 103.88 | G66: 1343.39 | H66: 635.36 | I66: 670.49 | J66: 37.54 | K66: 139551.35 | M66: 66001.2 | N66: 69650.5 | O66: 3899.66
A67: 34 | B67: A13-30 | C67: 细石砼面层 楼地面 | D67: 100m2 | E67: 14.67 | G67: 1751.59 | H67: 836.36 | I67: 877.69 | J67: 37.54 | K67: 25695.83 | M67: 12269.4 | N67: 12875.71 | O67: 550.71
A68: 35 | B68: A13-34 | C68: 水泥砂浆 踢脚线底12mm面8mm | D68: 100m2 | E68: 0.33 | G68: 2874.68 | H68: 2173.56 | I68: 664.69 | J68: 36.43 | K68: 948.64 | M68: 717.27 | N68: 219.35 | O68: 12.02
A69: 36 | B69: A13-95 | C69: 陶瓷锦砖 楼地面 拼花 水泥砂浆 | D69: 100m2 | E69: 75.61 | G69: 13686.79 | H69: 4560.64 | I69: 9087.51 | J69: 38.64 | K69: 1034858.2 | M69: 344829.99 | N69: 687106.63 | O69: 2921.57
A70: 37 | B70: A13-95 | C70: 防滑地砖面层 | D70: 100m2 | E70: 3.84 | G70: 17926.79 | H70: 4560.64 | I70: 13327.51 | J70: 38.64 | K70: 68838.87 | M70: 17512.86 | N70: 51177.64 | O70: 148.38
A71: 38 | B71: A13-99 | C71: 地砖 踢脚线 水泥砂浆 | D71: 100m2 | E71: 1.98 | G71: 13797.96 | H71: 5248.76 | I71: 8524.91 | J71: 24.29 | K71: 27319.96 | M71: 10392.54 | N71: 16879.32 | O71: 48.09
A72: 编制人: | F72: 审核人: | L72: 编制日期:
A74: 单位工程预结算书
A75: 工程名称：2601#土建工程 | L75: 第 5 页 共 7 页
A76: 序号 | B76: 编号 | C76: 定额名称 | D76: 单位 | E76: 工程量 | G76: 单价（元） | H76: 其中（元） | K76: 合价 | M76: 其中（元）
H77: 人工费单价 | I77: 材料费单价 | J77: 机械费单价 | M77: 人工费合价 | N77: 材料费合价 | O77: 机械费合价
A78: 39 | B78: A13-111 | C78: 玻化砖 踢脚线 水泥砂浆 | D78: 100m2 | E78: 0.99 | G78: 19261.8 | H78: 3485.76 | I78: 15751.75 | J78: 24.29 | K78: 19069.18 | M78: 3450.9 | N78: 15594.23 | O78: 24.05
A79: 40 | B79: A13-130换 | C79: 玻化砖 楼地面 | D79: 100m2 | E79: 19.14 | G79: 19574.93 | H79: 1849.64 | I79: 17725.29 | K79: 374664.16 | M79: 35402.11 | N79: 339262.05
A80: 41 | B80: A13-138 | C80: 防静电架空地板 | D80: 100m2 | E80: 0.51 | G80: 23274.02 | H80: 1474.16 | I80: 21799.86 | K80: 11869.75 | M80: 751.82 | N80: 11117.93
A81: 42 | B81: A13-169 | C81: 长条复合地板安装 铺在混凝土面上 | D81: 100m2 | E81: 2.33 | G81: 20783.04 | H81: 1587.46 | I81: 19195.58 | K81: 48424.48 | M81: 3698.78 | N81: 44725.7
A82: 43 | B82: A13-172 | C82: 成品木踢脚线安装 | D82: 100m | E82: 0.63 | G82: 5028.35 | H82: 383.64 | I82: 4643.24 | J82: 1.47 | K82: 3167.86 | M82: 241.69 | N82: 2925.24 | O82: 0.93
C83: 020102、墙、柱面工程 | K83: 4179165.1 | M83: 495295.73 | N83: 3681065.5 | O83: 2803.86
A84: 44 | B84: A14-23 | C84: 墙面抹灰 | D84: 100m2 | E84: 43.044 | G84: 2011.73 | H84: 1203.6 | I84: 763.97 | J84: 44.16 | K84: 86592.91 | M84: 51807.76 | N84: 32884.32 | O84: 1900.82
A85: 45 | B85: A14-138 | C85: 钢骨架上干挂石板 墙面 | D85: 100m2 | E85: 35.5 | G85: 91794.43 | H85: 7339.36 | I85: 84455.07 | K85: 3258702.3 | M85: 260547.28 | N85: 2998155
A86: 46 | B86: A14-149 | C86: 玻化砖 墙面 | D86: 100m2 | E86: 18.32 | G86: 20364.91 | H86: 4857.12 | I86: 15502.27 | J86: 5.52 | K86: 373085.15 | M86: 88982.44 | N86: 284001.59 | O86: 101.13
A87: 47 | B87: A14-149 | C87: 面砖防水 水泥砂浆粘贴 墙面 | D87: 100m2 | E87: 14.93 | G87: 17319.91 | H87: 4857.12 | I87: 12457.27 | J87: 5.52 | K87: 258586.26 | M87: 72516.8 | N87: 185987.04 | O87: 82.41
A88: 48 | B88: A14-213 | C88: 轻钢龙骨 中距(mm以内) 竖603横1500 | D88: 100m2 | E88: 7.33 | G88: 4049.79 | H88: 766.2 | I88: 3244.23 | J88: 39.36 | K88: 29684.96 | M88: 5616.25 | N88: 23780.21 | O88: 288.51
A89: 49 | B89: A14-213 | C89: 轻钢龙骨 中距(mm以内) 竖603横1500 | D89: 100m2 | E89: 10.95 | G89: 4049.79 | H89: 766.2 | I89: 3244.23 | J89: 39.36 | K89: 44345.2 | M89: 8389.89 | N89: 35524.32 | O89: 430.99
A90: 50 | B90: A14-217 | C90: 矿棉吸音板墙面 | D90: 100m2 | E90: 10.95 | G90: 5536.43 | H90: 282.28 | I90: 5254.15 | K90: 60623.91 | M90: 3090.97 | N90: 57532.94
A91: 51 | B91: A14-219 | C91: 穿孔石膏板吸声基层 | D91: 100m2 | E91: 7.33 | G91: 9214.79 | H91: 592.68 | I91: 8622.11 | K91: 67544.41 | M91: 4344.34 | N91: 63200.07
C92: 020103、幕墙工程 | K92: 256551.63 | M92: 18561.19 | N92: 237676.76 | O92: 313.67
A93: 52 | B93: A15-25 | C93: 玻璃幕墙 隐框 铝合 | D93: 100m2 | E93: 1.56 | G93: 164456.17 | H93: 11898.2 | I93: 152356.9 | J93: 201.07 | K93: 256551.63 | M93: 18561.19 | N93: 237676.76 | O93: 313.67
A94: 编制人: | F94: 审核人: | L94: 编制日期:
A96: 单位工程预结算书
A97: 工程名称：2601#土建工程 | L97: 第 6 页 共 7 页
A98: 序号 | B98: 编号 | C98: 定额名称 | D98: 单位 | E98: 工程量 | G98: 单价（元） | H98: 其中（元） | K98: 合价 | M98: 其中（元）
H99: 人工费单价 | I99: 材料费单价 | J99: 机械费单价 | M99: 人工费合价 | N99: 材料费合价 | O99: 机械费合价
C100: 金龙骨基层
C101: 020104、天棚工程 | K101: 1585942.7 | M101: 282692.17 | N101: 1303057 | O101: 193.48
A102: 53 | B102: A16-2 | C102: 天棚抹灰 | D102: 100m2 | E102: 7.01 | G102: 1709.31 | H102: 1192.32 | I102: 489.39 | J102: 27.6 | K102: 11982.26 | M102: 8358.16 | N102: 3430.62 | O102: 193.48
A103: 54 | B103: A16-39 | C103: 天棚装配式U型轻钢龙骨 | D103: 100m2 | E103: 3.45 | G103: 6049.05 | H103: 1869.54 | I103: 4179.51 | K103: 20869.22 | M103: 6449.91 | N103: 14419.31
A104: 55 | B104: A16-39 | C104: 天棚装配式U型轻钢龙骨 | D104: 100m2 | E104: 86.92 | G104: 6049.05 | H104: 1869.54 | I104: 4179.51 | K104: 525783.43 | M104: 162500.42 | N104: 363283.01
A105: 56 | B105: A16-40 | C105: 天棚装配式U型轻钢龙骨 | D105: 100m2 | E105: 6.17 | G105: 6995.25 | H105: 2088.58 | I105: 4906.67 | K105: 43160.69 | M105: 12886.54 | N105: 30274.15
A106: 57 | B106: A16-103 | C106: 天棚面层 塑料板 | D106: 100m2 | E106: 3.45 | G106: 11071.93 | H106: 1052.16 | I106: 10019.77 | K106: 38198.16 | M106: 3629.95 | N106: 34568.21
...

Sheet 土措
D2: 单价措施项目分项汇总表
A3: 工程名称：2601#土建工程 | J3: 第 1 页 共 2 页
A4: 序号 | B4: 定额编码 | C4: 子目名称 | E4: 工程量 | G4: 价值（元） | I4: 其中（元）
E5: 单位 | F5: 数量 | G5: 单价 | H5: 合价 | I5: 人工费合价 | K5: 材料费合价 | L5: 机械费合价
B6: 一 | C6: 排水降水
B7: 二 | C7: 混凝土、钢筋混凝土模板及支撑 | H7: 2887867.7 | I7: 1901708.8 | K7: 841205.19 | L7: 144953.65
A8: 1 | B8: A7-39 | C8: 矩形柱 组合钢模板 钢支撑 | E8: 100m2 | F8: 53.7 | G8: 5262.52 | H8: 282597.32 | I8: 184674.3 | K8: 86269.05 | L8: 11653.97
A9: 2 | B9: A7-39 | C9: 矩形柱 组合钢模板 钢支撑 | E9: 100m2 | F9: 12.7 | G9: 5262.52 | H9: 66834 | I9: 43675.3 | K9: 20402.55 | L9: 2756.15
A10: 3 | B10: A7-54 | C10: 单梁、连续梁 组合钢模板 钢支撑 | E10: 100m2 | F10: 73.6092 | G10: 5857.3 | H10: 431151.17 | I10: 306323.21 | K10: 98904.27 | L10: 25923.69
A11: 4 | B11: A7-54 | C11: 单梁、连续梁 组合钢模板 钢支撑 | E11: 100m2 | F11: 50.2285 | G11: 5857.3 | H11: 294203.39 | I11: 209024.9 | K11: 67489.02 | L11: 17689.47
A12: 5 | B12: A7-73 | C12: 直形墙 组合钢模板 钢支撑 | E12: 100m2 | F12: 115.056 | G12: 3399.15 | H12: 391092.6 | I12: 268706.38 | K12: 101356.28 | L12: 21029.94
A13: 6 | B13: A7-73 | C13: 直形墙 组合钢模板 钢支撑 | E13: 100m2 | F13: 36 | G13: 3399.15 | H13: 122369.4 | I13: 84075.84 | K13: 31713.48 | L13: 6580.08
A14: 7 | B14: A7-76 | C14: 电梯井壁 组合钢模板 钢支撑 | E14: 100m2 | F14: 42.8577 | G14: 4246.28 | H14: 181985.79 | I14: 128338.24 | K14: 46592.32 | L14: 7055.23
A15: 8 | B15: A7-86 | C15: 有梁板 组合钢模板 钢支撑 | E15: 100m2 | F15: 15.6352 | G15: 5491.71 | H15: 85863.98 | I15: 56209.79 | K15: 24808.68 | L15: 4845.5
A16: 9 | B16: A7-86 | C16: 有梁板 组合钢模板 钢支撑 | E16: 100m2 | F16: 127.6642 | G16: 5491.71 | H16: 701094.76 | I16: 458963.01 | K16: 202567.34 | L16: 39564.41
A17: 10 | B17: A7-109 | C17: 楼梯 直形 木模板木支撑 | E17: 10m2 | F17: 65 | G17: 1747.6 | H17: 113594 | I17: 57959.2 | K17: 53129.7 | L17: 2505.1
A18: 11 | B18: A7-113 | C18: 台阶 木模板木支撑 | E18: 10m2 | F18: 11 | G18: 398.21 | H18: 4380.31 | I18: 2380.84 | K18: 1941.83 | L18: 57.64
A19: 12 | B19: A7-118 | C19: 零星构件 木模板木支撑 | E19: 100m2 | F19: 7.6405 | G19: 9437.33 | H19: 72105.92 | I19: 29177.85 | K19: 41570.05 | L19: 1358.02
A20: 13 | B20: A7-118 | C20: 零星构件 木模板木支撑 | E20: 100m2 | F20: 6.549 | G20: 9437.33 | H20: 61805.07 | I20: 25009.58 | K20: 35631.47 | L20: 1164.02
A21: 14 | B21: A7-121 | C21: 混凝土散水 钢模板木支撑 | E21: 100m2 | G21: 193.68
A22: 15 | B22: A7-28 | C22: 独立式桩承台 组合钢模板 木支撑 | E22: 100m2 | F22: 12.50832 | G22: 4461.75 | H22: 55809 | I22: 33532.8 | K22: 20273.11 | L22: 2003.08
A23: 16 | B23: A7-30 | C23: 混凝土基础垫层 木模板 木支撑 | E23: 100m2 | F23: 0.13524 | G23: 4660.45 | H23: 630.28 | I23: 145.62 | K23: 477.67 | L23: 6.99
A24: 17 | B24: A7-50 | C24: 基础梁 组合钢模板 钢支撑 | E24: 100m2 | F24: 4.7481 | G24: 4707.29 | H24: 22350.68 | I24: 13511.95 | K24: 8078.37 | L24: 760.36
B25: 三 | C25: 脚手架 | H25: 173564.96 | I25: 86336.99 | K25: 74463.21 | L25: 12764.77
A26: 1 | B26: A21-8 | C26: 综合脚手架 | E26: 100m2 | F26: 122.2211 | G26: 1420.09 | H26: 173564.96 | I26: 86336.99 | K26: 74463.21 | L26: 12764.77
C28: 页合计 | H28: 3061432.6 | I28: 1988045.8 | K28: 915668.4 | L28: 157718.42
A29: 编制人: | D29: 审核人: | J29: 编制日期:
D31: 单价措施项目分项汇总表
A32: 工程名称：2601#土建工程 | J32: 第 2 页 共 2 页
A33: 序号 | B33: 定额编码 | C33: 子目名称 | E33: 工程量 | G33: 价值（元） | I33: 其中（元）
E34: 单位 | F34: 数量 | G34: 单价 | H34: 合价 | I34: 人工费合价 | K34: 材料费合价 | L34: 机械费合价
B35: 四 | C35: 垂直运输费 | H35: 306840.96 | I35: 218765.99 | L35: 88074.97
A36: 1 | B36: A22-4 | C36: 垂直运输工程 13~15层 檐高(m以内) 49.5 | E36: 100m2 | F36: 122.2211 | G36: 2510.54 | H36: 306840.96 | I36: 218765.99 | L36: 88074.97
B37: 五 | C37: 大型机械设备进出场及安拆费
B38: 六 | C38: 已完工程及设备保护费
B39: 七 | C39: 地上、地下设施、建筑物临时保护设施费
B40: 八 | C40: 其他
C54: 页合计 | H54: 306840.96 | I54: 218765.99 | L54: 88074.97
C55: 合计 | H55: 3368273.6 | I55: 2206811.8 | K55: 915668.4 | L55: 245793.39
A56: 编制人: | D56: 审核人: | J56: 编制日期:

Sheet 土差
A2: 单位工程人材机价差表
A3: 工程名称：2601#土建工程 | I3: 第 1 页 共 2 页
A4: 序号 | B4: 材料名称 | C4: 材料规格 | D4: 单位 | F4: 材料量 | G4: 预算价 | H4: 市场价 | J4: 价 差 | K4: 价差合计
A5: 1 | B5: 成品钢质防火门 | D5: m2 | F5: 315.2758 | G5: 590 | H5: 800 | J5: 210 | K5: 66207.92
A6: 2 | B6: 实木装饰门(成品) | D6: m2 | F6: 460.94 | G6: 550 | H6: 800 | J6: 250 | K6: 115235
A7: 3 | B7: 铝合金外门 | D7: m2 | F7: 10.4425 | G7: 350 | H7: 1500 | J7: 1150 | K7: 12008.88
A8: 4 | B8: 断桥铝合金窗 | D8: m2 | F8: 1446.4778 | G8: 253 | H8: 800 | J8: 547 | K8: 791223.36
A9: 5 | B9: 玻璃棉高级吸声板 | D9: m2 | F9: 244.65 | G9: 133 | H9: 160 | J9: 27 | K9: 6605.55
A10: 6 | B10: 花岗岩板 | D10: m2 | F10: 3621 | G10: 185 | H10: 800 | J10: 615 | K10: 2226915
A11: 7 | B11: 石膏板 | D11: m2 | F11: 9896.25 | G11: 9.2 | H11: 80 | J11: 70.8 | K11: 700654.5
A12: 8 | B12: 复合地板 | D12: m2 | F12: 244.65 | G12: 155 | H12: 180 | J12: 25 | K12: 6116.25
A13: 9 | B13: 陶瓷锦砖 | D13: m2 | F13: 8014.66 | G13: 11.35 | H13: 80 | J13: 68.65 | K13: 550206.41
A14: 10 | B14: 防滑地砖 | D14: m2 | F14: 407.04 | G14: 11.35 | H14: 120 | J14: 108.65 | K14: 44224.9
A15: 11 | B15: 玻化砖 | D15: m2 | F15: 1859.48 | G15: 11.35 | H15: 150 | J15: 138.65 | K15: 257816.9
A16: 12 | B16: 面砖防水 | D16: m2 | F16: 1515.395 | G16: 11.35 | H16: 120 | J16: 108.65 | K16: 164647.67
... A25: 21 | B25: 钢制复合防火卷帘门 | D25: m2 | F25: 210.3192 | G25: 280 | H25: 800 | J25: 520 | K25: 109365.98
A26: 22 | B26: 复合双面自粘橡胶沥青防水卷材 | C26: 3mm | D26: m2 | F26: 2647.5454 | G26: 40.2 | H26: 50 | J26: 9.8 | K26: 25945.94
A27: 编制人: | E27: 审核人: | I27: 编制日期:
A29: 单位工程人材机价差表
A30: 工程名称：2601#土建工程 | I30: 第 2 页 共 2 页
A31: 序号 | B31: 材料名称 | C31: 材料规格 | D31: 单位 | F31: 材料量 | G31: 预算价 | H31: 市场价 | J31: 价 差 | K31: 价差合计
A32: 23 | B32: SBS改性沥青防水卷材玻纤胎 | C32: 3mm | D32: m2 | F32: 1469.6616 | G32: 32 | H32: 45 | J32: 13 | K32: 19105.6
A33: 24 | B33: 聚苯乙烯泡沫塑料板 | C33: 3mm | D33: m2 | F33: 2647.5454 | G33: 32 | H33: 40 | J33: 8 | K33: 21180.36
A55: 合 计 | K55: 5667073.6
A56: 编制人: | E56: 审核人: | I56: 编制日期:

Sheet 水费
A2: 单位工程费用汇总表
A3: 工程名称：2601#给排水工程 | E3: 第 1 页 共 1 页
A4: 序号 | B4: 费用名称 | D4: 取费基数 | F4: 费率 | G4: 费用金额
A5: 1 | B5: 安装工程 | D5: 安装工程 | G5: 1376369.8
A6: 一 | B6: 分部分项工程费（含5%零星工程） | D6: (人工费+材料费+未计价材料费+施工机具使用费)*1.05 | G6: 1239179.8
A7: 1 | B7: 人工费 | D7: 人工费 | G7: 159933.29
A8: 2 | B8: 材料费 | D8: 材料费 | G8: 84606.05
A9: 3 | B9: 未计价材料费 | D9: 主材费 | G9: 927965.83
A10: 4 | B10: 施工机具使用费 | D10: 机械费 | G10: 7666.1
A11: 二 | B11: 措施项目费 | D11: 单价措施项目费+总价措施项目费 | G11: 16257.14
A12: 2.1 | B12: 单价措施项目费 | D12: 人工费+材料费+施工机具使用费
A13: 2.1.1 | B13: 人工费 | D13: 技术措施项目人工费
A14: 2.1.2 | B14: 材料费 | D14: 技术措施项目材料费
A15: 2.1.3 | B15: 施工机具使用费 | D15: 技术措施项目机械费
A16: 2.2 | B16: 总价措施项目费 | D16: 安全文明施工费+其它总价措施项目费 | G16: 16257.14
A17: 2.2.1 | B17: 安全文明施工费 | D17: 人工费+施工机具使用费+人工费+施工机具使用费 | F17: 9.05 | G17: 15167.74
A18: 2.2.2 | B18: 其它总价措施项目费 | D18: 人工费+施工机具使用费+人工费+施工机具使用费 | F18: 0.65 | G18: 1089.4
A19: 三 | B19: 总包服务费
A20: 四 | B20: 企业管理费 | D20: 人工费+施工机具使用费+人工费+施工机具使用费 | F20: 17.5 | G20: 29329.89
A21: 五 | B21: 利润 | D21: 人工费+施工机具使用费+人工费+施工机具使用费 | F21: 14.91 | G21: 24989.07
A22: 六 | B22: 规费 | D22: 人工费+施工机具使用费+人工费+施工机具使用费 | F22: 11.66 | G22: 19542.09
A23: 七 | B23: 索赔与现场签证
A24: 八 | B24: 不含税工程造价 | D24: 分部分项工程费（含5%零星工程）+措施项目费+总包服务费+企业管理费+利润+规费+索赔与现场签证 | G24: 1329298
A25: 九 | B25: 税前包干项目 | D25: 税前包干价
A26: 十 | B26: 税金 | D26: 不含税工程造价+税前包干价 | F26: 3.5411 | G26: 47071.77
A27: 十一 | B27: 税后包干项目 | D27: 税后包干价
A28: 十二 | B28: 设备费 | D28: 设备费
A29: 十三 | B29: 含税工程造价 | D29: 不含税工程造价+税金+税前包干项目+税后包干项目+设备费 | G29: 1376369.8
A31: 2 | B31: 工程造价 | D31: 专业造价总合计 | G31: 1376369.8
A37: 编制人: | C37: 审核人: | E37: 编制日期:

Sheet 水
A2: 单位工程预结算书
A3: 工程名称：2601#给排水工程 | K3: 第 1 页 共 9 页
A4: 序号 | B4: 定额编号 | C4: 子目名称 | D4: 工程量 | G4: 价值（元） | I4: 其中（元） | O4: 工日统计
D5: 单位 | E5: 数量 | G5: 单价 | H5: 合价 | I5: 人工合价 | J5: 材料合价 | L5: 机械合价 | M5: 主材合价 | N5: 设备合价
B6: 010901 | C6: 离心式泵 | H6: 2093.56 | I6: 1446.33 | J6: 387.61 | L6: 259.62 | O6: 17.26
A7: 1 | B7: C1-798 | C7: 潜污泵 安装 | D7: 台 | E7: 2 | G7: 334.84 | H7: 669.68 | I7: 394.94 | J7: 168.12 | L7: 106.62 | O7: 4.714
A8: 2 | B8: C1-801 | C8: 矢量变频给水设备 安装 | D8: 套 | E8: 1 | G8: 1423.88 | H8: 1423.88 | I8: 1051.39 | J8: 219.49 | L8: 153 | O8: 12.546
B9: 080703 | C9: 低压法兰阀门 | H9: 2868.72 | I9: 2210.22 | J9: 336.12 | L9: 322.38 | M9: 73810 | O9: 26.802
A10: 1 | B10: C8-1416 | C10: 低压法兰阀门 公称直径(50mm以内) | D10: 个 | E10: 12 | G10: 34.19 | H10: 410.28 | I10: 278.28 | J10: 61.8 | L10: 70.2 | M10: 5760 | O10: 3.384
B11: 主材 | C11: 铜截止阀 | D11: 个 | E11: 12 | G11: 480 | H11: 5760 | M11: 5760
A12: 2 | B12: C8-1417 | C12: 低压法兰阀门 公称直径(65mm以内) | D12: 个 | E12: 2 | G12: 48.87 | H12: 97.74 | I12: 73.68 | J12: 11.4 | L12: 12.66 | M12: 1100 | O12: 0.894
B13: 主材 | C13: 闸阀 | D13: 个 | E13: 2 | G13: 550 | H13: 1100 | M13: 1100
A14: 3 | B14: C8-1418 | C14: 低压法兰阀门 公称直径(80mm以内) | D14: 个 | E14: 2 | G14: 57.75 | H14: 115.5 | I14: 88.56 | J14: 13.32 | L14: 13.62 | M14: 1300 | O14: 1.074
B15: 主材 | C15: 低压法兰阀门 | D15: 个 | E15: 2 | G15: 650 | H15: 1300 | M15: 1300
A16: 4 | B16: C8-1419 | C16: 低压法兰阀门 公称直径(100mm以内) | D16: 个 | E16: 15 | G16: 74.84 | H16: 1122.6 | I16: 884.85 | J16: 124.8 | L16: 112.95 | M16: 9150 | O16: 10.725
B17: 主材 | C17: 蝶阀 | D17: 个 | E17: 15 | G17: 610 | H17: 9150 | M17: 9150
A18: 5 | B18: C8-1419 | C18: 湿式报警阀组安装 公称直径(100mm以内) | D18: 套 | E18: 2 | G18: 74.84 | H18: 149.68 | I18: 117.98 | J18: 16.64 | L18: 15.06 | M18: 11000 | O18: 1.43
B19: 主材 | C19: 湿式报警阀 | D19: 套 | E19: 2 | G19: 5500 | H19: 11000 | M19: 11000
A20: 6 | B20: C8-1419 | C20: 电触点信号阀 公称直径(100mm以内) | D20: 套 | E20: 13 | G20: 74.84 | H20: 972.92 | I20: 766.87 | J20: 108.16 | L20: 97.89 | M20: 45500 | O20: 9.295
B21: 主材 | C21: 信号阀 | D21: 套 | E21: 13 | G21: 3500 | H21: 45500 | M21: 45500
B22: 090105 | C22: 水流指示器安装 | H22: 4395.95 | I22: 2448.81 | J22: 1907.75 | L22: 39.39 | M22: 14300 | O22: 29.718
A23: 编制人: | F23: 审核人: | K23: 编制日期:
A25: 单位工程预结算书
A26: 工程名称：2601#给排水工程 | K26: 第 2 页 共 9 页
A27: 序号 | B27: 定额编号 | C27: 子目名称 | D27: 工程量 | G27: 价值（元） | I27: 其中（元） | O27: 工日统计
D28: 单位 | E28: 数量 | G28: 单价 | H28: 合价 | I28: 人工合价 | J28: 材料合价 | L28: 机械合价 | M28: 主材合价 | N28: 设备合价
A29: 1 | B29: C9-68 | C29: 水流指示器安装 螺纹连接 公称直径(100mm以内) | D29: 个 | E29: 13 | G29: 338.15 | H29: 4395.95 | I29: 2448.81 | J29: 1907.75 | L29: 39.39 | M29: 14300 | O29: 29.718
B30: 主材 | C30: 水流指示器 | D30: 个 | E30: 13 | G30: 1100 | H30: 14300 | M30: 14300
B31: 090107 | C31: 末端试水装置安装 | H31: 2277.86 | I31: 1590.68 | J31: 650.13 | L31: 37.05 | M31: 79749.6 | O31: 19.318
A32: 1 | B32: C9-80 | C32: 末端试水装置安装 公称直径(32mm以内) | D32: 组 | E32: 2 | G32: 175.22 | H32: 350.44 | I32: 244.72 | J32: 100.02 | L32: 5.7 | M32: 64640 | O32: 2.972
B33: 主材 | C33: 末端试水装置 | D33: 个 | E33: 4.04 | G33: 16000 | H33: 64640 | M33: 64640
A34: 2 | B34: C9-80 | C34: 末端试水装置安装 公称直径(32mm以内) | D34: 组 | E34: 11 | G34: 175.22 | H34: 1927.42 | I34: 1345.96 | J34: 550.11 | L34: 31.35 | M34: 15109.6 | O34: 16.346
B35: 主材 | C35: 末端试水阀 | D35: 个 | E35: 22.22 | G35: 680 | H35: 15109.6 | M35: 15109.6
B36: 090111 | C36: 消防水泵接合器安装 | H36: 1417.12 | I36: 673.2 | J36: 689.56 | L36: 54.36 | M36: 13200 | O36: 8.172
A37: 1 | B37: C9-102 | C37: 消防水泵接合器安装 地下式 DN150 | D37: 套 | E37: 4 | G37: 354.28 | H37: 1417.12 | I37: 673.2 | J37: 689.56 | L37: 54.36 | M37: 13200 | O37: 8.172
B38: 主材 | C38: 消防水泵接合器 | D38: 套 | E38: 4 | G38: 3300 | H38: 13200 | M38: 13200
B39: 090112 | C39: 灭火器具安装 | H39: 3620.94 | I39: 3269.95 | J39: 350.99 | M39: 240000 | O39: 54.502
A40: 1 | B40: C9-108 | C40: 灭火器 放置式 | D40: 10个 | E40: 15 | G40: 83.06 | H40: 1245.9 | I40: 1230.9 | J40: 15 | M40: 45000 | O40: 20.52
B41: 主材 | C41: 手提式磷酸铵盐干粉灭火器 | D41: 套 | E41: 150 | G41: 300 | H41: 45000 | M41: 45000
A42: 2 | B42: C9-111 | C42: 组合式消防柜 安装 | D42: 10个 | E42: 6.5 | G42: 365.39 | H42: 2375.04 | I42: 2039.05 | J42: 335.99 | M42: 195000 | O42: 33.982
B43: 主材 | C43: 组合式消防柜 | D43: 个 | E43: 65 | G43: 3000 | H43: 195000 | M43: 195000
B44: 090203 | C44: 选择阀安装 | H44: 1028.4 | I44: 582.9 | J44: 402.84 | L44: 42.66 | M44: 27000 | O44: 7.074
A45: 1 | B45: C9-140 | C45: 选择阀安装 法兰连接 公称直径(100mm以内) | D45: 个 | E45: 6 | G45: 171.4 | H45: 1028.4 | I45: 582.9 | J45: 402.84 | L45: 42.66 | M45: 27000 | O45: 7.074
A46: 编制人: | F46: 审核人: | K46: 编制日期:
A48: 单位工程预结算书
A49: 工程名称：2601#给排水工程 | K49: 第 3 页 共 9 页
A50: 序号 | B50: 定额编号 | C50: 子目名称 | D50: 工程量 | G50: 价值（元） | I50: 其中（元） | O50: 工日统计
D51: 单位 | E51: 数量 | G51: 单价 | H51: 合价 | I51: 人工合价 | J51: 材料合价 | L51: 机械合价 | M51: 主材合价 | N51: 设备合价
B52: 主材 | C52: 选择阀 | D52: 个 | E52: 6 | G52: 4500 | H52: 27000 | M52: 27000
B53: 090204 | C53: 气体喷头安装 | H53: 30816.72 | I53: 21115.02 | J53: 5728.94 | L53: 3972.76 | M53: 61266.6 | O53: 256.2408
A54: 1 | B54: C9-141 | C54: 吊顶型喷头 安装 公称直径(15mm以内) | D54: 10个 | E54: 120 | G54: 254.21 | H54: 30505.2 | I54: 20904 | J54: 5670 | L54: 3931.2 | M54: 60600 | O54: 253.68
B55: 主材 | C55: 标准喷头 | D55: 个 | E55: 1212 | G55: 50 | H55: 60600 | M55: 60600
A56: 2 | B56: C9-142 | C56: 气体喷头安装 公称直径(20mm以内) | D56: 10个 | E56: 1.2 | G56: 259.6 | H56: 311.52 | I56: 211.02 | J56: 58.94 | L56: 41.56 | M56: 666.6 | O56: 2.5608
B57: 主材 | C57: 气体灭火全淹没喷头 | D57: 个 | E57: 12.12 | G57: 55 | H57: 666.6 | M57: 666.6
B58: 090409 | C58: 警报装置 | H58: 110.9 | I58: 98.78 | J58: 10.76 | L58: 1.36 | M58: 444.4 | O58: 1.104
A59: 1 | B59: C9-227 | C59: 警报装置 警铃 | D59: 台 | E59: 2 | G59: 55.45 | H59: 110.9 | I59: 98.78 | J59: 10.76 | L59: 1.36 | M59: 444.4 | O59: 1.104
B60: 主材 | C60: 水力警铃 | D60: 套 | E60: 2.02 | G60: 220 | H60: 444.4 | M60: 444.4
B61: 100102 | C61: 室内管道安装 | H61: 142511.47 | I61: 122902.25 | J61: 16672.7 | L61: 2936.52 | M61: 311396.73 | O61: 1491.633
A62: 1 | B62: C10-186 | C62: 室内管道安装 焊接钢管(螺纹连接) 公称直径(25mm以内) | D62: 10m | E62: 44 | G62: 179.51 | H62: 7898.44 | I62: 6836.72 | J62: 975.48 | L62: 86.24 | M62: 7943.76 | O62: 82.984
B63: 主材 | C63: 热镀锌钢管 | D63: m | E63: 448.8 | G63: 17.7 | H63: 7943.76 | M63: 7943.76
A64: 2 | B64: C10-187 | C64: 室内管道安装 焊接钢管(螺纹连接) 公称直径(32mm以内) | D64: 10m | E64: 60 | G64: 181.61 | H64: 10896.6 | I64: 9322.8 | J64: 1456.2 | L64: 117.6 | M64: 13158 | O64: 113.16
B65: 主材 | C65: 热镀锌钢管 | D65: m | E65: 612 | G65: 21.5 | H65: 13158 | M65: 13158
A66: 3 | B66: C10-188 | C66: 室内管道安装 焊接钢管(螺纹连接) 公称直径(40mm以内) | D66: 10m | E66: 25 | G66: 203.07 | H66: 5076.75 | I66: 4627.5 | J66: 387.75 | L66: 61.5 | M66: 7318.5 | O66: 56.175
B67: 主材 | C67: 热镀锌钢管 | D67: m | E67: 255 | G67: 28.7 | H67: 7318.5 | M67: 7318.5
A68: 编制人: | F68: 审核人: | K68: 编制日期:
A70: 单位工程预结算书
A71: 工程名称：2601#给排水工程 | K71: 第 4 页 共 9 页
A72: 序号 | B72: 定额编号 | C72: 子目名称 | D72: 工程量 | G72: 价值（元） | I72: 其中（元） | O72: 工日统计
D73: 单位 | E73: 数量 | G73: 单价 | H73: 合价 | I73: 人工合价 | J73: 材料合价 | L73: 机械合价 | M73: 主材合价 | N73: 设备合价
A74: 4 | B74: C10-189 | C74: 室内管道安装 焊接钢管(螺纹连接) 公称直径(50mm以内) | D74: 10m | E74: 30 | G74: 216.6 | H74: 6498 | I74: 5682.3 | J74: 687.6 | L74: 128.1 | M74: 11260.8 | O74: 68.97
B75: 主材 | C75: 热镀锌钢管 | D75: m | E75: 306 | G75: 36.8 | H75: 11260.8 | M75: 11260.8
A76: 5 | B76: C10-190 | C76: 室内管道安装 焊接钢管(螺纹连接) 公称直径(65mm以内) | D76: 10m | E76: 17 | G76: 228.15 | H76: 3878.55 | I76: 3290.35 | J76: 497.93 | L76: 90.27 | M76: 7924.38 | O76: 39.933
B77: 主材 | C77: 热镀锌钢管 | D77: m | E77: 173.4 | G77: 45.7 | H77: 7924.38 | M77: 7924.38
A78: 6 | B78: C10-190 | C78: 室内管道安装 焊接钢管(螺纹连接) 公称直径(65mm以内) | D78: 10m | E78: 40 | G78: 228.15 | H78: 9126 | I78: 7742 | J78: 1171.6 | L78: 212.4 | M78: 22440 | O78: 93.96
B79: 主材 | C79: 热镀锌钢管 | D79: m | E79: 408 | G79: 55 | H79: 22440 | M79: 22440
A80: 7 | B80: C10-190 | C80: 室内管道安装 焊接钢管(螺纹连接) 公称直径(65mm以内) | D80: 10m | E80: 28 | G80: 228.15 | H80: 6388.2 | I80: 5419.4 | J80: 820.12 | L80: 148.68 | M80: 15708 | O80: 65.772
B81: 主材 | C81: 无缝钢管 | D81: m | E81: 285.6 | G81: 55 | H81: 15708 | M81: 15708
A82: 8 | B82: C10-191 | C82: 室内管道安装 焊接钢管(螺纹连接) 公称直径(80mm以内) | D82: 10m | E82: 36 | G82: 236.96 | H82: 8530.56 | I82: 7375.68 | J82: 995.4 | L82: 159.48 | M82: 22986.72 | O82: 89.496
B83: 主材 | C83: 热镀锌钢管 | D83: m | E83: 367.2 | G83: 62.6 | H83: 22986.72 | M83: 22986.72
A84: 9 | B84: C10-192 | C84: 室内管道安装 焊接钢管(螺纹连接) 公称直径(100mm以内) | D84: 10m | E84: 40 | G84: 274.2 | H84: 10968 | I84: 9297.6 | J84: 1358 | L84: 312.4 | M84: 34557.6 | O84: 112.84
B85: 主材 | C85: 热镀锌钢管 | D85: m | E85: 408 | G85: 84.7 | H85: 34557.6 | M85: 34557.6
A86: 10 | B86: C10-192 | C86: 室内管道安装 焊接钢管(螺纹连接) 公称直径 | D86: 10m | E86: 22 | G86: 274.2 | H86: 6032.4 | I86: 5113.68 | J86: 746.9 | L86: 171.82 | M86: 19006.68 | O86: 62.062
A87: 编制人: | F87: 审核人: | K87: 编制日期:
A89: 单位工程预结算书
A90: 工程名称：2601#给排水工程 | K90: 第 5 页 共 9 页
A91: 序号 | B91: 定额编号 | C91: 子目名称 | D91: 工程量 | G91: 价值（元） | I91: 其中（元） | O91: 工日统计
D92: 单位 | E92: 数量 | G92: 单价 | H92: 合价 | I92: 人工合价 | J92: 材料合价 | L92: 机械合价 | M92: 主材合价 | N92: 设备合价
C93: (100mm以内)
B94: 主材 | C94: 热镀锌钢管 | D94: m | E94: 224.4 | G94: 84.7 | H94: 19006.68 | M94: 19006.68
A95: 11 | B95: C10-192 | C95: 室内管道安装 焊接钢管(螺纹连接) 公称直径(100mm以内) | D95: 10m | E95: 3 | G95: 274.2 | H95: 822.6 | I95: 697.32 | J95: 101.85 | L95: 23.43 | M95: 2591.82 | O95: 8.463
B96: 主材 | C96: 无缝钢管 | D96: m | E96: 30.6 | G96: 84.7 | H96: 2591.82 | M96: 2591.82
A97: 12 | B97: C10-193 | C97: 室内管道安装 焊接钢管(螺纹连接) 公称直径(125mm以内) | D97: 10m | E97: 50 | G97: 304.56 | H97: 15228 | I97: 12895 | J97: 1547 | L97: 786 | M97: 51255 | O97: 156.5
B98: 主材 | C98: 热镀锌钢管 | D98: m | E98: 510 | G98: 100.5 | H98: 51255 | M98: 51255
A99: 13 | B99: C10-194 | C99: 室内管道安装 焊接钢管(螺纹连接) 公称直径(150mm以内) | D99: 10m | E99: 3 | G99: 342.5 | H99: 1027.5 | I99: 886.05 | J99: 99.24 | L99: 42.21 | M99: 3353.76 | O99: 10.755
B100: 主材 | C100: 热镀锌钢管 | D100: m | E100: 30.6 | G100: 109.6 | H100: 3353.76 | M100: 3353.76
A101: 14 | B101: C10-194 | C101: 室内管道安装 焊接钢管(螺纹连接) 公称直径(150mm以内) | D101: 10m | E101: 12 | G101: 342.5 | H101: 4110 | I101: 3544.2 | J101: 396.96 | L101: 168.84 | M101: 13415.04 | O101: 43.02
B102: 主材 | C102: 热镀锌钢管 | D102: m | E102: 122.4 | G102: 109.6 | H102: 13415.04 | M102: 13415.04
A103: 15 | B103: C10-311 | C103: 室内管道安装 塑料给水管(粘接) 公称直径(20mm以内) | D103: 10m | E103: 22 | G103: 129.98 | H103: 2859.56 | I103: 2728 | J103: 110.88 | L103: 20.68 | M103: 1767.48 | O103: 33.088
B104: 主材 | C104: 塑料给水管 | D104: m | E104: 226.6 | G104: 7.8 | H104: 1767.48 | M104: 1767.48
A105: 16 | B105: C10-312 | C105: 室内管道安装 塑料给水管(粘接) 公称直径(25mm以内) | D105: 10m | E105: 28 | G105: 139.32 | H105: 3900.96 | I105: 3585.96 | J105: 288.68 | L105: 26.32 | M105: 2653.28 | O105: 43.512
...

Sheet 暖费
A2: 单位工程费用汇总表
A3: 工程名称：2601# 暖通工程 | E3: 第 1 页 共 1 页
A4: 序号 | B4: 费用名称 | D4: 取费基数 | F4: 费率 | G4: 费用金额
A5: 1 | B5: 安装工程 | D5: 安装工程 | G5: 2696961.6
A6: 一 | B6: 分部分项工程费（含5%零星工程） | D6: (人工费+材料费+未计价材料费+施工机具使用费)*1.05 | G6: 2341518.5
A7: 1 | B7: 人工费 | D7: 人工费 | G7: 427991.63
A8: 2 | B8: 材料费 | D8: 材料费 | G8: 241775.43
A9: 3 | B9: 未计价材料费 | D9: 主材费 | G9: 1498736.6
A10: 4 | B10: 施工机具使用费 | D10: 机械费 | G10: 61513.95
A11: 二 | B11: 措施项目费 | D11: 单价措施项目费+总价措施项目费 | G11: 47482.04
A12: 2.1 | B12: 单价措施项目费 | D12: 人工费+材料费+施工机具使用费
A13: 2.1.1 | B13: 人工费 | D13: 技术措施项目人工费
A14: 2.1.2 | B14: 材料费 | D14: 技术措施项目材料费
A15: 2.1.3 | B15: 施工机具使用费 | D15: 技术措施项目机械费
A16: 2.2 | B16: 总价措施项目费 | D16: 安全文明施工费+其它总价措施项目费 | G16: 47482.04
A17: 2.2.1 | B17: 安全文明施工费 | D17: 人工费+施工机具使用费+人工费+施工机具使用费 | F17: 9.05 | G17: 44300.25
A18: 2.2.2 | B18: 其它总价措施项目费 | D18: 人工费+施工机具使用费+人工费+施工机具使用费 | F18: 0.65 | G18: 3181.79
A19: 三 | B19: 总包服务费
A20: 四 | B20: 企业管理费 | D20: 人工费+施工机具使用费+人工费+施工机具使用费 | F20: 17.5 | G20: 85663.48
A21: 五 | B21: 利润 | D21: 人工费+施工机具使用费+人工费+施工机具使用费 | F21: 14.91 | G21: 72985.28
A22: 六 | B22: 规费 | D22: 人工费+施工机具使用费+人工费+施工机具使用费 | F22: 11.66 | G22: 57076.35
A23: 七 | B23: 索赔与现场签证
A24: 八 | B24: 不含税工程造价 | D24: 分部分项工程费（含5%零星工程）+措施项目费+总包服务费+企业管理费+利润+规费+索赔与现场签证 | G24: 2604725.6
A25: 九 | B25: 税前包干项目 | D25: 税前包干价
A26: 十 | B26: 税金 | D26: 不含税工程造价+税前包干价 | F26: 3.5411 | G26: 92235.94
A27: 十一 | B27: 税后包干项目 | D27: 税后包干价
A28: 十二 | B28: 设备费 | D28: 设备费
A29: 十三 | B29: 含税工程造价 | D29: 不含税工程造价+税金+税前包干项目+税后包干项目+设备费 | G29: 2696961.6
A31: 2 | B31: 工程造价 | D31: 专业造价总合计 | G31: 2696961.6
A37: 编制人: | C37: 审核人: | E37: 编制日期:

Sheet 暖
A2: 单位工程预结算书
A3: 工程名称：2601# 暖通工程 | K3: 第 1 页 共 6 页
A4: 序号 | B4: 定额编号 | C4: 子目名称 | D4: 工程量 | G4: 价值（元） | I4: 其中（元） | O4: 工日统计
D5: 单位 | E5: 数量 | G5: 单价 | H5: 合价 | I5: 人工合价 | J5: 材料合价 | L5: 机械合价 | M5: 主材合价 | N5: 设备合价
B6: 010801 | C6: 离心式通(引)风机 | H6: 37543.4 | I6: 25583.59 | J6: 8723.48 | L6: 3236.33 | O6: 305.292
A7: 1 | B7: C1-680 | C7: 离心风机箱 安装 | D7: 台 | E7: 6 | G7: 655.83 | H7: 3934.98 | I7: 2519.1 | J7: 1096.02 | L7: 319.86 | O7: 30.06
A8: 2 | B8: C1-682 | C8: 斜流风机 安装 | D8: 台 | E8: 2 | G8: 1120.56 | H8: 2241.12 | I8: 1530.5 | J8: 511.26 | L8: 199.36 | O8: 18.264
A9: 3 | B9: C1-682 | C9: 新风机组 送风风量：1000m3/h 安装 | D9: 台 | E9: 1 | G9: 1120.56 | H9: 1120.56 | I9: 765.25 | J9: 255.63 | L9: 99.68 | O9: 9.132
A10: 4 | B10: C1-683 | C10: 新风机组 送风风量：2000m3/h 安装 | D10: 台 | E10: 1 | G10: 1408.73 | H10: 1408.73 | I10: 975.13 | J10: 296.52 | L10: 137.08 | O10: 11.636
A11: 5 | B11: C1-684 | C11: 全热交换器新风机组 送风风量：2500m3/h 安装 | D11: 台 | E11: 1 | G11: 1810.33 | H11: 1810.33 | I11: 1262.71 | J11: 384.29 | L11: 163.33 | O11: 15.068
A12: 6 | B12: C1-685 | C12: 全热交换器新风机组 送风风量：3000m3/h安装 | D12: 台 | E12: 8 | G12: 2558.14 | H12: 20465.12 | I12: 13863.84 | J12: 4857.28 | L12: 1744 | O12: 165.44
A13: 7 | B13: C1-686 | C13: 全热交换器新风机组 送风风量：3500m3/h 安装 | D13: 台 | E13: 2 | G13: 3281.28 | H13: 6562.56 | I13: 4667.06 | J13: 1322.48 | L13: 573.02 | O13: 55.692
B14: 010802 | C14: 轴流通风机 | H14: 11221.34 | I14: 7724.72 | J14: 2617.2 | L14: 879.42 | O14: 92.179
A15: 1 | B15: C1-692 | C15: 轴流通风机 设备重量(0.2t以内) | D15: 台 | E15: 1 | G15: 455.8 | H15: 455.8 | I15: 262.06 | J15: 140.43 | L15: 53.31 | O15: 3.127
A16: 2 | B16: C1-693 | C16: 轴流通风机 设备重量(0.5t以内) | D16: 台 | E16: 1 | G16: 615.1 | H16: 615.1 | I16: 414.34 | J16: 147.45 | L16: 53.31 | O16: 4.944
A17: 3 | B17: C1-696 | C17: 斜流风机 安装 | D17: 台 | E17: 6 | G17: 1691.74 | H17: 10150.44 | I17: 7048.32 | J17: 2329.32 | L17: 772.8 | O17: 84.108
B18: 010901 | C18: 离心式泵 | H18: 2422.43 | I18: 1611.98 | J18: 543.9 | L18: 266.55 | O18: 19.237
A19: 1 | B19: C1-798 | C19: 补水泵 安装 | D19: 台 | E19: 2 | G19: 334.84 | H19: 669.68 | I19: 394.94 | J19: 168.12 | L19: 106.62 | O19: 4.714
A20: 2 | B20: C1-799 | C20: 循环水泵 安装 | D20: 台 | E20: 3 | G20: 584.25 | H20: 1752.75 | I20: 1217.04 | J20: 375.78 | L20: 159.93 | O20: 14.523
B21: 021702 | C21: 凝聚澄清过滤系统 | H21: 7579.41 | I21: 1160.3 | J21: 5380.4 | L21: 1038.71 | O21: 12.84
A22: 1 | B22: C2-320换 | C22: 软化水箱 外形尺寸：1400X1400X1200 安装 | D22: 台 | E22: 1 | G22: 6601.1 | H22: 6601.1 | I22: 778.06 | J22: 5259.2 | L22: 563.84 | O22: 8.61
A23: 编制人: | F23: 审核人: | K23: 编制日期:
A25: 单位工程预结算书
A26: 工程名称：2601# 暖通工程 | K26: 第 2 页 共 6 页
A27: 序号 | B27: 定额编号 | C27: 子目名称 | D27: 工程量 | G27: 价值（元） | I27: 其中（元） | O27: 工日统计
D28: 单位 | E28: 数量 | G28: 单价 | H28: 合价 | I28: 人工合价 | J28: 材料合价 | L28: 机械合价 | M28: 主材合价 | N28: 设备合价
A29: 2 | B29: C2-343 | C29: 定压罐 安装 | D29: 台 | E29: 1 | G29: 978.31 | H29: 978.31 | I29: 382.24 | J29: 121.2 | L29: 474.87 | O29: 4.23
B30: 022202 | C30: 水处理设备 | H30: 2522.87 | I30: 1351.94 | J30: 544.99 | L30: 625.94 | O30: 16.133
A31: 1 | B31: C2-454 | C31: 软化水处理器 安装 | D31: 台 | E31: 1 | G31: 2522.87 | H31: 2522.87 | I31: 1351.94 | J31: 544.99 | L31: 625.94 | O31: 16.133
B32: 040417 | C32: 风扇 | H32: 883.5 | I32: 756.5 | J32: 127 | M32: 12500 | O32: 8.85
A33: 1 | B33: C4-377 | C33: 换气扇 | D33: 台 | E33: 25 | G33: 35.34 | H33: 883.5 | I33: 756.5 | J33: 127 | M33: 12500 | O33: 8.85
B34: 主材 | C34: 换气扇 | D34: 台 | E34: 25 | G34: 500 | H34: 12500 | M34: 12500
B35: 070104 | C35: 空调器 | H35: 90639.4 | I35: 10420.24 | J35: 80073.56 | L35: 145.6 | O35: 121.532
A36: 1 | B36: C7-46 | C36: 分体空调 安装 | D36: 台 | E36: 3 | G36: 160.78 | H36: 482.34 | I36: 473.34 | J36: 9 | O36: 5.52
A37: 2 | B37: C7-50 | C37: 恒温恒湿空调 安装 | D37: 台 | E37: 1 | G37: 1752.3 | H37: 1752.3 | I37: 1749.3 | J37: 3 | O37: 20.4
A38: 3 | B38: C7-65换 | C38: 热泵机组 安装 | D38: 台 | E38: 4 | G38: 22101.19 | H38: 88404.76 | I38: 8197.6 | J38: 80061.56 | L38: 145.6 | O38: 95.612
B39: 070106 | C39: 风机盘管 | H39: 52254.87 | I39: 27063 | J39: 23096.67 | L39: 2095.2 | O39: 314.28
A40: 1 | B40: C7-74 | C40: 风机盘管安装 吊顶式 | D40: 台 | E40: 291 | G40: 179.57 | H40: 52254.87 | I40: 27063 | J40: 23096.67 | L40: 2095.2 | O40: 314.28
B41: 070201 | C41: 碳钢通风管道 | H41: 191764.8 | I41: 162646.4 | J41: 20915.2 | L41: 8203.2 | M41: 100144 | O41: 1869.44
A42: 1 | B42: C7-99 | C42: 镀锌薄钢板风管 | D42: 10m2 | E42: 160 | G42: 1198.53 | H42: 191764.8 | I42: 162646.4 | J42: 20915.2 | L42: 8203.2 | M42: 100144 | O42: 1869.44
B43: 主材 | C43: 镀锌钢板 | D43: m2 | E43: 1820.8 | G43: 55 | H43: 100144 | M43: 100144
B44: 070301 | C44: 碳钢阀门 | H44: 10274.15 | I44: 9133.56 | J44: 1140.59 | M44: 135609 | O44: 106.22
A45: 1 | B45: C7-278 | C45: 方形散流器（带调节阀） | D45: 个 | E45: 400 | G45: 24.12 | H45: 9648 | I45: 8600 | J45: 1048 | M45: 128000 | O45: 100
B46: 主材 | C46: 方形散流器（带调节阀） | D46: 个 | E46: 400 | G46: 320 | H46: 128000 | M46: 128000
A47: 2 | B47: C7-288 | C47: 风管防火阀周长(2200mm以内) | D47: 个 | E47: 1 | G47: 24.1 | H47: 24.1 | I47: 15.24 | J47: 8.86 | M47: 633 | O47: 0.18
B48: 主材 | C48: 防火阀 | D48: 个 | E48: 1 | G48: 633 | H48: 633 | M48: 633
A49: 3 | B49: C7-288 | C49: 风管防火阀周长(2200mm | D49: 个 | E49: 1 | G49: 24.1 | H49: 24.1 | I49: 15.24 | J49: 8.86 | M49: 600 | O49: 0.18
A50: 编制人: | F50: 审核人: | K50: 编制日期:
A52: 单位工程预结算书
A53: 工程名称：2601# 暖通工程 | K53: 第 3 页 共 6 页
A54: 序号 | B54: 定额编号 | C54: 子目名称 | D54: 工程量 | G54: 价值（元） | I54: 其中（元） | O54: 工日统计
D55: 单位 | E55: 数量 | G55: 单价 | H55: 合价 | I55: 人工合价 | J55: 材料合价 | L55: 机械合价 | M55: 主材合价 | N55: 设备合价
C56: 以内)
B57: 主材 | C57: 防火阀 | D57: 个 | E57: 1 | G57: 600 | H57: 600 | M57: 600
A58: 4 | B58: C7-288 | C58: 风管防火阀周长(2200mm以内) | D58: 个 | E58: 1 | G58: 24.1 | H58: 24.1 | I58: 15.24 | J58: 8.86 | M58: 792 | O58: 0.18
B59: 主材 | C59: 防火阀 | D59: 个 | E59: 1 | G59: 792 | H59: 792 | M59: 792
A60: 5 | B60: C7-288 | C60: 风管防火阀周长(2200mm以内) | D60: 个 | E60: 1 | G60: 24.1 | H60: 24.1 | I60: 15.24 | J60: 8.86 | M60: 650 | O60: 0.18
B61: 主材 | C61: 280℃防火阀 | D61: 个 | E61: 1 | G61: 650 | H61: 650 | M61: 650
A62: 6 | B62: C7-289 | C62: 风管防火阀周长(3600mm以内) | D62: 个 | E62: 2 | G62: 105.95 | H62: 211.9 | I62: 189.04 | J62: 22.86 | M62: 2294 | O62: 2.2
B63: 主材 | C63: 防火阀 | D63: 个 | E63: 2 | G63: 1147 | H63: 2294 | M63: 2294
A64: 7 | B64: C7-289 | C64: 风管防火阀周长(3600mm以内) | D64: 个 | E64: 2 | G64: 105.95 | H64: 211.9 | I64: 189.04 | J64: 22.86 | M64: 1800 | O64: 2.2
B65: 主材 | C65: 防火阀 | D65: 个 | E65: 2 | G65: 900 | H65: 1800 | M65: 1800
A66: 8 | B66: C7-289 | C66: 风管防火阀周长(3600mm以内) | D66: 个 | E66: 1 | G66: 105.95 | H66: 105.95 | I66: 94.52 | J66: 11.43 | M66: 840 | O66: 1.1
B67: 主材 | C67: 防火阀 | D67: 个 | E67: 1 | G67: 840 | H67: 840 | M67: 840
B68: 070307 | C68: 碳钢风口、散流器、百叶窗 | H68: 4462.77 | I68: 3880.89 | J68: 565.5 | L68: 16.38 | M68: 8580 | O68: 45.357
A69: 1 | B69: C7-375 | C69: 百叶风口(周长5200mm以内) | D69: 个 | E69: 39 | G69: 114.43 | H69: 4462.77 | I69: 3880.89 | J69: 565.5 | L69: 16.38 | M69: 8580 | O69: 45.357
B70: 主材 | C70: 多叶送风口 | D70: 个 | E70: 39 | G70: 220 | H70: 8580 | M70: 8580
B71: 070320 | C71: 消声器 | H71: 2264.87 | I71: 2264.87 | M71: 510 | O71: 26.412
A72: 1 | B72: C7-527 | C72: 消声器安装 截面积 | D72: 10个 | E72: 0.4 | G72: 3327.1 | H72: 1330.84 | I72: 1330.84 | M72: 340 | O72: 15.52
A73: 编制人: | F73: 审核人: | K73: 编制日期:
A75: 单位工程预结算书
A76: 工程名称：2601# 暖通工程 | K76: 第 4 页 共 6 页
A77: 序号 | B77: 定额编号 | C77: 子目名称 | D77: 工程量 | G77: 价值（元） | I77: 其中（元） | O77: 工日统计
D78: 单位 | E78: 数量 | G78: 单价 | H78: 合价 | I78: 人工合价 | J78: 材料合价 | L78: 机械合价 | M78: 主材合价 | N78: 设备合价
C79: (0.8m2以下)
B80: 主材 | C80: 管式阻性消声器 | D80: 个 | E80: 0.4 | G80: 850 | H80: 340 | M80: 340
A81: 2 | B81: C7-528 | C81: 消声器安装 截面积(1.5m2以下) | D81: 10个 | E81: 0.2 | G81: 4670.14 | H81: 934.03 | I81: 934.03 | M81: 170 | O81: 10.892
B82: 主材 | C82: 管式阻性消声器 | D82: 个 | E82: 0.2 | G82: 850 | H82: 170 | M82: 170
B83: 080703 | C83: 低压法兰阀门 | H83: 594.98 | I83: 408.43 | J83: 44.78 | L83: 141.77 | M83: 6660 | O83: 4.957
A84: 1 | B84: C8-1420 | C84: 波纹补偿器 公称直径(125mm以内) | D84: 个 | E84: 1 | G84: 96.72 | H84: 96.72 | I84: 74.74 | J84: 10.24 | L84: 11.74 | M84: 1850 | O84: 0.907
B85: 主材 | C85: 波纹补偿器 | D85: 个 | E85: 1 | G85: 1850 | H85: 1850 | M85: 1850
A86: 2 | B86: C8-1422 | C86: 波纹补偿器 公称直径(200mm以内) | D86: 个 | E86: 1 | G86: 208.29 | H86: 208.29 | I86: 134.4 | J86: 15.18 | L86: 58.71 | M86: 2250 | O86: 1.631
B87: 主材 | C87: 波纹补偿器 | D87: 个 | E87: 1 | G87: 2250 | H87: 2250 | M87: 2250
A88: 3 | B88: C8-1423 | C88: 波纹补偿器 公称直径(250mm以内) | D88: 个 | E88: 1 | G88: 289.97 | H88: 289.97 | I88: 199.29 | J88: 19.36 | L88: 71.32 | M88: 2560 | O88: 2.419
B89: 主材 | C89: 波纹补偿器 | D89: 个 | E89: 1 | G89: 2560 | H89: 2560 | M89: 2560
B90: 090101 | C90: 水喷淋钢管安装 | H90: 148701.05 | I90: 103415.74 | J90: 14170.38 | L90: 31114.93 | M90: 170933.61 | O90: 1254.937
A91: 1 | B91: C9-1 | C91: 镀锌钢管(螺纹连接) 公称直径(25mm以内) | D91: 10m | E91: 24 | G91: 158.15 | H91: 3795.6 | I91: 3356.88 | J91: 332.4 | L91: 106.32 | M91: 4847.04 | O91: 40.728
B92: 主材 | C92: 镀锌钢管 | D92: m | E92: 244.8 | G92: 19.8 | H92: 4847.04 | M92: 4847.04
A93: 2 | B93: C9-1 | C93: 镀锌钢管(螺纹连接) 公称直径(20mm以内) | D93: 10m | E93: 260 | G93: 158.15 | H93: 41119 | I93: 36366.2 | J93: 3601 | L93: 1151.8 | M93: 39780 | O93: 441.22
B94: 主材 | C94: 镀锌钢管 | D94: m | E94: 2652 | G94: 15 | H94: 39780 | M94: 39780
A95: 3 | B95: C9-2 | C95: 镀锌钢管(螺纹连接) 公称直径(32mm以内) | D95: 10m | E95: 30 | G95: 168.46 | H95: 5053.8 | I95: 4340.1 | J95: 522.3 | L95: 191.4 | M95: 7650 | O95: 52.68
A96: 编制人: | F96: 审核人: | K96: 编制日期:
A98: 单位工程预结算书
A99: 工程名称：2601# 暖通工程 | K99: 第 5 页 共 6 页
A100: 序号 | B100: 定额编号 | C100: 子目名称 | D100: 工程量 | G100: 价值（元） | I100: 其中（元） | O100: 工日统计
D101: 单位 | E101: 数量 | G101: 单价 | H101: 合价 | I101: 人工合价 | J101: 材料合价 | L101: 机械合价 | M101: 主材合价 | N101: 设备合价
B102: 主材 | C102: 镀锌钢管 | D102: m | E102: 306 | G102: 25 | H102: 7650 | M102: 7650
A103: 4 | B103: C9-3 | C103: 镀锌钢管(螺纹连接) 公称直径(40mm以内) | D103: 10m | E103: 30 | G103: 205.99 | H103: 6179.7 | I103: 5011.5 | J103: 871.8 | L103: 296.4 | M103: 9486 | O103: 60.81
B104: 主材 | C104: 镀锌钢管 | D104: m | E104: 306 | G104: 31 | H104: 9486 | M104: 9486
A105: 5 | B105: C9-4 | C105: 镀锌钢管(螺纹连接) 公称直径(50mm以内) | D105: 10m | E105: 50 | G105: 208.48 | H105: 10424 | I105: 8592.5 | J105: 1402 | L105: 429.5 | M105: 20910 | O105: 104.3
...

Sheet 电费
A2: 单位工程费用汇总表
A3: 工程名称：2601# 电气工程 | E3: 第 1 页 共 1 页
A4: 序号 | B4: 费用名称 | D4: 取费基数 | F4: 费率 | G4: 费用金额
A5: 1 | B5: 安装工程 | D5: 安装工程 | G5: 2749590.7
A6: 一 | B6: 分部分项工程费（含5%零星工程） | D6: (人工费+材料费+未计价材料费+施工机具使用费)*1.05 | G6: 2495945.5
A7: 1 | B7: 人工费 | D7: 人工费 | G7: 263918.57
A8: 2 | B8: 材料费 | D8: 材料费 | G8: 64858.61
A9: 3 | B9: 未计价材料费 | D9: 主材费 | G9: 2015394.9
A10: 4 | B10: 施工机具使用费 | D10: 机械费 | G10: 32918.77
A11: 二 | B11: 措施项目费 | D11: 单价措施项目费+总价措施项目费 | G11: 28793.22
A12: 2.1 | B12: 单价措施项目费 | D12: 人工费+材料费+施工机具使用费
A13: 2.1.1 | B13: 人工费 | D13: 技术措施项目人工费
A14: 2.1.2 | B14: 材料费 | D14: 技术措施项目材料费
A15: 2.1.3 | B15: 施工机具使用费 | D15: 技术措施项目机械费
A16: 2.2 | B16: 总价措施项目费 | D16: 安全文明施工费+其它总价措施项目费 | G16: 28793.22
A17: 2.2.1 | B17: 安全文明施工费 | D17: 人工费+施工机具使用费+人工费+施工机具使用费 | F17: 9.05 | G17: 26863.78
A18: 2.2.2 | B18: 其它总价措施项目费 | D18: 人工费+施工机具使用费+人工费+施工机具使用费 | F18: 0.65 | G18: 1929.44
A19: 三 | B19: 总包服务费
A20: 四 | B20: 企业管理费 | D20: 人工费+施工机具使用费+人工费+施工机具使用费 | F20: 17.5 | G20: 51946.53
A21: 五 | B21: 利润 | D21: 人工费+施工机具使用费+人工费+施工机具使用费 | F21: 14.91 | G21: 44258.45
A22: 六 | B22: 规费 | D22: 人工费+施工机具使用费+人工费+施工机具使用费 | F22: 11.66 | G22: 34611.23
A23: 七 | B23: 索赔与现场签证
A24: 八 | B24: 不含税工程造价 | D24: 分部分项工程费（含5%零星工程）+措施项目费+总包服务费+企业管理费+利润+规费+索赔与现场签证 | G24: 2655554.9
A25: 九 | B25: 税前包干项目 | D25: 税前包干价
A26: 十 | B26: 税金 | D26: 不含税工程造价+税前包干价 | F26: 3.5411 | G26: 94035.85
A27: 十一 | B27: 税后包干项目 | D27: 税后包干价
A28: 十二 | B28: 设备费 | D28: 设备费
A29: 十三 | B29: 含税工程造价 | D29: 不含税工程造价+税金+税前包干项目+税后包干项目+设备费 | G29: 2749590.7
A31: 2 | B31: 工程造价 | D31: 专业造价总合计 | G31: 2749590.7
A37: 编制人: | C37: 审核人: | E37: 编制日期:

Sheet 电
A2: 单位工程预结算书
A3: 工程名称：2601# 电气工程 | K3: 第 1 页 共 7 页
A4: 序号 | B4: 定额编号 | C4: 子目名称 | D4: 工程量 | G4: 价值（元） | I4: 其中（元） | O4: 工日统计
D5: 单位 | E5: 数量 | G5: 单价 | H5: 合价 | I5: 人工合价 | J5: 材料合价 | L5: 机械合价 | M5: 主材合价 | N5: 设备合价
B6: 040102 | C6: 干式变压器安装 | H6: 2513.28 | I6: 1905 | J6: 293.32 | L6: 314.96 | O6: 21.22
A7: 1 | B7: C4-13 | C7: 干式变压器安装 容量(800kV·A以下) | D7: 台 | E7: 2 | G7: 1256.64 | H7: 2513.28 | I7: 1905 | J7: 293.32 | L7: 314.96 | O7: 21.22
B8: 040214 | C8: 高压成套配电柜安装 | H8: 3052.88 | I8: 2433.04 | J8: 207.12 | L8: 412.72 | O8: 27.108
A9: 1 | B9: C4-103 | C9: 高压开关柜 安装 | D9: 台 | E9: 4 | G9: 763.22 | H9: 3052.88 | I9: 2433.04 | J9: 207.12 | L9: 412.72 | O9: 27.108
B10: 040401 | C10: 控制、继电、模拟及配电屏安装 | H10: 4101.3 | I10: 2910.96 | J10: 486.36 | L10: 703.98 | O10: 34.02
A11: 1 | B11: C4-251 | C11: 抽屉式低压配电柜 | D11: 台 | E11: 9 | G11: 455.7 | H11: 4101.3 | I11: 2910.96 | J11: 486.36 | L11: 703.98 | O11: 34.02
B12: 040406 | C12: 成套配电箱安装 | H12: 19072.26 | I12: 15530.94 | J12: 2978.37 | L12: 562.95 | M12: 162000 | O12: 181.44
A13: 1 | B13: C4-277 | C13: 双电源投切箱 安装 | D13: 台 | E13: 25 | G13: 235.46 | H13: 5886.5 | I13: 4793.5 | J13: 919.25 | L13: 173.75 | M13: 50000 | O13: 56
B14: 主材 | C14: 双电源投切箱 | D14: 台 | E14: 25 | G14: 2000 | H14: 50000 | M14: 50000
A15: 2 | B15: C4-277 | C15: 动力配电柜 安装 | D15: 台 | E15: 33 | G15: 235.46 | H15: 7770.18 | I15: 6327.42 | J15: 1213.41 | L15: 229.35 | M15: 66000 | O15: 73.92
B16: 主材 | C16: 动力配电柜 | D16: 台 | E16: 33 | G16: 2000 | H16: 66000 | M16: 66000
A17: 3 | B17: C4-277 | C17: 照明配电箱 安装 | D17: 台 | E17: 13 | G17: 235.46 | H17: 3060.98 | I17: 2492.62 | J17: 478.01 | L17: 90.35 | M17: 26000 | O17: 29.12
B18: 主材 | C18: 照明配电箱 | D18: 台 | E18: 13 | G18: 2000 | H18: 26000 | M18: 26000
A19: 4 | B19: C4-277 | C19: 插座箱 安装 | D19: 台 | E19: 10 | G19: 235.46 | H19: 2354.6 | I19: 1917.4 | J19: 367.7 | L19: 69.5 | M19: 20000 | O19: 22.4
B20: 主材 | C20: 插座箱 | D20: 台 | E20: 10 | G20: 2000 | H20: 20000 | M20: 20000
B21: 040416 | C21: 端子箱 | H21: 1132.74 | I21: 855.12 | J21: 223.44 | L21: 54.18 | M21: 15000 | O21: 9.99
A22: 1 | B22: C4-371 | C22: 端子箱安装 户内 | D22: 台 | E22: 6 | G22: 188.79 | H22: 1132.74 | I22: 855.12 | J22: 223.44 | L22: 54.18 | M22: 15000 | O22: 9.99
B23: 主材 | C23: 接地端子箱 | D23: 台 | E23: 6 | G23: 2500 | H23: 15000 | M23: 15000
B24: 040418 | C24: 照明开关 | H24: 3693.25 | I24: 3407.85 | J24: 285.42 | M24: 49087.5 | O24: 39.811
A25: 1 | B25: C4-382 | C25: 扳式暗开关(单控) 单联 | D25: 10套 | E25: 6 | G25: 66.31 | H25: 397.86 | I25: 369.78 | J25: 28.08 | M25: 3672 | O25: 4.32
A26: 编制人: | F26: 审核人: | K26: 编制日期:
A28: 单位工程预结算书
A29: 工程名称：2601# 电气工程 | K29: 第 2 页 共 7 页
A30: 序号 | B30: 定额编号 | C30: 子目名称 | D30: 工程量 | G30: 价值（元） | I30: 其中（元） | O30: 工日统计
D31: 单位 | E31: 数量 | G31: 单价 | H31: 合价 | I31: 人工合价 | J31: 材料合价 | L31: 机械合价 | M31: 主材合价 | N31: 设备合价
B32: 主材 | C32: 暗装单联单控开关 | D32: 只 | E32: 61.2 | G32: 60 | H32: 3672 | M32: 3672
A33: 2 | B33: C4-382 | C33: 扳式暗开关(单控) 单联 | D33: 10套 | E33: 1 | G33: 66.31 | H33: 66.31 | I33: 61.63 | J33: 4.68 | M33: 612 | O33: 0.72
B34: 主材 | C34: 防水单联开关 | D34: 只 | E34: 10.2 | G34: 60 | H34: 612 | M34: 612
A35: 3 | B35: C4-383 | C35: 扳式暗开关(单控) 双联 | D35: 10套 | E35: 3.5 | G35: 71.12 | H35: 248.92 | I35: 226.49 | J35: 22.44 | M35: 3213 | O35: 2.646
B36: 主材 | C36: 暗装双联单控开关 | D36: 只 | E36: 35.7 | G36: 90 | H36: 3213 | M36: 3213
A37: 4 | B37: C4-383 | C37: 扳式暗开关(单控) 双联 | D37: 10套 | E37: 3.5 | G37: 71.12 | H37: 248.92 | I37: 226.49 | J37: 22.44 | M37: 3213 | O37: 2.646
B38: 主材 | C38: 防水双联开关 | D38: 只 | E38: 35.7 | G38: 90 | H38: 3213 | M38: 3213
A39: 5 | B39: C4-384 | C39: 扳式暗开关(单控) 三联 | D39: 10套 | E39: 12 | G39: 75.95 | H39: 911.4 | I39: 813.6 | J39: 97.8 | M39: 11016 | O39: 9.504
B40: 主材 | C40: 暗装三联单控开关 | D40: 只 | E40: 122.4 | G40: 90 | H40: 11016 | M40: 11016
A41: 6 | B41: C4-397 | C41: 声光控延时开关 | D41: 10套 | E41: 5.5 | G41: 77.44 | H41: 425.92 | I41: 400.18 | J41: 25.74 | M41: 5329.5 | O41: 4.675
B42: 主材 | C42: 声光控开关 | D42: 套 | E42: 56.1 | G42: 95 | H42: 5329.5 | M42: 5329.5
A43: 7 | B43: C4-397 | C43: 双控开关 安装 | D43: 10套 | E43: 18 | G43: 77.44 | H43: 1393.92 | I43: 1309.68 | J43: 84.24 | M43: 22032 | O43: 15.3
B44: 主材 | C44: 双控开关 | D44: 套 | E44: 183.6 | G44: 120 | H44: 22032 | M44: 22032
B45: 040419 | C45: 插座 | H45: 7293.99 | I45: 5161.54 | J45: 2132.45 | M45: 72522 | O45: 60.2718
A46: 1 | B46: C4-404 | C46: 空调控制面板 安装 | D46: 10套 | E46: 21.6 | G46: 112.91 | H46: 2438.86 | I46: 1725.84 | J46: 713.02 | M46: 33048 | O46: 20.1528
B47: 主材 | C47: 空调控制面板 | D47: 套 | E47: 220.32 | G47: 150 | H47: 33048 | M47: 33048
A48: 2 | B48: C4-404 | C48: 单相二、三极插座 安装 | D48: 10套 | E48: 41 | G48: 112.91 | H48: 4629.31 | I48: 3275.9 | J48: 1353.41 | M48: 37638 | O48: 38.253
B49: 主材 | C49: 单相二、三极插座 | D49: 套 | E49: 418.2 | G49: 90 | H49: 37638 | M49: 37638
A50: 3 | B50: C4-404 | C50: 密闭二、三极插座 安装 | D50: 10套 | E50: 2 | G50: 112.91 | H50: 225.82 | I50: 159.8 | J50: 66.02 | M50: 1836 | O50: 1.866
B51: 主材 | C51: 密闭二、三极插座 | D51: 套 | E51: 20.4 | G51: 90 | H51: 1836 | M51: 1836
B52: 040801 | C52: 电力电缆敷设 | H52: 91609.16 | I52: 53863.83 | J52: 29372.35 | L52: 8373 | M52: 783169.15 | O52: 710.908
A53: 编制人: | F53: 审核人: | K53: 编制日期:
A55: 单位工程预结算书
A56: 工程名称：2601# 电气工程 | K56: 第 3 页 共 7 页
A57: 序号 | B57: 定额编号 | C57: 子目名称 | D57: 工程量 | G57: 价值（元） | I57: 其中（元） | O57: 工日统计
D58: 单位 | E58: 数量 | G58: 单价 | H58: 合价 | I58: 人工合价 | J58: 材料合价 | L58: 机械合价 | M58: 主材合价 | N58: 设备合价
A59: 1 | B59: C4-724 | C59: 铜芯电力电缆敷设 竖直通道电缆沿支架敷设(截面35mm2以下) | D59: 100m | E59: 14 | G59: 2134.21 | H59: 29878.94 | I59: 17510.92 | J59: 11646.04 | L59: 721.98 | M59: 114534 | O59: 231.14
B60: 主材 | C60: 耐火电缆 | D60: m | E60: 1414 | G60: 81 | H60: 114534 | M60: 114534
A61: 2 | B61: C4-725 | C61: 铜芯电力电缆敷设 竖直通道电缆沿支架敷设(截面120mm2以下) | D61: 100m | E61: 2 | G61: 3368.28 | H61: 6736.56 | I61: 3901.04 | J61: 2377.74 | L61: 457.78 | M61: 52116 | O61: 51.48
B62: 主材 | C62: 电缆 | D62: m | E62: 202 | G62: 258 | H62: 52116 | M62: 52116
A63: 3 | B63: C4-726 | C63: 铜芯电力电缆敷设 竖直通道电缆沿支架敷设(截面240mm2以下) | D63: 100m | E63: 2.5 | G63: 4675.86 | H63: 11689.65 | I63: 6637.75 | J63: 3330.98 | L63: 1720.93 | M63: 221190 | O63: 87.6
B64: 主材 | C64: 耐火电缆 | D64: m | E64: 252.5 | G64: 876 | H64: 221190 | M64: 221190
A65: 4 | B65: C4-726 | C65: 铜芯电力电缆敷设 竖直通道电缆沿支架敷设(截面240mm2以下) | D65: 100m | E65: 3.2 | G65: 4675.86 | H65: 14962.75 | I65: 8496.32 | J65: 4263.65 | L65: 2202.78 | M65: 173558.4 | O65: 112.128
B66: 主材 | C66: 耐火电缆 | D66: m | E66: 323.2 | G66: 537 | H66: 173558.4 | M66: 173558.4
A67: 5 | B67: C4-726 | C67: 铜芯电力电缆敷设 竖直通道电缆沿支架敷设(截面240mm2以下) | D67: 100m | E67: 4 | G67: 4675.86 | H67: 18703.44 | I67: 10620.4 | J67: 5329.56 | L67: 2753.48 | M67: 183416 | O67: 140.16
B68: 主材 | C68: 电缆 | D68: m | E68: 404 | G68: 454 | H68: 183416 | M68: 183416
A69: 6 | B69: C4-726 | C69: 铜芯电力电缆敷设 竖直通道电缆沿支架敷设(截面240mm2以下) | D69: 100m | E69: 0.45 | G69: 4675.86 | H69: 2104.14 | I69: 1194.8 | J69: 599.58 | L69: 309.77 | M69: 16134.75 | O69: 15.768
B70: 主材 | C70: 电缆 | D70: m | E70: 45.45 | G70: 355 | H70: 16134.75 | M70: 16134.75
A71: 7 | B71: C4-728 | C71: 铜芯电力电缆敷设 竖直通道电缆沿桥架垂直敷设(截 | D71: 100m | E71: 4 | G71: 1883.42 | H71: 7533.68 | I71: 5502.6 | J71: 1824.8 | L71: 206.28 | M71: 22220 | O71: 72.632
A72: 编制人: | F72: 审核人: | K72: 编制日期:
A74: 单位工程预结算书
A75: 工程名称：2601# 电气工程 | K75: 第 4 页 共 7 页
A76: 序号 | B76: 定额编号 | C76: 子目名称 | D76: 工程量 | G76: 价值（元） | I76: 其中（元） | O76: 工日统计
D77: 单位 | E77: 数量 | G77: 单价 | H77: 合价 | I77: 人工合价 | J77: 材料合价 | L77: 机械合价 | M77: 主材合价 | N77: 设备合价
C78: 面35mm2以下)
B79: 主材 | C79: 电缆 | D79: m | E79: 404 | G79: 55 | H79: 22220 | M79: 22220
B80: 040901 | C80: 接地极 | H80: 69024.6 | I80: 47275 | J80: 4285.6 | L80: 17464 | M80: 17500 | O80: 550
A81: 1 | B81: C4-901 | C81: 热镀锌扁钢 安装 | D81: m | E81: 1200 | G81: 47.89 | H81: 57468 | I81: 38640 | J81: 3828 | L81: 15000 | M81: 12000 | O81: 448.8
B82: 主材 | C82: 热镀锌扁钢 | D82: m | E82: 1200 | G82: 10 | H82: 12000 | M82: 12000
A83: 2 | B83: C4-904 | C83: 圆钢接地极 坚土 | D83: m | E83: 220 | G83: 52.53 | H83: 11556.6 | I83: 8635 | J83: 457.6 | L83: 2464 | M83: 5500 | O83: 101.2
B84: 主材 | C84: 圆钢接地极 | D84: m | E84: 220 | G84: 25 | H84: 5500 | M84: 5500
B85: 041101 | C85: 配管 | H85: 80117.53 | I85: 69309.95 | J85: 7467.44 | L85: 3340.16 | M85: 155025.3 | O85: 852.0365
A86: 1 | B86: C4-1050 | C86: 钢管敷设 砖、混凝土结构暗配 钢管公称直径(15mm以内) | D86: 100m | E86: 100 | G86: 565.73 | H86: 56573 | I86: 49380 | J86: 4762 | L86: 2431 | M86: 97850 | O86: 607
B87: 主材 | C87: 钢管 | D87: m | E87: 10300 | G87: 9.5 | H87: 97850 | M87: 97850
A88: 2 | B88: C4-1051 | C88: 钢管敷设 砖、混凝土结构暗配 钢管公称直径(20mm以内) | D88: 100m | E88: 20 | G88: 606.24 | H88: 12124.8 | I88: 10540.8 | J88: 1097.8 | L88: 486.2 | M88: 27398 | O88: 129.6
B89: 主材 | C89: 钢管 | D89: m | E89: 2060 | G89: 13.3 | H89: 27398 | M89: 27398
A90: 3 | B90: C4-1054 | C90: 钢管敷设 砖、混凝土结构暗配 钢管公称直径(40mm以内) | D90: 100m | E90: 3 | G90: 1294.24 | H90: 3882.72 | I90: 3274.8 | J90: 458.88 | L90: 149.04 | M90: 8868.3 | O90: 40.26
B91: 主材 | C91: 钢管 | D91: m | E91: 309 | G91: 28.7 | H91: 8868.3 | M91: 8868.3
A92: 4 | B92: C4-1055 | C92: 钢管敷设 砖、混凝土结构暗配 钢管公称直径(50mm以内) | D92: 100m | E92: 3 | G92: 1413.84 | H92: 4241.52 | I92: 3491.64 | J92: 600.84 | L92: 149.04 | M92: 11371.2 | O92: 42.93
B93: 主材 | C93: 钢管 | D93: m | E93: 309 | G93: 36.8 | H93: 11371.2 | M93: 11371.2
A94: 编制人: | F94: 审核人: | K94: 编制日期:
A96: 单位工程预结算书
A97: 工程名称：2601# 电气工程 | K97: 第 5 页 共 7 页
A98: 序号 | B98: 定额编号 | C98: 子目名称 | D98: 工程量 | G98: 价值（元） | I98: 其中（元） | O98: 工日统计
D99: 单位 | E99: 数量 | G99: 单价 | H99: 合价 | I99: 人工合价 | J99: 材料合价 | L99: 机械合价 | M99: 主材合价 | N99: 设备合价
A100: 5 | B100: C4-1058 | C100: 钢管敷设 砖、混凝土结构暗配 钢管公称直径(100mm以内) | D100: 100m | E100: 0.5 | G100: 2938.8 | H100: 1469.4 | I100: 1153.83 | J100: 279.54 | L100: 36.04 | M100: 4362.05 | O100: 14.1865
B101: 主材 | C101: 钢管 | D101: m | E101: 51.5 | G101: 84.7 | H101: 4362.05 | M101: 4362.05
A102: 6 | B102: C4-1059 | C102: 钢管敷设 砖、混凝土结构暗配 钢管公称直径(125mm以内) | D102: 100m | E102: 0.5 | G102: 3652.18 | H102: 1826.09 | I102: 1468.88 | J102: 268.38 | L102: 88.84 | M102: 5175.75 | O102: 18.06
B103: 主材 | C103: 钢管 | D103: m | E103: 51.5 | G103: 100.5 | H103: 5175.75 | M103: 5175.75
B104: 041102 | C104: 线槽 | H104: 32917.24 | I104: 28191.76 | J104: 3032.66 | L104: 1692.82 | M104: 143994 | O104: 346.62
A105: 1 | B105: C4-1232 | C105: 金属线槽安装 宽+高(600mm以内) | D105: 10m | E105: 90 | G105: 310.54 | H105: 27948.6 | I105: 23936.4 | J105: 2574.9 | L105: 1437.3 | M105: 116802 | O105: 294.3
...

Sheet 外电费
A2: 单位工程费用汇总表
A3: 工程名称：室外电气工程 | E3: 第 1 页 共 1 页
A4: 序号 | B4: 费用名称 | D4: 取费基数 | F4: 费率 | G4: 费用金额
A5: 1 | B5: 安装工程 | D5: 安装工程 | G5: 290119.47
A6: 一 | B6: 分部分项工程费（含5%零星工程） | D6: (人工费+材料费+未计价材料费+施工机具使用费)*1.05 | G6: 279212.84
A7: 1 | B7: 人工费 | D7: 人工费 | G7: 1690.79
A8: 2 | B8: 材料费 | D8: 材料费 | G8: 220756.91
A9: 3 | B9: 未计价材料费 | D9: 主材费 | G9: 43329
A10: 4 | B10: 施工机具使用费 | D10: 机械费 | G10: 140.29
A11: 二 | B11: 措施项目费 | D11: 单价措施项目费+总价措施项目费 | G11: 177.61
A12: 2.1 | B12: 单价措施项目费 | D12: 人工费+材料费+施工机具使用费
A13: 2.1.1 | B13: 人工费 | D13: 技术措施项目人工费
A14: 2.1.2 | B14: 材料费 | D14: 技术措施项目材料费
A15: 2.1.3 | B15: 施工机具使用费 | D15: 技术措施项目机械费
A16: 2.2 | B16: 总价措施项目费 | D16: 安全文明施工费+其它总价措施项目费 | G16: 177.61
A17: 2.2.1 | B17: 安全文明施工费 | D17: 人工费+施工机具使用费+人工费+施工机具使用费 | F17: 9.05 | G17: 165.71
A18: 2.2.2 | B18: 其它总价措施项目费 | D18: 人工费+施工机具使用费+人工费+施工机具使用费 | F18: 0.65 | G18: 11.9
A19: 三 | B19: 总包服务费
A20: 四 | B20: 企业管理费 | D20: 人工费+施工机具使用费+人工费+施工机具使用费 | F20: 17.5 | G20: 320.44
A21: 五 | B21: 利润 | D21: 人工费+施工机具使用费+人工费+施工机具使用费 | F21: 14.91 | G21: 273.01
A22: 六 | B22: 规费 | D22: 人工费+施工机具使用费+人工费+施工机具使用费 | F22: 11.66 | G22: 213.5
A23: 七 | B23: 索赔与现场签证
A24: 八 | B24: 不含税工程造价 | D24: 分部分项工程费（含5%零星工程）+措施项目费+总包服务费+企业管理费+利润+规费+索赔与现场签证 | G24: 280197.4
A25: 九 | B25: 税前包干项目 | D25: 税前包干价
A26: 十 | B26: 税金 | D26: 不含税工程造价+税前包干价 | F26: 3.5411 | G26: 9922.07
A27: 十一 | B27: 税后包干项目 | D27: 税后包干价
A28: 十二 | B28: 设备费 | D28: 设备费
A29: 十三 | B29: 含税工程造价 | D29: 不含税工程造价+税金+税前包干项目+税后包干项目+设备费 | G29: 290119.47
A31: 2 | B31: 工程造价 | D31: 专业造价总合计 | G31: 290119.47
A37: 编制人: | C37: 审核人: | E37: 编制日期:

Sheet 外电
A2: 单位工程预结算书
A3: 工程名称：室外电气工程 | K3: 第 1 页 共 1 页
A4: 序号 | B4: 定额编号 | C4: 子目名称 | D4: 工程量 | G4: 价值（元） | I4: 其中（元） | O4: 工日统计
D5: 单位 | E5: 数量 | G5: 单价 | H5: 合价 | I5: 人工合价 | J5: 材料合价 | L5: 机械合价 | M5: 主材合价 | N5: 设备合价
B6: 040801 | C6: 电力电缆敷设 | H6: 2587.99 | I6: 1690.79 | J6: 756.91 | L6: 140.29 | M6: 43329 | O6: 22.308
A7: 1 | B7: C4-721 | C7: 铜芯电力电缆敷设 电缆(截面120mm2以下) | D7: 100m | E7: 2.2 | G7: 1176.36 | H7: 2587.99 | I7: 1690.79 | J7: 756.91 | L7: 140.29 | M7: 43329 | O7: 22.308
B8: 主材 | C8: 电缆 | D8: m | E8: 222.2 | G8: 195 | H8: 43329 | M8: 43329
C9: 补充分部 | H9: 220000 | J9: 220000
A10: 1 | B10: 补子目001 | C10: 电缆沟 | D10: m | E10: 220 | G10: 1000 | H10: 220000 | J10: 220000
A25: 合计 | H25: 265916.99 | I25: 1690.79 | J25: 220756.91 | L25: 140.29 | M25: 43329 | O25: 22.308
A26: 编制人: | F26: 审核人: | K26: 编制日期:

Sheet 外水费
A2: 单位工程费用汇总表
A3: 工程名称：室外给排水工程 | E3: 第 1 页 共 1 页
A4: 序号 | B4: 费用名称 | D4: 取费基数 | F4: 费率 | G4: 费用金额
A5: 1 | B5: 安装工程 | D5: 安装工程 | G5: 354543.05
A6: 一 | B6: 分部分项工程费（含5%零星工程） | D6: (人工费+材料费+未计价材料费+施工机具使用费)*1.05 | G6: 334516.14
A7: 1 | B7: 人工费 | D7: 人工费 | G7: 14286.36
A8: 2 | B8: 材料费 | D8: 材料费 | G8: 146588.69
A9: 3 | B9: 未计价材料费 | D9: 主材费 | G9: 157303
A10: 4 | B10: 施工机具使用费 | D10: 机械费 | G10: 408.75
A11: 二 | B11: 措施项目费 | D11: 单价措施项目费+总价措施项目费 | G11: 1425.43
A12: 2.1 | B12: 单价措施项目费 | D12: 人工费+材料费+施工机具使用费
A13: 2.1.1 | B13: 人工费 | D13: 技术措施项目人工费
A14: 2.1.2 | B14: 材料费 | D14: 技术措施项目材料费
A15: 2.1.3 | B15: 施工机具使用费 | D15: 技术措施项目机械费
A16: 2.2 | B16: 总价措施项目费 | D16: 安全文明施工费+其它总价措施项目费 | G16: 1425.43
A17: 2.2.1 | B17: 安全文明施工费 | D17: 人工费+施工机具使用费+人工费+施工机具使用费 | F17: 9.05 | G17: 1329.91
A18: 2.2.2 | B18: 其它总价措施项目费 | D18: 人工费+施工机具使用费+人工费+施工机具使用费 | F18: 0.65 | G18: 95.52
A19: 三 | B19: 总包服务费
A20: 四 | B20: 企业管理费 | D20: 人工费+施工机具使用费+人工费+施工机具使用费 | F20: 17.5 | G20: 2571.64
A21: 五 | B21: 利润 | D21: 人工费+施工机具使用费+人工费+施工机具使用费 | F21: 14.91 | G21: 2191.04
A22: 六 | B22: 规费 | D22: 人工费+施工机具使用费+人工费+施工机具使用费 | F22: 11.66 | G22: 1713.45
A23: 七 | B23: 索赔与现场签证
A24: 八 | B24: 不含税工程造价 | D24: 分部分项工程费（含5%零星工程）+措施项目费+总包服务费+企业管理费+利润+规费+索赔与现场签证 | G24: 342417.7
A25: 九 | B25: 税前包干项目 | D25: 税前包干价
A26: 十 | B26: 税金 | D26: 不含税工程造价+税前包干价 | F26: 3.5411 | G26: 12125.35
A27: 十一 | B27: 税后包干项目 | D27: 税后包干价
A28: 十二 | B28: 设备费 | D28: 设备费
A29: 十三 | B29: 含税工程造价 | D29: 不含税工程造价+税金+税前包干项目+税后包干项目+设备费 | G29: 354543.05
A31: 2 | B31: 工程造价 | D31: 专业造价总合计 | G31: 354543.05
A37: 编制人: | C37: 审核人: | E37: 编制日期:

Sheet 外水
A2: 单位工程预结算书
A3: 工程名称：室外给排水工程 | K3: 第 1 页 共 2 页
A4: 序号 | B4: 定额编号 | C4: 子目名称 | D4: 工程量 | G4: 价值（元） | I4: 其中（元） | O4: 工日统计
D5: 单位 | E5: 数量 | G5: 单价 | H5: 合价 | I5: 人工合价 | J5: 材料合价 | L5: 机械合价 | M5: 主材合价 | N5: 设备合价
B6: 090110 | C6: 室外消火栓安装 | H6: 250.05 | I6: 239.79 | J6: 10.26 | M6: 9000 | O6: 2.91
A7: 1 | B7: C9-93 | C7: 室外地上式消火栓 1.0MPa 深100型 | D7: 套 | E7: 3 | G7: 83.35 | H7: 250.05 | I7: 239.79 | J7: 10.26 | M7: 9000 | O7: 2.91
B8: 主材 | C8: 地上式消火栓 | D8: 套 | E8: 3 | G8: 3000 | H8: 9000 | M8: 9000
B9: 100101 | C9: 室外管道安装 | H9: 15433.75 | I9: 14046.57 | J9: 978.43 | L9: 408.75 | M9: 148303 | O9: 170.463
A10: 1 | B10: C10-19 | C10: 室外管道安装 钢管(焊接) 公称直径(150mm以内) | D10: 10m | E10: 15 | G10: 164.55 | H10: 2468.25 | I10: 1705.65 | J10: 365.55 | L10: 397.05 | M10: 16686.6 | O10: 20.7
B11: 主材 | C11: 热镀锌钢管 | D11: m | E11: 152.25 | G11: 109.6 | H11: 16686.6 | M11: 16686.6
A12: 2 | B12: C10-50 | C12: 室外管道安装 承插铸铁给水管(膨胀水泥接口) 公称直径(150mm以内) | D12: 10m | E12: 5 | G12: 154.86 | H12: 774.3 | I12: 686.9 | J12: 75.7 | L12: 11.7 | M12: 6000 | O12: 8.335
B13: 主材 | C13: 承插铸铁管 | D13: m | E13: 50 | G13: 120 | H13: 6000 | M13: 6000
A14: 3 | B14: C10-137 | C14: 室外管道安装 塑料排水管(粘接) 公称直径(300mm以内) | D14: 10m | E14: 12 | G14: 266.33 | H14: 3195.96 | I14: 3059.64 | J14: 136.32 | M14: 13885.2 | O14: 37.128
B15: 主材 | C15: 双壁波纹排水管 | D15: m | E15: 121.8 | G15: 114 | H15: 13885.2 | M15: 13885.2
A16: 4 | B16: C10-137 | C16: 室外管道安装 塑料排水管(粘接) 公称直径(300mm以内) | D16: 10m | E16: 16 | G16: 266.33 | H16: 4261.28 | I16: 4079.52 | J16: 181.76 | M16: 41574.4 | O16: 49.504
B17: 主材 | C17: HDPE排水管 | D17: m | E17: 162.4 | G17: 256 | H17: 41574.4 | M17: 41574.4
A18: 5 | B18: C10-138 | C18: 室外管道安装 塑料排水管(粘接) 公称直径(400mm以内) | D18: 10m | E18: 6 | G18: 338.14 | H18: 2028.84 | I18: 1934.94 | J18: 93.9 | M18: 23385.6 | O18: 23.484
B19: 主材 | C19: HDPE排水管 | D19: m | E19: 60.9 | G19: 384 | H19: 23385.6 | M19: 23385.6
A20: 编制人: | F20: 审核人: | K20: 编制日期:
A22: 单位工程预结算书
A23: 工程名称：室外给排水工程 | K23: 第 2 页 共 2 页
A24: 序号 | B24: 定额编号 | C24: 子目名称 | D24: 工程量 | G24: 价值（元） | I24: 其中（元） | O24: 工日统计
D25: 单位 | E25: 数量 | G25: 单价 | H25: 合价 | I25: 人工合价 | J25: 材料合价 | L25: 机械合价 | M25: 主材合价 | N25: 设备合价
A26: 6 | B26: C10-138 | C26: 室外管道安装 塑料排水管(粘接) 公称直径(400mm以内) | D26: 10m | E26: 8 | G26: 338.14 | H26: 2705.12 | I26: 2579.92 | J26: 125.2 | M26: 46771.2 | O26: 31.312
B27: 主材 | C27: HDPE排水管 | D27: m | E27: 81.2 | G27: 576 | H27: 46771.2 | M27: 46771.2
C28: 补充分部 | H28: 145600 | J28: 145600
A29: 1 | B29: 补子目001 | C29: 给水阀门井 φ1000 | D29: 座 | E29: 2 | G29: 3500 | H29: 7000 | J29: 7000
A30: 2 | B30: 补子目001 | C30: 污水检查井 φ700 | D30: 座 | E30: 8 | G30: 1200 | H30: 9600 | J30: 9600
A31: 3 | B31: 补子目001 | C31: 雨水检查井 φ700 | D31: 座 | E31: 15 | G31: 1200 | H31: 18000 | J31: 18000
A32: 4 | B32: 补子目001 | C32: 化粪池 | D32: 座 | E32: 1 | G32: 12000 | H32: 12000 | J32: 12000
A33: 5 | B33: 补子目001 | C33: 单篦雨水口 | D33: 座 | E33: 30 | G33: 200 | H33: 6000 | J33: 6000
A34: 6 | B34: 补子目002 | C34: 管道土方 | D34: m | E34: 620 | G34: 150 | H34: 93000 | J34: 93000
A45: 合计 | H45: 318586.8 | I45: 14286.36 | J45: 146588.69 | L45: 408.75 | M45: 157303 | O45: 173.373
A46: 编制人: | F46: 审核人: | K46: 编制日期:
