Workbook

Sheet 总概算表
A1: 表15.2-1
A2: 总概算表
A3: 项目名称：双柳基地专用设备制造车间建设项目
A4: 序号 | B4: 工程项目或费用名称 | D4: 建筑面积或工程量 | G4: 投资概算（万元、万美元） | M4: 备注
D5: 新建 | E5: 改造 | F5: 单位 | G5: 建筑工程费 | H5: 工艺设备购置费 | I5: 工艺设备安装费 | J5: 其他费用 | K5: 合计 | L5: 含外汇
B6: 合计 | D6: =D7+D18+D30+D32 -> 42843.6 | G6: =G7+G18+G30+G32 -> 11588.681 | H6: =H7+H18+H30+H32 -> 2660 | I6: =I7+I18+I30+I32 -> 266 | J6: =J7+J18+J30+J32 -> 1715.3407 | K6: =K7+K18+K30+K32 -> 16230.022 | N6: 16230 | O6: =K6-N6 -> 0.021764434
A7: 一 | B7: 工程费用 | D7: =D8+D12 -> 42843.6 | G7: =G8+G12 -> 11588.681 | H7: =H8+H12 -> 2660 | I7: =I8+I12 -> 266 | J7: =J8+J12 -> 0 | K7: =K8+K12 -> 14514.681 | O7: =16230-N6 -> 0
A8: （一） | B8: 室内工程 | D8: =SUM(D9) -> 42843.6 | F8: m2 | G8: =SUM(G9) -> 11199.88 | H8: =SUM(H9) -> 2660 | I8: =SUM(I9) -> 266 | J8: =SUM(J9) -> 0 | K8: =SUM(K9) -> 14125.88
A9: 1 | B9: 专用设备制造车间 | D9: =汇总表!C4 -> 42843.6 | F9: m2 | G9: =室内!H6 -> 11199.88 | H9: =设备取费!L7 -> 2660 | I9: =设备取费!O7 -> 266 | K9: =SUM(G9:J9) -> 14125.88 | N9: =K9/D9 -> 0.32970805
B10: 小计 | D10: =SUM(D9) -> 42843.6 | G10: =SUM(G9) -> 11199.88 | H10: =SUM(H9) -> 2660 | I10: =SUM(I9) -> 266 | K10: =SUM(K9) -> 14125.88
A12: （二） | B12: 室外工程 | G12: =SUM(G13:G16) -> 388.8014 | K12: =SUM(K13:K16) -> 388.8014
A13: 1 | B13: =室外!B8 -> 道路 | D13: （13000） | F13: m2 | G13: =室外!E8 -> 234 | K13: =SUM(G13:J13) -> 234
A14: 2 | B14: =室外!B9 -> 绿化 | D14: （2300） | F14: m2 | G14: =室外!E9 -> 18.4 | K14: =SUM(G14:J14) -> 18.4
A15: 3 | B15: 室外给排水管网 | G15: =室外!H7 -> 67.799589 | K15: =SUM(G15:J15) -> 67.799589
A16: 4 | B16: 室外电力管网 | G16: =室外!H10 -> 68.601815 | K16: =SUM(G16:J16) -> 68.601815
A18: 二 | B18: 工程建设其他费用 | J18: =SUM(J19:J28) -> 1088.8014 | K18: =SUM(K19:K28) -> 1088.8014
A19: 1 | B19: 建设单位管理费 | J19: =113+(N6-10000)*0.8% -> 162.84 | K19: =J19 -> 162.84
A20: 2 | B20: 前期工作费 | J20: =60+(N6-10000)*(139-60)/40000 -> 72.30425 | K20: =J20 -> 72.30425
A21: 3 | B21: 建设工程监理费 | J21: =218.6+(N21-10000)*(393.4-218.6)/10000 -> 251.01982 | K21: =J21 -> 251.01982 | N21: =G7+I7 -> 11854.681
A22: 4 | B22: 工程设计费 | J22: =(304.8+(K7-10000)*262/10000)*0.35*1.15*1.25+(304.8+(N21-10000)*262/10000)*0.65 -> 442.56968 | K22: =J22 -> 442.56968
A23: 5 | B23: 施工图审查费 | J23: =J22*5% -> 22.128484 | K23: =J23 -> 22.128484
A24: 6 | B24: 地勘费 | J24: =D6*15/10000 -> 64.2654 | K24: =J24 -> 64.2654
A25: 7 | B25: 招标代理费 | J25: =1.5+4.4+4+(O25-1000)*0.5%+1+2.8+2.75+14+10+(N25-10000)*0.05% -> 48.002341 | K25: =J25 -> 48.002341 | N25: =N21 -> 11854.681 | O25: =工艺设备!L24 -> 2325
A26: 8 | B26: 环境影响咨询费 | J26: =7.5+(N6-3000)*10.5/17000 -> 15.671471 | K26: =J26 -> 15.671471
A27: 9 | B27: 职业卫生评价费 | J27: 5 | K27: =J27 -> 5
A28: 10 | B28: 劳动安全评价费 | J28: 5 | K28: =J28 -> 5
N29: =J30/#REF! -> #REF!
A30: 三 | B30: 基本预备费 | J30: =(J18+K7)*4%+2.4 -> 626.5393 | K30: =J30 -> 626.5393
A32: 四 | B32: 建设期利息
A38: 序号 | B38: 工程费名称 | C38: 投资额 (万元) | D38: 占投资数（%） | F38: 其中外汇（万美元）
A39: 1 | B39: 建筑工程费 | C39: =G6 -> 11588.681 | D39: =C39/16230 -> 0.71402841
A40: 2 | B40: 设备工程费 | C40: =H6 -> 2660 | D40: =C40/16230 -> 0.16389402
A41: 3 | B41: 安装工程费 | C41: =I6 -> 266 | D41: =C41/16230 -> 0.016389402
A42: 4 | B42: 其他费用 | C42: =J18 -> 1088.8014 | D42: =C42/16230 -> 0.067085733
A43: 5 | B43: 基本预备费 | C43: =K30 -> 626.5393 | D43: =C43/16230 -> 0.038603777
B44: 合 计 | C44: =SUM(C39:C43) -> 16230.022 | D44: =SUM(D39:D43) -> 1.0000013

Sheet 汇总表
A1: 单位工程概算汇总表
A2: =总概算表!A3 -> 项目名称：双柳基地专用设备制造车间建设项目
A3: 序号 | B3: 名称 | C3: 概算（万元） | D3: 公用设备（万元） | E3: 单方造价（元/m2） | F3: 单方造价含设备（元/m2）
B4: 建筑面积（m2) | C4: 42843.6
A5: 1 | B5: 建筑工程 | C5: =土费!G96/10000 -> 9464.2851 | E5: =C5/C4*10000 -> 2209.0312 | F5: =C5/C4*10000 -> 2209.0312
A6: 2 | B6: 给排水工程 | C6: =水费!G31/10000+水设!H58 -> 180.63774 | D6: =水设!G58 -> 2.8 | E6: =C6/C4*10000 -> 42.162129 | F6: =(C6+D6)/C4*10000 -> 42.815668
A7: 3 | B7: 暖通工程 | C7: =暖费!G31/10000+暖设!I75 -> 35.972462 | D7: =暖设!H75 -> 338.005 | E7: =C7/C4*10000 -> 8.3962277 | F7: =(C7+D7)/C4*10000 -> 87.288991
A8: 4 | B8: 电气工程 | C8: =电费!G31/10000+电设!I58 -> 452.63209 | D8: =电设!H58 -> 575.3 | E8: =C8/C4*10000 -> 105.64754 | F8: =(C8+D8)/C4*10000 -> 239.92664
A9: 5 | B9: 动力工程 | C9: =动费!G31/10000+动设!H58 -> 66.681205 | D9: =动设!G58 -> 83.566 | E9: =C9/C4*10000 -> 15.563866 | F9: =(C9+D9)/C4*10000 -> 35.068763
B10: 小计 | C10: =SUM(C5:C9) -> 10200.209 | D10: =SUM(D5:D9) -> 999.671 | E10: =SUM(E5:E9) -> 2380.801 | F10: =SUM(F5:F9) -> 2614.1313

Sheet 室内
A1: 表15.2-2
A2: 室内工程概算表
A3: =总概算表!A3 -> 项目名称：双柳基地专用设备制造车间建设项目
A4: 序号 | B4: 工程名称 | C4: 建筑面积 （平方米） | E4: 建筑工程费（万元） | I4: 工艺设备购置费（万元） | J4: 工艺设备安装费（万元） | K4: 合计 （万元） | L4: 备注
C5: 新建 | D5: 改造 | E5: 土建及专业工程费 | F5: 建筑设备购置费 | G5: 建筑设备安装费 | H5: 小计
B6: 合计 | C6: =SUM(C7:C18) -> 42843.6 | E6: =SUM(E7:E18) -> 10100.242 | F6: =SUM(F7:F18) -> 999.671 | H6: =SUM(H7:H18) -> 11199.88 | I6: =SUM(I9:I11) -> 2660 | J6: =SUM(J9:J11) -> 266 | K6: =SUM(K7:K18) -> 14125.88
A7: 一 | B7: 建（构）筑物或单元/系统
A8: （一） | B8: 工艺设备
A9: 1 | B9: 国产新增设备 | I9: =设备取费!L7 -> 2660 | J9: =设备取费!O7 -> 266 | K9: =SUM(I9:J9) -> 2926
A10: 2 | B10: 进口新增设备
A11: 3 | B11: 改造设备
A12: 4 | B12: 工器具及生产家具
A13: （二） | B13: 建筑工程
A14: 1 | B14: 建筑 | C14: =汇总表!C4 -> 42843.6 | E14: =土费!G96/10000 -> 9464.2851 | H14: =SUM(E14:G14) -> 9464.2851 | K14: =SUM(H14,I14,J14) -> 9464.2851
A15: 2 | B15: 给排水 | E15: =水费!G31/10000 -> 180.35774 | F15: =水设!G58 -> 2.8 | G15: =水设!H58 -> 0.28 | H15: =SUM(E15:G15) -> 183.43774 | K15: =SUM(H15,I15,J15) -> 183.43774
A16: 3 | B16: 暖通 | E16: =暖费!G31/10000 -> 2.171962 | F16: =暖设!H75 -> 338.005 | G16: =暖设!I75 -> 33.8005 | H16: =SUM(E16:G16) -> 373.97746 | K16: =SUM(H16,I16,J16) -> 373.97746
A17: 4 | B17: 室内电 | E17: =电费!G31/10000 -> 395.10209 | F17: =电设!H58 -> 575.3 | G17: =电设!I58 -> 57.53 | H17: =SUM(E17:G17) -> 1027.9321 | K17: =SUM(H17,I17,J17) -> 1027.9321
A18: 5 | B18: 室内动力 | E18: =动费!G31/10000 -> 58.324605 | F18: =动设!G58 -> 83.566 | G18: =动设!H58 -> 8.3566 | H18: =SUM(E18:G18) -> 150.24721 | K18: =SUM(H18,I18,J18) -> 150.24721

Sheet 室外
A1: 表15.2-3
E2: 室外工程概算表
A3: =总概算表!A3 -> 项目名称：双柳基地专用设备制造车间建设项目
A4: 序号 | B4: 工程名称 | C4: 单位 | D4: 数量 | E4: 建筑工程费（万元） | I4: 指标 （元/单位） | J4: 备注
E5: 土建及专业工程费 | F5: 建筑设备购置费 | G5: 建筑设备安装费 | H5: 合计
B6: 合计 | E6: =SUM(E7:E10) -> 388.8014 | H6: =SUM(H7:H10) -> 388.8014
A7: 1 | B7: =总概算表!B15 -> 室外给排水管网 | E7: =室外水费!G31/10000 -> 67.799589 | H7: =SUM(E7:G7) -> 67.799589
A8: 2 | B8: 道路 | C8: m2 | D8: 13000 | E8: =I8*D8/10000 -> 234 | H8: =SUM(E8:G8) -> 234 | I8: 180
A9: 3 | B9: 绿化 | C9: m2 | D9: 2300 | E9: =I9*D9/10000 -> 18.4 | H9: =SUM(E9:G9) -> 18.4 | I9: 80
A10: 4 | B10: 室外电 | E10: =室外电费!G31/10000 -> 68.601815 | H10: =SUM(E10:G10) -> 68.601815

Sheet 厂外
A1: 表15.2-4
E2: 厂外工程概算表
A3: 项目名称：
A4: 序号 | B4: 工程名称 | C4: 单位 | D4: 数量 | E4: 建筑工程费（万元） | I4: 指标 （元/单位） | J4: 备注
E5: 土建及专业工程费 | F5: 建筑设备购置费 | G5: 建筑设备安装费 | H5: 合计
B6: 合计
A7: 1
A8: 2
A9: 3

Sheet 其他
A1: 表15.2-5
A2: 其他费用概算表
A3: =总概算表!A3 -> 项目名称：双柳基地专用设备制造车间建设项目
A4: 序号 | B4: 费用名称 | C4: 收费依据 | D4: 指标 | E4: 计算基数 | F4: 投资 （万元） | G4: 备注
B5: 合计 | F5: =SUM(F7:F16,F19) -> 1715.3407
A6: 一 | B6: 工程建设其他费用 | F6: =SUM(F7:F16) -> 1088.8014
A7: 1 | B7: =总概算表!B19 -> 建设单位管理费 | C7: 财建[2002]394号 | F7: =总概算表!K19 -> 162.84
A8: 2 | B8: =总概算表!B20 -> 前期工作费 | C8: 计价格[1999]1283号文 | D8: 插入法 | E8: =总概算表!N6 -> 16230 | F8: =总概算表!K20 -> 72.30425
A9: 3 | B9: =总概算表!B21 -> 建设工程监理费 | C9: 发改价格[2007]670号 | E9: =总概算表!#REF! -> #REF! | F9: =总概算表!K21 -> 251.01982
A10: 4 | B10: =总概算表!B22 -> 工程设计费 | C10: 计价格[2002]10号 | D10: 插入法 | E10: =E9 -> #REF! | F10: =总概算表!K22 -> 442.56968
A11: 5 | B11: =总概算表!B23 -> 施工图审查费 | C11: 发改价格[2011]534号文 | D11: 0.05 | E11: =F10 -> 442.56968 | F11: =总概算表!K23 -> 22.128484
A12: 6 | B12: =总概算表!B24 -> 地勘费 | D12: 15元/m2 | E12: =总概算表!#REF! -> #REF! | F12: =总概算表!K24 -> 64.2654
A13: 7 | B13: =总概算表!B25 -> 招标代理费 | F13: =总概算表!K25 -> 48.002341
A14: 8 | B14: =总概算表!B26 -> 环境影响咨询费 | C14: 计价格[2002]125号文 | D14: 插入法 | E14: =E8 -> 16230 | F14: =总概算表!K26 -> 15.671471
A15: 9 | B15: =总概算表!B27 -> 职业卫生评价费 | C15: 地方有关规定 | F15: =总概算表!K27 -> 5
A16: 10 | B16: =总概算表!B28 -> 劳动安全评价费 | C16: 地方有关规定 | F16: =总概算表!K28 -> 5
A18: 二 | B18: 预备费
A19: 1 | B19: 基本预备费 | D19: =F19/(总概算表!#REF!+总概算表!#REF!) -> #REF! | F19: =总概算表!K30 -> 626.5393
A21: 三 | B21: 建设期利息

Sheet 设备取费
A1: 表15.2-5
E2: 工艺设备购置费及安装费计算表
A3: 项目名称： | O3: 单位：万元、万美元
A4: 序号 | B4: 设备名称 | C4: 数量台/套 | D4: 设备购置费单价 | L4: 设备购置费合计 | N4: 设备安装费 | P4: 设备购置费及安装费合计
D5: 设备原价 | J5: 国内运杂费 | K5: 小计 | L5: 人民币合计 | M5: 含美元 | N5: 费率（%） | O5: 投资
D6: 人民币 | E6: 含美元CIF | F6: 关税 | G6: 增值税 | H6: 银行费公司费 | I6: 商检费
B7: 合计 | K7: =SUM(K15:K30) -> 1250 | L7: =SUM(L15:L30) -> 2660 | O7: =SUM(O15:O30) -> 266 | P7: =SUM(P15:P30) -> 2926
B8: 国产新增设备
B9: 进口新增设备
B10: 改造设备
B11: 工器具及生产家具
A12: 一 | B12: 建（构）筑物等
A13: （一） | B13: 新增设备
A14: =工艺设备!A6 -> 一 | B14: =工艺设备!B6 -> 钛合金产品制造区
A15: =工艺设备!A7 -> 1 | B15: =工艺设备!B7 -> 桥式起重机 | C15: =工艺设备!F7 -> 2 | D15: =工艺设备!G7 -> 75 | K15: =SUM(D15,F15:J15) -> 75 | L15: =K15*C15 -> 150 | N15: 0.1 | O15: =N15*L15 -> 15 | P15: =O15+L15 -> 165
A16: =工艺设备!A8 -> 2 | B16: =工艺设备!B8 -> 桥式起重机 | C16: =工艺设备!F8 -> 2 | D16: =工艺设备!G8 -> 35 | K16: =SUM(D16,F16:J16) -> 35 | L16: =K16*C16 -> 70 | N16: 0.1 | O16: =N16*L16 -> 7 | P16: =O16+L16 -> 77
A17: =工艺设备!A9 -> 3 | B17: =工艺设备!B9 -> 桥式起重机 | C17: =工艺设备!F9 -> 2 | D17: =工艺设备!G9 -> 20 | K17: =SUM(D17,F17:J17) -> 20 | L17: =K17*C17 -> 40 | N17: 0.1 | O17: =N17*L17 -> 4 | P17: =O17+L17 -> 44
A18: =工艺设备!A10 -> 二 | B18: =工艺设备!B10 -> 轻型设备制造区 | D18: =工艺设备!G10 -> 0
A19: =工艺设备!A11 -> 1 | B19: =工艺设备!B11 -> 桥式起重机 | C19: =工艺设备!F11 -> 2 | D19: =工艺设备!G11 -> 75 | K19: =SUM(D19,F19:J19) -> 75 | L19: =K19*C19 -> 150 | N19: 0.1 | O19: =N19*L19 -> 15 | P19: =O19+L19 -> 165
A20: =工艺设备!A12 -> 2 | B20: =工艺设备!B12 -> 桥式起重机 | C20: =工艺设备!F12 -> 2 | D20: =工艺设备!G12 -> 35 | K20: =SUM(D20,F20:J20) -> 35 | L20: =K20*C20 -> 70 | N20: 0.1 | O20: =N20*L20 -> 7 | P20: =O20+L20 -> 77
A21: =工艺设备!A13 -> 3 | B21: =工艺设备!B13 -> 桥式起重机 | C21: =工艺设备!F13 -> 2 | D21: =工艺设备!G13 -> 20 | K21: =SUM(D21,F21:J21) -> 20 | L21: =K21*C21 -> 40 | N21: 0.1 | O21: =N21*L21 -> 4 | P21: =O21+L21 -> 44
A22: =工艺设备!A14 -> 4 | B22: =工艺设备!B14 -> 低压电动平板车 | C22: =工艺设备!F14 -> 3 | D22: =工艺设备!G14 -> 15 | K22: =SUM(D22,F22:J22) -> 15 | L22: =K22*C22 -> 45 | N22: 0.1 | O22: =N22*L22 -> 4.5 | P22: =O22+L22 -> 49.5
A23: =工艺设备!A15 -> 三 | B23: =工艺设备!B15 -> 重型设备制造区 | D23: =工艺设备!G15 -> 0
A24: =工艺设备!A16 -> 1 | B24: =工艺设备!B16 -> 桥式起重机 | C24: =工艺设备!F16 -> 2 | D24: =工艺设备!G16 -> 420 | K24: =SUM(D24,F24:J24) -> 420 | L24: =K24*C24 -> 840 | N24: 0.1 | O24: =N24*L24 -> 84 | P24: =O24+L24 -> 924
A25: =工艺设备!A17 -> 2 | B25: =工艺设备!B17 -> 桥式起重机 | C25: =工艺设备!F17 -> 2 | D25: =工艺设备!G17 -> 200 | K25: =SUM(D25,F25:J25) -> 200 | L25: =K25*C25 -> 400 | N25: 0.1 | O25: =N25*L25 -> 40 | P25: =O25+L25 -> 440
A26: =工艺设备!A18 -> 3 | B26: =工艺设备!B18 -> 桥式起重机 | C26: =工艺设备!F18 -> 3 | D26: =工艺设备!G18 -> 100 | K26: =SUM(D26,F26:J26) -> 100 | L26: =K26*C26 -> 300 | N26: 0.1 | O26: =N26*L26 -> 30 | P26: =O26+L26 -> 330
A27: =工艺设备!A19 -> 4 | B27: =工艺设备!B19 -> 桥式起重机 | C27: =工艺设备!F19 -> 2 | D27: =工艺设备!G19 -> 100 | K27: =SUM(D27,F27:J27) -> 100 | L27: =K27*C27 -> 200 | N27: 0.1 | O27: =N27*L27 -> 20 | P27: =O27+L27 -> 220
A28: =工艺设备!A20 -> 5 | B28: =工艺设备!B20 -> 桥式起重机 | C28: =工艺设备!F20 -> 2 | D28: =工艺设备!G20 -> 75 | K28: =SUM(D28,F28:J28) -> 75 | L28: =K28*C28 -> 150 | N28: 0.1 | O28: =N28*L28 -> 15 | P28: =O28+L28 -> 165
A29: =工艺设备!A21 -> 6 | B29: =工艺设备!B21 -> 桥式起重机 | C29: =工艺设备!F21 -> 2 | D29: =工艺设备!G21 -> 35 | K29: =SUM(D29,F29:J29) -> 35 | L29: =K29*C29 -> 70 | N29: 0.1 | O29: =N29*L29 -> 7 | P29: =O29+L29 -> 77
A30: =工艺设备!A22 -> 7 | B30: =工艺设备!B22 -> 低压电动平板车 | C30: =工艺设备!F22 -> 3 | D30: =工艺设备!G22 -> 45 | K30: =SUM(D30,F30:J30) -> 45 | L30: =K30*C30 -> 135 | N30: 0.1 | O30: =N30*L30 -> 13.5 | P30: =O30+L30 -> 148.5

Sheet 工艺设备
A1: 附表2-2
A2: 新增（改造）主要工艺设备表
A4: 序号 | B4: 设备名称 | C4: 主要技术（性能）指标或规格要求 | D4: 国别 | E4: 单位 (台/套) | F4: 数量 | G4: 设备购置费(万元、万美元) | J4: 招标情况 | K4: 备注
G5: 单价 | H5: 合计 | I5: 含外汇
A6: 一 | B6: 钛合金产品制造区
A7: 1 | B7: 桥式起重机 | C7: Gn＝20t/5t，S=16.5m，H=12m，A5 | D7: 国产 | E7: 台 | F7: 2 | G7: 75 | H7: =G7*F7 -> 150 | L7: =H7 -> 150
A8: 2 | B8: 桥式起重机 | C8: Gn＝10t，S=16.5m，H=12m，A5 | D8: 国产 | E8: 台 | F8: 2 | G8: 35 | H8: =G8*F8 -> 70
A9: 3 | B9: 桥式起重机 | C9: Gn＝5t，S=16.5m，H=12m，A5 | D9: 国产 | E9: 台 | F9: 2 | G9: 20 | H9: =G9*F9 -> 40
A10: 二 | B10: 轻型设备制造区
A11: 1 | B11: 桥式起重机 | C11: Gn＝20t/5t，S=16.5m，H=12m，A5 | D11: 国产 | E11: 台 | F11: 2 | G11: 75 | H11: =G11*F11 -> 150 | L11: =H11 -> 150
A12: 2 | B12: 桥式起重机 | C12: Gn＝10t，S=16.5m，H=12m，A5 | D12: 国产 | E12: 台 | F12: 2 | G12: 35 | H12: =G12*F12 -> 70
A13: 3 | B13: 桥式起重机 | C13: Gn＝5t，S=16.5m，H=12m，A5 | D13: 国产 | E13: 台 | F13: 2 | G13: 20 | H13: =G13*F13 -> 40
A14: 4 | B14: 低压电动平板车 | C14: 20t | D14: 国产 | E14: 台 | F14: 3 | G14: 15 | H14: =F14*G14 -> 45
A15: 三 | B15: 重型设备制造区
A16: 1 | B16: 桥式起重机 | C16: Gn＝100t/20t，S=31m，H=25m | D16: 国产 | E16: 台 | F16: 2 | G16: 420 | H16: =G16*F16 -> 840 | L16: =H16 -> 840
A17: 2 | B17: 桥式起重机 | C17: Gn＝50t/10t，S=29.6m，H=18m | D17: 国产 | E17: 台 | F17: 2 | G17: 200 | H17: =G17*F17 -> 400 | L17: =H17 -> 400
A18: 3 | B18: 桥式起重机 | C18: Gn＝32t/5t，S=29.6m，H=18m | D18: 国产 | E18: 台 | F18: 3 | G18: 100 | H18: =G18*F18 -> 300 | L18: =H18 -> 300
A19: 4 | B19: 桥式起重机 | C19: Gn＝32t/5t，S=22.5m，H=12m，A5 | D19: 国产 | E19: 台 | F19: 2 | G19: 100 | H19: =G19*F19 -> 200 | L19: =H19 -> 200
A20: 5 | B20: 桥式起重机 | C20: Gn＝20t/5t，S=22.5m，H=12m，A5 | D20: 国产 | E20: 台 | F20: 2 | G20: 75 | H20: =G20*F20 -> 150 | L20: =H20 -> 150
A21: 6 | B21: 桥式起重机 | C21: Gn＝10t，S=22.5m，H=12m，A5 | D21: 国产 | E21: 台 | F21: 2 | G21: 35 | H21: =G21*F21 -> 70
A22: 7 | B22: 低压电动平板车 | C22: 50t | D22: 国产 | E22: 台 | F22: 3 | G22: 45 | H22: =G22*F22 -> 135 | L22: =H22 -> 135
B23: 合计 | F23: =SUM(F7:F22) -> 31 | H23: =SUM(H7:H22) -> 2660
L24: =SUM(L7:L23) -> 2325
F30: 1979

Sheet 土费
A1: 单位工程费用汇总表
A2: 工程名称：土建 | E2: 第 1 页 共 3 页
A3: 序号 | B3: 费用名称 | D3: 取费基数 | F3: 费率 | G3: 费用金额
A4: 1 | B4: 土石方工程 | D4: 土石方工程 | G4: 344064.09
A5: 一 | B5: 分部分项工程费 | D5: 人工费+材料费+未计价材料费+施工机具使用费 | F5: 103 | G5: 268206.35
A6: 1 | B6: 人工费 | D6: 人工费 | G6: 166272.05
A7: 2 | B7: 材料费 | D7: 材料费
A8: 3 | B8: 未计价材料费 | D8: 主材费
A9: 4 | B9: 施工机具使用费 | D9: 机械费 | G9: 94122.46
A10: 二 | B10: 措施项目费 | D10: 单价措施项目费+总价措施项目费 | G10: 15076.84
A11: 2.1 | B11: 单价措施项目费 | D11: 人工费+材料费+施工机具使用费
A12: 2.1.1 | B12: 人工费 | D12: 技术措施项目人工费
A13: 2.1.2 | B13: 材料费 | D13: 技术措施项目材料费
A14: 2.1.3 | B14: 施工机具使用费 | D14: 技术措施项目机械费
A15: 2.2 | B15: 总价措施项目费 | D15: 安全文明合计+其它总价措施项目费 | G15: 15076.84
A16: 2.2.1 | B16: 安全文明合计 | D16: 安全文明施工费+扬尘污染防治增加费 | G16: 13384.28
A17: 2.2.1.1 | B17: 安全文明施工费 | D17: 人工费+施工机具使用费+人工费+施工机具使用费 | F17: 3.46 | G17: 9009.65
A18: 2.2.1.2 | B18: 扬尘污染防治增加费 | D18: 人工费+施工机具使用费+人工费+施工机具使用费 | F18: 1.68 | G18: 4374.63
A19: 2.2.2 | B19: 其它总价措施项目费 | D19: 人工费+施工机具使用费+人工费+施工机具使用费 | F19: 0.65 | G19: 1692.56
A20: 三 | B20: 总包服务费
A21: 四 | B21: 企业管理费 | D21: 人工费+施工机具使用费+人工费+施工机具使用费 | F21: 7.6 | G21: 19789.98
A22: 五 | B22: 利润 | D22: 人工费+施工机具使用费+人工费+施工机具使用费 | F22: 4.96 | G22: 12915.57
A23: 六 | B23: 规费 | D23: 人工费+施工机具使用费+人工费+施工机具使用费 | F23: 6.11 | G23: 15910.1
A24: 七 | B24: 索赔与现场签证
A25: 八 | B25: 安全技术服务费 | D25: 分部分项工程费+措施项目费+总包服务费+企业管理费+利润+规费 | F25: 0.12 | G25: 398.28
A26: 九 | B26: 不含税工程造价 | D26: 分部分项工程费+措施项目费+总包服务费+企业管理费+利润+规费+索赔与现场签证+安全技术服务费 | G26: 332297.12
A27: 十 | B27: 税前包干项目 | D27: 税前包干价
A28: 十一 | B28: 税金 | D28: 不含税工程造价+税前包干价 | F28: 3.5411 | G28: 11766.97
A29: 十二 | B29: 税后包干项目 | D29: 税后包干价
A30: 十三 | B30: 含税工程造价 | D30: 不含税工程造价+税金+税前包干项目+税后包干项目 | G30: 344064.09
A32: 2 | B32: 建筑工程12层以下 | D32: 建筑工程12层以下 | G32: 81358631
A33: 一 | B33: 分部分项工程费 | D33: 人工费+材料费+未计价材料费+施工机具使用费 | F33: 103 | G33: 58226541
A34: 编制人: | C34: 审核人: | E34: 编制日期:
A35: 单位工程费用汇总表
A36: 工程名称：土建 | E36: 第 2 页 共 3 页
A37: 序号 | B37: 费用名称 | D37: 取费基数 | F37: 费率 | G37: 费用金额
A38: 1 | B38: 人工费 | D38: 人工费 | G38: 6860350.4
A39: 2 | B39: 材料费 | D39: 材料费 | G39: 46857002
A40: 3 | B40: 未计价材料费 | D40: 主材费
A41: 4 | B41: 施工机具使用费 | D41: 机械费 | G41: 2813269.9
A42: 二 | B42: 措施项目费 | D42: 单价措施项目费+总价措施项目费 | G42: 9725087.5
A43: 2.1 | B43: 单价措施项目费 | D43: 人工费+材料费+施工机具使用费 | G43: 7261743
A44: 2.1.1 | B44: 人工费 | D44: 技术措施项目人工费 | G44: 3188120.6
A45: 2.1.2 | B45: 材料费 | D45: 技术措施项目材料费 | G45: 1154808.8
A46: 2.1.3 | B46: 施工机具使用费 | D46: 技术措施项目机械费 | G46: 2918813.5
A47: 2.2 | B47: 总价措施项目费 | D47: 安全文明合计+其它总价措施项目费 | G47: 2463344.5
A48: 2.2.1 | B48: 安全文明合计 | D48: 安全文明施工费+扬尘污染防治增加费 | G48: 2360770.9
A49: 2.2.1.1 | B49: 安全文明施工费 | D49: 人工费+施工机具使用费+人工费+施工机具使用费 | F49: 13.28 | G49: 2095657.6
A50: 2.2.1.2 | B50: 扬尘污染防治增加费 | D50: 人工费+施工机具使用费+人工费+施工机具使用费 | F50: 1.68 | G50: 265113.31
A51: 2.2.2 | B51: 其它总价措施项目费 | D51: 人工费+施工机具使用费+人工费+施工机具使用费 | F51: 0.65 | G51: 102573.6
A52: 三 | B52: 总包服务费
A53: 四 | B53: 企业管理费 | D53: 人工费+施工机具使用费+人工费+施工机具使用费 | F53: 23.84 | G53: 3762084.2
A54: 五 | B54: 利润 | D54: 人工费+施工机具使用费+人工费+施工机具使用费 | F54: 18.17 | G54: 2867326.7
A55: 六 | B55: 规费 | D55: 人工费+施工机具使用费+人工费+施工机具使用费 | F55: 24.72 | G55: 3900953
A56: 七 | B56: 索赔与现场签证
A57: 八 | B57: 安全技术服务费 | D57: 分部分项工程费+措施项目费+总包服务费+企业管理费+利润+规费 | F57: 0.12 | G57: 94178.39
A58: 九 | B58: 不含税工程造价 | D58: 分部分项工程费+措施项目费+总包服务费+企业管理费+利润+规费+索赔与现场签证+安全技术服务费 | G58: 78576170
A59: 十 | B59: 税前包干项目 | D59: 税前包干价
A60: 十一 | B60: 税金 | D60: 不含税工程造价+税前包干价 | F60: 3.5411 | G60: 2782460.8
A61: 十二 | B61: 税后包干项目 | D61: 税后包干价
A62: 十三 | B62: 含税工程造价 | D62: 不含税工程造价+税金+税前包干项目+税后包干项目 | G62: 81358631
A64: 3 | B64: 装饰工程 | D64: 装饰工程 | G64: 12940156
A65: 一 | B65: 分部分项工程费 | D65: 人工费+材料费+未计价材料费+施工机具使用费 | F65: 103 | G65: 11556351
A66: 1 | B66: 人工费 | D66: 人工费 | G66: 1855348.1
A67: 2 | B67: 材料费 | D67: 材料费 | G67: 9270531.4
A68: 3 | B68: 未计价材料费 | D68: 主材费
A69: 编制人: | C69: 审核人: | E69: 编制日期:
A70: 单位工程费用汇总表
A71: 工程名称：土建 | E71: 第 3 页 共 3 页
A72: 序号 | B72: 费用名称 | D72: 取费基数 | F72: 费率 | G72: 费用金额
A73: 4 | B73: 施工机具使用费 | D73: 机械费 | G73: 93879.11
A74: 二 | B74: 措施项目费 | D74: 单价措施项目费+总价措施项目费 | G74: 142293.59
A75: 2.1 | B75: 单价措施项目费 | D75: 人工费+材料费+施工机具使用费
A76: 2.1.1 | B76: 人工费 | D76: 技术措施项目人工费
A77: 2.1.2 | B77: 材料费 | D77: 技术措施项目材料费
A78: 2.1.3 | B78: 施工机具使用费 | D78: 技术措施项目机械费
A79: 2.2 | B79: 总价措施项目费 | D79: 安全文明合计+其它总价措施项目费 | G79: 142293.59
A80: 2.2.1 | B80: 安全文明合计 | D80: 安全文明施工费+扬尘污染防治增加费 | G80: 129623.61
A81: 2.2.1.1 | B81: 安全文明施工费 | D81: 人工费+施工机具使用费+人工费+施工机具使用费 | F81: 5.81 | G81: 113250.1
A82: 2.2.1.2 | B82: 扬尘污染防治增加费 | D82: 人工费+施工机具使用费+人工费+施工机具使用费 | F82: 0.84 | G82: 16373.51
A83: 2.2.2 | B83: 其它总价措施项目费 | D83: 人工费+施工机具使用费+人工费+施工机具使用费 | F83: 0.65 | G83: 12669.98
A84: 三 | B84: 总包服务费
A85: 四 | B85: 企业管理费 | D85: 人工费+施工机具使用费+人工费+施工机具使用费 | F85: 13.47 | G85: 262560.9
A86: 五 | B86: 利润 | D86: 人工费+施工机具使用费+人工费+施工机具使用费 | F86: 15.8 | G86: 307977.9
A87: 六 | B87: 规费 | D87: 人工费+施工机具使用费+人工费+施工机具使用费 | F87: 10.95 | G87: 213440.38
A88: 七 | B88: 索赔与现场签证
A89: 八 | B89: 安全技术服务费 | D89: 分部分项工程费+措施项目费+总包服务费+企业管理费+利润+规费 | F89: 0.12 | G89: 14979.15
A90: 九 | B90: 不含税工程造价 | D90: 分部分项工程费+措施项目费+总包服务费+企业管理费+利润+规费+索赔与现场签证+安全技术服务费 | G90: 12497603
A91: 十 | B91: 税前包干项目 | D91: 税前包干价
A92: 十一 | B92: 税金 | D92: 不含税工程造价+税前包干价 | F92: 3.5411 | G92: 442552.63
A93: 十二 | B93: 税后包干项目 | D93: 税后包干价
A94: 十三 | B94: 含税工程造价 | D94: 不含税工程造价+税金+税前包干项目+税后包干项目 | G94: 12940156
A96: 4 | B96: 工程造价 | D96: 专业造价总合计 | G96: 94642851
A105: 编制人: | C105: 审核人: | E105: 编制日期:

Sheet 土措

Sheet 土
A1: 单位工程直接费表
A2: 工程名称：土建 | K2: 第 1 页 共 6 页
A3: 序号 | B3: 定额编号 | C3: 子目名称 | D3: 工程量 | G3: 价值（元） | I3: 其中（元） | O3: 工日统计
D4: 单位 | E4: 数量 | G4: 单价 | H4: 合价 | I4: 人工合价 | J4: 材料合价 | L4: 机械合价 | M4: 主材合价 | N4: 设备合价
C5: 土石方 | H5: 260394.51 | I5: 166272.05 | L5: 94122.46 | O5: 2771.2009
A6: 1 | B6: G1-85 | C6: 正铲挖掘机 装车 (斗容量0.6m3) 一、二类土 | D6: 1000m3 | E6: 10.452 | G6: 3321.92 | H6: 34720.71 | I6: 3762.72 | L6: 30957.99 | O6: 62.712
A7: 2 | B7: G1-227 | C7: 人工装、机动翻斗车运土 运距200m内 | D7: 100m3 | E7: 34.8427 | G7: 2188.39 | H7: 76249.42 | I7: 31504.77 | L7: 44744.65 | O7: 525.0795
A8: 3 | B8: G1-282 | C8: 填土夯实 平地 | D8: 100m3 | E8: 104.5274 | G8: 812.82 | H8: 84961.96 | I8: 66542.14 | L8: 18419.82 | O8: 1109.0357
A9: 4 | B9: G1-283 | C9: 平整场地 | D9: 100m2 | E9: 341.071 | G9: 189 | H9: 64462.42 | I9: 64462.42 | O9: 1074.3737
C10: 桩基 | H10: 10882833 | I10: 2793151.9 | J10: 6472830 | L10: 1616850.7 | O10: 33527.755
A11: 1 | B11: G3-159 | C11: 沉管灌注混凝土桩 锤击式 | D11: 10m3 | E11: 1580.186 | G11: 1673.77 | H11: 2644867.9 | I11: 1184886.7 | J11: 183712.42 | L11: 1276268.8 | O11: 14379.693
A12: 2 | B12: A2-443 | C12: 现浇构件圆钢筋(mm以内) φ12 | D12: t | E12: 2149.053 | G12: 3833.3 | H12: 8237964.7 | I12: 1608265.3 | J12: 6289117.5 | L12: 340581.91 | O12: 19148.062
C13: 混凝土 | H13: 5800214.5 | I13: 915314.92 | J13: 4772470.4 | L13: 112429.19 | O13: 11526.728
A14: 1 | B14: A2-74 | C14: 独立式桩承台 C20商品混凝土 | D14: 10m3 | E14: 298.06 | G14: 3769.58 | H14: 1123561 | I14: 120654.69 | J14: 1002906.3 | O14: 1621.4464
A15: 2 | B15: A2-443 | C15: 现浇构件圆钢筋(mm以内) φ12 | D15: t | E15: 119.224 | G15: 3833.3 | H15: 457021.36 | I15: 89222.47 | J15: 348904.27 | L15: 18894.62 | O15: 1062.2858
A16: 3 | B16: A2-80 | C16: 矩形柱 C20商品混凝土 | D16: 10m3 | E16: 36.98 | G16: 4136.26 | H16: 152958.89 | I16: 28063.38 | J16: 124895.51 | O16: 377.196
A17: 4 | B17: A2-443 | C17: 现浇构件圆钢筋(mm以内) φ12 | D17: t | E17: 61.3868 | G17: 3833.3 | H17: 235314.02 | I17: 45939.43 | J17: 179646.01 | L17: 9728.58 | O17: 546.9564
A18: 5 | B18: A2-85 | C18: 基础梁 C20商品混凝土 | D18: 10m3 | E18: 50.36 | G18: 3740.06 | H18: 188349.42 | I18: 17464.85 | J18: 170884.57 | O18: 234.6776
A19: 6 | B19: A2-443 | C19: 现浇构件圆钢筋(mm以内) φ12 | D19: t | E19: 59.9284 | G19: 3833.3 | H19: 229723.54 | I19: 44848.02 | J19: 175378.07 | L19: 9497.45 | O19: 533.962
A20: 编制人: | F20: 审核人: | K20: 编制日期:
A21: 单位工程直接费表
A22: 工程名称：土建 | K22: 第 2 页 共 6 页
A23: 序号 | B23: 定额编号 | C23: 子目名称 | D23: 工程量 | G23: 价值（元） | I23: 其中（元） | O23: 工日统计
D24: 单位 | E24: 数量 | G24: 单价 | H24: 合价 | I24: 人工合价 | J24: 材料合价 | L24: 机械合价 | M24: 主材合价 | N24: 设备合价
A25: 7 | B25: A2-86 | C25: 单梁、连续梁悬臂梁 C20商品混凝土 | D25: 10m3 | E25: 115.588 | G25: 3892.27 | H25: 449899.7 | I25: 58478.28 | J25: 391421.42 | O25: 785.9984
A26: 8 | B26: A2-443 | C26: 现浇构件圆钢筋(mm以内) φ12 | D26: t | E26: 165.29084 | G26: 3833.3 | H26: 633609.38 | I26: 123697.05 | J26: 483717.03 | L26: 26195.29 | O26: 1472.7414
A27: 9 | B27: A2-101 | C27: 有梁板 C20商品混凝土 | D27: 10m3 | E27: 85.36 | G27: 3835.85 | H27: 327428.16 | I27: 36264.34 | J27: 291163.81 | O27: 487.4056
A28: 10 | B28: A2-443 | C28: 现浇构件圆钢筋(mm以内) φ12 | D28: t | E28: 122.0648 | G28: 3833.3 | H28: 467911 | I28: 91348.41 | J28: 357217.75 | L28: 19344.83 | O28: 1087.5974
A29: 11 | B29: A2-113 | C29: 整体楼梯 C20商品混凝土 | D29: 10m2 | E29: 40.32 | G29: 1085.56 | H29: 43769.78 | I29: 11007.36 | J29: 32762.42 | O29: 147.9744
A30: 12 | B30: A2-443 | C30: 现浇构件圆钢筋(mm以内) φ12 | D30: t | E30: 48.384 | G30: 3833.3 | H30: 185470.39 | I30: 36208.65 | J30: 141593.84 | L30: 7667.9 | O30: 431.1014
A31: 13 | B31: A2-79 | C31: 设备基础 块体体积(m3) 5以外 C20商品混凝土 | D31: 10m3 | E31: 77.85 | G31: 3701.71 | H31: 288178.12 | I31: 26880.05 | J31: 261298.08 | O31: 361.224
A32: 14 | B32: A2-443 | C32: 现浇构件圆钢筋(mm以内) φ12 | D32: t | E32: 128.4525 | G32: 3833.3 | H32: 492396.97 | I32: 96128.71 | J32: 375911.1 | L32: 20357.15 | O32: 1144.5118
A33: 15 | B33: A2-75换 | C33: 基础垫层 C15商品混凝土 | D33: 10m3 | E33: 99.648 | G33: 3626.46 | H33: 361369.49 | I33: 42697.18 | J33: 318672.31 | O33: 573.9725
A34: 16 | B34: A13-10 | C34: 砾(碎)石垫层 干铺 | D34: 10m3 | E34: 99.648 | G34: 1638.3 | H34: 163253.32 | I34: 46412.05 | J34: 116097.89 | L34: 743.37 | O34: 657.6768
C35: 钢结构 | H35: 20727177 | I35: 1301872.4 | J35: 18348782 | L35: 1076523.2 | O35: 15997.282
A36: 1 | B36: A4-51 | C36: 钢屋架拼装 每榀构件重量(t) 10以外 履带吊 | D36: t | E36: 562.9 | G36: 346.82 | H36: 195224.98 | I36: 45527.35 | J36: 62498.79 | L36: 87198.84 | O36: 551.642
A37: 2 | B37: A4-3 | C37: 钢柱安装 每根构件重量(t以内) 4.0 履带吊 | D37: t | E37: 90.5 | G37: 8355.4 | H37: 756163.7 | I37: 51150.6 | J37: 696148.63 | L37: 8864.48 | O37: 620.83
A38: 3 | B38: A4-14 | C38: 钢梁安装 每根构件重量(t以内) 4.0 履带吊 | D38: t | E38: 789.85 | G38: 8122.82 | H38: 6415809.4 | I38: 249245.07 | J38: 5855971.6 | L38: 310592.72 | O38: 3025.1255
A39: 4 | B39: A4-106 | C39: 钢檩条 每根构件重量(t | D39: t | E39: 306 | G39: 6260.31 | H39: 1915654.8 | I39: 74149.92 | J39: 1776382 | L39: 65122.92 | O39: 899.64
A40: 编制人: | F40: 审核人: | K40: 编制日期:
A41: 单位工程直接费表
A42: 工程名称：土建 | K42: 第 3 页 共 6 页
A43: 序号 | B43: 定额编号 | C43: 子目名称 | D43: 工程量 | G43: 价值（元） | I43: 其中（元） | O43: 工日统计
D44: 单位 | E44: 数量 | G44: 单价 | H44: 合价 | I44: 人工合价 | J44: 材料合价 | L44: 机械合价 | M44: 主材合价 | N44: 设备合价
C45: 以内) 0.3 履带吊 | H45: 6 | J45: 2
A46: 5 | B46: A4-118 | C46: 钢墙架安装 每根构件重量(t) 1.0以内 履带吊 | D46: t | E46: 307.3 | G46: 7276.39 | H46: 2236034.6 | I46: 169936.9 | J46: 1853882.5 | L46: 212215.23 | O46: 2061.983
A47: 6 | B47: A4-25 | C47: 钢吊车梁安装在钢柱上 每根构件重量(t以内) 3.0 履带吊 | D47: t | E47: 641.6 | G47: 8127.12 | H47: 5214360.2 | I47: 145874.18 | J47: 5027847.1 | L47: 40638.94 | O47: 1770.816
A48: 7 | B48: A4-90 | C48: 单式柱间支撑 每根构件重量(t以内) 0.3 履带吊 | D48: t | E48: 293.8 | G48: 8196.83 | H48: 2408228.6 | I48: 193402.66 | J48: 2050885.6 | L48: 163940.4 | O48: 2347.462
A49: 8 | B49: A5-32 | C49: 压型钢板楼板 | D49: 10m2 | E49: 1029.05 | G49: 1080.74 | H49: 1112135.5 | I49: 301552.81 | J49: 810582.69 | O49: 3807.485
A50: 9 | B50: A4-122 | C50: 钢平台安装 钢板 | D50: t | E50: 19.4 | G50: 8653.68 | H50: 167881.39 | I50: 32450.77 | J50: 134548.31 | L50: 882.31 | O50: 393.82
A51: 10 | B51: A4-126 | C51: 钢楼梯安装 踏步式 | D51: t | E51: 10 | G51: 7141.98 | H51: 71419.8 | I51: 16058.8 | J51: 52905.2 | L51: 2455.8 | O51: 194.9
A52: 11 | B52: A11-7 | C52: 金属结构构件 运距(1km以内) 一类构件 | D52: 10t | E52: 91.414 | G52: 715.56 | H52: 65412.2 | I52: 7901.83 | J52: 7781.16 | L52: 49729.22 | O52: 116.0958
A53: 12 | B53: A11-8 | C53: 金属结构构件 运距(1km以内) 二类构件 | D53: 10t | E53: 174.468 | G53: 761.45 | H53: 132848.66 | I53: 11305.53 | J53: 17511.35 | L53: 104031.78 | O53: 160.5106
A54: 13 | B54: A11-9 | C54: 金属结构构件 运距(1km以内) 三类构件 | D54: 10t | E54: 31.738 | G54: 1134.39 | H54: 36003.27 | I54: 3315.99 | J54: 1836.68 | L54: 30850.61 | O54: 46.9722
C55: 砌块 | H55: 1144965.3 | I55: 313971.05 | J55: 823565.94 | L55: 7428.28 | O55: 4046.5123
A56: 1 | B56: A1-45 | C56: 加气混凝土砌块墙 600*300*100 混合砂浆M5 | D56: 10m3 | E56: 341.99 | G56: 3297.13 | H56: 1127585.5 | I56: 307011.26 | J56: 813286.42 | L56: 7287.81 | O56: 3956.8243
A57: 2 | B57: A1-39 | C57: 蒸压灰砂砖 | D57: 10m3 | E57: 6.06 | G57: 2867.95 | H57: 17379.78 | I57: 6959.79 | J57: 10279.52 | L57: 140.47 | O57: 89.688
C58: 屋面 | H58: 18132068 | I58: 1581287.7 | J58: 16550020 | L58: 760.1 | O58: 19963.427
A59: 1 | B59: A5-22 | C59: 彩钢夹心板屋面 板 | D59: 10m2 | E59: 3130.85 | G59: 1814.2 | H59: 5679988 | I59: 401500.2 | J59: 5278487.8 | O59: 5071.977
A60: 编制人: | F60: 审核人: | K60: 编制日期:
A61: 单位工程直接费表
A62: 工程名称：土建 | K62: 第 4 页 共 6 页
A63: 序号 | B63: 定额编号 | C63: 子目名称 | D63: 工程量 | G63: 价值（元） | I63: 其中（元） | O63: 工日统计
D64: 单位 | E64: 数量 | G64: 单价 | H64: 合价 | I64: 人工合价 | J64: 材料合价 | L64: 机械合价 | M64: 主材合价 | N64: 设备合价
C65: 厚(mm) 50 | H65: 7 | J65: 7
A66: 2 | B66: A6-2 | C66: 屋面保温 沥青玻璃棉毡 | D66: 10m3 | E66: 3130.85 | G66: 3863.81 | H66: 12097010 | I66: 1155909.8 | J66: 10941100 | O66: 14589.761
A67: 3 | B67: A6-20 | C67: 屋面现浇特种混凝土隔热层 加气混凝土 每增减10mm | D67: 100m2 | E67: 111.944 | G67: 279.14 | H67: 31248.05 | I67: 4329.99 | J67: 26157.95 | L67: 760.1 | O67: 54.8526
A68: 4 | B68: A6-43 | C68: 屋面保温 聚苯乙烯泡沫板(mm) 50 | D68: 100m2 | E68: 27.986 | G68: 6533.76 | H68: 182853.81 | I68: 3989.68 | J68: 178864.12 | O68: 50.3748
A69: 5 | B69: A5-36 | C69: 高聚物改性沥青防水卷材屋面 满铺 | D69: 100m2 | E69: 27.986 | G69: 5037.11 | H69: 140968.56 | I69: 15557.98 | J69: 125410.58 | O69: 196.4617
C70: 楼地面 | H70: 4156019.1 | I70: 888420.92 | J70: 3241366.6 | L70: 26231.58 | O70: 10909.555
A71: 1 | B71: A13-30 | C71: 混凝土 楼地面 厚度20mm | D71: 100m2 | E71: 313.085 | G71: 1751.59 | H71: 548396.56 | I71: 261851.77 | J71: 274791.57 | L71: 11753.21 | O71: 3215.383
A72: 2 | B72: A13-53 | C72: 金属骨料 楼地面 | D72: 100m2 | E72: 313.085 | G72: 7152.58 | H72: 2239365.5 | I72: 388288.02 | J72: 1841052.5 | L72: 10024.98 | O72: 4768.2846
A73: 3 | B73: A13-30 | C73: 混凝土 楼地面 厚度20mm | D73: 100m2 | E73: 3.417 | G73: 1751.59 | H73: 5985.18 | I73: 2857.84 | J73: 2999.07 | L73: 128.27 | O73: 35.0926
A74: 4 | B74: A13-104 | C74: 陶瓷地砖 楼地面 周长(mm以内) 2000 水泥砂浆 | D74: 100m2 | E74: 64.2436 | G74: 13006.7 | H74: 835597.23 | I74: 132740.13 | J74: 700374.73 | L74: 2482.37 | O74: 1629.8601
A75: 5 | B75: A13-103 | C75: 陶瓷地砖 楼地面 周长(mm以内) 1600 水泥砂浆 | D75: 100m2 | E75: 6.204 | G75: 11043.62 | H75: 68514.62 | I75: 13357.96 | J75: 54916.94 | L75: 239.72 | O75: 164.0338
A76: 6 | B76: A13-103 | C76: 玻化砖 楼地面 周长(mm以内) 1600 水泥砂浆 | D76: 100m2 | E76: 41.4864 | G76: 11043.62 | H76: 458160.04 | I76: 89325.2 | J76: 367231.8 | L76: 1603.03 | O76: 1096.9004
C77: 墙面 | H77: 395624.49 | I77: 238082.25 | J77: 157510.03 | L77: 32.21 | O77: 2802.2532
A78: 1 | B78: A14-149 | C78: 陶瓷锦砖 水泥砂浆粘贴 墙面 | D78: 100m2 | E78: 5.836 | G78: 10214.91 | H78: 59614.21 | I78: 28346.15 | J78: 31235.85 | L78: 32.21 | O78: 348.059
A79: 编制人: | F79: 审核人: | K79: 编制日期:
A80: 单位工程直接费表
A81: 工程名称：土建 | K81: 第 5 页 共 6 页
A82: 序号 | B82: 定额编号 | C82: 子目名称 | D82: 工程量 | G82: 价值（元） | I82: 其中（元） | O82: 工日统计
D83: 单位 | E83: 数量 | G83: 单价 | H83: 合价 | I83: 人工合价 | J83: 材料合价 | L83: 机械合价 | M83: 主材合价 | N83: 设备合价
A84: 2 | B84: A18-270 | C84: 抹灰面乳胶漆 两遍 刮腻子两遍 | D84: 100m2 | E84: 193.0916 | G84: 1740.16 | H84: 336010.28 | I84: 209736.1 | J84: 126274.18 | O84: 2454.1942
C85: 天棚 | H85: 1256495 | I85: 348258.03 | J85: 908236.98 | O85: 3972.7308
A86: 1 | B86: A18-270 | C86: 抹灰面乳胶漆 两遍 刮腻子两遍 | D86: 100m2 | E86: 3.417 | G86: 1740.16 | H86: 5946.13 | I86: 3711.55 | J86: 2234.58 | O86: 43.4301
A87: 2 | B87: A16-39 | C87: 天棚装配式U型轻钢龙骨 不上人型 面层规格(mm) 300*300 平面 | D87: 100m2 | E87: 125.4566 | G87: 6049.05 | H87: 758893.25 | I87: 234546.13 | J87: 524347.11 | O87: 2674.7347
A88: 3 | B88: A16-110 | C88: 矿棉板天棚面层 搁放在龙骨上 | D88: 100m2 | E88: 125.4566 | G88: 3918.93 | H88: 491655.63 | I88: 110000.35 | J88: 381655.29 | O88: 1254.566
C89: 门窗 | H89: 5248366.7 | I89: 334174.83 | J89: 4847319.9 | L89: 66871.95 | O89: 3821.2394
A90: 1 | B90: A17-58 | C90: 钢制门安装 平开门 | D90: 100m2 | E90: 0.2844 | G90: 49766.51 | H90: 14153.6 | I90: 1383.91 | J90: 12539.42 | L90: 230.26 | O90: 15.7842
A91: 2 | B91: A17-34 | C91: 铝合金门安装 平开门推拉门 | D91: 100m2 | E91: 0.264 | G91: 41529.21 | H91: 10963.71 | I91: 1712.92 | J91: 9020.92 | L91: 229.88 | O91: 19.536
A92: 3 | B92: A17-1 | C92: 带纱木门 单扇带亮 框扇安装 | D92: 100m2 | E92: 2.5854 | G92: 56279.71 | H92: 145505.56 | I92: 10494.76 | J92: 135006.25 | L92: 4.55 | O92: 119.704
A93: 4 | B93: A17-70 | C93: 钢防盗门 安装 | D93: 100m2 | E93: 0.105 | G93: 79506.02 | H93: 8348.13 | I93: 254.11 | J93: 8094.03 | O93: 2.898
A94: 5 | B94: A17-84 | C94: 钢制防火门 成品安装 | D94: 100m2 | E94: 2.0874 | G94: 51431.64 | H94: 107358.41 | I94: 17936.28 | J94: 89422.13 | O94: 204.5652
A95: 6 | B95: A17-49 | C95: 铝合金卷闸门 安装 | D95: 100m2 | E95: 1.944 | G95: 42505.55 | H95: 82630.79 | I95: 11352.14 | J95: 70840.12 | L95: 438.53 | O95: 129.4704
A96: 7 | B96: A17-102 | C96: 全钢板大门 推拉式 门扇安装 | D96: 100m2 | E96: 13.45 | G96: 167546.66 | H96: 2253502.6 | I96: 19896.85 | J96: 2206746.8 | L96: 26858.98 | O96: 236.8545
A97: 8 | B97: A17-43 | C97: 隔热断桥铝塑复合门窗安装 推拉窗 | D97: 100m2 | E97: 16.3704 | G97: 68013.03 | H97: 1113400.5 | I97: 108671.95 | J97: 992912.23 | L97: 11816.32 | O97: 1239.403
A98: 编制人: | F98: 审核人: | K98: 编制日期:
A99: 单位工程直接费表
A100: 工程名称：土建 | K100: 第 6 页 共 6 页
...

Sheet 价差
A1: 单位工程人材机价差表
A2: 工程名称：土建 | I2: 第 1 页 共 1 页
A3: 序号 | B3: 材料名称 | C3: 材料规格 | D3: 单位 | F3: 材料量 | G3: 预算价 | H3: 市场价 | J3: 价 差 | K3: 价差合计
A4: 1 | B4: 商品混凝土C15 | C4: 碎石20 | D4: m3 | F4: 1026.927 | G4: 338 | H4: 310 | J4: -28 | K4: -28753.96
A5: 2 | B5: 商品混凝土C20 | C5: 碎石20 | D5: m3 | F5: 6839.5873 | G5: 351 | H5: 330 | J5: -21 | K5: -143631.33
A6: 3 | B6: 金属骨料 | D6: kg | F6: 159673.35 | G6: 5 | H6: 10 | J6: 5 | K6: 798366.75
A7: 4 | B7: 钢防盗门 | D7: m2 | F7: 10.101 | G7: 303 | H7: 800 | J7: 497 | K7: 5020.2
A8: 5 | B8: 推拉全钢板大门(成品) | D8: m2 | F8: 1321.866 | G8: 224 | H8: 1500 | J8: 1276 | K8: 1686701
A9: 6 | B9: 成品钢质防火门 | D9: m2 | F9: 202.1647 | G9: 590 | H9: 440 | J9: -150 | K9: -30324.71
A10: 7 | B10: 铝合金卷闸门 | D10: m2 | F10: 194.4 | G10: 180 | H10: 360 | J10: 180 | K10: 34992
A11: 8 | B11: 铝合金固定窗 | D11: m2 | F11: 2540.967 | G11: 204 | H11: 349 | J11: 145 | K11: 368440.22
A12: 9 | B12: 铝合金推拉窗 | D12: m2 | F12: 872.8836 | G12: 253 | H12: 382 | J12: 129 | K12: 112601.98
A13: 10 | B13: 隔热断桥铝塑复合推拉窗 | D13: m2 | F13: 1549.2947 | G13: 560 | H13: 620 | J13: 60 | K13: 92957.68
A14: 11 | B14: 钢制大门 | D14: m2 | F14: 27.1005 | G14: 275 | H14: 409 | J14: 134 | K14: 3631.47
A15: 12 | B15: 陶瓷地砖 | C15: 400*400 | D15: m2 | F15: 4888.266 | G15: 39.83 | H15: 80 | J15: 40.17 | K15: 196361.65
A16: 13 | B16: 陶瓷锦砖 | D16: m2 | F16: 592.354 | G16: 11.35 | H16: 50 | J16: 38.65 | K16: 22894.48
A17: 14 | B17: 聚苯乙烯泡沫板δ50 | D17: m2 | F17: 2938.53 | G17: 20.3 | H17: 60 | J17: 39.7 | K17: 116659.64
A18: 15 | B18: 钢支撑(成品) | D18: t | F18: 293.8 | G18: 6922 | H18: 6530 | J18: -392 | K18: -115169.6
A19: 16 | B19: 钢檩条(成品) | D19: t | F19: 306 | G19: 6922 | H19: 5490 | J19: -1432 | K19: -438192
A20: 17 | B20: 钢平台(成品) | D20: t | F20: 19.4 | G20: 6922 | H20: 6740 | J20: -182 | K20: -3530.8
A21: 18 | B21: 钢楼梯踏步式(成品) | D21: t | F21: 10 | G21: 8065 | H21: 5090 | J21: -2975 | K21: -29750
A22: 19 | B22: 圆钢φ12 | D22: t | F22: 2982.2046 | G22: 3914 | H22: 2730 | J22: -1184 | K22: -3530930.2
A23: 20 | B23: 彩钢夹芯板50 | D23: m2 | F23: 32560.84 | G23: 157.64 | H23: 130 | J23: -27.64 | K23: -899981.62
A27: 合 计 | K27: -1781637.2
A28: 编制人: | E28: 审核人: | I28: 编制日期:

Sheet 措施
A1: 措施项目分项汇总表
A2: 工程名称：土建 | F2: 第 1 页 共 1 页
A3: 序号 | B3: 措施项目名称 | D3: 单位 | E3: 工程量 | G3: 合价
A4: 1 | B4: 单价措施项目费
A5: 1 | B5: 排水降水 | D5: 项 | E5: 1
A6: 2 | B6: 混凝土、钢筋混凝土模板及支撑 | D6: 项 | E6: 1 | G6: 1768692.2
A7: 3 | B7: 脚手架 | D7: 项 | E7: 1 | G7: 1035979.7
A8: 4 | B8: 垂直运输费 | D8: 项 | E8: 1 | G8: 4457071.1
A9: 5 | B9: 大型机械设备进出场及安拆费 | D9: 项 | E9: 1
A10: 6 | B10: 已完工程及设备保护费 | D10: 项 | E10: 1
A11: 7 | B11: 地上、地下设施、建筑物临时保护设施费 | D11: 项 | E11: 1
A12: 8 | B12: 其他 | D12: 项 | E12: 1
B13: 小计 | D13: 元 | G13: 7261743
A42: 编制人: | C42: 审核人: | F42: 2016年8月16日

Sheet 水费
A1: 单位工程费用汇总表
A2: 工程名称：给排水 | E2: 第 1 页 共 1 页
A3: 序号 | B3: 费用名称 | D3: 取费基数 | F3: 费率 | G3: 费用金额
A4: 1 | B4: 安装工程 | D4: 安装工程 | G4: 1803577.4
A5: 一 | B5: 分部分项工程费 | D5: 人工费+材料费+未计价材料费+施工机具使用费+设备费 | F5: 105 | G5: 1600483.9
A6: 1 | B6: 人工费 | D6: 人工费 | G6: 250776.33
A7: 2 | B7: 材料费 | D7: 材料费 | G7: 64438.25
A8: 3 | B8: 未计价材料费 | D8: 主材费 | G8: 1200722.2
A9: 4 | B9: 施工机具使用费 | D9: 机械费 | G9: 8333.64
A10: 5 | B10: 设备费 | D10: 设备费
A11: 二 | B11: 措施项目费 | D11: 单价措施项目费+总价措施项目费 | G11: 25133.66
A12: 2.1 | B12: 单价措施项目费 | D12: 人工费+材料费+施工机具使用费
A13: 2.1.1 | B13: 人工费 | D13: 技术措施项目人工费
A14: 2.1.2 | B14: 材料费 | D14: 技术措施项目材料费
A15: 2.1.3 | B15: 施工机具使用费 | D15: 技术措施项目机械费
A16: 2.2 | B16: 总价措施项目费 | D16: 安全文明施工费+其它总价措施项目费 | G16: 25133.66
A17: 2.2.1 | B17: 安全文明施工费 | D17: 人工费+施工机具使用费+人工费+施工机具使用费 | F17: 9.05 | G17: 23449.45
A18: 2.2.2 | B18: 其它总价措施项目费 | D18: 人工费+施工机具使用费+人工费+施工机具使用费 | F18: 0.65 | G18: 1684.21
A19: 三 | B19: 总包服务费
A20: 四 | B20: 企业管理费 | D20: 人工费+施工机具使用费+人工费+施工机具使用费 | F20: 17.5 | G20: 45344.24
A21: 五 | B21: 利润 | D21: 人工费+施工机具使用费+人工费+施工机具使用费 | F21: 14.91 | G21: 38633.3
A22: 六 | B22: 规费 | D22: 人工费+施工机具使用费+人工费+施工机具使用费 | F22: 11.66 | G22: 30212.22
A23: 七 | B23: 索赔与现场签证
A24: 八 | B24: 安全技术服务费 | D24: 分部分项工程费+措施项目费+总包服务费+企业管理费+利润+规费-设备费 | F24: 0.12 | G24: 2087.77
A25: 九 | B25: 不含税工程造价 | D25: 分部分项工程费+措施项目费+总包服务费+企业管理费+利润+规费+索赔与现场签证+安全技术服务费 | G25: 1741895.1
A26: 十 | B26: 税前包干项目 | D26: 税前包干价
A27: 十一 | B27: 税金 | D27: 不含税工程造价+税前包干价 | F27: 3.5411 | G27: 61682.25
A28: 十二 | B28: 税后包干项目 | D28: 税后包干价
A29: 十四 | B29: 含税工程造价 | D29: 不含税工程造价+税金+税前包干项目+税后包干项目 | G29: 1803577.4
A31: 2 | B31: 工程造价 | D31: 专业造价总合计 | G31: 1803577.4
A36: 编制人: | C36: 审核人: | E36: 编制日期:

Sheet 水
A1: 单位工程直接费表
A2: 工程名称：给排水 | K2: 第 1 页 共 7 页
A3: 序号 | B3: 定额编号 | C3: 子目名称 | D3: 工程量 | G3: 价值（元） | I3: 其中（元） | O3: 工日统计
D4: 单位 | E4: 数量 | G4: 单价 | H4: 合价 | I4: 人工合价 | J4: 材料合价 | L4: 机械合价 | M4: 主材合价 | N4: 设备合价
C5: 给排水 | H5: 24743.17 | I5: 9736.83 | J5: 13726.24 | L5: 1280.08 | M5: 194855.2 | O5: 118.1572
A6: 1 | B6: C10-644 | C6: 闸阀 DN50 | D6: 个 | E6: 4 | G6: 100.09 | H6: 400.36 | I6: 116.72 | J6: 240.44 | L6: 43.2 | M6: 2080 | O6: 1.416
B7: 主材 | C7: 闸阀 DN50 | D7: 个 | E7: 4 | G7: 520 | H7: 2080 | M7: 2080
A8: 2 | B8: C10-646 | C8: 闸阀 DN80 | D8: 个 | E8: 6 | G8: 156.15 | H8: 936.9 | I8: 252.12 | J8: 570.18 | L8: 114.6 | M8: 4500 | O8: 3.06
B9: 主材 | C9: 闸阀 DN80 | D9: 个 | E9: 6 | G9: 750 | H9: 4500 | M9: 4500
A10: 3 | B10: C10-647 | C10: 闸阀 DN100 | D10: 个 | E10: 2 | G10: 190.39 | H10: 380.78 | I10: 106.44 | J10: 229.5 | L10: 44.84 | M10: 1960 | O10: 1.292
B11: 主材 | C11: 闸阀 DN100 | D11: 个 | E11: 2 | G11: 980 | H11: 1960 | M11: 1960
A12: 4 | B12: C10-644 | C12: 止回阀 DN50 | D12: 个 | E12: 2 | G12: 100.09 | H12: 200.18 | I12: 58.36 | J12: 120.22 | L12: 21.6 | M12: 400 | O12: 0.708
B13: 主材 | C13: 止回阀 DN50 | D13: 个 | E13: 2 | G13: 200 | H13: 400 | M13: 400
A14: 5 | B14: C10-646 | C14: 止回阀 DN80 | D14: 个 | E14: 3 | G14: 156.15 | H14: 468.45 | I14: 126.06 | J14: 285.09 | L14: 57.3 | M14: 930 | O14: 1.53
B15: 主材 | C15: 止回阀 DN80 | D15: 个 | E15: 3 | G15: 310 | H15: 930 | M15: 930
A16: 6 | B16: C10-647 | C16: 止回阀 DN100 | D16: 个 | E16: 1 | G16: 190.39 | H16: 190.39 | I16: 53.22 | J16: 114.75 | L16: 22.42 | M16: 380 | O16: 0.646
B17: 主材 | C17: 止回阀 DN100 | D17: 个 | E17: 1 | G17: 380 | H17: 380 | M17: 380
A18: 7 | B18: C10-644 | C18: 自动排气阀 DN50 | D18: 个 | E18: 2 | G18: 100.09 | H18: 200.18 | I18: 58.36 | J18: 120.22 | L18: 21.6 | M18: 640 | O18: 0.708
B19: 主材 | C19: 自动排气阀 DN50 | D19: 个 | E19: 2 | G19: 320 | H19: 640 | M19: 640
A20: 8 | B20: C10-646 | C20: 自动排气阀 DN80 | D20: 个 | E20: 3 | G20: 156.15 | H20: 468.45 | I20: 126.06 | J20: 285.09 | L20: 57.3 | M20: 1410 | O20: 1.53
B21: 主材 | C21: 自动排气阀 DN80 | D21: 个 | E21: 3 | G21: 470 | H21: 1410 | M21: 1410
A22: 9 | B22: C10-647 | C22: 自动排气阀 DN100 | D22: 个 | E22: 1 | G22: 190.39 | H22: 190.39 | I22: 53.22 | J22: 114.75 | L22: 22.42 | M22: 590 | O22: 0.646
B23: 主材 | C23: 自动排气阀 DN100 | D23: 个 | E23: 1 | G23: 590 | H23: 590 | M23: 590
A24: 10 | B24: C10-644 | C24: 截止阀 DN50 | D24: 个 | E24: 37 | G24: 100.09 | H24: 3703.33 | I24: 1079.66 | J24: 2224.07 | L24: 399.6 | M24: 8510 | O24: 13.098
B25: 主材 | C25: 截止阀 DN50 | D25: 个 | E25: 37 | G25: 230 | H25: 8510 | M25: 8510
A26: 编制人: | F26: 审核人: | K26: 编制日期:
A27: 单位工程直接费表
A28: 工程名称：给排水 | K28: 第 2 页 共 7 页
A29: 序号 | B29: 定额编号 | C29: 子目名称 | D29: 工程量 | G29: 价值（元） | I29: 其中（元） | O29: 工日统计
D30: 单位 | E30: 数量 | G30: 单价 | H30: 合价 | I30: 人工合价 | J30: 材料合价 | L30: 机械合价 | M30: 主材合价 | N30: 设备合价
A31: 11 | B31: C10-643 | C31: 截止阀 DN40 | D31: 个 | E31: 15 | G31: 85.42 | H31: 1281.3 | I31: 379.5 | J31: 739.8 | L31: 162 | M31: 2700 | O31: 4.605
B32: 主材 | C32: 截止阀 DN40 | D32: 个 | E32: 15 | G32: 180 | H32: 2700 | M32: 2700
A33: 12 | B33: C10-642 | C33: 截止阀 DN32 | D33: 个 | E33: 29 | G33: 77.11 | H33: 2236.19 | I33: 695.71 | J33: 1227.28 | L33: 313.2 | M33: 4350 | O33: 8.439
B34: 主材 | C34: 截止阀 DN32 | D34: 个 | E34: 29 | G34: 150 | H34: 4350 | M34: 4350
A35: 13 | B35: C10-638 | C35: 截止阀 DN25 | D35: 个 | E35: 22 | G35: 38.74 | H35: 852.28 | I35: 373.34 | J35: 478.94 | M35: 2420 | O35: 4.532
B36: 主材 | C36: 截止阀 DN25 | D36: 个 | E36: 22 | G36: 110 | H36: 2420 | M36: 2420
A37: 14 | B37: C10-971 | C37: 大便器安装 蹲式 普通阀冲洗 | D37: 10套 | E37: 10.8 | G37: 877.3 | H37: 9474.84 | I37: 3977.96 | J37: 5496.88 | M37: 57812.4 | O37: 48.276
B38: 主材 | C38: 瓷蹲式大便器 | D38: 个 | E38: 109.08 | G38: 530 | H38: 57812.4 | M38: 57812.4
A39: 15 | B39: C10-980 | C39: 小便器安装 挂斗式 普通式 | D39: 10套 | E39: 3.8 | G39: 598.2 | H39: 2273.16 | I39: 816.66 | J39: 1456.5 | M39: 31087.8 | O39: 9.9104
B40: 主材 | C40: 挂式小便器 | D40: 个 | E40: 38.38 | G40: 810 | H40: 31087.8 | M40: 31087.8
A41: 16 | B41: C10-1006 | C41: 水龙头 DN20 | D41: 10个 | E41: 11 | G41: 18.68 | H41: 205.48 | I41: 196.68 | J41: 8.8 | M41: 69993 | O41: 2.387
B42: 主材 | C42: 水龙头 DN20 | D42: 个 | E42: 111.1 | G42: 630 | H42: 69993 | M42: 69993
A43: 17 | B43: C10-1009 | C43: 圆地漏 De50 | D43: 10个 | E43: 0.4 | G43: 101.95 | H43: 40.78 | I43: 40.5 | J43: 0.28 | M43: 188 | O43: 0.4916
B44: 主材 | C44: 圆地漏 De50 | D44: 个 | E44: 4 | G44: 47 | H44: 188 | M44: 188
A45: 18 | B45: C10-1010 | C45: 圆地漏 De75 | D45: 10个 | E45: 4.6 | G45: 127.7 | H45: 587.42 | I45: 582.59 | J45: 4.83 | M45: 3496 | O45: 7.0702
B46: 主材 | C46: 圆地漏 De75 | D46: 个 | E46: 46 | G46: 76 | H46: 3496 | M46: 3496
A47: 19 | B47: C10-1012 | C47: 圆地漏 De110 | D47: 10个 | E47: 0.6 | G47: 187.76 | H47: 112.66 | I47: 111.38 | J47: 1.27 | M47: 600 | O47: 1.3518
B48: 主材 | C48: 圆地漏 De110 | D48: 个 | E48: 6 | G48: 100 | H48: 600 | M48: 600
A49: 20 | B49: C10-1016 | C49: 清扫口 De75 | D49: 10个 | E49: 0.8 | G49: 64.34 | H49: 51.47 | I49: 49.63 | J49: 1.84 | M49: 288 | O49: 0.6024
B50: 主材 | C50: 清扫口 De75 | D50: 个 | E50: 8 | G50: 36 | H50: 288 | M50: 288
A51: 编制人: | F51: 审核人: | K51: 编制日期:
A52: 单位工程直接费表
A53: 工程名称：给排水 | K53: 第 3 页 共 7 页
A54: 序号 | B54: 定额编号 | C54: 子目名称 | D54: 工程量 | G54: 价值（元） | I54: 其中（元） | O54: 工日统计
D55: 单位 | E55: 数量 | G55: 单价 | H55: 合价 | I55: 人工合价 | J55: 材料合价 | L55: 机械合价 | M55: 主材合价 | N55: 设备合价
A56: 21 | B56: C10-1012 | C56: 87型雨水斗 De110 | D56: 10个 | E56: 2.6 | G56: 187.76 | H56: 488.18 | I56: 482.66 | J56: 5.51 | M56: 520 | O56: 5.8578
B57: 主材 | C57: 87型雨水斗 De110 | D57: 个 | E57: 26 | G57: 20 | H57: 520 | M57: 520
C58: 雨水 | H58: 1590.39 | I58: 1460.94 | J58: 129.47 | M58: 2462.8 | O58: 17.7302
A59: 1 | B59: C10-1010 | C59: 虹吸雨水斗 De75 | D59: 10个 | E59: 1.1 | G59: 127.7 | H59: 140.47 | I59: 139.32 | J59: 1.16 | M59: 154 | O59: 1.6907
B60: 主材 | C60: 虹吸雨水斗 De75 | D60: 个 | E60: 11 | G60: 14 | H60: 154 | M60: 154
A61: 2 | B61: C10-1011 | C61: 虹吸雨水斗 De90 | D61: 10个 | E61: 1.1 | G61: 153.21 | H61: 168.53 | I61: 167.15 | J61: 1.39 | M61: 198 | O61: 2.0284
B62: 主材 | C62: 虹吸雨水斗 De90 | D62: 个 | E62: 11 | G62: 18 | H62: 198 | M62: 198
A63: 3 | B63: C10-1012 | C63: 虹吸雨水斗 De110 | D63: 10个 | E63: 4.3 | G63: 187.76 | H63: 807.37 | I63: 798.25 | J63: 9.12 | M63: 860 | O63: 9.6879
B64: 主材 | C64: 虹吸雨水斗 De110 | D64: 个 | E64: 43 | G64: 20 | H64: 860 | M64: 860
A65: 4 | B65: C10-1012 | C65: 虹吸雨水斗 De125 | D65: 10个 | E65: 0.4 | G65: 187.76 | H65: 75.1 | I65: 74.26 | J65: 0.85 | M65: 108 | O65: 0.9012
B66: 主材 | C66: 虹吸雨水斗 De125 | D66: 个 | E66: 4 | G66: 27 | H66: 108 | M66: 108
A67: 5 | B67: C10-386 | C67: 波纹管 De160 | D67: 10m | E67: 0.4 | G67: 183.04 | H67: 73.22 | I67: 51.78 | J67: 21.43 | M67: 108.8 | O67: 0.6284
B68: 主材 | C68: 波纹管 De160 | D68: m | E68: 4 | G68: 27.2 | H68: 108.8 | M68: 108.8
A69: 6 | B69: C10-387 | C69: 波纹管 De200 | D69: 10m | E69: 0.6 | G69: 203.56 | H69: 122.14 | I69: 86.32 | J69: 35.82 | M69: 306 | O69: 1.0476
B70: 主材 | C70: 波纹管 De200 | D70: m | E70: 6 | G70: 51 | H70: 306 | M70: 306
A71: 7 | B71: C10-387 | C71: 波纹管 De250 | D71: 10m | E71: 1 | G71: 203.56 | H71: 203.56 | I71: 143.86 | J71: 59.7 | M71: 728 | O71: 1.746
B72: 主材 | C72: 波纹管 De250 | D72: m | E72: 10 | G72: 72.8 | H72: 728 | M72: 728
C73: 消火栓 | H73: 42342.14 | I73: 25650.86 | J73: 14492.79 | L73: 2198.51 | M73: 311316.67 | O73: 337.0176
A74: 1 | B74: C9-107 | C74: 手提式磷酸铵盐干粉灭火器 MFT/ABC4 | D74: 10个 | E74: 34.6 | G74: 168.9 | H74: 5843.94 | I74: 5677.86 | J74: 166.08 | M74: 34254 | O74: 94.631
B75: 主材 | C75: 手提式磷酸铵盐干粉灭火器 MFT/ABC4 | D75: 个 | E75: 346 | G75: 99 | H75: 34254 | M75: 34254
A76: 编制人: | F76: 审核人: | K76: 编制日期:
A77: 单位工程直接费表
A78: 工程名称：给排水 | K78: 第 4 页 共 7 页
A79: 序号 | B79: 定额编号 | C79: 子目名称 | D79: 工程量 | G79: 价值（元） | I79: 其中（元） | O79: 工日统计
D80: 单位 | E80: 数量 | G80: 单价 | H80: 合价 | I80: 人工合价 | J80: 材料合价 | L80: 机械合价 | M80: 主材合价 | N80: 设备合价
A81: 2 | B81: C9-84 | C81: 室内消火栓 | D81: 套 | E81: 167 | G81: 105.31 | H81: 17586.77 | I81: 14408.76 | J81: 3052.76 | L81: 125.25 | M81: 250500 | O81: 174.849
B82: 主材 | C82: 组合消防箱 | D82: 套 | E82: 167 | G82: 1500 | H82: 250500 | M82: 250500
A83: 3 | B83: C9-103 | C83: 室外地上式消防水泵接合器 SQS100-A | D83: 套 | E83: 2 | G83: 281.8 | H83: 563.6 | I83: 327.28 | J83: 218.28 | L83: 18.04 | M83: 1986 | O83: 3.972
B84: 主材 | C84: 室外地上式消防水泵接合器 SQS100-A | D84: 套 | E84: 2 | G84: 993 | H84: 1986 | M84: 1986
A85: 4 | B85: C10-647 | C85: 蝶阀 DN100 | D85: 个 | E85: 81 | G85: 190.39 | H85: 15421.59 | I85: 4310.82 | J85: 9294.75 | L85: 1816.02 | M85: 18630 | O85: 52.326
B86: 主材 | C86: 蝶阀 DN100 | D86: 个 | E86: 81 | G86: 230 | H86: 18630 | M86: 18630
A87: 5 | B87: C10-649 | C87: 蝶阀 DN150 | D87: 个 | E87: 6 | G87: 320.94 | H87: 1925.64 | I87: 494.94 | J87: 1281.18 | L87: 149.52 | M87: 2640 | O87: 6.006
B88: 主材 | C88: 蝶阀 DN150 | D88: 个 | E88: 6 | G88: 440 | H88: 2640 | M88: 2640
A89: 6 | B89: C10-133 | C89: 波纹管 DN100 | D89: 10m | E89: 3.4 | G89: 64.86 | H89: 220.52 | I89: 201.42 | J89: 19.11 | M89: 531.45 | O89: 2.4446
B90: 主材 | C90: 波纹管 DN100 | D90: m | E90: 34.51 | G90: 15.4 | H90: 531.45 | M90: 531.45
A91: 7 | B91: C10-134 | C91: 波纹管 DN150 | D91: 10m | E91: 0.2 | G91: 92.61 | H91: 18.52 | I91: 16.9 | J91: 1.63 | M91: 55.22 | O91: 0.205
B92: 主材 | C92: 波纹管 DN150 | D92: m | E92: 2.03 | G92: 27.2 | H92: 55.22 | M92: 55.22
A93: 8 | B93: C10-647 | C93: 止回阀 DN100 | D93: 个 | E93: 2 | G93: 190.39 | H93: 380.78 | I93: 106.44 | J93: 229.5 | L93: 44.84 | M93: 760 | O93: 1.292
B94: 主材 | C94: 止回阀 DN100 | D94: 个 | E94: 2 | G94: 380 | H94: 760 | M94: 760
A95: 9 | B95: C10-647 | C95: 闸阀 DN100 | D95: 个 | E95: 2 | G95: 190.39 | H95: 380.78 | I95: 106.44 | J95: 229.5 | L95: 44.84 | M95: 1960 | O95: 1.292
B96: 主材 | C96: 闸阀 DN100 | D96: 个 | E96: 2 | G96: 980 | H96: 1960 | M96: 1960
C97: 室内 | H97: 254872.47 | I97: 213927.7 | J97: 36089.75 | L97: 4855.05 | M97: 692087.52 | O97: 2596.1595
A98: 1 | B98: C10-424 | C98: 衬塑复合钢管 DN20 | D98: 10m | E98: 26 | G98: 143.4 | H98: 3728.4 | I98: 3335.8 | J98: 325.52 | L98: 67.08 | M98: 7743.84 | O98: 40.482
B99: 主材 | C99: 衬塑复合钢管 DN20 | D99: m | E99: 265.2 | G99: 29.2 | H99: 7743.84 | M99: 7743.84
A100: 2 | B100: C10-425 | C100: 衬塑复合钢管 DN25 | D100: 10m | E100: 47 | G100: 178.53 | H100: 8390.91 | I100: 7366.78 | J100: 854.93 | L100: 169.2 | M100: 19511.58 | O100: 89.394
...

Sheet 水设
A1: 附表1-6
A2: 新增主要公用设备表
A3: 0 | I3: 单位：万元
A4: 序号 | B4: 设备名称 | C4: 型号规格 | D4: 单位 | E4: 数量 | F4: 单价 | G4: 合计 | H4: 安装费 | I4: 备注
A6: 1 | B6: 落地式电热水器 | C6: DAY-T814,容积50L，功率9KW。 | D6: 台 | E6: 4 | F6: 0.6 | G6: =F6*E6 -> 2.4 | H6: =G6*0.1 -> 0.24
A7: 2 | B7: 虹吸雨水排水系统 | C7: 屋面面积约31200平方米、28个管道系统 | D7: 台 | E7: 1 | F7: 0.4 | G7: =F7*E7 -> 0.4 | H7: =G7*0.1 -> 0.04
B58: 合计 | E58: =SUM(E6:E7) -> 5 | G58: =SUM(G6:G7) -> 2.8 | H58: =SUM(H6:H7) -> 0.28

Sheet 暖费
A1: 单位工程费用汇总表
A2: 工程名称：暖通 | E2: 第 1 页 共 1 页
A3: 序号 | B3: 费用名称 | D3: 取费基数 | F3: 费率 | G3: 费用金额
A4: 1 | B4: 安装工程 | D4: 安装工程 | G4: 21719.62
A5: 一 | B5: 分部分项工程费 | D5: 人工费+材料费+未计价材料费+施工机具使用费+设备费 | G5: 20716.8
A6: 1 | B6: 人工费 | D6: 人工费 | G6: 436.8
A7: 2 | B7: 材料费 | D7: 材料费
A8: 3 | B8: 未计价材料费 | D8: 主材费 | G8: 20280
A9: 4 | B9: 施工机具使用费 | D9: 机械费
A10: 5 | B10: 设备费 | D10: 设备费
A11: 二 | B11: 措施项目费 | D11: 单价措施项目费+总价措施项目费 | G11: 42.37
A12: 2.1 | B12: 单价措施项目费 | D12: 人工费+材料费+施工机具使用费
A13: 2.1.1 | B13: 人工费 | D13: 技术措施项目人工费
A14: 2.1.2 | B14: 材料费 | D14: 技术措施项目材料费
A15: 2.1.3 | B15: 施工机具使用费 | D15: 技术措施项目机械费
A16: 2.2 | B16: 总价措施项目费 | D16: 安全文明施工费+其它总价措施项目费 | G16: 42.37
A17: 2.2.1 | B17: 安全文明施工费 | D17: 人工费+施工机具使用费+人工费+施工机具使用费 | F17: 9.05 | G17: 39.53
A18: 2.2.2 | B18: 其它总价措施项目费 | D18: 人工费+施工机具使用费+人工费+施工机具使用费 | F18: 0.65 | G18: 2.84
A19: 三 | B19: 总包服务费
A20: 四 | B20: 企业管理费 | D20: 人工费+施工机具使用费+人工费+施工机具使用费 | F20: 17.5 | G20: 76.44
A21: 五 | B21: 利润 | D21: 人工费+施工机具使用费+人工费+施工机具使用费 | F21: 14.91 | G21: 65.13
A22: 六 | B22: 规费 | D22: 人工费+施工机具使用费+人工费+施工机具使用费 | F22: 11.66 | G22: 50.93
A23: 七 | B23: 索赔与现场签证
A24: 八 | B24: 安全技术服务费 | D24: 分部分项工程费+措施项目费+总包服务费+企业管理费+利润+规费-设备费 | F24: 0.12 | G24: 25.14
A25: 九 | B25: 不含税工程造价 | D25: 分部分项工程费+措施项目费+总包服务费+企业管理费+利润+规费+索赔与现场签证+安全技术服务费 | G25: 20976.81
A26: 十 | B26: 税前包干项目 | D26: 税前包干价
A27: 十一 | B27: 税金 | D27: 不含税工程造价+税前包干价 | F27: 3.5411 | G27: 742.81
A28: 十二 | B28: 税后包干项目 | D28: 税后包干价
A29: 十四 | B29: 含税工程造价 | D29: 不含税工程造价+税金+税前包干项目+税后包干项目 | G29: 21719.62
A31: 2 | B31: 工程造价 | D31: 专业造价总合计 | G31: 21719.62
A36: 编制人: | C36: 审核人: | E36: 编制日期:

Sheet 暖
A1: 单位工程直接费表
A2: 工程名称：暖通 | K2: 第 1 页 共 1 页
A3: 序号 | B3: 定额编号 | C3: 子目名称 | D3: 工程量 | G3: 价值（元） | I3: 其中（元） | O3: 工日统计
D4: 单位 | E4: 数量 | G4: 单价 | H4: 合价 | I4: 人工合价 | J4: 材料合价 | L4: 机械合价 | M4: 主材合价 | N4: 设备合价
A5: 1 | B5: 补充主材001@1 | C5: 通风天窗 MCW1ZD-6050n | D5: m | E5: 276 | G5: 50 | H5: 13800 | M5: 13800
A6: 2 | B6: C7-28 | C6: 卫生间通风器 BLD-400 | D6: 台 | E6: 16 | G6: 10.92 | H6: 174.72 | I6: 174.72 | M6: 2400 | O6: 2.128
B7: 主材 | C7: 卫生间通风器 BLD-400 | D7: 台 | E7: 16 | G7: 150 | H7: 2400 | M7: 2400
A8: 3 | B8: C7-28 | C8: 卫生间通风器 BLD-600 | D8: 台 | E8: 24 | G8: 10.92 | H8: 262.08 | I8: 262.08 | M8: 4080 | O8: 3.192
B9: 主材 | C9: 卫生间通风器 BLD-600 | D9: 台 | E9: 24 | G9: 170 | H9: 4080 | M9: 4080
A25: 合计 | H25: 20716.8 | I25: 436.8 | M25: 20280 | O25: 5.32
A26: 编制人: | F26: 审核人: | K26: 编制日期:

Sheet 暖设
A1: 附表1-6
A2: 新增主要公用设备表
A3: =[1]投资估算!A3 -> #REF! | J3: 单位：万元
A4: 序号 | B4: 总图编号 | C4: 设备名称 | D4: 型号规格 | E4: 单位 | F4: 数量 | G4: 单价 | H4: 合计 | I4: 安装费 | J4: 备注
A6: 1 | C6: 离心式冷水机组 | D6: LC600A 制冷量：2110kW | E6: 台 | F6: 2 | G6: 8 | H6: =G6*F6 -> 16 | I6: =H6*0.1 -> 1.6
A7: 2 | C7: 冷冻水泵（立式离心泵） | D7: SLZD200-315(I)A 流量：:374m3/h 扬程：28mH2O 功率:45kW | E7: 台 | F7: 2 | G7: 2.2 | H7: =G7*F7 -> 4.4 | I7: =H7*0.1 -> 0.44
A8: 3 | C8: 冷却水泵（立式离心泵） | D8: SLZD250-315A 流量：500m3/h 扬程：28mH2O 功率:55kW | E8: 台 | F8: 2 | G8: 2.5 | H8: =G8*F8 -> 5 | I8: =H8*0.1 -> 0.5
A9: 4 | C9: 方形逆流冷却塔 | D9: KFT500 冷却水量:500m3/h 扬程：5.3mH2O | E9: 台 | F9: 2 | G9: 13 | H9: =G9*F9 -> 26 | I9: =H9*0.1 -> 2.6
A10: 5 | C10: 全自动软水器 | D10: TRB-400 产水量：4~5m3/h | E10: 台 | F10: 1 | G10: 0.6 | H10: =G10*F10 -> 0.6 | I10: =H10*0.1 -> 0.06
A11: 6 | C11: 软化水箱 | D11: 公称容积：2.0m3 | E11: 只 | F11: 1 | G11: 0.8 | H11: =G11*F11 -> 0.8 | I11: =H11*0.1 -> 0.08
A12: 7 | C12: 补水定压机组 | D12: XQG-15/1.0-1000L | E12: 台 | F12: 1 | G12: 1.2 | H12: =G12*F12 -> 1.2 | I12: =H12*0.1 -> 0.12
A13: 8 | C13: 补水定压罐 | D13: 总容积：1.36m3 | E13: 只 | F13: 1 | G13: 1.5 | H13: =G13*F13 -> 1.5 | I13: =H13*0.1 -> 0.15
A14: 9 | C14: 补水泵 | D14: SLZD40-200 流量:2.2m3/h 扬程：12.8mH20 | E14: 台 | F14: 2 | G14: 0.3 | H14: =G14*F14 -> 0.6 | I14: =H14*0.1 -> 0.06
A15: 10 | C15: 集水器 | D15: %%CXL=800X3400 | E15: 个 | F15: 1 | G15: 0.5 | H15: =G15*F15 -> 0.5 | I15: =H15*0.1 -> 0.05
A16: 11 | C16: 分水器 | D16: %%CXL=800X3400 | E16: 个 | F16: 1 | G16: 0.55 | H16: =G16*F16 -> 0.55 | I16: =H16*0.1 -> 0.055
A17: 12 | C17: 全自动全效水处理器 | D17: 流量：870m3/h 功率：0.7kw | E17: 只 | F17: 1 | G17: 2 | H17: =G17*F17 -> 2 | I17: =H17*0.1 -> 0.2
... A43: 38 | C43: 恒温恒湿机 | D43: HFD13W Q冷=12.6kw | E43: 台 | F43: 3 | G43: 3.15 | H43: =G43*F43 -> 9.45 | I43: =H43*0.1 -> 0.945
C75: 合计 | F75: =SUM(F6:F74) -> 376 | H75: =SUM(H6:H74) -> 338.005 | I75: =SUM(I6:I74) -> 33.8005

Sheet 电费
A1: 单位工程费用汇总表
A2: 工程名称：室内电 | E2: 第 1 页 共 1 页
A3: 序号 | B3: 费用名称 | D3: 取费基数 | F3: 费率 | G3: 费用金额
A4: 1 | B4: 安装工程 | D4: 安装工程 | G4: 3951020.9
A5: 一 | B5: 分部分项工程费 | D5: 人工费+材料费+未计价材料费+施工机具使用费+设备费 | F5: 103 | G5: 3470209
A6: 1 | B6: 人工费 | D6: 人工费 | G6: 599021.45
A7: 2 | B7: 材料费 | D7: 材料费 | G7: 168455.85
A8: 3 | B8: 未计价材料费 | D8: 主材费 | G8: 2566285.4
A9: 4 | B9: 施工机具使用费 | D9: 机械费 | G9: 35372.34
A10: 5 | B10: 设备费 | D10: 设备费
A11: 二 | B11: 措施项目费 | D11: 单价措施项目费+总价措施项目费 | G11: 61536.2
A12: 2.1 | B12: 单价措施项目费 | D12: 人工费+材料费+施工机具使用费
A13: 2.1.1 | B13: 人工费 | D13: 技术措施项目人工费
A14: 2.1.2 | B14: 材料费 | D14: 技术措施项目材料费
A15: 2.1.3 | B15: 施工机具使用费 | D15: 技术措施项目机械费
A16: 2.2 | B16: 总价措施项目费 | D16: 安全文明施工费+其它总价措施项目费 | G16: 61536.2
A17: 2.2.1 | B17: 安全文明施工费 | D17: 人工费+施工机具使用费+人工费+施工机具使用费 | F17: 9.05 | G17: 57412.64
A18: 2.2.2 | B18: 其它总价措施项目费 | D18: 人工费+施工机具使用费+人工费+施工机具使用费 | F18: 0.65 | G18: 4123.56
A19: 三 | B19: 总包服务费
A20: 四 | B20: 企业管理费 | D20: 人工费+施工机具使用费+人工费+施工机具使用费 | F20: 17.5 | G20: 111018.91
A21: 五 | B21: 利润 | D21: 人工费+施工机具使用费+人工费+施工机具使用费 | F21: 14.91 | G21: 94588.11
A22: 六 | B22: 规费 | D22: 人工费+施工机具使用费+人工费+施工机具使用费 | F22: 11.66 | G22: 73970.32
A23: 七 | B23: 索赔与现场签证
A24: 八 | B24: 安全技术服务费 | D24: 分部分项工程费+措施项目费+总包服务费+企业管理费+利润+规费-设备费 | F24: 0.12 | G24: 4573.59
A25: 九 | B25: 不含税工程造价 | D25: 分部分项工程费+措施项目费+总包服务费+企业管理费+利润+规费+索赔与现场签证+安全技术服务费 | G25: 3815896.2
A26: 十 | B26: 税前包干项目 | D26: 税前包干价
A27: 十一 | B27: 税金 | D27: 不含税工程造价+税前包干价 | F27: 3.5411 | G27: 135124.7
A28: 十二 | B28: 税后包干项目 | D28: 税后包干价
A29: 十四 | B29: 含税工程造价 | D29: 不含税工程造价+税金+税前包干项目+税后包干项目 | G29: 3951020.9
A31: 2 | B31: 工程造价 | D31: 专业造价总合计 | G31: 3951020.9
A36: 编制人: | C36: 审核人: | E36: 编制日期:

Sheet 电
A1: 单位工程直接费表
A2: 工程名称：室内电 | K2: 第 1 页 共 7 页
A3: 序号 | B3: 定额编号 | C3: 子目名称 | D3: 工程量 | G3: 价值（元） | I3: 其中（元） | O3: 工日统计
D4: 单位 | E4: 数量 | G4: 单价 | H4: 合价 | I4: 人工合价 | J4: 材料合价 | L4: 机械合价 | M4: 主材合价 | N4: 设备合价
C5: 强电 | H5: 757360.37 | I5: 560038.57 | J5: 163623.05 | L5: 33698.74 | M5: 2136450.2 | O5: 6797.6204
A6: 1 | B6: C4-1440 | C6: LED工矿灯 JR-GK003-K400 400W | D6: 10套 | E6: 10.4 | G6: 261.42 | H6: 2718.77 | I6: 2198.14 | J6: 520.62 | M6: 63024 | O6: 27.04
B7: 主材 | C7: LED工矿灯 JR-GK003-K400 400W | D7: 套 | E7: 105.04 | G7: 600 | H7: 63024 | M7: 63024
A8: 2 | B8: C4-1440 | C8: LED工矿灯 JR-GK003-K250 250W | D8: 10套 | E8: 26 | G8: 261.42 | H8: 6796.92 | I8: 5495.36 | J8: 1301.56 | M8: 118170 | O8: 67.6
B9: 主材 | C9: LED工矿灯 JR-GK003-K250 250W | D9: 套 | E9: 262.6 | G9: 450 | H9: 118170 | M9: 118170
A10: 3 | B10: C4-1440 | C10: LED工矿灯 JR-GK005-P50 50W | D10: 10套 | E10: 1.2 | G10: 261.42 | H10: 313.7 | I10: 253.63 | J10: 60.07 | M10: 3878.4 | O10: 3.12
B11: 主材 | C11: LED工矿灯 JR-GK005-P50 50W | D11: 套 | E11: 12.12 | G11: 320 | H11: 3878.4 | M11: 3878.4
A12: 4 | B12: C4-1440 | C12: LED工矿灯 JR-GK005-P80 80W | D12: 10套 | E12: 4.2 | G12: 261.42 | H12: 1097.96 | I12: 887.71 | J12: 210.25 | M12: 14847 | O12: 10.92
B13: 主材 | C13: LED工矿灯 JR-GK005-P80 80W | D13: 套 | E13: 42.42 | G13: 350 | H13: 14847 | M13: 14847
A14: 5 | B14: C4-1676 | C14: T5型单管荧光灯 （1X35W） | D14: 10套 | E14: 2.4 | G14: 220.47 | H14: 529.13 | I14: 353.57 | J14: 175.56 | M14: 2908.8 | O14: 4.344
B15: 主材 | C15: T5型单管荧光灯 （1X35W） | D15: 套 | E15: 24.24 | G15: 120 | H15: 2908.8 | M15: 2908.8
A16: 6 | B16: C4-1690 | C16: T5型三管格栅荧光灯 （3X35W） | D16: 10套 | E16: 1.5 | G16: 315.39 | H16: 473.09 | I16: 358.55 | J16: 114.54 | M16: 5454 | O16: 4.407
B17: 主材 | C17: T5型三管格栅荧光灯 （3X35W） | D17: 套 | E17: 15.15 | G17: 360 | H17: 5454 | M17: 5454
A18: 7 | B18: C4-1689 | C18: T5型双管格栅荧光灯 | D18: 10套 | E18: 47.9 | G18: 266.33 | H18: 12757.21 | I18: 9287.33 | J18: 3469.88 | M18: 116109.6 | O18: 114.1457
A19: 编制人: | F19: 审核人: | K19: 编制日期:
A20: 单位工程直接费表
A21: 工程名称：室内电 | K21: 第 2 页 共 7 页
A22: 序号 | B22: 定额编号 | C22: 子目名称 | D22: 工程量 | G22: 价值（元） | I22: 其中（元） | O22: 工日统计
D23: 单位 | E23: 数量 | G23: 单价 | H23: 合价 | I23: 人工合价 | J23: 材料合价 | L23: 机械合价 | M23: 主材合价 | N23: 设备合价
C24: （2X35W）
B25: 主材 | C25: T5型双管格栅荧光灯 （2X35W） | D25: 套 | E25: 483.79 | G25: 240 | H25: 116109.6 | M25: 116109.6
A26: 8 | B26: C4-1676 | C26: T5型单管荧光灯配控照型灯具 （1X35W） | D26: 10套 | E26: 15 | G26: 220.47 | H26: 3307.05 | I26: 2209.8 | J26: 1097.25 | M26: 19695 | O26: 27.15
B27: 主材 | C27: T5型单管荧光灯配控照型灯具 （1X35W） | D27: 套 | E27: 151.5 | G27: 130 | H27: 19695 | M27: 19695
A28: 9 | B28: C4-1676 | C28: T5型单管荧光灯配控照型灯具 （1X35W,自带180min蓄电池） | D28: 10套 | E28: 5.1 | G28: 220.47 | H28: 1124.4 | I28: 751.33 | J28: 373.07 | M28: 9271.8 | O28: 9.231
B29: 主材 | C29: T5型单管荧光灯配控照型灯具 （1X35W,自带180min蓄电池） | D29: 套 | E29: 51.51 | G29: 180 | H29: 9271.8 | M29: 9271.8
A30: 10 | B30: C4-1676 | C30: T5型双管荧光灯配控照型灯具 （2X35W,自带180min蓄电池） | D30: 10套 | E30: 3 | G30: 220.47 | H30: 661.41 | I30: 441.96 | J30: 219.45 | M30: 10908 | O30: 5.43
B31: 主材 | C31: T5型双管荧光灯配控照型灯具 （2X35W,自带180min蓄电池） | D31: 套 | E31: 30.3 | G31: 360 | H31: 10908 | M31: 10908
A32: 11 | B32: C4-1412 | C32: 节能吸顶灯 25W | D32: 10套 | E32: 22 | G32: 197.03 | H32: 4334.66 | I32: 3402.08 | J32: 932.58 | M32: 48884 | O32: 41.8
B33: 主材 | C33: 节能吸顶灯 25W | D33: 套 | E33: 222.2 | G33: 220 | H33: 48884 | M33: 48884
A34: 12 | B34: C4-1432 | C34: 双头应急灯 | D34: 10套 | E34: 7.4 | G34: 225.09 | H34: 1665.67 | I34: 1596.18 | J34: 69.49 | M34: 26906.4 | O34: 19.6248
B35: 主材 | C35: 双头应急灯 | D35: 套 | E35: 74.74 | G35: 360 | H35: 26906.4 | M35: 26906.4
A36: 13 | B36: C4-1622 | C36: 疏散指示灯（自带蓄电池） | D36: 10套 | E36: 7 | G36: 231.6 | H36: 1621.2 | I36: 1219.12 | J36: 402.08 | M36: 26159 | O36: 14.98
A37: 编制人: | F37: 审核人: | K37: 编制日期:
A38: 单位工程直接费表
A39: 工程名称：室内电 | K39: 第 3 页 共 7 页
A40: 序号 | B40: 定额编号 | C40: 子目名称 | D40: 工程量 | G40: 价值（元） | I40: 其中（元） | O40: 工日统计
D41: 单位 | E41: 数量 | G41: 单价 | H41: 合价 | I41: 人工合价 | J41: 材料合价 | L41: 机械合价 | M41: 主材合价 | N41: 设备合价
B42: 主材 | C42: 疏散指示灯（自带蓄电池） | D42: 套 | E42: 70.7 | G42: 370 | H42: 26159 | M42: 26159
A43: 14 | B43: C4-1622 | C43: 出口指示灯 | D43: 10套 | E43: 2.6 | G43: 231.6 | H43: 602.16 | I43: 452.82 | J43: 149.34 | M43: 9191 | O43: 5.564
B44: 主材 | C44: 出口指示灯 | D44: 套 | E44: 26.26 | G44: 350 | H44: 9191 | M44: 9191
A45: 15 | B45: C4-1440 | C45: 防水防潮灯 （1X18W节能灯） | D45: 10套 | E45: 8 | G45: 261.42 | H45: 2091.36 | I45: 1690.88 | J45: 400.48 | M45: 18584 | O45: 20.8
B46: 主材 | C46: 防水防潮灯 （1X18W节能灯） | D46: 套 | E46: 80.8 | G46: 230 | H46: 18584 | M46: 18584
A47: 16 | B47: C4-416 | C47: 二三孔组合插座 250V 10A | D47: 10套 | E47: 70 | G47: 69.02 | H47: 4831.4 | I47: 4218.2 | J47: 613.2 | M47: 24990 | O47: 49.28
B48: 主材 | C48: 二三孔组合插座 250V 10A | D48: 套 | E48: 714 | G48: 35 | H48: 24990 | M48: 24990
A49: 17 | B49: C4-1405 | C49: 空调隔离开关箱 | D49: 10个 | E49: 9 | G49: 36.36 | H49: 327.24 | I49: 281.97 | J49: 45.27 | M49: 91800 | O49: 3.456
B50: 主材 | C50: 空调隔离开关箱 | D50: 个 | E50: 91.8 | G50: 1000 | H50: 91800 | M50: 91800
A51: 18 | B51: C4-416 | C51: 空调三孔插座 250V 16A | D51: 10套 | E51: 4.2 | G51: 69.02 | H51: 289.88 | I51: 253.09 | J51: 36.79 | M51: 1927.8 | O51: 2.9568
B52: 主材 | C52: 空调三孔插座 250V 16A | D52: 套 | E52: 42.84 | G52: 45 | H52: 1927.8 | M52: 1927.8
A53: 19 | B53: C4-416 | C53: 单相两三孔安全型组合插座（烘手器）250V 16A | D53: 10套 | E53: 2.4 | G53: 69.02 | H53: 165.65 | I53: 144.62 | J53: 21.02 | M53: 807.84 | O53: 1.6896
B54: 主材 | C54: 单相两三孔安全型组合插座（烘手器）250V 16A | D54: 套 | E54: 24.48 | G54: 33 | H54: 807.84 | M54: 807.84
A55: 20 | B55: C4-382 | C55: 单联暗装翘板开关 250V,10A | D55: 10套 | E55: 13 | G55: 66.31 | H55: 862.03 | I55: 801.19 | J55: 60.84 | M55: 3315 | O55: 9.36
B56: 主材 | C56: 单联暗装翘板开关 | D56: 只 | E56: 132.6 | G56: 25 | H56: 3315 | M56: 3315
A57: 编制人: | F57: 审核人: | K57: 编制日期:
A58: 单位工程直接费表
A59: 工程名称：室内电 | K59: 第 4 页 共 7 页
A60: 序号 | B60: 定额编号 | C60: 子目名称 | D60: 工程量 | G60: 价值（元） | I60: 其中（元） | O60: 工日统计
D61: 单位 | E61: 数量 | G61: 单价 | H61: 合价 | I61: 人工合价 | J61: 材料合价 | L61: 机械合价 | M61: 主材合价 | N61: 设备合价
C62: 250V,10A
A63: 21 | B63: C4-383 | C63: 双联暗装翘板开关 250V,10A | D63: 10套 | E63: 20 | G63: 71.13 | H63: 1422.6 | I63: 1294.4 | J63: 128.2 | M63: 6732 | O63: 15.12
B64: 主材 | C64: 双联暗装翘板开关 250V,10A | D64: 只 | E64: 204 | G64: 33 | H64: 6732 | M64: 6732
A65: 22 | B65: C4-384 | C65: 三联暗装翘板开关 250V,10A | D65: 10套 | E65: 3 | G65: 75.96 | H65: 227.88 | I65: 203.43 | J65: 24.45 | M65: 1071 | O65: 2.376
B66: 主材 | C66: 三联暗装翘板开关 250V,10A | D66: 只 | E66: 30.6 | G66: 35 | H66: 1071 | M66: 1071
A67: 23 | B67: C4-382 | C67: 事故风机暗装翘板开关 （带指示标志） 250V,10A | D67: 10套 | E67: 0.4 | G67: 66.31 | H67: 26.52 | I67: 24.65 | J67: 1.87 | M67: 155.04 | O67: 0.288
B68: 主材 | C68: 事故风机暗装翘板开关 （带指示标志） 250V,10A | D68: 只 | E68: 4.08 | G68: 38 | H68: 155.04 | M68: 155.04
A69: 24 | B69: C4-187 | C69: 全浇筑多功能母线槽（三相五线）HTKC-3BF 3150A | D69: 10m | E69: 17 | G69: 1133.29 | H69: 19265.93 | I69: 11199.6 | J69: 5585.01 | L69: 2481.32 | M69: 148920 | O69: 137.7
B70: 主材 | C70: 全浇筑多功能母线槽（三相五线）HTKC-3BF 3150A | D70: m | E70: 17 | G70: 8760 | H70: 148920 | M70: 148920
A71: 25 | B71: C4-186 | C71: 全浇筑多功能母线槽（三相五线）HTKC-3BF 1600A | D71: 10m | E71: 61.5 | G71: 890.34 | H71: 54755.91 | I71: 29936.97 | J71: 17076.09 | L71: 7742.85 | M71: 295815 | O71: 368.0775
B72: 主材 | C72: 全浇筑多功能母线槽（三相五线）HTKC-3BF 1600A | D72: m | E72: 61.5 | G72: 4810 | H72: 295815 | M72: 295815
A73: 26 | B73: C4-185 | C73: 全浇筑多功能母线槽（三相五线）HTKC-3BF 1250A | D73: 10m | E73: 56 | G73: 663.34 | H73: 37147.04 | I73: 18173.12 | J73: 12298.16 | L73: 6675.76 | M73: 210000 | O73: 223.44
B74: 主材 | C74: 全浇筑多功能母线槽（ | D74: m | E74: 56 | G74: 3750 | H74: 210000 | M74: 210000
A75: 编制人: | F75: 审核人: | K75: 编制日期:
A76: 单位工程直接费表
A77: 工程名称：室内电 | K77: 第 5 页 共 7 页
A78: 序号 | B78: 定额编号 | C78: 子目名称 | D78: 工程量 | G78: 价值（元） | I78: 其中（元） | O78: 工日统计
D79: 单位 | E79: 数量 | G79: 单价 | H79: 合价 | I79: 人工合价 | J79: 材料合价 | L79: 机械合价 | M79: 主材合价 | N79: 设备合价
C80: 三相五线）HTKC-3BF 1250A
A81: 27 | B81: C4-185 | C81: 全浇筑多功能母线槽（三相五线）HTKC-3BF 1000A | D81: 10m | E81: 12 | G81: 663.34 | H81: 7960.08 | I81: 3894.24 | J81: 2635.32 | L81: 1430.52 | M81: 36000 | O81: 47.88
B82: 主材 | C82: 全浇筑多功能母线槽（三相五线）HTKC-3BF 1000A | D82: m | E82: 12 | G82: 3000 | H82: 36000 | M82: 36000
A83: 28 | B83: C4-184 | C83: 全浇筑多功能母线槽（三相五线）HTKC-3BF 800A | D83: 10m | E83: 42.5 | G83: 537.7 | H83: 22852.25 | I83: 11052.13 | J83: 7301.93 | L83: 4498.2 | M83: 102000 | O83: 135.83
B84: 主材 | C84: 全浇筑多功能母线槽（三相五线）HTKC-3BF 800A | D84: m | E84: 42.5 | G84: 2400 | H84: 102000 | M84: 102000
A85: 29 | B85: C4-184 | C85: 全浇筑多功能母线槽（三相五线）HTKC-3BF 630A | D85: 10m | E85: 30 | G85: 537.7 | H85: 16131 | I85: 7801.5 | J85: 5154.3 | L85: 3175.2 | M85: 56700 | O85: 95.88
B86: 主材 | C86: 全浇筑多功能母线槽（三相五线）HTKC-3BF 630A | D86: m | E86: 30 | G86: 1890 | H86: 56700 | M86: 56700
A87: 30 | B87: C4-1237 | C87: 电缆桥架 500x150 | D87: 10m | E87: 10 | G87: 387.11 | H87: 3871.1 | I87: 3318.4 | J87: 376.9 | L87: 175.8 | M87: 13457 | O87: 40.8
B88: 主材 | C88: 电缆桥架 500x150 | D88: m | E88: 100.5 | G88: 133.9 | H88: 13456.95 | M88: 13456.95
A89: 31 | B89: C4-1237 | C89: 电缆桥架 400x150 | D89: 10m | E89: 20 | G89: 387.11 | H89: 7742.2 | I89: 6636.8 | J89: 753.8 | L89: 351.6 | M89: 22954.2 | O89: 81.6
B90: 主材 | C90: 电缆桥架 400x150 | D90: m | E90: 201 | G90: 114.2 | H90: 22954.2 | M90: 22954.2
A91: 32 | B91: C4-1237 | C91: 电缆桥架 300x150 | D91: 10m | E91: 90 | G91: 387.11 | H91: 34839.9 | I91: 29865.6 | J91: 3392.1 | L91: 1582.2 | M91: 72360 | O91: 367.2
B92: 主材 | C92: 电缆桥架 300x150 | D92: m | E92: 904.5 | G92: 80 | H92: 72360 | M92: 72360
A93: 33 | B93: C4-1236 | C93: 电缆桥架 200x100 | D93: 10m | E93: 250 | G93: 251.25 | H93: 62812.5 | I93: 51620 | J93: 8535 | L93: 2657.5 | M93: 151252.5 | O93: 635
B94: 主材 | C94: 电缆桥架 200x100 | D94: m | E94: 2512.5 | G94: 60.2 | H94: 151252.5 | M94: 151252.5
A95: 34 | B95: C4-722 | C95: 电缆 YJV-1KV-3X185+2X95 | D95: 100m | E95: 1 | G95: 1828.84 | H95: 1828.84 | I95: 1083.78 | J95: 395.93 | L95: 349.13 | M95: 40256.58 | O95: 14.3
A96: 编制人: | F96: 审核人: | K96: 编制日期:
A97: 单位工程直接费表
A98: 工程名称：室内电 | K98: 第 6 页 共 7 页
A99: 序号 | B99: 定额编号 | C99: 子目名称 | D99: 工程量 | G99: 价值（元） | I99: 其中（元） | O99: 工日统计
D100: 单位 | E100: 数量 | G100: 单价 | H100: 合价 | I100: 人工合价 | J100: 材料合价 | L100: 机械合价 | M100: 主材合价 | N100: 设备合价
...

Sheet 电设
A1: 附表1-6
A2: 新增主要公用设备表
J3: 单位：万元
A4: 序号 | B4: 总图编号 | C4: 设备名称 | D4: 型号规格 | E4: 单位 | F4: 数量 | G4: 单价 | H4: 合计 | I4: 安装费 | J4: 备注
A6: 1 | C6: 干式变压器 | D6: SCB11-10/0.4 2000kVA | E6: 台 | F6: 1 | G6: 28 | H6: =F6*G6 -> 28 | I6: =H6*0.1 -> 2.8
A7: 2 | C7: 干式变压器 | D7: SCB11-10/0.4 1600kVA | E7: 台 | F7: 2 | G7: 22 | H7: =F7*G7 -> 44 | I7: =H7*0.1 -> 4.4
A8: 3 | C8: 干式变压器 | D8: SCB11-10/0.4 1000kVA | E8: 台 | F8: 4 | G8: 18 | H8: =F8*G8 -> 72 | I8: =H8*0.1 -> 7.2
A9: 4 | C9: 高压开关柜 | D9: KYN28A-12 | E9: 台 | F9: 16 | G9: 3 | H9: =F9*G9 -> 48 | I9: =H9*0.1 -> 4.8
A10: 5 | C10: 高压环网柜 | D10: SV1-C-12 | E10: 台 | F10: 6 | G10: 3.5 | H10: =F10*G10 -> 21 | I10: =H10*0.1 -> 2.1
A11: 6 | C11: 低压配电柜 | D11: GCS型 | E11: 台 | F11: 37 | G11: 2 | H11: =F11*G11 -> 74 | I11: =H11*0.1 -> 7.4
A12: 7 | C12: 照明配电箱 | D12: XRM301 | E12: 台 | F12: 26 | G12: 0.5 | H12: =F12*G12 -> 13 | I12: =H12*0.1 -> 1.3
A13: 8 | C13: 照明控制箱 | E13: 台 | F13: 8 | G13: 0.6 | H13: =F13*G13 -> 4.8 | I13: =H13*0.1 -> 0.48
A14: 9 | C14: 事故照明配电箱 | E14: 台 | F14: 6 | G14: 0.65 | H14: =F14*G14 -> 3.9 | I14: =H14*0.1 -> 0.39
A15: 10 | C15: 双电源自动切换箱 | E15: 台 | F15: 6 | G15: 2.1 | H15: =F15*G15 -> 12.6 | I15: =H15*0.1 -> 1.26
A16: 11 | C16: 动力配电柜 | D16: XL52 | E16: 台 | F16: 78 | G16: 3 | H16: =F16*G16 -> 234 | I16: =H16*0.1 -> 23.4
A17: 12 | C17: 动力配电箱 | D17: XL53 | E17: 台 | F17: 20 | G17: 1 | H17: =F17*G17 -> 20 | I17: =H17*0.1 -> 2
C58: 合计 | F58: =SUM(F6:F57) -> 210 | H58: =SUM(H6:H57) -> 575.3 | I58: =SUM(I6:I57) -> 57.53

Sheet 动费
A1: 单位工程费用汇总表
A2: 工程名称：动力 | E2: 第 1 页 共 1 页
A3: 序号 | B3: 费用名称 | D3: 取费基数 | F3: 费率 | G3: 费用金额
A4: 1 | B4: 安装工程 | D4: 安装工程 | G4: 583246.05
A5: 一 | B5: 分部分项工程费 | D5: 人工费+材料费+未计价材料费+施工机具使用费+设备费 | F5: 103 | G5: 520359.5
A6: 1 | B6: 人工费 | D6: 人工费 | G6: 75560.23
A7: 2 | B7: 材料费 | D7: 材料费 | G7: 3830.83
A8: 3 | B8: 未计价材料费 | D8: 主材费 | G8: 422770.32
A9: 4 | B9: 施工机具使用费 | D9: 机械费 | G9: 3042.02
A10: 5 | B10: 设备费 | D10: 设备费
A11: 二 | B11: 措施项目费 | D11: 单价措施项目费+总价措施项目费 | G11: 7624.41
A12: 2.1 | B12: 单价措施项目费 | D12: 人工费+材料费+施工机具使用费
A13: 2.1.1 | B13: 人工费 | D13: 技术措施项目人工费
A14: 2.1.2 | B14: 材料费 | D14: 技术措施项目材料费
A15: 2.1.3 | B15: 施工机具使用费 | D15: 技术措施项目机械费
A16: 2.2 | B16: 总价措施项目费 | D16: 安全文明施工费+其它总价措施项目费 | G16: 7624.41
A17: 2.2.1 | B17: 安全文明施工费 | D17: 人工费+施工机具使用费+人工费+施工机具使用费 | F17: 9.05 | G17: 7113.5
A18: 2.2.2 | B18: 其它总价措施项目费 | D18: 人工费+施工机具使用费+人工费+施工机具使用费 | F18: 0.65 | G18: 510.91
A19: 三 | B19: 总包服务费
A20: 四 | B20: 企业管理费 | D20: 人工费+施工机具使用费+人工费+施工机具使用费 | F20: 17.5 | G20: 13755.39
A21: 五 | B21: 利润 | D21: 人工费+施工机具使用费+人工费+施工机具使用费 | F21: 14.91 | G21: 11719.6
A22: 六 | B22: 规费 | D22: 人工费+施工机具使用费+人工费+施工机具使用费 | F22: 11.66 | G22: 9165.02
A23: 七 | B23: 索赔与现场签证
A24: 八 | B24: 安全技术服务费 | D24: 分部分项工程费+措施项目费+总包服务费+企业管理费+利润+规费-设备费 | F24: 0.12 | G24: 675.15
A25: 九 | B25: 不含税工程造价 | D25: 分部分项工程费+措施项目费+总包服务费+企业管理费+利润+规费+索赔与现场签证+安全技术服务费 | G25: 563299.07
A26: 十 | B26: 税前包干项目 | D26: 税前包干价
A27: 十一 | B27: 税金 | D27: 不含税工程造价+税前包干价 | F27: 3.5411 | G27: 19946.98
A28: 十二 | B28: 税后包干项目 | D28: 税后包干价
A29: 十四 | B29: 含税工程造价 | D29: 不含税工程造价+税金+税前包干项目+税后包干项目 | G29: 583246.05
A31: 2 | B31: 工程造价 | D31: 专业造价总合计 | G31: 583246.05
A36: 编制人: | C36: 审核人: | E36: 编制日期:

Sheet 动
A1: 单位工程直接费表
A2: 工程名称：动力 | K2: 第 1 页 共 6 页
A3: 序号 | B3: 定额编号 | C3: 子目名称 | D3: 工程量 | G3: 价值（元） | I3: 其中（元） | O3: 工日统计
D4: 单位 | E4: 数量 | G4: 单价 | H4: 合价 | I4: 人工合价 | J4: 材料合价 | L4: 机械合价 | M4: 主材合价 | N4: 设备合价
C5: 压缩空气管道 | H5: 35040.66 | I5: 33137.05 | J5: 1072.6 | L5: 831.01 | M5: 229306 | O5: 401.082
A6: 1 | B6: C8-11 | C6: 无缝钢管 %%C219X6 | D6: 10m | E6: 8 | G6: 131.15 | H6: 1049.2 | I6: 1020 | J6: 19.2 | L6: 10 | M6: 12400 | O6: 12.384
B7: 主材 | C7: 无缝钢管 %%C219X6 | D7: m | E7: 80 | G7: 155 | H7: 12400 | M7: 12400
A8: 2 | B8: C8-11 | C8: 无缝钢管 133X5 | D8: 10m | E8: 110 | G8: 131.15 | H8: 14426.5 | I8: 14025 | J8: 264 | L8: 137.5 | M8: 91300 | O8: 170.28
B9: 主材 | C9: 无缝钢管 133X5 | D9: m | E9: 1100 | G9: 83 | H9: 91300 | M9: 91300
A10: 3 | B10: C8-10 | C10: 无缝钢管 108X4 | D10: 10m | E10: 25 | G10: 111.82 | H10: 2795.5 | I10: 2719.25 | J10: 52 | L10: 24.25 | M10: 18075 | O10: 33
B11: 主材 | C11: 无缝钢管 108X4 | D11: m | E11: 250 | G11: 72.3 | H11: 18075 | M11: 18075
A12: 4 | B12: C8-9 | C12: 无缝钢管 %%C89X4 | D12: 10m | E12: 130 | G12: 94.56 | H12: 12292.8 | I12: 11970.4 | J12: 232.7 | L12: 89.7 | M12: 74620 | O12: 145.21
B13: 主材 | C13: 无缝钢管 %%C89X4 | D13: m | E13: 1300 | G13: 57.4 | H13: 74620 | M13: 74620
A14: 5 | B14: C8-1422 | C14: 截止阀 J41H-16C DN200 PN1.6 | D14: 个 | E14: 2 | G14: 208.29 | H14: 416.58 | I14: 268.8 | J14: 30.36 | L14: 117.42 | M14: 4600 | O14: 3.262
B15: 主材 | C15: 截止阀 J41H-16C DN200 PN1.6 | D15: 个 | E15: 2 | G15: 2300 | H15: 4600 | M15: 4600
A16: 6 | B16: C8-1420 | C16: 截止阀 J41H-16C DN125 PN1.6 | D16: 个 | E16: 10 | G16: 96.72 | H16: 967.2 | I16: 747.4 | J16: 102.4 | L16: 117.4 | M16: 9600 | O16: 9.07
B17: 主材 | C17: 截止阀 J41H-16C DN125 PN1.6 | D17: 个 | E17: 10 | G17: 960 | H17: 9600 | M17: 9600
A18: 7 | B18: C6-78 | C18: DY型数字式涡旋流量计 DN150 | D18: 台 | E18: 1 | G18: 515.48 | H18: 515.48 | I18: 397.7 | J18: 61.99 | L18: 55.79 | M18: 5346 | O18: 4.646
B19: 主材 | C19: DY型数字式涡旋流量计 DN150 | D19: 台 | E19: 1 | G19: 5346 | H19: 5346 | M19: 5346
A20: 8 | B20: C6-78 | C20: DY型数字式涡旋流量计 DN80 | D20: 台 | E20: 5 | G20: 515.48 | H20: 2577.4 | I20: 1988.5 | J20: 309.95 | L20: 278.95 | M20: 13365 | O20: 23.23
B21: 主材 | C21: DY型数字式涡旋流量计 | D21: 台 | E21: 5 | G21: 2673 | H21: 13365 | M21: 13365
A22: 编制人: | F22: 审核人: | K22: 编制日期:
A23: 单位工程直接费表
A24: 工程名称：动力 | K24: 第 2 页 共 6 页
A25: 序号 | B25: 定额编号 | C25: 子目名称 | D25: 工程量 | G25: 价值（元） | I25: 其中（元） | O25: 工日统计
D26: 单位 | E26: 数量 | G26: 单价 | H26: 合价 | I26: 人工合价 | J26: 材料合价 | L26: 机械合价 | M26: 主材合价 | N26: 设备合价
C27: DN80
C28: 氩气 | H28: 2327.75 | I28: 2259.16 | J28: 48.3 | L28: 20.29 | M28: 12715.9 | O28: 27.4215
A29: 1 | B29: C8-9 | C29: 无缝钢管 %%C89X4 | D29: 10m | E29: 3 | G29: 94.56 | H29: 283.68 | I29: 276.24 | J29: 5.37 | L29: 2.07 | M29: 1722 | O29: 3.351
B30: 主材 | C30: 无缝钢管 %%C89X4 | D30: m | E30: 30 | G30: 57.4 | H30: 1722 | M30: 1722
A31: 2 | B31: C8-8 | C31: 无缝钢管 %%C76X4 | D31: 10m | E31: 13 | G31: 83.9 | H31: 1090.7 | I31: 1064.44 | J31: 19.11 | L31: 7.15 | M31: 6266 | O31: 12.922
B32: 主材 | C32: 无缝钢管 %%C76X4 | D32: m | E32: 130 | G32: 48.2 | H32: 6266 | M32: 6266
A33: 3 | B33: C8-7 | C33: 无缝钢管 %%C60X4 | D33: 10m | E33: 4.7 | G33: 71.35 | H33: 335.35 | I33: 327.03 | J33: 6.06 | L33: 2.26 | M33: 1677.9 | O33: 3.9715
B34: 主材 | C34: 无缝钢管 %%C60X4 | D34: m | E34: 47 | G34: 35.7 | H34: 1677.9 | M34: 1677.9
A35: 4 | B35: C8-6 | C35: 无缝钢管 %%C48X3 | D35: 10m | E35: 10 | G35: 56.03 | H35: 560.3 | I35: 547.2 | J35: 11.1 | L35: 2 | M35: 2630 | O35: 6.64
B36: 主材 | C36: 无缝钢管 %%C48X3 | D36: m | E36: 100 | G36: 26.3 | H36: 2630 | M36: 2630
A37: 5 | B37: C8-1418 | C37: 截止阀 J41H-16C DN80 PN1.6MPa | D37: 个 | E37: 1 | G37: 57.72 | H37: 57.72 | I37: 44.25 | J37: 6.66 | L37: 6.81 | M37: 420 | O37: 0.537
B38: 主材 | C38: 截止阀 J41H-16C DN80 PN1.6MPa | D38: 个 | E38: 1 | G38: 420 | H38: 420 | M38: 420
C39: 氮气 | H39: 2727.02 | I39: 2634.22 | J39: 61.18 | L39: 31.62 | M39: 14714 | O39: 31.98
A40: 1 | B40: C8-9 | C40: 无缝钢管 %%C89X4 | D40: 10m | E40: 8 | G40: 94.56 | H40: 756.48 | I40: 736.64 | J40: 14.32 | L40: 5.52 | M40: 4592 | O40: 8.936
B41: 主材 | C41: 无缝钢管 %%C89X4 | D41: m | E41: 80 | G41: 57.4 | H41: 4592 | M41: 4592
A42: 2 | B42: C8-7 | C42: 无缝钢管 %%C60X4 | D42: 10m | E42: 26 | G42: 71.35 | H42: 1855.1 | I42: 1809.08 | J42: 33.54 | L42: 12.48 | M42: 9282 | O42: 21.97
B43: 主材 | C43: 无缝钢管 %%C60X4 | D43: m | E43: 260 | G43: 35.7 | H43: 9282 | M43: 9282
A44: 3 | B44: C8-1418 | C44: 截止阀 J41H-16C DN80 PN1.6MPa | D44: 个 | E44: 2 | G44: 57.72 | H44: 115.44 | I44: 88.5 | J44: 13.32 | L44: 13.62 | M44: 840 | O44: 1.074
B45: 主材 | C45: 截止阀 J41H-16C DN80 PN1.6MPa | D45: 个 | E45: 2 | G45: 420 | H45: 840 | M45: 840
A46: 编制人: | F46: 审核人: | K46: 编制日期:
A47: 单位工程直接费表
A48: 工程名称：动力 | K48: 第 3 页 共 6 页
A49: 序号 | B49: 定额编号 | C49: 子目名称 | D49: 工程量 | G49: 价值（元） | I49: 其中（元） | O49: 工日统计
D50: 单位 | E50: 数量 | G50: 单价 | H50: 合价 | I50: 人工合价 | J50: 材料合价 | L50: 机械合价 | M50: 主材合价 | N50: 设备合价
C51: 二氧化碳 | H51: 11572.95 | I51: 10539.48 | J51: 588.03 | L51: 445.44 | M51: 47680.6 | O51: 126.8462
A52: 1 | B52: C8-8 | C52: 无缝钢管 %%C76X4 | D52: 10m | E52: 2.8 | G52: 83.9 | H52: 234.92 | I52: 229.26 | J52: 4.12 | L52: 1.54 | M52: 1349.6 | O52: 2.7832
B53: 主材 | C53: 无缝钢管 %%C76X4 | D53: m | E53: 28 | G53: 48.2 | H53: 1349.6 | M53: 1349.6
A54: 2 | B54: C8-7 | C54: 无缝钢管 %%C60X4 | D54: 10m | E54: 45 | G54: 71.35 | H54: 3210.75 | I54: 3131.1 | J54: 58.05 | L54: 21.6 | M54: 16065 | O54: 38.025
B55: 主材 | C55: 无缝钢管 %%C60X4 | D55: m | E55: 450 | G55: 35.7 | H55: 16065 | M55: 16065
A56: 3 | B56: C8-6 | C56: 无缝钢管 %%C48X3 | D56: 10m | E56: 82 | G56: 56.03 | H56: 4594.46 | I56: 4487.04 | J56: 91.02 | L56: 16.4 | M56: 21566 | O56: 54.448
B57: 主材 | C57: 无缝钢管 %%C48X3 | D57: m | E57: 820 | G57: 26.3 | H57: 21566 | M57: 21566
A58: 4 | B58: C8-1417 | C58: 截止阀 J41H-16C DN65 PN1.6MPa | D58: 个 | E58: 2 | G58: 48.87 | H58: 97.74 | I58: 73.68 | J58: 11.4 | L58: 12.66 | M58: 620 | O58: 0.894
B59: 主材 | C59: 截止阀 J41H-16C DN65 PN1.6MPa | D59: 个 | E59: 2 | G59: 310 | H59: 620 | M59: 620
A60: 5 | B60: C8-1416 | C60: 截止阀 J41H-16C DN50 PN1.6MPa | D60: 个 | E60: 10 | G60: 34.22 | H60: 342.2 | I60: 232.2 | J60: 51.5 | L60: 58.5 | M60: 2300 | O60: 2.82
B61: 主材 | C61: 截止阀 J41H-16C DN50 PN1.6MPa | D61: 个 | E61: 10 | G61: 230 | H61: 2300 | M61: 2300
A62: 6 | B62: C6-78 | C62: DY型数字式涡旋流量计 DN50 | D62: 台 | E62: 1 | G62: 515.48 | H62: 515.48 | I62: 397.7 | J62: 61.99 | L62: 55.79 | M62: 1080 | O62: 4.646
B63: 主材 | C63: DY型数字式涡旋流量计 DN50 | D63: 台 | E63: 1 | G63: 1080 | H63: 1080 | M63: 1080
A64: 7 | B64: C6-78 | C64: DY型数字式涡旋流量计 DN40 | D64: 台 | E64: 5 | G64: 515.48 | H64: 2577.4 | I64: 1988.5 | J64: 309.95 | L64: 278.95 | M64: 4700 | O64: 23.23
B65: 主材 | C65: DY型数字式涡旋流量计 DN40 | D65: 台 | E65: 5 | G65: 940 | H65: 4700 | M65: 4700
C66: 氧气 | H66: 11605.49 | I66: 10561.66 | J66: 590.32 | L66: 453.51 | M66: 48206.66 | O66: 127.1154
A67: 编制人: | F67: 审核人: | K67: 编制日期:
A68: 单位工程直接费表
A69: 工程名称：动力 | K69: 第 4 页 共 6 页
A70: 序号 | B70: 定额编号 | C70: 子目名称 | D70: 工程量 | G70: 价值（元） | I70: 其中（元） | O70: 工日统计
D71: 单位 | E71: 数量 | G71: 单价 | H71: 合价 | I71: 人工合价 | J71: 材料合价 | L71: 机械合价 | M71: 主材合价 | N71: 设备合价
A72: 1 | B72: C8-116 | C72: 不锈钢管 %%C76X4 | D72: 10m | E72: 0.2 | G72: 162.69 | H72: 32.54 | I72: 22.18 | J72: 2.29 | L72: 8.07 | M72: 526.06 | O72: 0.2692
B73: 主材 | C73: 不锈钢管 %%C76X4 | D73: m | E73: 1.906 | G73: 276 | H73: 526.06 | M73: 526.06
A74: 2 | B74: C8-8 | C74: 无缝钢管 %%C76X4 | D74: 10m | E74: 2.8 | G74: 83.9 | H74: 234.92 | I74: 229.26 | J74: 4.12 | L74: 1.54 | M74: 1349.6 | O74: 2.7832
B75: 主材 | C75: 无缝钢管 %%C76X4 | D75: m | E75: 28 | G75: 48.2 | H75: 1349.6 | M75: 1349.6
A76: 3 | B76: C8-7 | C76: 无缝钢管 %%C60X4 | D76: 10m | E76: 45 | G76: 71.35 | H76: 3210.75 | I76: 3131.1 | J76: 58.05 | L76: 21.6 | M76: 16065 | O76: 38.025
B77: 主材 | C77: 无缝钢管 %%C60X4 | D77: m | E77: 450 | G77: 35.7 | H77: 16065 | M77: 16065
A78: 4 | B78: C8-6 | C78: 无缝钢管 %%C48X3 | D78: 10m | E78: 82 | G78: 56.03 | H78: 4594.46 | I78: 4487.04 | J78: 91.02 | L78: 16.4 | M78: 21566 | O78: 54.448
B79: 主材 | C79: 无缝钢管 %%C48X3 | D79: m | E79: 820 | G79: 26.3 | H79: 21566 | M79: 21566
A80: 5 | B80: C8-1417 | C80: 截止阀 J41H-16C DN65 PN1.6MPa | D80: 个 | E80: 2 | G80: 48.87 | H80: 97.74 | I80: 73.68 | J80: 11.4 | L80: 12.66 | M80: 620 | O80: 0.894
B81: 主材 | C81: 截止阀 J41H-16C DN65 PN1.6MPa | D81: 个 | E81: 2 | G81: 310 | H81: 620 | M81: 620
A82: 6 | B82: C8-1416 | C82: 截止阀 J41H-16C DN50 PN1.6MPa | D82: 个 | E82: 10 | G82: 34.22 | H82: 342.2 | I82: 232.2 | J82: 51.5 | L82: 58.5 | M82: 2300 | O82: 2.82
B83: 主材 | C83: 截止阀 J41H-16C DN50 PN1.6MPa | D83: 个 | E83: 10 | G83: 230 | H83: 2300 | M83: 2300
A84: 7 | B84: C6-78 | C84: DY型数字式涡旋流量计 DN50 | D84: 台 | E84: 1 | G84: 515.48 | H84: 515.48 | I84: 397.7 | J84: 61.99 | L84: 55.79 | M84: 1080 | O84: 4.646
B85: 主材 | C85: DY型数字式涡旋流量计 DN50 | D85: 台 | E85: 1 | G85: 1080 | H85: 1080 | M85: 1080
A86: 8 | B86: C6-78 | C86: DY型数字式涡旋流量计 DN40 | D86: 台 | E86: 5 | G86: 515.48 | H86: 2577.4 | I86: 1988.5 | J86: 309.95 | L86: 278.95 | M86: 4700 | O86: 23.23
B87: 主材 | C87: DY型数字式涡旋流量计 DN40 | D87: 台 | E87: 5 | G87: 940 | H87: 4700 | M87: 4700
A88: 编制人: | F88: 审核人: | K88: 编制日期:
A89: 单位工程直接费表
A90: 工程名称：动力 | K90: 第 5 页 共 6 页
A91: 序号 | B91: 定额编号 | C91: 子目名称 | D91: 工程量 | G91: 价值（元） | I91: 其中（元） | O91: 工日统计
D92: 单位 | E92: 数量 | G92: 单价 | H92: 合价 | I92: 人工合价 | J92: 材料合价 | L92: 机械合价 | M92: 主材合价 | N92: 设备合价
C93: 天然气 | H93: 16511.56 | I93: 14356.66 | J93: 1175.1 | L93: 979.8 | M93: 60947.16 | O93: 171.5472
A94: 1 | B94: C8-8 | C94: 无缝钢管 %%C76X4 | D94: 10m | E94: 2.8 | G94: 83.9 | H94: 234.92 | I94: 229.26 | J94: 4.12 | L94: 1.54 | M94: 1349.6 | O94: 2.7832
B95: 主材 | C95: 无缝钢管 %%C76X4 | D95: m | E95: 28 | G95: 48.2 | H95: 1349.6 | M95: 1349.6
A96: 2 | B96: C8-7 | C96: 无缝钢管 %%C60X4 | D96: 10m | E96: 45 | G96: 71.35 | H96: 3210.75 | I96: 3131.1 | J96: 58.05 | L96: 21.6 | M96: 16065 | O96: 38.025
B97: 主材 | C97: 无缝钢管 %%C60X4 | D97: m | E97: 450 | G97: 35.7 | H97: 16065 | M97: 16065
A98: 3 | B98: C8-6 | C98: 无缝钢管 %%C48X3 | D98: 10m | E98: 82 | G98: 56.03 | H98: 4594.46 | I98: 4487.04 | J98: 91.02 | L98: 16.4 | M98: 21566 | O98: 54.448
B99: 主材 | C99: 无缝钢管 %%C48X3 | D99: m | E99: 820 | G99: 26.3 | H99: 21566 | M99: 21566
A100: 4 | B100: C8-114 | C100: 不锈钢管 %%C48X3 | D100: 10m | E100: 2 | G100: 94.24 | H100: 188.48 | I100: 160.52 | J100: 13.74 | L100: 14.22 | M100: 2376.56 | O100: 1.948
...

Sheet 动设
A1: 附表1-6
A2: 新增主要公用设备表
I3: 单位：万元
A4: 序号 | B4: 设备名称 | C4: 型号规格 | D4: 单位 | E4: 数量 | F4: 单价 | G4: 合计 | H4: 安装费 | I4: 备注
A6: 1 | B6: 压缩空气配气器 | C6: 4接头φ168X6 | D6: 套 | E6: 78 | F6: 0.037 | G6: =F6*E6 -> 2.886 | H6: =G6*0.1 -> 0.2886
A7: 2 | B7: 氩气配气器 | C7: 4接头φ60X4 | D7: 个 | E7: 8 | F7: 0.5 | G7: =F7*E7 -> 4 | H7: =G7*0.1 -> 0.4
A8: 3 | B8: 氮气配气器 | C8: 4接头φ60X4 | D8: 个 | E8: 12 | F8: 0.7 | G8: =F8*E8 -> 8.4 | H8: =G8*0.1 -> 0.84
A9: 4 | B9: 二氧化碳配气器 | C9: 4接头φ89X4 | D9: 个 | E9: 14 | F9: 0.85 | G9: =F9*E9 -> 11.9 | H9: =G9*0.1 -> 1.19
A10: 5 | B10: 二氧化碳配气器 | C10: 8接头φ89X4 | D10: 个 | E10: 12 | F10: 1 | G10: =F10*E10 -> 12 | H10: =G10*0.1 -> 1.2
A11: 6 | B11: 氧气配气器 | C11: 4接头φ89X4 | D11: 套 | E11: 14 | F11: 0.77 | G11: =F11*E11 -> 10.78 | H11: =G11*0.1 -> 1.078
A12: 7 | B12: 氧气配气器 | C12: 8接头φ89X4 | D12: 套 | E12: 12 | F12: 1.1 | G12: =F12*E12 -> 13.2 | H12: =G12*0.1 -> 1.32
A13: 8 | B13: 天然气配气器 | C13: 4接头φ114X4.5 | D13: 套 | E13: 14 | F13: 0.65 | G13: =F13*E13 -> 9.1 | H13: =G13*0.1 -> 0.91
A14: 9 | B14: 天然气配气器 | C14: 8接头φ114X4.5 | D14: 套 | E14: 12 | F14: 0.9 | G14: =F14*E14 -> 10.8 | H14: =G14*0.1 -> 1.08
A15: 10 | B15: LD1000系列冷冻式干燥器（风冷） | C15: 处理量：105m3/min；功率：25kw | D15: 套 | E15: 1 | F15: 0.3 | G15: =F15*E15 -> 0.3 | H15: =G15*0.1 -> 0.03
A16: 11 | B16: 压缩空气除油净化器 | C16: J100 处理量：100m3/min | D16: 套 | E16: 1 | F16: 0.2 | G16: =F16*E16 -> 0.2 | H16: =G16*0.1 -> 0.02
B58: 合计 | E58: =SUM(E6:E57) -> 178 | G58: =SUM(G6:G57) -> 83.566 | H58: =SUM(H6:H57) -> 8.3566

Sheet 室外水费
A1: 单位工程费用汇总表
A2: 工程名称：室外水 | E2: 第 1 页 共 1 页
A3: 序号 | B3: 费用名称 | D3: 取费基数 | F3: 费率 | G3: 费用金额
A4: 1 | B4: 安装工程 | D4: 安装工程 | G4: 677995.89
A5: 一 | B5: 分部分项工程费 | D5: 人工费+材料费+未计价材料费+施工机具使用费+设备费 | G5: 606605.43
A6: 1 | B6: 人工费 | D6: 人工费 | G6: 83845.81
A7: 2 | B7: 材料费 | D7: 材料费 | G7: 14735.52
A8: 3 | B8: 未计价材料费 | D8: 主材费 | G8: 503682.81
A9: 4 | B9: 施工机具使用费 | D9: 机械费 | G9: 4341.29
A10: 5 | B10: 设备费 | D10: 设备费
A11: 二 | B11: 措施项目费 | D11: 单价措施项目费+总价措施项目费 | G11: 8554.15
A12: 2.1 | B12: 单价措施项目费 | D12: 人工费+材料费+施工机具使用费
A13: 2.1.1 | B13: 人工费 | D13: 技术措施项目人工费
A14: 2.1.2 | B14: 材料费 | D14: 技术措施项目材料费
A15: 2.1.3 | B15: 施工机具使用费 | D15: 技术措施项目机械费
A16: 2.2 | B16: 总价措施项目费 | D16: 安全文明施工费+其它总价措施项目费 | G16: 8554.15
A17: 2.2.1 | B17: 安全文明施工费 | D17: 人工费+施工机具使用费+人工费+施工机具使用费 | F17: 9.05 | G17: 7980.93
A18: 2.2.2 | B18: 其它总价措施项目费 | D18: 人工费+施工机具使用费+人工费+施工机具使用费 | F18: 0.65 | G18: 573.22
A19: 三 | B19: 总包服务费
A20: 四 | B20: 企业管理费 | D20: 人工费+施工机具使用费+人工费+施工机具使用费 | F20: 17.5 | G20: 15432.74
A21: 五 | B21: 利润 | D21: 人工费+施工机具使用费+人工费+施工机具使用费 | F21: 14.91 | G21: 13148.7
A22: 六 | B22: 规费 | D22: 人工费+施工机具使用费+人工费+施工机具使用费 | F22: 11.66 | G22: 10282.62
A23: 七 | B23: 索赔与现场签证
A24: 八 | B24: 安全技术服务费 | D24: 分部分项工程费+措施项目费+总包服务费+企业管理费+利润+规费-设备费 | F24: 0.12 | G24: 784.83
A25: 九 | B25: 不含税工程造价 | D25: 分部分项工程费+措施项目费+总包服务费+企业管理费+利润+规费+索赔与现场签证+安全技术服务费 | G25: 654808.47
A26: 十 | B26: 税前包干项目 | D26: 税前包干价
A27: 十一 | B27: 税金 | D27: 不含税工程造价+税前包干价 | F27: 3.5411 | G27: 23187.42
A28: 十二 | B28: 税后包干项目 | D28: 税后包干价
A29: 十四 | B29: 含税工程造价 | D29: 不含税工程造价+税金+税前包干项目+税后包干项目 | G29: 677995.89
A31: 2 | B31: 工程造价 | D31: 专业造价总合计 | G31: 677995.89
A36: 编制人: | C36: 审核人: | E36: 编制日期:

Sheet 室外水
A1: 单位工程直接费表
A2: 工程名称：室外水 | K2: 第 1 页 共 2 页
A3: 序号 | B3: 定额编号 | C3: 子目名称 | D3: 工程量 | G3: 价值（元） | I3: 其中（元） | O3: 工日统计
D4: 单位 | E4: 数量 | G4: 单价 | H4: 合价 | I4: 人工合价 | J4: 材料合价 | L4: 机械合价 | M4: 主材合价 | N4: 设备合价
A5: 1 | B5: C10-231 | C5: 球墨铸铁给水管 DN100 | D5: 10m | E5: 21 | G5: 150.9 | H5: 3168.9 | I5: 2744.28 | J5: 395.01 | L5: 29.61 | M5: 17220 | O5: 33.306
B6: 主材 | C6: 球墨铸铁给水管 DN100 | D6: m | E6: 210 | G6: 82 | H6: 17220 | M6: 17220
A7: 2 | B7: C12-53 | C7: 管道刷油 红丹防锈漆 第一遍 | D7: 10m2 | E7: 6.5982 | G7: 42.71 | H7: 281.81 | I7: 123.06 | J7: 158.75 | O7: 1.4912
A8: 3 | B8: C10-232 | C8: 球墨铸铁给水管 DN150 | D8: 10m | E8: 17 | G8: 215.45 | H8: 3662.65 | I8: 3136.16 | J8: 486.71 | L8: 39.78 | M8: 21420 | O8: 38.063
B9: 主材 | C9: 球墨铸铁给水管 DN150 | D9: m | E9: 170 | G9: 126 | H9: 21420 | M9: 21420
A10: 4 | B10: C12-53 | C10: 管道刷油 红丹防锈漆 第一遍 | D10: 10m2 | E10: 8.0121 | G10: 42.71 | H10: 342.2 | I10: 149.43 | J10: 192.77 | O10: 1.8107
A11: 5 | B11: C10-233 | C11: 球墨铸铁给水管 DN200 | D11: 10m | E11: 110 | G11: 262.59 | H11: 28884.9 | I11: 20292.8 | J11: 4334 | L11: 4258.1 | M11: 206800 | O11: 246.29
B12: 主材 | C12: 球墨铸铁给水管 DN200 | D12: m | E12: 1100 | G12: 188 | H12: 206800 | M12: 206800
A13: 6 | B13: C12-53 | C13: 管道刷油 红丹防锈漆 第一遍 | D13: 10m2 | E13: 69.124 | G13: 42.71 | H13: 2952.29 | I13: 1289.16 | J13: 1663.12 | O13: 15.622
A14: 7 | B14: C10-363 | C14: UPVC双壁波纹排水管 De200 | D14: 10m | E14: 24 | G14: 372.44 | H14: 8938.56 | I14: 7613.76 | J14: 1322.4 | L14: 2.4 | M14: 11566.8 | O14: 92.4
B15: 主材 | C15: UPVC双壁波纹排水管 De200 | D15: m | E15: 226.8 | G15: 51 | H15: 11566.8 | M15: 11566.8
A16: 8 | B16: C10-365 | C16: UPVC双壁波纹排水管 De300 | D16: 10m | E16: 94 | G16: 471.7 | H16: 44339.8 | I16: 39261.92 | J16: 5068.48 | L16: 9.4 | M16: 86609.72 | O16: 476.486
B17: 主材 | C17: UPVC双壁波纹排水管 De300 | D17: m | E17: 888.3 | G17: 97.5 | H17: 86609.25 | M17: 86609.25
A18: 9 | B18: C10-365 | C18: UPVC双壁波纹排水管 De500 | D18: 10m | E18: 19 | G18: 471.7 | H18: 8962.3 | I18: 7935.92 | J18: 1024.48 | L18: 1.9 | M18: 43810.2 | O18: 96.311
B19: 主材 | C19: UPVC双壁波纹排水管 De500 | D19: m | E19: 179.55 | G19: 244 | H19: 43810.2 | M19: 43810.2
A20: 10 | B20: C10-365 | C20: UPVC双壁波纹排水管 | D20: 10m | E20: 1 | G20: 471.7 | H20: 471.7 | I20: 417.68 | J20: 53.92 | L20: 0.1 | M20: 3366.09 | O20: 5.069
A21: 编制人: | F21: 审核人: | K21: 编制日期:
A22: 单位工程直接费表
A23: 工程名称：室外水 | K23: 第 2 页 共 2 页
A24: 序号 | B24: 定额编号 | C24: 子目名称 | D24: 工程量 | G24: 价值（元） | I24: 其中（元） | O24: 工日统计
D25: 单位 | E25: 数量 | G25: 单价 | H25: 合价 | I25: 人工合价 | J25: 材料合价 | L25: 机械合价 | M25: 主材合价 | N25: 设备合价
C26: De800
B27: 主材 | C27: UPVC双壁波纹排水管 De800 | D27: m | E27: 9.45 | G27: 356.2 | H27: 3366.09 | M27: 3366.09
A28: 11 | B28: 补充主材001@6 | C28: 室外水表井 DN100 | D28: 座 | E28: 2 | G28: 1000 | H28: 2000 | M28: 2000
A29: 12 | B29: 补充主材001@1 | C29: 室外水表井 DN80 | D29: 座 | E29: 2 | G29: 950 | H29: 1900 | M29: 1900
A30: 13 | B30: 补充主材001@2 | C30: 钢筋混凝土化粪池 G8-25SQ，容积25m3 | D30: 座 | E30: 1 | G30: 30000 | H30: 30000 | M30: 30000
A31: 14 | B31: 补充主材001@3 | C31: 砖砌排水检查井 700 | D31: 座 | E31: 48 | G31: 1200 | H31: 57600 | M31: 57600
A32: 15 | B32: 补充主材001@4 | C32: 钢筋混凝土矩形检查井 2200×1300mm | D32: 座 | E32: 4 | G32: 2000 | H32: 8000 | M32: 8000
A33: 16 | B33: 补充主材001@5 | C33: 砖砌给水阀门井 800，井径D1200 | D33: 座 | E33: 4 | G33: 2300 | H33: 9200 | M33: 9200
A34: 17 | B34: C9-92 | C34: 室外地上式消火栓 SSF100/65-1.0 | D34: 套 | E34: 10 | G34: 71.32 | H34: 713.2 | I34: 679 | J34: 34.2 | M34: 670 | O34: 8.24
B35: 主材 | C35: 室外地上式消火栓 SSF100/65-1.0 | D35: 套 | E35: 10 | G35: 67 | H35: 670 | M35: 670
A36: 18 | B36: C10-1010 | C36: 砖砌雨水口 铸铁井圈及篦子 | D36: 10个 | E36: 1.6 | G36: 127.7 | H36: 204.32 | I36: 202.64 | J36: 1.68 | M36: 3520 | O36: 2.4592
B37: 主材 | C37: 砖砌雨水口 铸铁井圈及篦子 | D37: 个 | E37: 16 | G37: 220 | H37: 3520 | M37: 3520
A39: 合计 | H39: 606605.44 | I39: 83845.81 | J39: 14735.52 | L39: 4341.29 | M39: 503682.81 | O39: 1017.5481
A40: 编制人: | F40: 审核人: | K40: 编制日期:

Sheet 室外电费
A1: 单位工程费用汇总表
A2: 工程名称：室外电 | E2: 第 1 页 共 1 页
A3: 序号 | B3: 费用名称 | D3: 取费基数 | F3: 费率 | G3: 费用金额
A4: 1 | B4: 安装工程 | D4: 安装工程 | G4: 686018.15
A5: 一 | B5: 分部分项工程费 | D5: 人工费+材料费+未计价材料费+施工机具使用费+设备费 | G5: 648278.94
A6: 1 | B6: 人工费 | D6: 人工费 | G6: 18966.15
A7: 2 | B7: 材料费 | D7: 材料费 | G7: 6928.78
A8: 3 | B8: 未计价材料费 | D8: 主材费 | G8: 616274.23
A9: 4 | B9: 施工机具使用费 | D9: 机械费 | G9: 6109.78
A10: 5 | B10: 设备费 | D10: 设备费
A11: 二 | B11: 措施项目费 | D11: 单价措施项目费+总价措施项目费 | G11: 2432.36
A12: 2.1 | B12: 单价措施项目费 | D12: 人工费+材料费+施工机具使用费
A13: 2.1.1 | B13: 人工费 | D13: 技术措施项目人工费
A14: 2.1.2 | B14: 材料费 | D14: 技术措施项目材料费
A15: 2.1.3 | B15: 施工机具使用费 | D15: 技术措施项目机械费
A16: 2.2 | B16: 总价措施项目费 | D16: 安全文明施工费+其它总价措施项目费 | G16: 2432.36
A17: 2.2.1 | B17: 安全文明施工费 | D17: 人工费+施工机具使用费+人工费+施工机具使用费 | F17: 9.05 | G17: 2269.37
A18: 2.2.2 | B18: 其它总价措施项目费 | D18: 人工费+施工机具使用费+人工费+施工机具使用费 | F18: 0.65 | G18: 162.99
A19: 三 | B19: 总包服务费
A20: 四 | B20: 企业管理费 | D20: 人工费+施工机具使用费+人工费+施工机具使用费 | F20: 17.5 | G20: 4388.29
A21: 五 | B21: 利润 | D21: 人工费+施工机具使用费+人工费+施工机具使用费 | F21: 14.91 | G21: 3738.82
A22: 六 | B22: 规费 | D22: 人工费+施工机具使用费+人工费+施工机具使用费 | F22: 11.66 | G22: 2923.85
A23: 七 | B23: 索赔与现场签证
A24: 八 | B24: 安全技术服务费 | D24: 分部分项工程费+措施项目费+总包服务费+企业管理费+利润+规费-设备费 | F24: 0.12 | G24: 794.11
A25: 九 | B25: 不含税工程造价 | D25: 分部分项工程费+措施项目费+总包服务费+企业管理费+利润+规费+索赔与现场签证+安全技术服务费 | G25: 662556.37
A26: 十 | B26: 税前包干项目 | D26: 税前包干价
A27: 十一 | B27: 税金 | D27: 不含税工程造价+税前包干价 | F27: 3.5411 | G27: 23461.78
A28: 十二 | B28: 税后包干项目 | D28: 税后包干价
A29: 十四 | B29: 含税工程造价 | D29: 不含税工程造价+税金+税前包干项目+税后包干项目 | G29: 686018.15
A31: 2 | B31: 工程造价 | D31: 专业造价总合计 | G31: 686018.15
A36: 编制人: | C36: 审核人: | E36: 编制日期:

Sheet 室外电
A1: 单位工程直接费表
A2: 工程名称：室外电 | K2: 第 1 页 共 1 页
A3: 序号 | B3: 定额编号 | C3: 子目名称 | D3: 工程量 | G3: 价值（元） | I3: 其中（元） | O3: 工日统计
D4: 单位 | E4: 数量 | G4: 单价 | H4: 合价 | I4: 人工合价 | J4: 材料合价 | L4: 机械合价 | M4: 主材合价 | N4: 设备合价
A5: 1 | B5: C4-722 | C5: 铜芯电力电缆 YJV-8.7/10kV-3x185 | D5: 100m | E5: 17.5 | G5: 1828.84 | H5: 32004.7 | I5: 18966.15 | J5: 6928.78 | L5: 6109.78 | M5: 616274.23 | O5: 250.25
B6: 主材 | C6: 铜芯电力电缆 YJV-8.7/10kV-3x185 | D6: m | E6: 1767.5 | G6: 348.67 | H6: 616274.23 | M6: 616274.23
A24: 合计 | H24: 648278.93 | I24: 18966.15 | J24: 6928.78 | L24: 6109.78 | M24: 616274.23 | O24: 250.25
A25: 编制人: | F25: 审核人: | K25: 编制日期:
