Workbook
Name _Toc146509935: #REF!
Name _Toc146509935: #REF!
Name _Toc146509935: #REF!
Name aaaaa: #REF!
Name aaaaa: #REF!
Name aaaaa: #REF!
Name edline: #REF!
Name edline: #REF!
Name edline: #REF!
Name edline: #REF!
Name OLE_LINK1: #REF!
Name OLE_LINK1: #REF!
Name OLE_LINK1: #REF!
Name Print_Area1: #REF!
Name Print_Area1: #REF!
Name Print_Area1: #REF!
Name 道概: #REF!
Name 道概: #REF!
Name 道概: #REF!
Name 道取: #REF!
Name 道取: #REF!
Name 道取: #REF!
Name 图1: #REF!
Name 图1: #REF!
Name 图1: #REF!
Name 图2: [1]工程量屋面屋架柱!$A$1
Name 土建概: #REF!
Name 土建概: #REF!
Name 土建概: #REF!
Name 卧式旋铆机: #REF!
Name 卧式旋铆机: #REF!
Name 卧式旋铆机: #REF!
Name 项目名称_淄博蓄电池厂牵引电池150万KVAH技术改造建设项目: #REF!
Name 项目名称_淄博蓄电池厂牵引电池150万KVAH技术改造建设项目: #REF!
Name 项目名称_淄博蓄电池厂牵引电池150万KVAH技术改造建设项目: #REF!
Name 装饰工程预算表: [2]装饰工程预算表!#REF!
Name 装饰工程预算表: [2]装饰工程预算表!#REF!
Name 装饰工程预算表: [2]装饰工程预算表!#REF!

Sheet 设备对比表
A1: 附表13.2-9
A2: 新 增 （改造）工 艺 设 备 对 比 表
A3: 项目名称：大连船舶重工集团公司专船需求设施改造项目
A4: 序号 | B4: 设备名称 | C4: 可研批复 | K4: 初步设计 | S4: 调整情况
C5: 主要技术（性能）指标或规格要求 | D5: 国别 | E5: 单位 （台/套) | F5: 数量 | G5: 设备购置费（万元、万美元） | J5: 招标情况 | K5: 主要技术（性能）指标或规格要求 | L5: 国别 | M5: 单位 （台/套) | N5: 数量 | O5: 设备购置费（万元、万美元） | R5: 招标情况 | S5: 数量 | T5: 设备购置费（万元、万美元）
G6: 单价 | H6: 合计 | I6: 其中 外汇 | O6: 单价 | P6: 合计 | Q6: 其中 外汇 | T6: 单价 | U6: 合计 | V6: 其中外汇
A7: 一 | B7: 生产设备
A8: 1 | B8: 接板用压力架 | C8: 适用板厚 为：2m~10mm 板宽范围：1.5m~3m； 长度范围：4m~12m 工作温度 极端最高气温36℃，极端最低温度-22℃ | D8: 国产 | E8: 套 | F8: 2 | G8: 500 | H8: =G8*F8 -> 1000 | J8: 公开招标 | K8: 适用板厚 为：2m~10mm 板宽范围：1.5m~3m； 长度范围：4m~12m 工作温度 极端最高气温36℃，极端最低温度-22℃ | L8: 国产 | M8: 套 | N8: 2 | O8: ='新增（改造）工艺设备明细表'!G7 -> 425 | P8: =O8*N8 -> 850 | R8: 公开招标 | T8: =O8-G8 -> -75 | U8: =P8-H8 -> -150
A9: 2 | B9: 焊接应力消除设备 | C9: 工作频率 20000 HZ 最大输出振幅 50μm 处理速度 20～40 m/h | D9: 国产 | E9: 台 | F9: 8 | G9: 28.2 | H9: =G9*F9 -> 225.6 | J9: 公开招标 | K9: 工作频率 20000 HZ 最大输出振幅 50μm 处理速度 20～40 m/h | L9: 国产 | M9: 套 | N9: 8 | O9: 28.2 | P9: =O9*N9 -> 225.6 | R9: 公开招标
A10: 3 | B10: 有机废气处理设备 | C10: 额定处理风量 70000m³/h | D10: 国产 | E10: 套 | F10: 1 | G10: 320 | H10: =G10*F10 -> 320 | J10: 公开招标 | K10: 额定处理风量 70000m³/h | L10: 国产 | M10: 套 | N10: 1 | O10: 400 | P10: =O10*N10 -> 400 | R10: 公开招标 | T10: =O10-G10 -> 80 | U10: =P10-H10 -> 80
B12: 合计 | F12: =SUM(F8:F11) -> 11 | H12: =SUM(H8:H11) -> 1545.6 | N12: =SUM(N8:N11) -> 11 | P12: =SUM(P8:P11) -> 1475.6 | U12: =SUM(U8:U11) -> -70

Sheet 概算对比表
A1: 表13.2-8
A2: 设计概算和可研批复投资估算对比表
A3: =设备对比表!A3 -> 项目名称：大连船舶重工集团公司专船需求设施改造项目
A4: 序号 | B4: 工程项目或费用名称 | C4: 可研批复 | H4: 设计概算 | M4: 调整情况
C5: 新建面积 | D5: 改造面积 | E5: 设备 （台/套） | F5: 投资 | G5: 其中 外汇 | H5: 新建面积 | I5: 改造面积 | J5: 设备 （台/套） | K5: 投资 | L5: 其中 外汇 | M5: 新建面积 | N5: 改造面积 | O5: 设备 （台/套） | P5: 投资 | Q5: 其中 外汇
B6: 合计 | F6: =SUM(F7,F12,F22) -> 3496.0365 | K6: =SUM(K7,K12,K22) -> 3495.9599
A7: 一 | B7: 工程费用 | F7: =SUM(F9:F11) -> 3050.7047 | K7: =SUM(K9:K11) -> 3130.6918 | P7: =K7-F7 -> 79.987087
A8: （一） | B8: 室内工程
A9: 1 | B9: 新增设备 | E9: 11 | F9: 1545.6 | J9: 11 | K9: =总概算表!J8 -> 1625.5871 | P9: =K9-F9 -> 79.987087
A10: （二） | B10: 室外工程
A11: 1 | B11: 新建1-1坞中间坞门槛 | F11: 1505.1047 | K11: 1505.1047
A12: 二 | B12: 工程建设其他费用 | F12: =SUM(F13:F21) -> 247.53173 | K12: =SUM(K13:K21) -> 261.30284 | P12: =K12-F12 -> 13.771117
A13: 1 | B13: 建设单位管理费 | F13: 45 | K13: =总概算表!J13 -> 57.5 | P13: =K13-F13 -> 12.5
A14: 2 | B14: 前期工作咨询费 | F14: 29.357143 | K14: =总概算表!J14 -> 29.357143
A15: 3 | B15: 工程建设监理费 | F15: 42.222514 | K15: =总概算表!J15 -> 42.222999
A16: 4 | B16: 工程设计费 | F16: 88.881313 | K16: =总概算表!J16 -> 90.091362 | P16: =K16-F16 -> 1.2100492
A17: 5 | B17: 施工图审查费 | F17: 4.4440657 | K17: =总概算表!J17 -> 4.5045681 | P17: =K17-F17 -> 0.060502461
A18: 6 | B18: 招标代理服务费 | F18: 19.817867 | K18: =总概算表!J18 -> 19.817947
A19: 7 | B19: 环境影响咨询费 | F19: 7.8088235 | K19: =总概算表!J19 -> 7.8088235
A20: 8 | B20: 职业安全评价费 | F20: 5 | K20: =总概算表!J20 -> 5
A21: 9 | B21: 职业卫生评价费 | F21: 5 | K21: =总概算表!J21 -> 5
A22: 三 | B22: 基本预备费 | F22: 197.8 | K22: =总概算表!J22 -> 103.96526 | P22: =K22-F22 -> -93.834744

Sheet 总概算表
A1: 表13.2-1
A2: 总概算表
A3: 项目名称：大连船舶重工集团公司专船需求设施改造项目
A4: 序号 | B4: 工程项目或费用名称 | C4: 建筑面积或工程量 | F4: 投资概算（万元、万美元） | L4: 备注
C5: 新建 | D5: 改造 | E5: 单位 | F5: 建筑工程费 | G5: 工艺设备购置费 | H5: 工艺设备安装费 | I5: 其他费用 | J5: 合计 | K5: 含外汇
B6: 合计 | F6: =SUM(F7,F12,F22) -> 1655.112 | G6: =SUM(G7,G12,G22) -> 1475.6 | I6: =SUM(I7,I12,I22) -> 365.2681 | J6: =SUM(J7,J12,J22) -> 3495.9801 | M6: =O6-J6 -> 0.019869013 | N6: 3500 | O6: 3496
A7: 一 | B7: 工程费用 | F7: =SUM(F8,F10) -> 1655.112 | G7: =SUM(G8,G10) -> 1475.6 | J7: =SUM(J8,J10) -> 3130.712
A8: （一） | B8: 室内工程 | F8: =SUM(F9) -> 149.98709 | G8: =SUM(G9) -> 1475.6 | J8: =SUM(J9) -> 1625.5871
A9: 1 | B9: 新增设备 | F9: =室内!H7 -> 149.98709 | G9: =室内!I6 -> 1475.6 | J9: =SUM(F9:I9) -> 1625.5871
A10: （二） | B10: 室外工程 | F10: =SUM(F11) -> 1505.1249 | J10: =SUM(J11) -> 1505.1249
A11: 1 | B11: 新建1-1坞中间坞门槛 | F11: =室外!H6 -> 1505.1249 | J11: =SUM(F11:I11) -> 1505.1249
A12: 二 | B12: 工程建设其他费用 | I12: =SUM(I13:I21) -> 261.30284 | J12: =SUM(J13:J21) -> 261.30284
A13: 1 | B13: 建设单位管理费 | I13: =20+(N6-1000)*1.5% -> 57.5 | J13: =SUM(F13:I13) -> 57.5
A14: 2 | B14: 前期工作咨询费 | I14: =27+(60-27)*(N6-3000)/7000 -> 29.357143 | J14: =SUM(F14:I14) -> 29.357143
A15: 3 | B15: 工程建设监理费 | I15: =30.1+(78.1-30.1)*(F10-1000)/2000 -> 42.222999 | J15: =SUM(F15:I15) -> 42.222999
A16: 4 | B16: 工程设计费 | I16: =(103.8+(163.9-103.8)*(J7-3000)/2000)*35%*1.15*1.25+(38.8+(103.8-38.8)*(F10-1000)/2000)*65% -> 90.091362 | J16: =SUM(F16:I16) -> 90.091362
A17: 5 | B17: 施工图审查费 | I17: =I16*5% -> 4.5045681 | J17: =SUM(F17:I17) -> 4.5045681
A18: 6 | B18: 招标代理服务费 | I18: 19.817947 | J18: =SUM(F18:I18) -> 19.817947
A19: 7 | B19: 环境影响咨询费 | I19: =7.5+(18-7.5)*(N6-3000)/17000 -> 7.8088235 | J19: =SUM(F19:I19) -> 7.8088235
A20: 8 | B20: 职业安全评价费 | I20: 5 | J20: =SUM(F20:I20) -> 5
A21: 9 | B21: 职业卫生评价费 | I21: 5 | J21: =SUM(F21:I21) -> 5
A22: 三 | B22: 基本预备费 | I22: =(J7+J12)*3.065% -> 103.96526 | J22: =SUM(F22:I22) -> 103.96526
B26: 建筑工程费 | C26: =F7 -> 1655.112 | D26: =C26/C30 -> 0.47343291
B27: 设备工程费 | C27: =G7 -> 1475.6 | D27: =C27/C30 -> 0.42208478
B28: 其他费用 | C28: =J12 -> 261.30284 | D28: =C28/C30 -> 0.074743801
B29: 基本预备费 | C29: =J22 -> 103.96526 | D29: =C29/C30 -> 0.029738515
B30: 合计 | C30: =SUM(C26:C29) -> 3495.9801 | D30: =SUM(D26:D29) -> 1

Sheet 室内
A1: 表13.2-2
A2: 室内工程概算表
A3: =总概算表!A3 -> 项目名称：大连船舶重工集团公司专船需求设施改造项目
A4: 序号 | B4: 工程名称 | C4: 建筑面积 （平方米） | E4: 建筑工程费（万元） | I4: 工艺设备购置费（万元） | J4: 工艺设备安装费（万元） | K4: 合计 （万元） | L4: 备注
C5: 新建 | D5: 改造 | E5: 土建及专业工程费 | F5: 建筑设备购置费 | G5: 建筑设备安装费 | H5: 小计
B6: 合计 | E6: =SUM(E7) -> 143.37909 | H6: =SUM(H7) -> 149.98709 | I6: =SUM(I7) -> 1475.6 | K6: =SUM(K7) -> 1625.5871
A7: （一） | B7: 工艺设备 | E7: =SUM(E8) -> 143.37909 | H7: =SUM(H8) -> 149.98709 | I7: =SUM(I8) -> 1475.6 | K7: =SUM(K8) -> 1625.5871
A8: 1 | B8: 新增工艺设备 | E8: =设备取费!Q8 -> 143.37909 | F8: =公用设备!G12+公用设备!G16 -> 5.9 | G8: =公用设备!G13+公用设备!G17 -> 0.708 | H8: =SUM(E8:G8) -> 149.98709 | I8: =设备取费!L7 -> 1475.6 | K8: =SUM(H8:J8) -> 1625.5871
G12: =150-H8 -> 0.012913

Sheet 室外
A1: 表13.2-3
E2: 室外工程概算表
A3: =总概算表!A3 -> 项目名称：大连船舶重工集团公司专船需求设施改造项目
A4: 序号 | B4: 工程名称 | C4: 单位 | D4: 数量 | E4: 建筑工程费（万元） | I4: 指标 （元/单位） | J4: 备注
E5: 土建及专业工程费 | F5: 建筑设备购置费 | G5: 建筑设备安装费 | H5: 合计
B6: 合计 | E6: =SUM(E7) -> 1505.1249 | F6: =SUM(F7) -> 0 | G6: =SUM(G7) -> 0 | H6: =SUM(H7) -> 1505.1249 | I6: =SUM(I7) -> 0 | J6: =SUM(J7) -> 0
A7: 1 | B7: 新建1-1坞中间坞门槛 | C7: 项 | D7: 1 | E7: =船坞改造费用!G20/10000 -> 1505.1249 | H7: =SUM(E7:G7) -> 1505.1249

Sheet 其他
A1: 表13.2-5
A2: 其他费用概算表
A3: =总概算表!A3 -> 项目名称：大连船舶重工集团公司专船需求设施改造项目
A4: 序号 | B4: 费用名称 | C4: 收费依据 | D4: 指标 | E4: 计算基数 | F4: 投资 （万元） | G4: 备注
B5: 合计 | F5: =SUM(F6,F16) -> 365.2681
A6: 一 | B6: 工程建设其他费用 | F6: =SUM(F7:F15) -> 261.30284
A7: 1 | B7: =总概算表!B13 -> 建设单位管理费 | C7: 财建[2016]504号文 | D7: 插入法 | E7: =总概算表!J6 -> 3495.9801 | F7: =总概算表!J13 -> 57.5
A8: 2 | B8: =总概算表!B14 -> 前期工作咨询费 | C8: 计价格[1999]1283号文 | D8: 插入法 | E8: =E7 -> 3495.9801 | F8: =总概算表!J14 -> 29.357143
A9: 3 | B9: =总概算表!B15 -> 工程建设监理费 | C9: 发改价格[2007]670号文 | D9: 插入法 | E9: 1505.0666 | F9: =总概算表!J15 -> 42.222999
A10: 4 | B10: =总概算表!B16 -> 工程设计费 | C10: 计价格[2002]10号文 | D10: 插入法 | F10: =总概算表!J16 -> 90.091362
A11: 5 | B11: =总概算表!B17 -> 施工图审查费 | C11: 发改价格[2011]534号文 | D11: 0.05 | E11: =F10 -> 90.091362 | F11: =总概算表!J17 -> 4.5045681
A12: 6 | B12: =总概算表!B18 -> 招标代理服务费 | C12: 计价格[2002]1980号文 | D12: 差额定律累进法 | F12: =总概算表!J18 -> 19.817947
A13: 7 | B13: =总概算表!B19 -> 环境影响咨询费 | C13: 计价格[2002]125号文 | E13: =E8 -> 3495.9801 | F13: =总概算表!J19 -> 7.8088235
A14: 8 | B14: =总概算表!B20 -> 职业安全评价费 | C14: 有关规定 | F14: =总概算表!J20 -> 5
A15: 9 | B15: =总概算表!B21 -> 职业卫生评价费 | C15: 有关规定 | F15: =总概算表!J21 -> 5
A16: 二 | B16: 预备费 | F16: =SUM(F17) -> 103.96526
A17: 1 | B17: 基本预备费 | C17: 科工计［2005］496号 | D17: =F17/E17 -> 0.03065 | E17: =总概算表!J7+总概算表!J12 -> 3392.0149 | F17: =总概算表!J22 -> 103.96526

Sheet 设备取费
A1: 附表13.2-6
E2: 工艺设备购置费及安装费计算表 | T2: $
A3: 项目名称：大连船舶重工集团公司专船需求设施改造项目 | O3: 单位：万元、万美元 | Q3: 单位：万元、万美元
A4: 序号 | B4: 设备名称 | C4: 数量台/套 | D4: 设备购置费单价 | L4: 设备购置费合计 | N4: 设备安装费 | P4: 设备基础费 | R4: 设备购置费及安装基础费合计
D5: 设备原价 | J5: 国内运杂费 | K5: 小计 | L5: 人民币合计 | M5: 其中美元 | N5: 费率（%） | O5: 投资 | P5: 费率（%） | Q5: 投资
D6: 人民币 | E6: 含美元CIF | F6: 关税 | G6: 增值税 | H6: 银行费公司费 | I6: 商检费
B7: 合计 | L7: =SUM(L8) -> 1475.6 | M7: =SUM(M8) -> 0 | N7: =SUM(N8) -> 0 | O7: =SUM(O8) -> 0 | P7: =SUM(P8) -> 0 | Q7: =SUM(Q8) -> 143.37909 | R7: =SUM(R8) -> 1618.9791
A8: 其中 | B8: 新增设备 | L8: =SUM(L9:L11) -> 1475.6 | M8: =SUM(M9:M11) -> 0 | N8: =SUM(N9:N11) -> 0 | O8: =SUM(O9:O11) -> 0 | P8: =SUM(P9:P11) -> 0 | Q8: =SUM(Q9:Q11) -> 143.37909 | R8: =SUM(R9:R11) -> 1618.9791
A9: 1 | B9: ='新增（改造）工艺设备明细表'!B7 -> 接板用压力架 | C9: ='新增（改造）工艺设备明细表'!F7 -> 2 | D9: ='新增（改造）工艺设备明细表'!G7 -> 425 | K9: 425 | L9: =C9*K9 -> 850 | O9: =C9*D9*N9 -> 0 | Q9: =(土费!G30+电费!G30)/10000 -> 143.37909 | R9: =SUM(L9,O9,Q9) -> 993.37909
A10: 2 | B10: ='新增（改造）工艺设备明细表'!B8 -> 焊接应力消除设备 | C10: ='新增（改造）工艺设备明细表'!F8 -> 8 | D10: ='新增（改造）工艺设备明细表'!G8 -> 28.2 | K10: =SUM(D10,F10:J10) -> 28.2 | L10: =C10*K10 -> 225.6 | O10: =C10*D10*N10 -> 0 | Q10: =E10*F10*P10 -> 0 | R10: =SUM(L10,O10) -> 225.6
A11: 3 | B11: ='新增（改造）工艺设备明细表'!B9 -> 有机废气处理设备 | C11: ='新增（改造）工艺设备明细表'!F9 -> 1 | D11: ='新增（改造）工艺设备明细表'!G9 -> 400 | K11: =SUM(D11,F11:J11) -> 400 | L11: =C11*K11 -> 400 | O11: =C11*D11*N11 -> 0 | Q11: =E11*F11*P11 -> 0 | R11: =SUM(L11,O11) -> 400

Sheet 公用设备
A1: 附表13.2-7
A2: 新增主要公用设备表
A3: =总概算表!A3 -> 项目名称：大连船舶重工集团公司专船需求设施改造项目 | I3: 单位：万元
A4: 序号 | B4: 设备名称 | C4: 规格型号 | D4: 单位 | E4: 数量 | F4: 设备价格 | I4: 备 注
F5: 单价 | G5: 总价 | H5: 其中外汇
A6: 一 | B6: 接板用压力架
A7: （一） | B7: 电气工程
A8: 1 | B8: 动力配电箱 | C8: XL-52型 | D8: 台 | E8: 1 | F8: 0.4 | G8: =F8*E8 -> 0.4
A9: 2 | B9: 照明配电箱 | C9: XLM301型 | D9: 台 | E9: 1 | F9: 0.4 | G9: =F9*E9 -> 0.4
A10: 3 | B10: 6#变电所内增加断路器 | C10: 1600A | D10: 台 | E10: 1 | F10: 3 | G10: =F10*E10 -> 3
A11: 4 | B11: 设备专用接地箱 | D11: 台 | E11: 3 | F11: 0.3 | G11: =F11*E11 -> 0.9
B12: 小计 | G12: =SUM(G8:G11) -> 4.7
B13: 设备安装费 | G13: =G12*12% -> 0.564
A14: （二） | B14: 动力工程
A15: 1 | B15: 混合气体汇流排及接头箱 | D15: 台 | E15: 2 | F15: 0.6 | G15: =F15*E15 -> 1.2
B16: 小计 | G16: =SUM(G15:G15) -> 1.2
B17: 设备安装费 | G17: =G16*12% -> 0.144
B18: 合计 | G18: =SUM(G12:G13,G16:G17) -> 6.608

Sheet 新增（改造）工艺设备明细表
A1: 附表2.3-2
A2: 新 增 （改造）工 艺 设 备 明 细 表
A3: 项目名称：大连船舶重工集团公司专船需求设施改造项目
A4: 序号 | B4: 设备名称 | C4: 主要技术（性能）指标或规格要求 | D4: 国别 | E4: 单位（台/套) | F4: 数量 | G4: 设备购置费（万元、万美元） | J4: 招标情况 | K4: 备注
G5: 单价 | H5: 合计 | I5: 其中外汇
A6: 一 | B6: 生产设备
A7: 1 | B7: 接板用压力架 | C7: 适用板厚 为：2m~10mm 板宽范围：1.5m~3m； 长度范围：4m~12m 工作温度 极端最高气温36℃，极端最低温度-22℃ | D7: 国产 | E7: 套 | F7: 2 | G7: 425 | H7: =G7*F7 -> 850 | J7: 公开招标
A8: 2 | B8: 焊接应力消除设备 | C8: 工作频率 20000 HZ 最大输出振幅 50μm 处理速度 20～40 m/h | D8: 国产 | E8: 套 | F8: 8 | G8: 28.2 | H8: =G8*F8 -> 225.6 | J8: 公开招标
A9: 3 | B9: 有机废气处理设备 | C9: 额定处理风量 300000m³/h | D9: 国产 | E9: 套 | F9: 1 | G9: 400 | H9: =G9*F9 -> 400 | J9: 公开招标
B11: 合计 | F11: =SUM(F7:F10) -> 11 | H11: =SUM(H7:H10) -> 1475.6

Sheet 土
A1: 单位工程概预算表
A2: 项目名称：接板用压力架土建工程 | I2: 第 1 页 共 1 页
A3: 序号 | B3: 编码 | C3: 子目名称 | E3: 工程量 | G3: 价值（元） | J3: 其中（元）
E4: 单位 | F4: 数量 | G4: 单价 | H4: 合价 | J4: 人工费 | K4: 材料费
A5: 1 | B5: 2-25换 | C5: 混凝土桩 液压静力压桩机压预制钢筋混凝土方桩 静力压桩机压预制方桩 桩长在12m以内 | E5: 10m3 | F5: 19.5 | G5: 18560.92 | H5: 361937.94 | J5: 69642.69 | K5: 24787.62
A6: 2 | B6: 4-58换 | C6: 现浇混凝土板 现浇砼 基础 商砼 | E6: 10m3 | F6: 86.4 | G6: 4151.31 | H6: 358673.18 | J6: 22876.99 | K6: 335796.19
A7: 3 | B7: 12-90 | C7: 混凝土、钢筋混凝土模板及支架现浇混凝土模板 平板 组合钢模板 钢支撑 | E7: 100m2 | F7: 8.64 | G7: 3266.78 | H7: 28224.98 | J7: 19217.35 | K7: 7106.75
A8: 4 | B8: 4-286 | C8: 现浇混凝土钢筋 螺纹钢筋 Φ20 | E8: t | F8: 25.92 | G8: 3553.35 | H8: 92102.83 | J8: 9392.63 | K8: 81065.58
C9: 分部小计 | H9: 840938.93 | J9: 121129.66 | K9: 448756.14
C43: 小计 | H43: 840938.93 | J43: 121129.66 | K43: 448756.14
C44: 合计 | H44: 840938.93 | J44: 121129.66 | K44: 448756.14

Sheet 土费
A1: 单位工程费用表
A2: 项目名称：接板用压力架土建工程 | F2: 第 1 页 共 1 页
A3: 序号 | B3: 费用名称 | D3: 取费说明 | E3: 费率(%) | G3: 费用金额
A4: 1 | B4: 分部分项工程费合计 | D4: 直接费+主材费 | E4: 105 | G4: 882985.88
A5: 1.1 | B5: 其中：人工费+机械费 | D5: 人工费+机械费-燃料动力价差 | G5: 392182.8
A6: 2 | B6: 企业管理费 | D6: 其中：人工费+机械费 | E6: 12.5 | G6: 49022.85
A7: 3 | B7: 利润 | D7: 其中：人工费+机械费 | E7: 15.93 | G7: 62474.72
A8: 4 | B8: 措施项目费 | D8: 安全文明施工措施费+夜间施工增加费+二次搬运费+已完工程及设备保护费+冬雨季施工费+市政工程干扰费+其他措施项目费 | G8: 93182.63
A9: 4.1 | B9: 安全文明施工措施费 | D9: 其中：人工费+机械费 | E9: 12.65 | G9: 49611.12
A10: 4.2 | B10: 夜间施工增加费
A11: 4.3 | B11: 二次搬运费
A12: 4.4 | B12: 已完工程及设备保护费
A13: 4.5 | B13: 冬雨季施工费 | D13: 其中：人工费+机械费 | E13: 7.06 | G13: 27688.11
A14: 4.6 | B14: 市政工程干扰费 | D14: 其中：人工费+机械费 | E14: 4.05 | G14: 15883.4
A15: 4.7 | B15: 其他措施项目费
A16: 5 | B16: 其他项目费
A17: 6 | B17: 税费前工程造价合计 | D17: 分部分项工程费合计+企业管理费+利润+措施项目费+其他项目费 | G17: 1087666.1
A18: 7 | B18: 规费 | D18: 工程排污费+社会保障费+住房公积金+危险作业意外伤害保险 | G18: 134793.23
A19: 7.1 | B19: 工程排污费
A20: 7.2 | B20: 社会保障费 | D20: 养老保险+失业保险+医疗保险+生育保险+工伤保险 | G20: 102712.68
A21: 7.2.1 | B21: 养老保险 | D21: 其中：人工费+机械费 | E21: 16.36 | G21: 64161.11
A22: 7.2.2 | B22: 失业保险 | D22: 其中：人工费+机械费 | E22: 1.64 | G22: 6431.8
A23: 7.2.3 | B23: 医疗保险 | D23: 其中：人工费+机械费 | E23: 6.55 | G23: 25687.97
A24: 7.2.4 | B24: 生育保险 | D24: 其中：人工费+机械费 | E24: 0.82 | G24: 3215.9
A25: 7.2.5 | B25: 工伤保险 | D25: 其中：人工费+机械费 | E25: 0.82 | G25: 3215.9
A26: 7.3 | B26: 住房公积金 | D26: 其中：人工费+机械费 | E26: 8.18 | G26: 32080.55
A27: 7.4 | B27: 危险作业意外伤害保险
A28: 8 | B28: 人工费动态调整 | D28: 人工费+机械人工费 | E28: 0
A29: 9 | B29: 税金 | D29: 税费前工程造价合计+规费+人工费动态调整 | E29: 11 | G29: 134470.52
A30: 10 | B30: 工程总造价 | D30: 税费前工程造价合计+规费+税金+人工费动态调整 | G30: 1356929.8

Sheet 单位工程人材机价差表
A1: 单位工程人材机价差表
A2: 工程名称：接板用压力架土建工程 | G2: 专业：土建工程 | J2: 第 1 页 共 1 页
A3: 序号 | B3: 材料名 | C3: 规格 | D3: 单位 | E3: 材料量 | F3: 预算价 | H3: 市场价 | I3: 价 差 | K3: 价差合计
A4: 1 | B4: 技工 | D4: 工日 | E4: 223.64 | F4: 68 | H4: 81 | I4: 13 | K4: 2907.37
A5: 2 | B5: 普工 | D5: 工日 | E5: 560.85 | F5: 53 | H5: 66 | I5: 13 | K5: 7291.09
B48: 小计 | K48: 10198.46
B49: 合计 | K49: 10198.46

Sheet 电
A1: 单位工程概预算表（主材单列）
A2: 工程名称：接板用压力架电气工程 | K2: 第 1 页 共 1 页
A3: 序号 | B3: 编码 | C3: 子目名称 | E3: 工程量 | G3: 价值（元） | I3: 其中（元）
E4: 单位 | F4: 数量 | G4: 单价 | H4: 合价 | I4: 人工费 | J4: 材料费 | L4: 机械费
A6: 1 | B6: 2-1728换 | C6: 成套型荧光灯 吊链式 双管 | E6: 10套 | F6: 0.2 | G6: 271.37 | H6: 54.27 | I6: 39.04 | J6: 15.24
B7: Z03384@7 | C7: 双管荧光灯 2*36W | E7: 套 | F7: 2.02 | G7: 240 | H7: 484.8
A8: 2 | B8: 2-383换 | C8: 扳式暗开关(单控) 双联 | E8: 10套 | F8: 0.1 | G8: 76.89 | H8: 7.69 | I8: 7.23 | J8: 0.46
B9: Z03702@2 | C9: 双联单极开关 | E9: 只 | F9: 1.02 | G9: 30 | H9: 30.6
A10: 3 | B10: 2-415换 | C10: 单相暗插座15A 5孔 | E10: 10套 | F10: 0.4 | G10: 96.6 | H10: 38.64 | I10: 35.54 | J10: 3.1
B11: Z03383@1 | C11: 二、三孔组合暗装插座 | E11: 套 | F11: 4.08 | G11: 30 | H11: 122.4
A12: 4 | B12: 2-413换 | C12: 三极暗插座 | E12: 10套 | F12: 0.2 | G12: 79.7 | H12: 15.94 | I12: 14.7 | J12: 1.24
B13: Z03383@3 | C13: 三孔暗装插座 | E13: 套 | F13: 2.04 | G13: 60 | H13: 122.4
A14: 5 | B14: 2-608 | C14: 电力电缆敷设 电缆截面400mm2以下 | E14: 100m | F14: 0.5 | G14: 2452.45 | H14: 1226.23 | I14: 697.29 | J14: 172.77 | L14: 356.17
B15: 补充主材001@3 | C15: YJV-0.6/1KV-3(1*690)+2(1*300) | E15: m | F15: 50 | G15: 1200 | H15: 60000
A16: 6 | B16: 2-605换 | C16: 电力电缆敷设 电缆截面35mm2以下 | E16: 100m | F16: 0.3 | G16: 703 | H16: 210.9 | I16: 142.58 | J16: 65.33 | L16: 3
B17: 补充主材002@1 | C17: YJV-0.6/1KV-5*10 | E17: m | F17: 30 | G17: 37.82 | H17: 1134.6
A18: 7 | B18: 2-779 | C18: 钢管接地极制作、安装 普通土 | E18: 根 | F18: 6 | G18: 51.1 | H18: 306.6 | I18: 212.1 | J18: 15.72 | L18: 78.78
B19: 补充主材001@2 | C19: 接地极 热镀锌钢管DN40 | E19: 根 | F19: 6 | G19: 80 | H19: 480
A20: 8 | B20: 2-579 | C20: 扁钢安装 40×4 | E20: 100m／单相 | F20: 0.15 | G20: 609.93 | H20: 91.49 | I20: 68.43 | J20: 17.88 | L20: 5.18
B21: 补充主材001@1 | C21: 热镀锌扁钢 40×4 | E21: m | F21: 15 | G21: 20 | H21: 300
C22: 分部小计 | H22: 64626.56 | I22: 1216.91 | J22: 291.74 | L22: 443.13
C35: 小计 | H35: 64626.56 | I35: 1216.91 | J35: 291.74 | L35: 443.13
C36: 合计 | H36: 64626.56 | I36: 1216.91 | J36: 291.74 | L36: 443.13

Sheet 电费
A1: 单位工程费用表
A2: 项目名称：接板用压力架电气工程 | F2: 第 1 页 共 1 页
A3: 序号 | B3: 费用名称 | D3: 取费说明 | E3: 费率(%) | G3: 费用金额
A4: 1 | B4: 分部分项工程费合计 | D4: 直接费+主材费+设备费 | E4: 105 | G4: 67857.89
A5: 1.1 | B5: 其中：人工费+机械费 | D5: 人工费+机械费-燃料动力价差 | G5: 1660.04
A6: 2 | B6: 企业管理费 | D6: 其中：人工费+机械费 | E6: 11.42 | G6: 189.58
A7: 3 | B7: 利润 | D7: 其中：人工费+机械费 | E7: 14.57 | G7: 241.87
A8: 4 | B8: 措施项目费 | D8: 安全文明施工措施费+夜间施工增加费+二次搬运费+已完工程及设备保护费+冬雨季施工费+市政工程干扰费+其他措施项目费 | G8: 384.3
A9: 4.1 | B9: 安全文明施工措施费 | D9: 其中：人工费+机械费 | E9: 12.04 | G9: 199.87
A10: 4.2 | B10: 夜间施工增加费
A11: 4.3 | B11: 二次搬运费
A12: 4.4 | B12: 已完工程及设备保护费
A13: 4.5 | B13: 冬雨季施工费 | D13: 其中：人工费+机械费 | E13: 7.06 | G13: 117.2
A14: 4.6 | B14: 市政工程干扰费 | D14: 其中：人工费+机械费 | E14: 4.05 | G14: 67.23
A15: 4.7 | B15: 其他措施项目费
A16: 5 | B16: 其他项目费
A17: 6 | B17: 税费前工程造价合计 | D17: 分部分项工程费合计+企业管理费+利润+措施项目费+其他项目费 | G17: 68673.64
A18: 7 | B18: 规费 | D18: 工程排污费+社会保障费+住房公积金+危险作业意外伤害保险 | G18: 570.54
A19: 7.1 | B19: 工程排污费
A20: 7.2 | B20: 社会保障费 | D20: 养老保险+失业保险+医疗保险+生育保险+工伤保险 | G20: 434.75
A21: 7.2.1 | B21: 养老保险 | D21: 其中：人工费+机械费 | E21: 16.36 | G21: 271.58
A22: 7.2.2 | B22: 失业保险 | D22: 其中：人工费+机械费 | E22: 1.64 | G22: 27.22
A23: 7.2.3 | B23: 医疗保险 | D23: 其中：人工费+机械费 | E23: 6.55 | G23: 108.73
A24: 7.2.4 | B24: 生育保险 | D24: 其中：人工费+机械费 | E24: 0.82 | G24: 13.61
A25: 7.2.5 | B25: 工伤保险 | D25: 其中：人工费+机械费 | E25: 0.82 | G25: 13.61
A26: 7.3 | B26: 住房公积金 | D26: 其中：人工费+机械费 | E26: 8.18 | G26: 135.79
A27: 7.4 | B27: 危险作业意外伤害保险
A28: 8 | B28: 人工费动态调整 | D28: 人工费+机械人工费 | E28: 0
A29: 9 | B29: 税金 | D29: 税费前工程造价合计+规费+人工费动态调整 | E29: 11 | G29: 7616.86
A30: 10 | B30: 工程总造价 | D30: 税费前工程造价合计+规费+税金+人工费动态调整 | G30: 76861.04

Sheet 船坞改造
A2: 单位工程概预算表
A3: 工程名称：船坞改造土建工程 | H3: 第 1 页 共 1 页
A4: 序号 | B4: 定 额_x000D__x000D_ 编 号 | C4: 子目名称 | E4: 工程量 | G4: 价值（元） | J4: 其中（元）
E6: 单位 | F6: 数量 | G6: 单价 | I6: 合价 | J6: 人工费 | K6: 材料费
A7: 1 | B7: 2599 | C7: 拆除造船坞底板 | E7: 10m3 | F7: 112.5 | G7: 15630.96 | I7: 1758483 | J7: 1202850 | K7: 317696.63
A8: 2 | B8: 4109 | C8: 现浇坞门槛底板C35F300现浇砼 | E8: 10m3 | F8: 196.8 | G8: 8848.12 | I8: 1741310 | J8: 681616.8 | K8: 809397.07
A9: 3 | B9: 3541换 | C9: 钢筋加工(预应力构件),梁与板 | E9: 1t | F9: 236.16 | G9: 8057.1 | I9: 1902764.7 | J9: 315627.84 | K9: 1504717.1
A10: 4 | B10: 2599 | C10: 拆除坞墙前趾底板 | E10: 10m3 | F10: 16.35 | G10: 15630.96 | I10: 255566.2 | J10: 174814.2 | K10: 46171.91
A11: 5 | B11: 4109 | C11: 现浇坞墙前趾底板C35 F300现浇砼 | E11: 10m3 | F11: 17.25 | G11: 8848.12 | I11: 152630.07 | J11: 59745.38 | K11: 70945.63
A12: 6 | B12: 3541换 | C12: 钢筋加工(预应力构件),梁与板 | E12: 1t | F12: 17.25 | G12: 8057.1 | I12: 138984.98 | J12: 23054.63 | K12: 109910.1
A13: 7 | B13: 补 | C13: 拆除坞壁楼梯 | E13: m3 | F13: 21 | G13: 450 | I13: 9450 | J13: 9450
A14: 8 | B14: 4109 | C14: 坞墙现浇混凝土填补找平C35F300 | E14: 10m3 | F14: 25.2 | G14: 8848.12 | I14: 222972.62 | J14: 87280.2 | K14: 103642.31
A15: 9 | B15: 3541换 | C15: 预应力钢筋加工(预应力构件),梁与板 | E15: 1t | F15: 20.16 | G15: 8057.1 | I15: 162431.14 | J15: 26943.84 | K15: 128451.46
A16: 10 | B16: 4109 | C16: 现浇坞门止水面C35 F300 | E16: 10m3 | F16: 0.75 | G16: 8848.12 | I16: 6636.09 | J16: 2597.63 | K16: 3084.59
A17: 11 | B17: 3541换 | C17: 钢筋加工(预应力构件),梁与板 | E17: 1t | F17: 3 | G17: 8057.1 | I17: 24171.3 | J17: 4009.5 | K17: 19114.8
A18: 12 | B18: 1449 | C18: 止水帷幕灌浆C35 | E18: 100m3 | F18: 10.53 | G18: 47833.97 | I18: 503691.7 | J18: 328393.85 | K18: 173397.4
A19: 13 | B19: 补 | C19: 预埋排水管DN350 | E19: m | F19: 15 | G19: 450 | I19: 6750 | J19: 6750
A20: 14 | B20: 6102 | C20: 钢盖板制作安装,水上安 | E20: 1t | F20: 3.3 | G20: 11230.38 | I20: 37060.25 | J20: 12429.45 | K20: 22639.91
A21: 15 | B21: 2601换 | C21: C12素混凝土 | E21: 10m3 | F21: 15 | G21: 9423.7 | I21: 141355.5 | J21: 112846.5 | K21: 11248.8
A22: 16 | B22: 6110 | C22: 坞门槛底板埋件制作安装 | E22: 1t | F22: 93 | G22: 13387.26 | I22: 1245015.2 | J22: 463279.5 | K22: 724046.85
A23: 17 | B23: 6143 | C23: 止水缝处理(橡胶止水带) | E23: 10延米 | F23: 61.8 | G23: 444.5 | I23: 27470.1 | J23: 7508.7 | K23: 19961.4
A24: 18 | B24: 补 | C24: 拆除原橡胶护舷 | E24: 套 | F24: 1 | G24: 1000 | I24: 1000 | J24: 1000
A25: 19 | B25: 6069换 | C25: 陆上安装橡胶护舷,鼓型H=2000mm,三鼓一板 | E25: 1套 | F25: 1 | G25: 18983.29 | I25: 18983.29 | J25: 6825.47 | K25: 9589.34
C26: 小计 | I26: 8356726.2 | J26: 3527023.5 | K26: 4074015.3
C47: 合计 | I47: 8356726.2 | J47: 3527023.5 | K47: 4074015.3

Sheet 船坞改造费用
A2: 单位工程费用表
A3: 项目名称：船坞改造土建工程 | E3: 第 1 页 共 1 页
A4: 序号 | B4: 费用名称 | D4: 取费说明 | F4: 费率（%） | G4: 费用金额
A5: (一) | B5: 基价定额直接费 | D5: 预算价直接费-外购自置材料不计费 | F5: 108 | G5: 4114350.2
A6: (二) | B6: 定额直接费 | D6: 直接费+主材费+设备费 | F6: 108 | G6: 9025264.3
A7: (三) | B7: 其他直接费 | D7: 临时设施费+冬季、雨季及夜间施工增加费+材料二次倒运费+施工辅助费+施工队伍进退场费+外海工程拖船费 | G7: 269901.39
A8: 1 | B8: 临时设施费 | D8: 基价定额直接费 | F8: 1.392 | G8: 57271.76
A9: 2 | B9: 冬季、雨季及夜间施工增加费 | D9: 基价定额直接费 | F9: 1.859 | G9: 76485.77
A10: 3 | B10: 材料二次倒运费 | D10: 基价定额直接费 | F10: 0.353 | G10: 14523.66
A11: 4 | B11: 施工辅助费 | D11: 基价定额直接费 | F11: 1.116 | G11: 45916.15
A12: 5 | B12: 施工队伍进退场费 | D12: 基价定额直接费 | F12: 0.707 | G12: 29088.46
A13: 6 | B13: 外海工程拖船费 | D13: 基价定额直接费 | F13: 1.133 | G13: 46615.59
A14: (四) | B14: 直接工程费 | D14: 定额直接费+其他直接费 | G14: 9295165.7
A15: (五) | B15: 企业管理费 | D15: 基价定额直接费+其他直接费 | F15: 8.919 | G15: 391031.4
A16: (六) | B16: 财务费用 | D16: 基价定额直接费+其他直接费 | F16: 0.754 | G16: 33057.26
A17: (七) | B17: 利润 | D17: 基价定额直接费+其他直接费+企业管理费+财务费用 | F17: 7 | G17: 336583.82
A18: (八) | B18: 税金 | D18: 直接工程费+企业管理费+财务费用+利润 | F18: 3.41 | G18: 342904.08
A19: (九) | B19: 专项费用 | D19: 基价定额直接费 | F19: 113.08 | G19: 4652507.2
A20: (十) | B20: 单位工程概预算金额 | D20: 直接工程费+企业管理费+财务费用+利润+税金+专项费用 | G20: 15051249
